Workbook

Sheet Prices per feedstock & per IVC
A1: This sheet is mostly redundant since the price data is in th "feedstock MIX price per IVC " sheet. But references and Eurostat mapping in here
A2: Prices of feedstocks
B4: Eurostat sector | C4: Share per feedstock of overall feedstock mix (2030 medium) | D4: Share per feedstock of overall feedstock mix (2030 high) | E4: Price estimate [€/t] | F4: Source | G4: Share distribution of feedstocks within IVC 2030 | H4: Share distribution of feedstocks within IVC 2050 | I4: share feedstock costs | J4: CAPEX [€/t] | K4: share CAPEX | L4: OPEX [€/t] | M4: share OPEX | N4: OVERALL costs
A5: IVC 1 | E5: 520 | I5: =E5/N5 -> 0.59770115 | J5: 83 | K5: =J5/N5 -> 0.095402299 | L5: 267 | M5: =L5/N5 -> 0.30689655 | N5: =E5+J5+L5 -> 870
A6: Oil crops abandoned, degraded, intercropping | B6: A01: Products of agriculture, hunting and related services | D6: 1 | E6: 520 €/t | F6: Study 2, p. 124 | G6: 1 | H6: 1
A7: IVC 2 - HVO | C7: =SUM(C8:C10) -> 1 | D7: =SUM(D8:D10) -> 1 | E7: =D8*E8+D10*E10 -> 87.837631 | I7: =E7/N7 -> 0.11529705 | J7: 269 | K7: =J7/N7 -> 0.35309361 | L7: 405 | M7: =L7/N7 -> 0.53160934 | N7: =E7+J7+L7 -> 761.83763
A8: Oil crops abandoned, degraded, intercropping | B8: A01: Products of agriculture, hunting and related services | C8: 0 | D8: 0 | E8: 520 | F8: Study 2, p. 124
A9: Tall Oil | C9: ='[2]Availabilities EU Austria'!$N$13/'[2]Availabilities EU Austria'!$N$10 -> 0.063011547 | D9: ='[2]Availabilities EU Austria'!$Q$13/'[2]Availabilities EU Austria'!$Q$10 -> 0.089199177 | E9: ??
A10: Intermediate Bioenergy carriers (biocrude, FPBO) | B10: C20: Chemicals and chemical products | C10: =('[2]Availabilities EU Austria'!$N$15+'[2]Availabilities EU Austria'!$N$14)/'[2]Availabilities EU Austria'!$N$10 -> 0.93698845 | D10: =('[2]Availabilities EU Austria'!$Q$14+'[2]Availabilities EU Austria'!$Q$15)/'[2]Availabilities EU Austria'!$Q$10 -> 0.91080082 | E10: 96.44 | F10: CHECK
A11: IVC 2 - HEFA | C11: =SUM(C12:C14) -> 1 | D11: =SUM(D12:D14) -> 1 | E11: =D12*E12+D14*E14 -> 137.72093 | I11: =E11/N11 -> 0.12755234 | J11: 376 | K11: =J11/N11 -> 0.34823813 | L11: 566 | M11: =L11/N11 -> 0.52420953 | N11: =E11+J11+L11 -> 1079.7209
A12: Oil crops abandoned, degraded, intercropping | B12: A01: Products of agriculture, hunting and related services | C12: ='[2]Availabilities EU Austria'!$N$21/'[2]Availabilities EU Austria'!$N$16 -> 0.072434801 | D12: ='[2]Availabilities EU Austria'!$Q$21/'[2]Availabilities EU Austria'!$Q$16 -> 0.11542722 | E12: 520 | F12: Study 2, p. 124
A13: Tall oil | C13: ='[2]Availabilities EU Austria'!$N$23/'[2]Availabilities EU Austria'!$N$16 -> 0.058447318 | D13: ='[2]Availabilities EU Austria'!$Q$23/'[2]Availabilities EU Austria'!$Q$16 -> 0.078903164 | E13: ?
A14: Intermediate Bioenergy carriers (biocrude, FPBO) | B14: C20: Chemicals and chemical products | C14: =('[2]Availabilities EU Austria'!$N$24+'[2]Availabilities EU Austria'!$N$25)/'[2]Availabilities EU Austria'!$N$16 -> 0.86911788 | D14: =('[2]Availabilities EU Austria'!$Q$24+'[2]Availabilities EU Austria'!$Q$25)/'[2]Availabilities EU Austria'!$Q$16 -> 0.80566962 | E14: 96.44
A15: IVC 5 | C15: =SUM(C16:C19) -> 1 | D15: =SUM(D16:D19) -> 1 | E15: =D16*E16+D17*E17+D18*E18+D19*E19 -> 60.376239
A16: Straw | B16: A01: Products of agriculture, hunting and related services | C16: ='[2]Availabilities EU Austria'!$N$27/'[2]Availabilities EU Austria'!$N$26 -> 0.73688393 | D16: ='[2]Availabilities EU Austria'!$Q$27/'[2]Availabilities EU Austria'!$Q$26 -> 0.74789495 | E16: 58 | F16: Study 2, p. 97
A17: Lignocrops abandoned degraded | B17: A01: Products of agriculture, hunting and related services | C17: ='[2]Availabilities EU Austria'!$N$28/'[2]Availabilities EU Austria'!$N$26 -> 0.028841348 | D17: ='[2]Availabilities EU Austria'!$Q$28/'[2]Availabilities EU Austria'!$Q$26 -> 0.031508836 | E17: 69 | F17: Study 2, p. 193
A18: Lignocrops inter & cover cropping | B18: A01: Products of agriculture, hunting and related services | C18: ='[2]Availabilities EU Austria'!$N$29/'[2]Availabilities EU Austria'!$N$26 -> 0.013130549 | D18: ='[2]Availabilities EU Austria'!$Q$29/'[2]Availabilities EU Austria'!$Q$26 -> 0.022137974 | E18: 69 | F18: Study 2, p. 193
A19: Secondary forest residues | B19: C17 Paper and paper products (en) | C19: ='[2]Availabilities EU Austria'!$N$30/'[2]Availabilities EU Austria'!$N$26 -> 0.22114418 | D19: ='[2]Availabilities EU Austria'!$Q$30/'[2]Availabilities EU Austria'!$Q$26 -> 0.19845824 | E19: 67
A20: IVC 6 | E20: =D21*E21 -> 96.44
A21: Intermediate Bioenergy carrier (ethanol, methanol) | B21: C20: Chemicals and chemical products | C21: 1 | D21: 1 | E21: 96.44
A22: IVC 7 | C22: =SUM(C23:C31) -> 1 | D22: =SUM(D23:D31) -> 1 | E22: =D23*E23+D24*E24+D25*E25+D26*E26+D27*E27+D28*E28+D29*E29+D30*E30+D31*E31 -> 30.965299
A23: Prunings & damaged crops (olive stones excluded) | B23: A01: Products of agriculture, hunting and related services | C23: ='[2]Availabilities EU Austria'!$N$41/'[2]Availabilities EU Austria'!$N$40 -> 0.030601718 | D23: ='[2]Availabilities EU Austria'!$Q$41/'[2]Availabilities EU Austria'!$Q$40 -> 0.03010511 | E23: 44 | F23: Study 2, p. 111
A24: Lignocrops abandoned degraded | B24: A01: Products of agriculture, hunting and related services | C24: ='[2]Availabilities EU Austria'!$N$42/'[2]Availabilities EU Austria'!$N$40 -> 0.018454385 | D24: ='[2]Availabilities EU Austria'!$Q$42/'[2]Availabilities EU Austria'!$Q$40 -> 0.021462821 | E24: 69 | F24: Study 2, p. 193 | G24: =0.21/2 -> 0.105
A25: Lignocrops inter & cover cropping | B25: A01: Products of agriculture, hunting and related services | C25: ='[2]Availabilities EU Austria'!$N$43/'[2]Availabilities EU Austria'!$N$40 -> 0.0084016949 | D25: ='[2]Availabilities EU Austria'!$Q$43/'[2]Availabilities EU Austria'!$Q$40 -> 0.015079687 | E25: 69 | F25: Study 2, p. 193 | G25: =0.21/2 -> 0.105
A26: Agroprocessing residues | B26: CPA_C10-12 (Food, beverages and tobacco products) | C26: ='[2]Availabilities EU Austria'!$N$44/'[2]Availabilities EU Austria'!$N$40 -> 0.023575445 | D26: ='[2]Availabilities EU Austria'!$Q$44/'[2]Availabilities EU Austria'!$Q$40 -> 0.024015373 | E26: 44 | F26: Study 2, p. 111 | G26: 0.24
A27: Straw | B27: A01: Products of agriculture, hunting and related services (en); A01.1: non-perennial crops | C27: ='[2]Availabilities EU Austria'!$N$45/'[2]Availabilities EU Austria'!$N$40 -> 0.47150152 | D27: ='[2]Availabilities EU Austria'!$Q$45/'[2]Availabilities EU Austria'!$Q$40 -> 0.50944236 | E27: 58
A28: Manure | B28: A01: Products of agriculture, hunting and related services; A01.4: Live animals and animal products | C28: ='[2]Availabilities EU Austria'!$N$46/'[2]Availabilities EU Austria'!$N$40 -> 0.347493 | D28: ='[2]Availabilities EU Austria'!$Q$46/'[2]Availabilities EU Austria'!$Q$40 -> 0.3159246 | E28: 0 | G28: 0.32
A29: Sewage sludge | B29: Sewerage services; sewage sludge; waste collection, treatment and disposal services; materials recovery services; remediation services and other waste management services | C29: ='[2]Availabilities EU Austria'!$N$47/'[2]Availabilities EU Austria'!$N$40 -> 0.031761184 | D29: ='[2]Availabilities EU Austria'!$Q$47/'[2]Availabilities EU Austria'!$Q$40 -> 0.024204717 | E29: 0
A30: Biowastes (post consumer woods excluded) | B30: Sewerage services; sewage sludge; waste collection, treatment and disposal services; materials recovery services; remediation services and other waste management services | C30: ='[2]Availabilities EU Austria'!$N$48/'[2]Availabilities EU Austria'!$N$40 -> 0.065902037 | D30: ='[2]Availabilities EU Austria'!$Q$48/'[2]Availabilities EU Austria'!$Q$40 -> 0.05819089 | E30: =-(55+70)/2 -> -62.5 | F30: Study 2, annex 4, page 40 | H30: wird hier das Minuszeichen richtig in die Formel übernommen?
A31: Intermediate Bioenergy carrier (crude glycerine) | B31: C20: Chemicals and chemical products | C31: ='[2]Availabilities EU Austria'!$N$49/'[2]Availabilities EU Austria'!$N$40 -> 0.0023090105 | D31: ='[2]Availabilities EU Austria'!$Q$49/'[2]Availabilities EU Austria'!$Q$40 -> 0.0015744344 | E31: 96.44 | F31: CETO 2026, p. 29
A32: IVC 8a | C32: =SUM(C33:C42) -> 1 | D32: =SUM(D33:D42) -> 1 | E32: =D33*E33+D34*E34+D35*E35+D36*E36+D37*E37+D38*E38+D39*E39+D40*E40+D41*E41+D42*E42 -> 57.287316
A33: Straw | B33: A01: Products of agriculture, hunting and related services (en); A01.1: non-perennial crops | C33: ='[2]Availabilities EU Austria'!$N$61/'[2]Availabilities EU Austria'!$N$60 -> 0.5178381 | D33: ='[2]Availabilities EU Austria'!$Q$61/'[2]Availabilities EU Austria'!$Q$60 -> 0.56804069 | E33: 58
A34: Prunings & damaged crops | B34: A01: Products of agriculture, hunting and related services | C34: ='[2]Availabilities EU Austria'!$N$62/'[2]Availabilities EU Austria'!$N$60 -> 0.033609087 | D34: ='[2]Availabilities EU Austria'!$Q$62/'[2]Availabilities EU Austria'!$Q$60 -> 0.033570732 | E34: 44
A35: Sewage sludge | B35: E: WATER SUPPLY; SEWERAGE, WASTE MANAGEMENT AND REMEDIATION SERVICES (en); E37: Sewage services, sewage sludge | C35: ='[2]Availabilities EU Austria'!$N$63/'[2]Availabilities EU Austria'!$N$60 -> 0.034882499 | D35: ='[2]Availabilities EU Austria'!$Q$63/'[2]Availabilities EU Austria'!$Q$60 -> 0.026988851 | E35: 0 | F35: CHECK
A36: Agroprocessing residues - maize cobs | B36: CPA_C10-12 (Food, beverages and tobacco products) | C36: ='[2]Availabilities EU Austria'!$N$64/'[2]Availabilities EU Austria'!$N$60 -> 0.013662908 | D36: ='[2]Availabilities EU Austria'!$Q$64/'[2]Availabilities EU Austria'!$Q$60 -> 0.014187521 | E36: 44
A37: Lignocrops abandoned degraded | B37: A01: Products of agriculture, hunting and related services | C37: ='[2]Availabilities EU Austria'!$N$65/'[2]Availabilities EU Austria'!$N$60 -> 0.020267981 | D37: ='[2]Availabilities EU Austria'!$Q$65/'[2]Availabilities EU Austria'!$Q$60 -> 0.02393157 | E37: 69
A38: Lignocrops inter & cover cropping | B38: A01: Products of agriculture, hunting and related services | C38: ='[2]Availabilities EU Austria'!$N$66/'[2]Availabilities EU Austria'!$N$60 -> 0.0092273673 | D38: ='[2]Availabilities EU Austria'!$Q$66/'[2]Availabilities EU Austria'!$Q$60 -> 0.01681422 | E38: 69
A39: Primary forestry residues | B39: A02: Products of forestry, logging and related services (en) | C39: ='[2]Availabilities EU Austria'!$N$67/'[2]Availabilities EU Austria'!$N$60 -> 0.14802813 | D39: ='[2]Availabilities EU Austria'!$Q$67/'[2]Availabilities EU Austria'!$Q$60 -> 0.10247464 | E39: 69 | F39: CHECK
A40: Secondary forest residues | B40: C MANUFACTURED PRODUCTS, C17: Paper and paper products (en) | C40: ='[2]Availabilities EU Austria'!$N$68/'[2]Availabilities EU Austria'!$N$60 -> 0.15540695 | D40: ='[2]Availabilities EU Austria'!$Q$68/'[2]Availabilities EU Austria'!$Q$60 -> 0.15073288 | E40: 69 | F40: CHECK
A41: Biowastes - Post consumer wood | B41: E WATER SUPPLY; SEWERAGE, WASTE MANAGEMENT AND REMEDIATION SERVICES (en) | C41: ='[2]Availabilities EU Austria'!$N$69/'[2]Availabilities EU Austria'!$N$60 -> 0.046552014 | D41: ='[2]Availabilities EU Austria'!$Q$69/'[2]Availabilities EU Austria'!$Q$60 -> 0.042968416 | E41: 0 | F41: CHECK
A42: Intermediate Bioenergy carrier (FPBO with lower quality) | B42: C20: Chemicals and chemical products | C42: ='[2]Availabilities EU Austria'!$N$70/'[2]Availabilities EU Austria'!$N$60 -> 0.020524961 | D42: ='[2]Availabilities EU Austria'!$Q$70/'[2]Availabilities EU Austria'!$Q$60 -> 0.020290488 | E42: 96.44
A43: IVC 8b | E43: =D44*E44 -> 96.44
A44: Intermediate Bioenergy carrier (biomethane) | B44: A01: Products of agriculture, hunting and related services | C44: 1 | D44: =100% -> 1 | E44: 96.44
A45: IVC 8c | E45: =D46*E46 -> 96.44
A46: e-biofuel feedstocks (biogenic CO2 and hydrogen from electrolysis) | B46: C20: Chemicals and chemical products | C46: 1 | D46: 1 | E46: 96.44
A47: IVC 9a | C47: =SUM(C48:C57) -> 1 | D47: =SUM(D48:D57) -> 1 | E47: =D48*E48+D49*E49+D50*E50+D51*E51+D52*E52+D53*E53+D54*E54+D55*E55+D56*E56+D57*E57 -> 57.287316
A48: Straw | B48: A01: Products of agriculture, hunting and related services | C48: ='[2]Availabilities EU Austria'!$N$80/'[2]Availabilities EU Austria'!$N$79 -> 0.5178381 | D48: ='[2]Availabilities EU Austria'!$Q$80/'[2]Availabilities EU Austria'!$Q$79 -> 0.56804069 | E48: 58
A49: Prunings & damaged crops | B49: A01: Products of agriculture, hunting and related services | C49: ='[2]Availabilities EU Austria'!$N$81/'[2]Availabilities EU Austria'!$N$79 -> 0.033609087 | D49: ='[2]Availabilities EU Austria'!$Q$81/'[2]Availabilities EU Austria'!$Q$79 -> 0.033570732 | E49: 44
A50: Sewage sludge | B50: E: WATER SUPPLY; SEWERAGE, WASTE MANAGEMENT AND REMEDIATION SERVICES (en); E37: Sewage services, sewage sludge | C50: ='[2]Availabilities EU Austria'!$N$82/'[2]Availabilities EU Austria'!$N$79 -> 0.034882499 | D50: ='[2]Availabilities EU Austria'!$Q$82/'[2]Availabilities EU Austria'!$Q$79 -> 0.026988851 | E50: 0 | F50: CHECK
A51: Agroprocessing residues - maize cobs | B51: CPA_C10-12 (Food, beverages and tobacco products) | C51: ='[2]Availabilities EU Austria'!$N$83/'[2]Availabilities EU Austria'!$N$79 -> 0.013662908 | D51: ='[2]Availabilities EU Austria'!$Q$83/'[2]Availabilities EU Austria'!$Q$79 -> 0.014187521 | E51: 44
A52: Lignocrops abandoned degraded | B52: A01: Products of agriculture, hunting and related services | C52: ='[2]Availabilities EU Austria'!$N$84/'[2]Availabilities EU Austria'!$N$79 -> 0.020267981 | D52: ='[2]Availabilities EU Austria'!$Q$84/'[2]Availabilities EU Austria'!$Q$79 -> 0.02393157 | E52: 69
A53: Lignocrops inter & cover cropping | B53: A01: Products of agriculture, hunting and related services | C53: ='[2]Availabilities EU Austria'!$N$85/'[2]Availabilities EU Austria'!$N$79 -> 0.0092273673 | D53: ='[2]Availabilities EU Austria'!$Q$85/'[2]Availabilities EU Austria'!$Q$79 -> 0.01681422 | E53: 69
A54: Primary forestry residues | B54: A02: Products of forestry, logging and related services (en) | C54: ='[2]Availabilities EU Austria'!$N$86/'[2]Availabilities EU Austria'!$N$79 -> 0.14802813 | D54: ='[2]Availabilities EU Austria'!$Q$86/'[2]Availabilities EU Austria'!$Q$79 -> 0.10247464 | E54: 69 | F54: CHECK
A55: Secondary forest residues | B55: C MANUFACTURED PRODUCTS, C17: Paper and paper products (en) | C55: ='[2]Availabilities EU Austria'!$N$87/'[2]Availabilities EU Austria'!$N$79 -> 0.15540695 | D55: ='[2]Availabilities EU Austria'!$Q$87/'[2]Availabilities EU Austria'!$Q$79 -> 0.15073288 | E55: 69 | F55: CHECK
A56: Biowastes - Post consumer wood | B56: E WATER SUPPLY; SEWERAGE, WASTE MANAGEMENT AND REMEDIATION SERVICES (en) | C56: ='[2]Availabilities EU Austria'!$N$88/'[2]Availabilities EU Austria'!$N$79 -> 0.046552014 | D56: ='[2]Availabilities EU Austria'!$Q$88/'[2]Availabilities EU Austria'!$Q$79 -> 0.042968416 | E56: 0 | F56: CHECK
A57: Intermediate Bioenergy carriers (FPBO with lower quality ) | B57: C20: Chemicals and chemical products | C57: ='[2]Availabilities EU Austria'!$N$89/'[2]Availabilities EU Austria'!$N$79 -> 0.020524961 | D57: ='[2]Availabilities EU Austria'!$Q$89/'[2]Availabilities EU Austria'!$Q$79 -> 0.020290488 | E57: 96.44
A58: IVC 9b | E58: =D59*E59 -> 96.44
A59: e-biofuel feedstocks (biogenic CO2 and hydrogen from electrolysis) | B59: C20: Chemicals and chemical products | D59: 1 | E59: 96.44
A60: IVC 11a | C60: =SUM(C61:C70) -> 1 | D60: =SUM(D61:D70) -> 1 | E60: =D61*E61+D62*E62+D63*E63+D64*E64+D65*E65+D66*E66+D67*E67+D68*E68+D69*E69+D70*E70 -> 57.287316
A61: Straw | B61: A01: Products of agriculture, hunting and related services | C61: ='[2]Availabilities EU Austria'!$N$115/'[2]Availabilities EU Austria'!$N$114 -> 0.5178381 | D61: ='[2]Availabilities EU Austria'!$Q$115/'[2]Availabilities EU Austria'!$Q$114 -> 0.56804069 | E61: 58
A62: Prunings & damaged crops | B62: A01: Products of agriculture, hunting and related services | C62: ='[2]Availabilities EU Austria'!$N$116/'[2]Availabilities EU Austria'!$N$114 -> 0.033609087 | D62: ='[2]Availabilities EU Austria'!$Q$116/'[2]Availabilities EU Austria'!$Q$114 -> 0.033570732 | E62: 44
A63: Sewage sludge | B63: E: WATER SUPPLY; SEWERAGE, WASTE MANAGEMENT AND REMEDIATION SERVICES (en); E37: Sewage services, sewage sludge | C63: ='[2]Availabilities EU Austria'!$N$117/'[2]Availabilities EU Austria'!$N$114 -> 0.034882499 | D63: ='[2]Availabilities EU Austria'!$Q$117/'[2]Availabilities EU Austria'!$Q$114 -> 0.026988851 | E63: 0 | F63: CHECK
A64: Agroprocessing residues - maize cobs | B64: CPA_C10-12 (Food, beverages and tobacco products) | C64: ='[2]Availabilities EU Austria'!$N$118/'[2]Availabilities EU Austria'!$N$114 -> 0.013662908 | D64: ='[2]Availabilities EU Austria'!$Q$118/'[2]Availabilities EU Austria'!$Q$114 -> 0.014187521 | E64: 44
A65: Lignocrops abandoned degraded | B65: A01: Products of agriculture, hunting and related services | C65: ='[2]Availabilities EU Austria'!$N$119/'[2]Availabilities EU Austria'!$N$114 -> 0.020267981 | D65: ='[2]Availabilities EU Austria'!$Q$119/'[2]Availabilities EU Austria'!$Q$114 -> 0.02393157 | E65: 69
A66: Lignocrops inter & cover cropping | B66: A01: Products of agriculture, hunting and related services | C66: ='[2]Availabilities EU Austria'!$N$120/'[2]Availabilities EU Austria'!$N$114 -> 0.0092273673 | D66: ='[2]Availabilities EU Austria'!$Q$120/'[2]Availabilities EU Austria'!$Q$114 -> 0.01681422 | E66: 69
A67: Primary forestry residues | B67: A02: Products of forestry, logging and related services (en) | C67: ='[2]Availabilities EU Austria'!$N$121/'[2]Availabilities EU Austria'!$N$114 -> 0.14802813 | D67: ='[2]Availabilities EU Austria'!$Q$121/'[2]Availabilities EU Austria'!$Q$114 -> 0.10247464 | E67: 69 | F67: CHECK
A68: Secondary forest residues | B68: C MANUFACTURED PRODUCTS, C17: Paper and paper products (en) | C68: ='[2]Availabilities EU Austria'!$N$122/'[2]Availabilities EU Austria'!$N$114 -> 0.15540695 | D68: ='[2]Availabilities EU Austria'!$Q$122/'[2]Availabilities EU Austria'!$Q$114 -> 0.15073288 | E68: 69 | F68: CHECK
A69: Biowastes - Post consumer wood | B69: E WATER SUPPLY; SEWERAGE, WASTE MANAGEMENT AND REMEDIATION SERVICES (en) | C69: ='[2]Availabilities EU Austria'!$N$123/'[2]Availabilities EU Austria'!$N$114 -> 0.046552014 | D69: ='[2]Availabilities EU Austria'!$Q$123/'[2]Availabilities EU Austria'!$Q$114 -> 0.042968416 | E69: 0 | F69: CHECK
A70: Intermediate Bioenergy carriers (FPBO with lower quality ) | C70: ='[2]Availabilities EU Austria'!$N$124/'[2]Availabilities EU Austria'!$N$114 -> 0.020524961 | D70: ='[2]Availabilities EU Austria'!$Q$124/'[2]Availabilities EU Austria'!$Q$114 -> 0.020290488 | E70: 96.44
A71: IVC 12 | E71: =D72*E72 -> 96.44
A72: Intermediate Bioenergy carriers (Syngas) | C72: 1 | D72: 1 | E72: 96.44
A73: IVC13a | C73: =SUM(C74:C81) -> 1 | D73: =SUM(D74:D81) -> 1 | E73: =D74*E74+D75*E75+D76*E76+D77*E77+D78*E78+D79*E79+D80*E80+D81*E81 -> 57.544764
A74: Straw | B74: A01: Products of agriculture, hunting and related services | C74: ='[2]Availabilities EU Austria'!$N$130/'[2]Availabilities EU Austria'!$N$129 -> 0.5482132 | D74: ='[2]Availabilities EU Austria'!$Q$140/'[2]Availabilities EU Austria'!$Q$138 -> 0.59623005 | E74: 58
A75: Prunings & damaged crops | B75: A01: Products of agriculture, hunting and related services | C75: ='[2]Availabilities EU Austria'!$N$131/'[2]Availabilities EU Austria'!$N$129 -> 0.035580513 | D75: ='[2]Availabilities EU Austria'!$Q$141/'[2]Availabilities EU Austria'!$Q$138 -> 0.0352367 | E75: 44
A76: Agroprocessing residues - maize cobs | B76: CPA_C10-12 (Food, beverages and tobacco products) | C76: ='[2]Availabilities EU Austria'!$N$132/'[2]Availabilities EU Austria'!$N$129 -> 0.01446434 | D76: ='[2]Availabilities EU Austria'!$Q$142/'[2]Availabilities EU Austria'!$Q$138 -> 0.014891586 | E76: 44
A77: Lignocrops abandoned degraded | B77: A01: Products of agriculture, hunting and related services | C77: ='[2]Availabilities EU Austria'!$N$133/'[2]Availabilities EU Austria'!$N$129 -> 0.02145685 | D77: ='[2]Availabilities EU Austria'!$Q$143/'[2]Availabilities EU Austria'!$Q$138 -> 0.025119189 | E77: 69
A78: Lignocrops inter & cover cropping | B78: A01: Products of agriculture, hunting and related services | C78: ='[2]Availabilities EU Austria'!$N$134/'[2]Availabilities EU Austria'!$N$129 -> 0.0097686219 | D78: ='[2]Availabilities EU Austria'!$Q$144/'[2]Availabilities EU Austria'!$Q$138 -> 0.017648636 | E78: 69
A79: Primary forestry residues | B79: A02: Products of forestry, logging and related services (en) | C79: ='[2]Availabilities EU Austria'!$N$135/'[2]Availabilities EU Austria'!$N$129 -> 0.1567111 | D79: ='[2]Availabilities EU Austria'!$Q$145/'[2]Availabilities EU Austria'!$Q$138 -> 0.10756001 | E79: 67
A80: Secondary forest residues | B80: C MANUFACTURED PRODUCTS, C17: Paper and paper products (en) | C80: ='[2]Availabilities EU Austria'!$N$136/'[2]Availabilities EU Austria'!$N$129 -> 0.16452273 | D80: ='[2]Availabilities EU Austria'!$Q$146/'[2]Availabilities EU Austria'!$Q$138 -> 0.15821309 | E80: 67
A81: Biowastes - Post consumer wood | B81: E WATER SUPPLY; SEWERAGE, WASTE MANAGEMENT AND REMEDIATION SERVICES (en) | C81: ='[2]Availabilities EU Austria'!$N$137/'[2]Availabilities EU Austria'!$N$129 -> 0.04928264 | D81: ='[2]Availabilities EU Austria'!$Q$147/'[2]Availabilities EU Austria'!$Q$138 -> 0.04510075 | E81: 0 | F81: CHECK

Sheet LCoP CONVENTIONAL
B1: TOTAL absolute costs [€/ t product] | C1: Feedstock share | E1: Absolute feedstock costs [€/t product] | F1: CAPEX share | H1: Absolute CAPEX | I1: OPEX share | K1: Absolute OPEX | L1: Share of feedstock CETO report 2026, p. 27) | M1: Origin | N1: Price of 1t of feedstock [€/t] | O1: Converison factor [t product/ t feedstock] | P1: Feestock cost to produce 1t of fuel | Q1: NEW share of feedstock mix 2030 medium (taking into account the feedstock split in 2030) | R1: money [€] spent on each feedtsock when producing 1t of product (and weighted feedstock mix cost) | S1: NEW share of feedstock mix 2030 high (taking into account the feedstock split in 2030) | T1: money [€] spent on each feedtsock when producing 1t of product (and weighted feedstock mix cost) | U1: NOTES
A2: Conventional biodiesel | H2: for now just any number
A3: transesterification of food/feed crops | C3: 0.75 | D3: money [€] spent on each feedtsock when producing 1t of product | F3: 0.065 | G3: =SUM(G4:G8) -> 1 | H3: 1000000 | I3: 0.185 | J3: =SUM(J4:J9) -> 1 | L3: =SUM(L4:L7) -> 0.48
B4: primarily EU | C4: Rapeseed oil | D4: ='Feedtstocks only CONVENTIONAL'!I4 -> 354.464 | E4: 0.76 | F4: Machinery and equipment | G4: 0.45 | H4: =G4*H$3 -> 450000 | I4: Chemical and chemical products | J4: 0.3 | L4: 0.38 | M4: primarily EU
B5: imported | C5: Soybean oil | D5: ='Feedtstocks only CONVENTIONAL'!I5 -> 74.624 | E5: 0.16 | F5: Architectural and engineering services | G5: 0.3 | H5: =G5*H$3 -> 300000 | I5: Electricity, gas, steam & AC | J5: 0.2 | L5: 0.08 | M5: imported
B6: pirmarily EU | C6: Sunflower oil | D6: ='Feedtstocks only CONVENTIONAL'!I6 -> 18.656 | E6: 0.04 | F6: Constructions and construction works | G6: 0.15 | H6: =G6*H$3 -> 150000 | I6: Legal and accounting services; services of head offices; management consultancy services | J6: 0.25 | L6: 0.02
B7: imported | C7: Palm oil | D7: ='Feedtstocks only CONVENTIONAL'!I7 -> 18.333333 | E7: 0.04 | F7: Fabricated metal products | G7: 0.07 | H7: =G7*H$3 -> 70000 | I7: Repair and installation services | J7: 0.15
F8: Computer, electronic and optical products | G8: 0.03 | H8: =G8*H$3 -> 30000 | I8: Land transport services and transport services via pipelines | J8: 0.1
I9: Waster management services | J9: 0
A10: transesterification of cover crops from marginal lands | C10: 0.7 | F10: 0.07 | G10: =SUM(G11:G15) -> 1 | H10: 1000000 | I10: 0.23 | J10: =SUM(J11:J16) -> 1
F11: Machinery and equipment | G11: 0.48 | H11: =G11*H$10 -> 480000 | I11: Chemical and chemical products | J11: 0.25
F12: Architectural and engineering services | G12: 0.3 | H12: =G12*H$10 -> 300000 | I12: Electricity, gas, steam & AC | J12: 0.15
F13: Constructions and construction works | G13: 0.12 | H13: =G13*H$10 -> 120000 | I13: Legal and accounting services; services of head offices; management consultancy services | J13: 0.2
F14: Fabricated metal products | G14: 0.07 | H14: =G14*H$10 -> 70000 | I14: Repair and installation services | J14: 0.15
F15: Computer, electronic and optical products | G15: 0.03 | H15: =G15*H$10 -> 30000 | I15: Land transport services and transport services via pipelines | J15: 0.25
I16: Waster management services | J16: 0
A17: transesterification of UCO and AF | B17: =E17+H17+K17 -> 1253 | C17: =E17/B17 -> 0.72067039 | E17: 903 | F17: =H17/B17 -> 0.066241022 | G17: =SUM(G18:G22) -> 1 | H17: 83 | I17: =K17/B17 -> 0.21308859 | J17: =SUM(J18:J23) -> 1 | K17: 267
C18: UCO imported | D18: =0.6618*0.6 -> 0.39708 | E18: =D18*E17 -> 358.56324 | F18: Machinery and equipment | G18: 0.5 | H18: =G18*H$17 -> 41.5 | I18: Chemical and chemical products | J18: 0.25 | K18: =J18*K$17 -> 66.75 | N18: 880
C19: UCO domestic | D19: =0.6618*0.4 -> 0.26472 | E19: =D19*E18 -> 94.918861 | F19: Architectural and engineering services | G19: 0.3 | H19: =G19*H$17 -> 24.9 | I19: Electricity, gas, steam & AC | J19: 0.15 | K19: =J19*K$17 -> 40.05
C20: Animal Fat | D20: 0.3382 | E20: =D20*E19 -> 32.101559 | F20: Constructions and construction works | G20: 0.1 | H20: =G20*H$17 -> 8.3 | I20: Legal and accounting services; services of head offices; management consultancy services | J20: 0.2 | K20: =J20*K$17 -> 53.4
F21: Fabricated metal products | G21: 0.07 | H21: =G21*H$17 -> 5.81 | I21: Repair and installation services | J21: 0.2 | K21: =J21*K$17 -> 53.4
F22: Computer, electronic and optical products | G22: 0.03 | H22: =G22*H$17 -> 2.49 | I22: Land transport services and transport services via pipelines | J22: 0.1 | K22: =J22*K$17 -> 26.7
I23: Waster management services | J23: 0.1 | K23: =J23*K$17 -> 26.7
A24: hydrotreatment of food/feed crops | C24: 0.7 | F24: 0.1 | G24: =SUM(G25:G29) -> 1 | I24: 0.2 | J24: =SUM(J25:J30) -> 1
F25: Machinery and equipment | G25: 0.55 | I25: Chemical and chemical products | J25: 0.4
F26: Architectural and engineering services | G26: 0.25 | I26: Electricity, gas, steam & AC | J26: 0.2
F27: Constructions and construction works | G27: 0.1 | I27: Legal and accounting services; services of head offices; management consultancy services | J27: 0.2
F28: Fabricated metal products | G28: 0.07 | I28: Repair and installation services | J28: 0.15
F29: Computer, electronic and optical products | G29: 0.03 | I29: Land transport services and transport services via pipelines | J29: 0.05
I30: Waster management services | J30: 0
A31: hydrotreatment of cover crops from marginal lands (non-aviation part) | C31: 0.64 | F31: 0.14 | G31: =SUM(G32:G36) -> 1 | I31: 0.22 | J31: =SUM(J32:J37) -> 1
F32: Machinery and equipment | G32: 0.58 | I32: Chemical and chemical products | J32: 0.35
F33: Architectural and engineering services | G33: 0.25 | I33: Electricity, gas, steam & AC | J33: 0.15
F34: Constructions and construction works | G34: 0.08 | I34: Legal and accounting services; services of head offices; management consultancy services | J34: 0.18
F35: Fabricated metal products | G35: 0.06 | I35: Repair and installation services | J35: 0.15
F36: Computer, electronic and optical products | G36: 0.03 | I36: Land transport services and transport services via pipelines | J36: 0.17
I37: Waster management services | J37: 0
A38: HVO (road) hydrotreatment of UCO and AF | B38: =E38+H38+K38 -> 2016 | C38: =E38/B38 -> 0.6656746 | E38: 1342 | F38: =H38/B38 -> 0.13343254 | G38: =SUM(G39:G43) -> 1 | H38: 269 | I38: =K38/B38 -> 0.20089286 | J38: =SUM(J39:J44) -> 1 | K38: 405
B39: 60% imported | C39: UCO | F39: Machinery and equipment | G39: 0.6 | H39: =G39*H$38 -> 161.4 | I39: Chemical and chemical products | J39: 0.15 | K39: =J39*K$38 -> 60.75
B40: domestic | C40: Animal fat | F40: Architectural and engineering services | G40: 0.25 | H40: =G40*H$38 -> 67.25 | I40: Electricity, gas, steam & AC | J40: 0.4 | K40: =J40*K$38 -> 162
F41: Constructions and construction works | G41: 0.07 | H41: =G41*H$38 -> 18.83 | I41: Legal and accounting services; services of head offices; management consultancy services | J41: 0.2 | K41: =J41*K$38 -> 81
F42: Fabricated metal products | G42: 0.05 | H42: =G42*H$38 -> 13.45 | I42: Repair and installation services | J42: 0.15 | K42: =J42*K$38 -> 60.75
F43: Computer, electronic and optical products | G43: 0.03 | H43: =G43*H$38 -> 8.07 | I43: Land transport services and transport services via pipelines | J43: 0.1 | K43: =J43*K$38 -> 40.5
I44: Waster management services | J44: 0 | K44: =J44*K$38 -> 0
A45: HEFA (aviationn) hydrotreatment of UCO and AF | B45: =E45+H45+K45 -> 2903 | C45: =E45/B45 -> 0.6755081 | E45: 1961 | F45: =H45/B45 -> 0.12952118 | G45: =SUM(G46:G50) -> 1 | H45: 376 | I45: =K45/B45 -> 0.19497072 | J45: =SUM(J46:J51) -> 1 | K45: 566
B46: 60% imported | C46: UCO | F46: Machinery and equipment | G46: 0.6 | H46: =G46*H$45 -> 225.6 | I46: Chemical and chemical products | J46: 0.15 | K46: =J46*K$45 -> 84.9
B47: domestic | C47: Animal fat | F47: Architectural and engineering services | G47: 0.25 | H47: =G47*H$45 -> 94 | I47: Electricity, gas, steam & AC | J47: 0.4 | K47: =J47*K$45 -> 226.4
F48: Constructions and construction works | G48: 0.07 | H48: =G48*H$45 -> 26.32 | I48: Legal and accounting services; services of head offices; management consultancy services | J48: 0.2 | K48: =J48*K$45 -> 113.2
F49: Fabricated metal products | G49: 0.05 | H49: =G49*H$45 -> 18.8 | I49: Repair and installation services | J49: 0.15 | K49: =J49*K$45 -> 84.9
F50: Computer, electronic and optical products | G50: 0.03 | H50: =G50*H$45 -> 11.28 | I50: Land transport services and transport services via pipelines | J50: 0.1 | K50: =J50*K$45 -> 56.6
I51: Waster management services | J51: 0 | K51: =J51*K$45 -> 0
A52: Conventional biogasoline (Ethanol)
A53: ethanol fermentation of food/ feed crops | B53: 903.57 | C53: 0.7 | D53: source: CETO 2026 report, p. 28 | E53: =C53*B53 -> 632.499 | F53: 0.1 | H53: =F53*B53 -> 90.357 | I53: 0.2 | J53: =SUM(J54:J59) -> 1 | K53: =I53*B53 -> 180.714
C54: Wheat kernels | D54: 0.17 | F54: Machinery and equipment | G54: 0.5 | H54: =G54*H$53 -> 45.1785 | I54: Chemical and chemical products | J54: 0.15 | K54: =J54*K$53 -> 27.1071
C55: corn kernsels | D55: 0.43 | F55: Architectural and engineering services | G55: 0.25 | H55: =G55*H$53 -> 22.58925 | I55: Electricity, gas, steam & AC | J55: 0.4 | K55: =J55*K$53 -> 72.2856
C56: triticale | D56: 0.09 | F56: Constructions and construction works | G56: 0.15 | H56: =G56*H$53 -> 13.55355 | I56: Legal and accounting services; services of head offices; management consultancy services | J56: 0.2 | K56: =J56*K$53 -> 36.1428
C57: Barely Kernels | D57: 0.03 | F57: Fabricated metal products | G57: 0.07 | H57: =G57*H$53 -> 6.32499 | I57: Repair and installation services | J57: 0.15 | K57: =J57*K$53 -> 27.1071
C58: Rye Kernels | D58: 0.02 | F58: Computer, electronic and optical products | G58: 0.03 | H58: =G58*H$53 -> 2.71071 | I58: Land transport services and transport services via pipelines | J58: 0.1 | K58: =J58*K$53 -> 18.0714
C59: Sugar Beets | D59: 0.26 | I59: Waster management services | J59: 0 | K59: =J59*K$53 -> 0

Sheet 2023 costs
B1: marrket price | C1: market value asbolute [€/t] | D1: in Mtoe | E1: Conversion factor [t/toe] | F1: in t | G1: Cost of production [€/t] | H1: Cost spent per IVC | I1: Feedstock share of costs | J1: Eurostat sector | K1: money [€] spent on each feedtsock when producing 1t of product | L1: Absolute feedstock costs [€] | M1: CAPEX share of costs | N1: CAPEX distribution | O1: Absoluet CAPEX [€] | P1: OPEX share of costs | R1: Absolute OPEX [€] | S1: ENTIRE production costs
A2: Advanced biodiesel
A3: TOTAL | C3: =SUM(C4:C18) -> 2.0926449e+09 | D3: =D4+D11+D18 -> 1.3 | F3: =SUM(F4:F18) -> 1443203.4 | H3: =SUM(H4:H18) -> 1.480528e+10 | L3: =L4+L11+L18 -> 1.4236257e+10 | O3: =O4+O11+O18 -> 1.5900413e+08 | R3: =R4+R11+R18 -> 4.1001916e+08
A4: of which IVC 1 | B4: 1450 | C4: =B4*F4 -> 1.8704812e+09 | D4: 1.14 | E4: ='[2]Conversion factors selected IV '!$O$4 -> 1.1315676 | F4: =D4*E4*1000000 -> 1289987 | G4: ='LCoP 2030 MEDIUM'!E24 -> 10350 | H4: =F4*G4 -> 1.3351366e+10 | I4: ='LCoP 2030 MEDIUM'!H24 -> 0.96618357 | L4: =I4*H4 -> 1.289987e+10 | M4: ='LCoP 2030 MEDIUM'!F24 -> 0.0080193237 | O4: =M4*H4 -> 1.0706892e+08 | P4: ='LCoP 2030 MEDIUM'!G24 -> 0.025797101 | R4: =P4*H4 -> 3.4442654e+08 | S4: =L4+O4+R4 -> 1.3351366e+10
H5: imported | I5: POME | J5: Food, beverages and tobacco products | K5: 850 | L5: =K5*F4 -> 1.096489e+09 | M5: Fabricated metal products | N5: 0.05 | O5: =N5*O$4 -> 5353446.2 | P5: Electricity, gas, steam and air conditioning | Q5: 0.35 | R5: =Q5*R$4 -> 1.2054929e+08
M6: Electrical equipment | N6: 0.02 | O6: =N6*O$4 -> 2141378.5 | P6: Chemicals and chemical products | Q6: 0.25 | R6: =Q6*R$4 -> 86106634
M7: Machinery and equipment n.e.c. | N7: 0.45 | O7: =N7*O$4 -> 48181015 | P7: Legal and accounting services; services of head offices; management consultancy services | Q7: 0.2 | R7: =Q7*R$4 -> 68885307
M8: Constructions and construction works | N8: 0.15 | O8: =N8*O$4 -> 16060338 | P8: Repair and installation services of machinery and equipment | Q8: 0.15 | R8: =Q8*R$4 -> 51663980
M9: Architectural and engineering services; technical testing and analysis services | N9: 0.3 | O9: =N9*O$4 -> 32120677 | P9: Land transport services and transport services via pipelines | Q9: 0.05 | R9: =Q9*R$4 -> 17221327
M10: Computer, electronic and optical products | N10: 0.03 | O10: =N10*O$4 -> 3212067.7 | Q10: =SUM(Q5:Q9) -> 1 | R10: =SUM(R5:R9) -> 3.4442654e+08
A11: of which IVC 2 | B11: 1450 | C11: =B11*F11 -> 1.9316373e+08 | D11: 0.14 | E11: ='[2]Conversion factors selected IV '!$O$7 -> 0.95154545 | F11: =D11*E11*1000000 -> 133216.36 | G11: ='LCoP 2030 MEDIUM'!E25 -> 10674 | H11: =F11*G11 -> 1.4219515e+09 | I11: ='LCoP 2030 MEDIUM'!H25 -> 0.93685591 | L11: =I11*H11 -> 1.3321636e+09 | M11: ='LCoP 2030 MEDIUM'!F25 -> 0.025201424 | N11: =SUM(N12:N17) -> 1 | O11: =M11*H11 -> 35835202 | P11: ='LCoP 2030 MEDIUM'!G25 -> 0.037942664 | R11: =P11*H11 -> 53952627 | S11: =L11+O11+R11 -> 1.4219515e+09
H12: imported | I12: POME | J12: Food, beverages and tobacco products | K12: 850 | L12: =K12*F11 -> 1.1323391e+08 | M12: Fabricated metal products | N12: 0.05 | O12: =N12*O$11 -> 1791760.1 | P12: Electricity, gas, steam and air conditioning | Q12: 0.35 | R12: =Q12*R$11 -> 18883420
M13: Electrical equipment | N13: 0.02 | O13: =N13*O$11 -> 716704.04 | P13: Chemicals and chemical products | Q13: 0.25 | R13: =Q13*R$11 -> 13488157
M14: Machinery and equipment n.e.c. | N14: 0.45 | O14: =N14*O$11 -> 16125841 | P14: Legal and accounting services; services of head offices; management consultancy services | Q14: 0.2 | R14: =Q14*R$11 -> 10790525
M15: Constructions and construction works | N15: 0.15 | O15: =N15*O$11 -> 5375280.3 | P15: Repair and installation services of machinery and equipment | Q15: 0.15 | R15: =Q15*R$11 -> 8092894.1
M16: Architectural and engineering services; technical testing and analysis services | N16: 0.3 | O16: =N16*O$11 -> 10750561 | P16: Land transport services and transport services via pipelines | Q16: 0.05 | R16: =Q16*R$11 -> 2697631.4
M17: Computer, electronic and optical products | N17: 0.03 | O17: =N17*O$11 -> 1075056.1 | Q17: =SUM(Q12:Q16) -> 1 | R17: =SUM(R12:R16) -> 53952627
A18: of which IVC 13a | B18: 1450 | C18: =B18*F18 -> 29000000 | D18: 0.02 | E18: ='[2]Conversion factors selected IV '!$O$98 -> 1 | F18: =D18*E18*1000000 -> 20000 | G18: ='LCoP 2030 MEDIUM'!E20 -> 1598.1345 | H18: =F18*G18 -> 31962689 | I18: ='LCoP 2030 MEDIUM'!H20 -> 0.13211308 | L18: =SUM(L19:L26) -> 4222689.2 | M18: ='LCoP 2030 MEDIUM'!F20 -> 0.50371231 | O18: =M18*H18 -> 16100000 | P18: ='LCoP 2030 MEDIUM'!G20 -> 0.36417461 | R18: =P18*H18 -> 11640000 | S18: =L18+O18+R18 -> 31962689
A19: I am assuming the feedstock split to be as in 2030 medium | G19: of which | H19: domestic | I19: Straw | J19: Products of agriculture, hunting and related services | K19: ='Feedstock MIX per IVC'!G89 -> 104.52294 | L19: =K19*F$18 -> 2090458.8 | M19: Fabricated metal products | N19: 0.15 | O19: =N19*O$18 -> 2415000 | P19: Electricity, gas, steam and air conditioning | Q19: 0.15 | R19: =Q19*R$18 -> 1746000
H20: domestic | I20: Prunings & damaged crops | J20: Products of agriculture, hunting and related services | K20: ='Feedstock MIX per IVC'!G90 -> 6.0040708 | L20: =K20*F$18 -> 120081.42 | M20: Electrical equipment | N20: 0.02 | O20: =N20*O$18 -> 322000 | P20: Chemicals and chemical products | Q20: 0.25 | R20: =Q20*R$18 -> 2910000
H21: domestic | I21: Agroprocessing residues - maize cobs | J21: Food, beverages and tobacco products | K21: ='Feedstock MIX per IVC'!G91 -> 2.9289602 | L21: =K21*F$18 -> 58579.204 | M21: Machinery and equipment n.e.c. | N21: 0.45 | O21: =N21*O$18 -> 7245000 | P21: Legal and accounting services; services of head offices; management consultancy services | Q21: 0.2 | R21: =Q21*R$18 -> 2328000
H22: domestic | I22: Lignocrops abandoned degraded | J22: Products of agriculture, hunting and related services | K22: ='Feedstock MIX per IVC'!G92 -> 4.8668638 | L22: =K22*F$18 -> 97337.275 | M22: Constructions and construction works | N22: 0.1 | O22: =N22*O$18 -> 1610000 | P22: Repair and installation services of machinery and equipment | Q22: 0.3 | R22: =Q22*R$18 -> 3492000
H23: domestic | I23: Lignocrops inter & cover cropping | J23: Products of agriculture, hunting and related services | K23: ='Feedstock MIX per IVC'!G93 -> 2.2157284 | L23: =K23*F$18 -> 44314.568 | M23: Architectural and engineering services; technical testing and analysis services | N23: 0.25 | O23: =N23*O$18 -> 4025000 | P23: Land transport services and transport services via pipelines | Q23: 0.1 | R23: =Q23*R$18 -> 1164000
H24: domestic | I24: Primary forestry residues | J24: Products of forestry, logging and related services | K24: ='Feedstock MIX per IVC'!G94 -> 48.32109 | L24: =K24*F$18 -> 966421.8 | M24: Computer, electronic and optical products | N24: 0.03 | O24: =N24*O$18 -> 483000 | Q24: =SUM(Q19:Q23) -> 1 | R24: =SUM(R19:R23) -> 11640000
H25: domestic | I25: Secondary forest residues | J25: Paper and paper products | K25: ='Feedstock MIX per IVC'!G95 -> 42.274808 | L25: =K25*F$18 -> 845496.15
H26: domestic | I26: Biowastes - Post consumer wood | J26: Sewerage services; sewage sludge; waste collection, treatment and disposal services; materials recovery services; remediation services and other waste management services | K26: ='Feedstock MIX per IVC'!G96 -> 0 | L26: =K26*F$18 -> 0 | M26: =K26*F$18 -> 0
J28: TOTALS domestic | L28: =SUM(L29:L34) -> 4222689.2 | M28: TOTALS | O28: =SUM(O29:O34) -> 1.5900413e+08 | R28: =SUM(R29:R33) -> 4.1001916e+08 | S28: =S4+S11+S18 -> 1.480528e+10
J29: Products of agriculture, hunting and related services | L29: =L19+L20+L22+L23 -> 2352192.1 | M29: Fabricated metal products | O29: =O5+O12+O19 -> 9560206.3 | P29: Electricity, gas, steam and air conditioning | R29: =R5+R12+R19 -> 1.4117871e+08
J30: Paper and paper products | L30: =L25 -> 845496.15 | M30: Electrical equipment | O30: =O6+O13+O20 -> 3180082.5 | P30: Chemicals and chemical products | R30: =R6+R13+R20 -> 1.0250479e+08
G31: or does that rather come from a biofuels sector directly? | J31: Chemicals and chemical products | L31: =L13 -> 0 | M31: Machinery and equipment n.e.c. | O31: =O7+O14+O21 -> 71551856 | P31: Legal and accounting services; services of head offices; management consultancy services | R31: =R7+R14+R21 -> 82003833
J32: Food, beverages and tobacco products | L32: =L21 -> 58579.204 | M32: Constructions and construction works | O32: =O8+O15+O22 -> 23045619 | P32: Repair and installation services of machinery and equipment | R32: =R8+R15+R22 -> 63248875
J33: Sewerage services; sewage sludge; waste collection, treatment and disposal services; materials recovery services; remediation services and other waste management services | L33: =L26 -> 0 | M33: Architectural and engineering services; technical testing and analysis services | O33: =O9+O16+O23 -> 46896238 | P33: Land transport services and transport services via pipelines | R33: =R9+R16+R23 -> 21082958
J34: Products of forestry, logging and related services | L34: =L24 -> 966421.8 | M34: Computer, electronic and optical products | O34: =O10+O17+O24 -> 4770123.8
J35: TOTAL imported | L35: =L36 -> 1.2097229e+09
J36: Food, beverages and tobacco products | L36: =L12+L5 -> 1.2097229e+09
J37: ALL | L37: =L35+L28 -> 1.2139456e+09 | M37: =L28+L37+O28+R28 -> 1.7871915e+09 | N37: =M37/1000000 -> 1787.1915
A38: Advanced biogasoline
A39: TOTAL | C39: =SUM(C40:C47) -> 2.3058667e+08 | D39: =SUM(D40:D47) -> 0.15 | F39: =SUM(F40:F47) -> 221586.67 | H39: =SUM(H40:H47) -> 3.1124595e+08 | L39: =L40+L47 -> 67606625 | O39: =O40+O47 -> 127980600 | R39: =R40+R47 -> 115658720
A40: of which IVC 5 | B40: 1000 | C40: =B40*F40 -> 2.0158667e+08 | D40: 0.13 | E40: ='[2]Conversion factors selected IV '!$O$18 -> 1.5506667 | F40: =D40*E40*1000000 -> 201586.67 | G40: ='LCoP 2030 MEDIUM'!E5 -> 1385.4252 | H40: =F40*G40 -> 2.7928326e+08 | I40: ='LCoP 2030 MEDIUM'!H5 -> 0.22695215 | L40: =I40*H40 -> 63383936 | M40: ='LCoP 2030 MEDIUM'!F5 -> 0.40059902 | O40: =M40*H40 -> 111880600 | P40: ='LCoP 2030 MEDIUM'!G5 -> 0.37244882 | R40: =P40*H40 -> 104018720 | S40: =L40+O40+R40 -> 2.7928326e+08
H41: domestic | I41: Straw | J41: Products of agriculture, hunting and related services | K41: ='Feedstock MIX per IVC'!G13 -> 228.35941 | L41: =K41*F$40 -> 46034213 | M41: Fabricated metal products | N41: 0 | O41: =N41*O$40 -> 0 | P41: Electricity, gas, steam and air conditioning | Q41: 0.2 | R41: =Q41*R$40 -> 20803744
H42: domestic | I42: Lignocrops abandoned degraded | J42: Products of agriculture, hunting and related services | K42: ='Feedstock MIX per IVC'!G14 -> 10.633017 | L42: =K42*F$40 -> 2143474.4 | M42: Electrical equipment | N42: 0.02 | O42: =N42*O$40 -> 2237612 | P42: Chemicals and chemical products | Q42: 0.5 | R42: =Q42*R$40 -> 52009360
H43: domestic | I43: Lignocrops inter & cover cropping | J43: Products of agriculture, hunting and related services | K43: ='Feedstock MIX per IVC'!G15 -> 4.8408745 | L43: =K43*F$40 -> 975855.76 | M43: Machinery and equipment n.e.c. | N43: 0.5 | O43: =N43*O$40 -> 55940300 | P43: Legal and accounting services; services of head offices; management consultancy services | Q43: 0.15 | R43: =Q43*R$40 -> 15602808
H44: domestic | I44: Secondary forest residues | J44: Paper and paper products | K44: ='Feedstock MIX per IVC'!G16 -> 70.591935 | L44: =K44*F$40 -> 14230393 | M44: Constructions and construction works | N44: 0.15 | O44: =N44*O$40 -> 16782090 | P44: Repair and installation services of machinery and equipment | Q44: 0.1 | R44: =Q44*R$40 -> 10401872
M45: Architectural and engineering services; technical testing and analysis services | N45: 0.3 | O45: =N45*O$40 -> 33564180 | P45: Land transport services and transport services via pipelines | Q45: 0.05 | R45: =Q45*R$40 -> 5200936
M46: Computer, electronic and optical products | N46: 0.03 | O46: =N46*O$40 -> 3356418 | Q46: =SUM(Q41:Q45) -> 1 | R46: =SUM(R41:R45) -> 104018720
A47: of which IVC 13a | B47: 1450 | C47: =B47*F47 -> 29000000 | D47: =0.04/2 -> 0.02 | E47: ='[2]Conversion factors selected IV '!$O$89 -> 1 | F47: =D47*E47*1000000 -> 20000 | G47: ='LCoP 2030 MEDIUM'!E20 -> 1598.1345 | H47: =F47*G47 -> 31962689 | I47: ='LCoP 2030 MEDIUM'!H20 -> 0.13211308 | K47: =SUM(K48:K55) -> 211.13446 | L47: =I47*H47 -> 4222689.2 | M47: ='LCoP 2030 MEDIUM'!F20 -> 0.50371231 | O47: =M47*H47 -> 16100000 | P47: ='LCoP 2030 MEDIUM'!G20 -> 0.36417461 | R47: =P47*H47 -> 11640000 | S47: =L47+O47+R47 -> 31962689
H48: domestic | I48: Straw | J48: Products of agriculture, hunting and related services | K48: ='Feedstock MIX per IVC'!G89 -> 104.52294 | L48: =K48*$F$47 -> 2090458.8 | M48: Fabricated metal products | N48: 0.15 | O48: =N48*O$47 -> 2415000 | P48: Electricity, gas, steam and air conditioning | Q48: 0.15 | R48: =Q48*R$47 -> 1746000
H49: domestic | I49: Prunings & damaged crops | J49: Products of agriculture, hunting and related services | K49: ='Feedstock MIX per IVC'!G90 -> 6.0040708 | L49: =K49*$F$47 -> 120081.42 | M49: Electrical equipment | N49: 0.02 | O49: =N49*O$47 -> 322000 | P49: Chemicals and chemical products | Q49: 0.25 | R49: =Q49*R$47 -> 2910000
H50: domestic | I50: Agroprocessing residues - maize cobs | J50: Food, beverages and tobacco products | K50: ='Feedstock MIX per IVC'!G91 -> 2.9289602 | L50: =K50*$F$47 -> 58579.204 | M50: Machinery and equipment n.e.c. | N50: 0.45 | O50: =N50*O$47 -> 7245000 | P50: Legal and accounting services; services of head offices; management consultancy services | Q50: 0.2 | R50: =Q50*R$47 -> 2328000
H51: domestic | I51: Lignocrops abandoned degraded | J51: Products of agriculture, hunting and related services | K51: ='Feedstock MIX per IVC'!G92 -> 4.8668638 | L51: =K51*$F$47 -> 97337.275 | M51: Constructions and construction works | N51: 0.1 | O51: =N51*O$47 -> 1610000 | P51: Repair and installation services of machinery and equipment | Q51: 0.3 | R51: =Q51*R$47 -> 3492000
H52: domestic | I52: Lignocrops inter & cover cropping | J52: Products of agriculture, hunting and related services | K52: ='Feedstock MIX per IVC'!G93 -> 2.2157284 | L52: =K52*$F$47 -> 44314.568 | M52: Architectural and engineering services; technical testing and analysis services | N52: 0.25 | O52: =N52*O$47 -> 4025000 | P52: Land transport services and transport services via pipelines | Q52: 0.1 | R52: =Q52*R$47 -> 1164000
H53: domestic | I53: Primary forestry residues | J53: Products of forestry, logging and related services | K53: ='Feedstock MIX per IVC'!G94 -> 48.32109 | L53: =K53*$F$47 -> 966421.8 | M53: Computer, electronic and optical products | N53: 0.03 | O53: =N53*O$47 -> 483000 | Q53: =SUM(Q48:Q52) -> 1 | R53: =SUM(R48:R52) -> 11640000
H54: domestic | I54: Secondary forest residues | J54: Paper and paper products | K54: ='Feedstock MIX per IVC'!G95 -> 42.274808 | L54: =K54*$F$47 -> 845496.15
H55: domestic | I55: Biowastes - Post consumer wood | J55: Sewerage services; sewage sludge; waste collection, treatment and disposal services; materials recovery services; remediation services and other waste management services | K55: ='Feedstock MIX per IVC'!G96 -> 0 | L55: =K55*$F$47 -> 0
J56: TOTALS domestic | L56: =SUM(L57:L62) -> 67606625 | M56: TOTALS | O56: =O40+O47 -> 127980600 | R56: =SUM(R57:R61) -> 115658720
I57: of which | J57: Products of agriculture, hunting and related services | L57: =L41+L42+L43+L48+L49+L51+L52 -> 51505735 | M57: Fabricated metal products | O57: =O41+O48 -> 2415000 | P57: Electricity, gas, steam and air conditioning | R57: =R41+R48 -> 22549744
J58: Paper and paper products | L58: =L44+L54 -> 15075889 | M58: Electrical equipment | O58: =O42+O49 -> 2559612 | P58: Chemicals and chemical products | R58: =R42+R49 -> 54919360
J59: Chemicals and chemical products | L59: =0 -> 0 | M59: Machinery and equipment n.e.c. | O59: =O43+O50 -> 63185300 | P59: Legal and accounting services; services of head offices; management consultancy services | R59: =R43+R50 -> 17930808
J60: Food, beverages and tobacco products | L60: =L50 -> 58579.204 | M60: Constructions and construction works | O60: =O44+O51 -> 18392090 | P60: Repair and installation services of machinery and equipment | R60: =R44+R51 -> 13893872
J61: Sewerage services; sewage sludge; waste collection, treatment and disposal services; materials recovery services; remediation services and other waste management services | L61: =L55 -> 0 | M61: Architectural and engineering services; technical testing and analysis services | O61: =O45+O52 -> 37589180 | P61: Land transport services and transport services via pipelines | R61: =R45+R52 -> 6364936
J62: Products of forestry, logging and related services | L62: =L53 -> 966421.8 | M62: Computer, electronic and optical products | O62: =O46+O53 -> 3839418
A63: Advanced biogas
A64: TOTAL | C64: =C65 -> 1.3868147e+08 | D64: 0.13 | F64: =F65 -> 108769.78 | H64: =H65 -> 1.1142578e+08
A65: of which IVC 7 | B65: 1275 | C65: =B65*F65 -> 1.3868147e+08 | D65: 0.13 | E65: ='[2]Conversion factors selected IV '!$O$29 -> 0.83669065 | F65: =D65*E65*1000000 -> 108769.78 | G65: ='LCoP 2030 MEDIUM'!E10 -> 1024.4185 | H65: =F65*G65 -> 1.1142578e+08 | I65: ='LCoP 2030 MEDIUM'!H10 -> -0.020579023 | L65: =I65*H65 -> -2293033.6 | M65: ='LCoP 2030 MEDIUM'!F10 -> 0.59057897 | O65: =M65*H65 -> 65805719 | P65: ='LCoP 2030 MEDIUM'!G10 -> 0.43000006 | R65: =P65*H65 -> 47913090 | S65: =L65+O65+R65 -> 1.1142578e+08
H66: domestic | I66: Prunings & damaged crops (olive stones excluded) | J66: Products of agriculture, hunting and related services | K66: ='Feedstock MIX per IVC'!G25 -> 0.84774671 | L66: =K66*$F$65 -> 92209.227 | M66: Fabricated metal products | N66: 0.05 | O66: =N66*$O$65 -> 3290286 | P66: Electricity, gas, steam and air conditioning | Q66: 0.2 | R66: =Q66*R$65 -> 9582618
H67: domestic | I67: Lignocrops abandoned degraded | J67: Products of agriculture, hunting and related services | K67: ='Feedstock MIX per IVC'!G26 -> 0.6871784 | L67: =K67*$F$65 -> 74744.246 | M67: Electrical equipment | N67: 0.02 | O67: =N67*$O$65 -> 1316114.4 | P67: Chemicals and chemical products | Q67: 0.5 | R67: =Q67*R$65 -> 23956545
H68: domestic | I68: Lignocrops inter & cover cropping | J68: Products of agriculture, hunting and related services | K68: ='Feedstock MIX per IVC'!G27 -> 0.31285048 | L68: =K68*$F$65 -> 34028.679 | M68: Machinery and equipment n.e.c. | N68: 0.4 | O68: =N68*$O$65 -> 26322288 | P68: Legal and accounting services; services of head offices; management consultancy services | Q68: 0.15 | R68: =Q68*R$65 -> 7186963.5
H69: domestic | I69: Agroprocessing residues | J69: Food, beverages and tobacco products | K69: ='Feedstock MIX per IVC'!G28 -> 3.9186047 | L69: =K69*$F$65 -> 426225.79 | M69: Constructions and construction works | N69: 0.3 | O69: =N69*$O$65 -> 19741716 | P69: Repair and installation services of machinery and equipment | Q69: 0.1 | R69: =Q69*R$65 -> 4791309
H70: domestic | I70: Straw | J70: Products of agriculture, hunting and related services | K70: ='Feedstock MIX per IVC'!G29 -> 14.75815 | L70: =K70*$F$65 -> 1605240.8 | M70: Architectural and engineering services; technical testing and analysis services | N70: 0.2 | O70: =N70*$O$65 -> 13161144 | P70: Land transport services and transport services via pipelines | Q70: 0.05 | R70: =Q70*R$65 -> 2395654.5
H71: domestic | I71: Manure | J71: Products of agriculture, hunting and related services | K71: ='Feedstock MIX per IVC'!G30 -> 0 | L71: =K71*$F$65 -> 0 | M71: Computer, electronic and optical products | N71: 0.03 | O71: =N71*$O$65 -> 1974171.6 | Q71: =SUM(Q66:Q70) -> 1 | R71: =Q71*R$65 -> 47913090
H72: domestic | I72: Sewage sludge | J72: Sewerage services; sewage sludge; waste collection, treatment and disposal services; materials recovery services; remediation services and other waste management services | K72: ='Feedstock MIX per IVC'!G31 -> 0 | L72: =K72*$F$65 -> 0 | N72: =SUM(N66:N71) -> 1 | O72: =SUM(O66:O71) -> 65805719
H73: domestic | I73: Biowastes (post consumer woods excluded) | J73: Sewerage services; sewage sludge; waste collection, treatment and disposal services; materials recovery services; remediation services and other waste management services | K73: ='Feedstock MIX per IVC'!G32 -> -42.314992 | L73: =K73*$F$65 -> -4602592.6
H74: domestic | I74: Intermediate Bioenergy carrier (crude glycerine) | J74: Chemical and chemical products | K74: ='Feedstock MIX per IVC'!G33 -> 0.70893032 | L74: =K74*$F$65 -> 77110.198
J75: TOTALS | L75: =SUM(L76:L80) -> -2293033.6 | M75: TOTALS | O75: =O65 -> 65805719 | R75: =R65 -> 47913090
I76: of which | J76: Products of agriculture, hunting and related services | L76: =L66+L67+L68+L70+L71 -> 1806223 | M76: Fabricated metal products | O76: =O66 -> 3290286 | P76: Electricity, gas, steam and air conditioning | R76: =R66 -> 9582618
J77: Paper and paper products | L77: =0 -> 0 | M77: Electrical equipment | O77: =O67 -> 1316114.4 | P77: Chemicals and chemical products | R77: =R67 -> 23956545
J78: Chemical and chemical products | L78: =L74 -> 77110.198 | M78: Machinery and equipment n.e.c. | O78: =O68 -> 26322288 | P78: Legal and accounting services; services of head offices; management consultancy services | R78: =R68 -> 7186963.5
J79: Food, beverages and tobacco products | L79: =L69 -> 426225.79 | M79: Constructions and construction works | O79: =O69 -> 19741716 | P79: Repair and installation services of machinery and equipment | R79: =R69 -> 4791309
G80: include this as a SELLING product in the IO | J80: Sewerage services; sewage sludge; waste collection, treatment and disposal services; materials recovery services; remediation services and other waste management services | L80: =L72+L73 -> -4602592.6 | M80: Architectural and engineering services; technical testing and analysis services | O80: =O70 -> 13161144 | P80: Land transport services and transport services via pipelines | R80: =R70 -> 2395654.5
L81: =SUM(L76:L79) -> 2309558.9 | M81: Computer, electronic and optical products | O81: =O71 -> 1974171.6
A82: Conventional biodiesel
A83: TOTAL | C83: =SUM(C84:C98) -> 1.5963965e+10 | D83: =SUM(D84:D98) -> 12.938449 | E83: 1.1627907 | F83: =SUM(F84:F98) -> 13695614 | H83: =H84+H91+H98 -> 10982503260 | L83: =L84+L91+L98 -> 7941942282 | O83: =O84+O91+O98 -> 835722326 | R83: =R84+R91+R98 -> 2204838652
A84: transestification of food/ feed crops | B84: 1165.6261 | C84: =B84*F84 -> 6.0612559e+09 | D84: ='[1]GAP analysis Sc. 1'!$G$18 -> 4.5953951 | E84: ='[2]Conversion factors selected IV '!$O$4 -> 1.1315676 | F84: =D84*E84*1000000 -> 5200000 | G84: 629 | H84: =G84*F84 -> 3.2708e+09 | I84: 0.75 | K84: =I84*G84 -> 471.75 | L84: =I84*H84 -> 2.4531e+09 | M84: 0.065 | O84: =M84*H84 -> 2.12602e+08 | P84: 0.185 | R84: =P84*H84 -> 6.05098e+08
H85: domestic | I85: rapeseed oil | J85: Food, beverages and tobacco products | K85: ='Feedtstocks only CONVENTIONAL'!$J$4 -> 0.76052615 | L85: =K85*L$84 -> 1.8656467e+09 | M85: Machinery and equipment | N85: 0.45 | O85: =N85*$O$84 -> 95670900 | P85: Chemical and chemical products | Q85: 0.3 | R85: =Q85*R$84 -> 1.815294e+08
F86: NOTE: made of imported soybeans, pick up in discussion | H86: domestic | I86: soybean oil | J86: Food, beverages and tobacco products | K86: ='Feedtstocks only CONVENTIONAL'!$J$5 -> 0.16011077 | L86: =K86*L$84 -> 3.9276773e+08 | M86: Architectural and engineering services | N86: 0.3 | O86: =N86*$O$84 -> 63780600 | P86: Electricity, gas, steam & AC | Q86: 0.2 | R86: =Q86*R$84 -> 1.210196e+08
H87: domestic | I87: sunflower oil | J87: Food, beverages and tobacco products | K87: ='Feedtstocks only CONVENTIONAL'!$J$6 -> 0.040027692 | L87: =K87*L$84 -> 98191932 | M87: Constructions and construction works | N87: 0.15 | O87: =N87*$O$84 -> 31890300 | P87: Legal and accounting services; services of head offices; management consultancy services | Q87: 0.25 | R87: =Q87*R$84 -> 1.512745e+08
H88: imported | I88: palm oil | J88: Food, beverages and tobacco products | K88: ='Feedtstocks only CONVENTIONAL'!$J$7 -> 0.039335389 | L88: =K88*L$84 -> 96493643 | M88: Fabricated metal products | N88: 0.07 | O88: =N88*$O$84 -> 14882140 | P88: Repair and installation services | Q88: 0.15 | R88: =Q88*R$84 -> 90764700
M89: Computer, electronic and optical products | N89: 0.03 | O89: =N89*$O$84 -> 6378060 | P89: Land transport services and transport services via pipelines | Q89: 0.1 | R89: =Q89*R$84 -> 60509800
P90: Sewerage services; sewage sludge; waste collection, treatment and disposal services; materials recovery services; remediation services and other waste management services | Q90: 0 | R90: =Q90*R$84 -> 0
A91: transestification of UCO and AF | B91: 1165.6261 | C91: =B91*F91 -> 4.0796915e+09 | D91: ='[1]GAP analysis Sc. 1'!$G$23 -> 3.0930544 | E91: ='[2]Conversion factors selected IV '!$O$4 -> 1.1315676 | F91: =D91*E91*1000000 -> 3500000 | G91: ='LCoP CONVENTIONAL'!B17 -> 1253 | H91: =G91*F91 -> 4385500000 | I91: ='LCoP CONVENTIONAL'!C17 -> 0.72067039 | K91: ='Feedtstocks only CONVENTIONAL'!I15 -> 853.09425 | L91: =H91*I91 -> 3160500000 | M91: ='LCoP CONVENTIONAL'!F17 -> 0.066241022 | O91: =M91*H91 -> 290500000 | P91: ='LCoP CONVENTIONAL'!I17 -> 0.21308859 | R91: =P91*H91 -> 934500000
H92: domestic | I92: UCO domestic | J92: Food, beverages and tobacco products | K92: ='Feedtstocks only CONVENTIONAL'!J37 -> 0.42676656 | L92: =K92*L91 -> 1.3487957e+09 | M92: Machinery and equipment | N92: 0.5 | O92: =N92*O$91 -> 145250000 | P92: Chemical and chemical products | Q92: 0.25 | R92: =Q92*R$91 -> 233625000 | S92: Electricity, gas, steam and air conditioning
H93: imported | I93: UCO imported | J93: Food, beverages and tobacco products | K93: ='Feedtstocks only CONVENTIONAL'!J38 -> 0.28451104 | L93: =K93*L91 -> 8.9919714e+08 | M93: Architectural and engineering services | N93: 0.3 | O93: =N93*O$91 -> 87150000 | P93: Electricity, gas, steam & AC | Q93: 0.15 | R93: =Q93*R$91 -> 140175000 | S93: Chemicals and chemical products
H94: domestic | I94: animal fats | J94: Food, beverages and tobacco products | K94: ='Feedtstocks only CONVENTIONAL'!J39 -> 0.2887224 | L94: =K94*L91 -> 9.1250714e+08 | M94: Constructions and construction works | N94: 0.1 | O94: =N94*O$91 -> 29050000 | P94: Legal and accounting services; services of head offices; management consultancy services | Q94: 0.2 | R94: =Q94*R$91 -> 186900000 | S94: Legal and accounting services; services of head offices; management consultancy services
K95: =SUM(K92:K94) -> 1 | L95: =SUM(L92:L94) -> 3160500000 | M95: Fabricated metal products | N95: 0.07 | O95: =N95*O$91 -> 20335000 | P95: Repair and installation services | Q95: 0.2 | R95: =Q95*R$91 -> 186900000 | S95: Repair and installation services of machinery and equipment
M96: Computer, electronic and optical products | N96: 0.03 | O96: =N96*O$91 -> 8715000 | P96: Land transport services and transport services via pipelines | Q96: 0.1 | R96: =Q96*R$91 -> 93450000 | S96: Land transport services and transport services via pipelines
K97: from: | P97: Sewerage services; sewage sludge; waste collection, treatment and disposal services; materials recovery services; remediation services and other waste management services | Q97: 0.1 | R97: =Q97*R$91 -> 93450000
A98: hydrotreatment of food/ feed crops | B98: 1165.6261 | C98: =B98*F98 -> 5.8230178e+09 | D98: 5.25 | E98: ='[2]Conversion factors selected IV '!$O$7 -> 0.95154545 | F98: =D98*E98*1000000 -> 4995613.6 | G98: =K98/7*10 -> 665.82476 | H98: =G98*F98 -> 3.3262033e+09 | I98: 0.7 | K98: ='Feedtstocks only CONVENTIONAL'!I22 -> 466.07733 | L98: =I98*H98 -> 2328342282 | M98: 0.1 | O98: =M98*H98 -> 3.3262033e+08 | P98: 0.2 | R98: =P98*H98 -> 6.6524065e+08
H99: domestic | I99: rapeseed oil | J99: Food, beverages and tobacco products | K99: ='Feedtstocks only CONVENTIONAL'!J$4 -> 0.76052615 | L99: =K99*L$98 -> 1770765192 | M99: Machinery and equipment | N99: 0.55 | O99: =N99*O$98 -> 1.8294118e+08 | P99: Chemical and chemical products | Q99: 0.4 | R99: =Q99*R$98 -> 2.6609626e+08
F100: NOTE: made of imported soybeans, pick up in discussion | H100: domestic | I100: soybean oil | J100: Food, beverages and tobacco products | K100: ='Feedtstocks only CONVENTIONAL'!J$5 -> 0.16011077 | L100: =K100*L$98 -> 372792672 | M100: Architectural and engineering services | N100: 0.25 | O100: =N100*O$98 -> 83155082 | P100: Electricity, gas, steam & AC | Q100: 0.2 | R100: =Q100*R$98 -> 1.3304813e+08
H101: domestic | I101: sunflower oil | J101: Food, beverages and tobacco products | K101: ='Feedtstocks only CONVENTIONAL'!J$6 -> 0.040027692 | L101: =K101*L$98 -> 93198168 | M101: Constructions and construction works | N101: 0.1 | O101: =N101*O$98 -> 33262033 | P101: Legal and accounting services; services of head offices; management consultancy services | Q101: 0.2 | R101: =Q101*R$98 -> 1.3304813e+08
...

Sheet 2030 costs Sc 1
A1: Contribution of each IVC to final product in Scenario (1) 2030
A2: Assumptions:
A3: technical capacity = cmc | E3: feedstock availability: 2030 medium
A4: Market value of ALLL biofule production | C4: =C6+C196+C225+C274+C283 -> 3.7066586e+10
B5: market price [€/t] | C5: makret value of overall amount produced | D5: produced in Mtoe | E5: Conversion factor [t/toe] | F5: produced in t | G5: Cost of production [€/t] | H5: Money spent on each IVC | I5: Feedstock share of costs | J5: Eurostat sector | K5: money [€] spent on each feedtsock when producing 1t of product | L5: Absolute feedstock costs [€] | M5: CAPEX share of costs | N5: CAPEX distribution | O5: Absoluet CAPEX [€] | P5: OPEX share of costs | R5: Absolute OPEX [€] | S5: TOTAL production costs
A6: SUMME ALL advanced | C6: =C8+C44+C86+C120+C154 -> 1.0819763e+10 | D6: =D8+D44+D86+D120+D154 -> 7.3763477
A7: Advanced biodiesel
A8: TOTAL | B8: =C8/1000000 -> 3061.585 | C8: =C9+C23+C16 -> 3.061585e+09 | D8: =D9+D23+D43+D16 -> 1.8575045 | F8: =F9+F23+F16 -> 2040905.7 | H8: =H9+H23+H16 -> 2.7528869e+09 | L8: =L9+L16+L23 -> 1.8846907e+09 | O8: =O9+O16+O23+#REF! -> #REF! | R8: =R9+R16+R23+#REF! -> #REF!
A9: of which IVC 1 | B9: 1450 | C9: =B9*F9 -> 2.465e+09 | D9: ='[1]GAP analysis Sc. 1'!$P$55+'[1]GAP analysis Sc. 1'!$P$68 -> 1.5023407 | E9: ='[2]Conversion factors selected IV '!$O$4 -> 1.1315676 | F9: =D9*E9*1000000 -> 1700000 | G9: ='LCoP 2030 MEDIUM'!E2 -> 1350 | H9: =G9*F9 -> 2.295e+09 | I9: ='LCoP 2030 MEDIUM'!H2 -> 0.74074074 | L9: =I9*H9 -> 1.7e+09 | M9: ='LCoP 2030 MEDIUM'!F2 -> 0.061481481 | O9: =M9*H9 -> 1.411e+08 | P9: ='LCoP 2030 MEDIUM'!G2 -> 0.19777778 | R9: =P9*H9 -> 4.539e+08 | S9: =SUM(S10:S15) -> 0 | T9: =L9+O9+R9 -> 2.295e+09
C10: =C9/C8 -> 0.80513852 | H10: imported | I10: POME | J10: Food, beverages and tobacco products | K10: 1000 | L10: =K10*F9 -> 1.7e+09 | M10: Fabricated metal products | N10: 0.05 | O10: =N10*O$9 -> 7055000 | P10: Electricity, gas, steam and air conditioning | Q10: 0.35 | R10: =Q10*R$9 -> 1.58865e+08
M11: Electrical equipment | N11: 0.02 | O11: =N11*O$9 -> 2822000 | P11: Chemicals and chemical products | Q11: 0.25 | R11: =Q11*R$9 -> 1.13475e+08
M12: Machinery and equipment n.e.c. | N12: 0.45 | O12: =N12*O$9 -> 63495000 | P12: Legal and accounting services; services of head offices; management consultancy services | Q12: 0.2 | R12: =Q12*R$9 -> 90780000
M13: Constructions and construction works | N13: 0.15 | O13: =N13*O$9 -> 21165000 | P13: Repair and installation services of machinery and equipment | Q13: 0.15 | R13: =Q13*R$9 -> 68085000
M14: Architectural and engineering services; technical testing and analysis services | N14: 0.3 | O14: =N14*O$9 -> 42330000 | P14: Land transport services and transport services via pipelines | Q14: 0.05 | R14: =Q14*R$9 -> 22695000
M15: Computer, electronic and optical products | N15: 0.03 | O15: =N15*O$9 -> 4233000
A16: of which IVC 2 HVO | B16: 1750 | C16: =B16*F16 -> 4.9e+08 | D16: ='[1]GAP analysis Sc. 1'!$P$56+'[1]GAP analysis Sc. 1'!$P$69 -> 0.29425814 | E16: ='[2]Conversion factors selected IV '!$O$7 -> 0.95154545 | F16: =D16*E16*1000000 -> 280000 | G16: ='LCoP 2030 MEDIUM'!E3 -> 1287.6835 | H16: =G16*F16 -> 3.6055137e+08 | I16: ='LCoP 2030 MEDIUM'!H3 -> 0.47657943 | L16: =I16*H16 -> 1.7183137e+08 | M16: ='LCoP 2030 MEDIUM'!F3 -> 0.20890227 | O16: =M16*H16 -> 75320000 | P16: ='LCoP 2030 MEDIUM'!G3 -> 0.31451829 | R16: =P16*H16 -> 1.134e+08 | S16: =L16+O16+R16 -> 3.6055137e+08
C17: =C16/C8 -> 0.16004782 | H17: domestic | I17: Tall oil | J17: Products of agriculture, hunting and related services | K17: ='Feedstock MIX per IVC'!G6 -> 88.966549 | L17: =K17*$F$16 -> 24910634 | M17: Fabricated metal products | N17: 0.05 | O17: =N17*O$16 -> 3766000 | P17: Electricity, gas, steam and air conditioning | Q17: 0.35 | R17: =Q17*R$16 -> 39690000
I18: FPBO (Intermediate bioenergy carrier) | J18: Advanced biodiesel | K18: ='Feedstock MIX per IVC'!G7*0.85 -> 446.00937 | L18: =K18*$F$16 -> 1.2488262e+08 | M18: Electrical equipment | N18: 0.02 | O18: =N18*O$16 -> 1506400 | P18: Chemicals and chemical products | Q18: 0.25 | R18: =Q18*R$16 -> 28350000
I19: biocrude (Intermediate Bioenergy carrier) | J19: Chemicals and chemical products | K19: ='Feedstock MIX per IVC'!G7*0.15 -> 78.707535 | L19: =K19*$F$16 -> 22038110 | M19: Machinery and equipment n.e.c. | N19: 0.45 | O19: =N19*O$16 -> 33894000 | P19: Legal and accounting services; services of head offices; management consultancy services | Q19: 0.2 | R19: =Q19*R$16 -> 22680000
L20: =SUM(L17:L19) -> 1.7183137e+08 | M20: Constructions and construction works | N20: 0.15 | O20: =N20*O$16 -> 11298000 | P20: Repair and installation services of machinery and equipment | Q20: 0.15 | R20: =Q20*R$16 -> 17010000
M21: Architectural and engineering services; technical testing and analysis services | N21: 0.3 | O21: =N21*O$16 -> 22596000 | P21: Land transport services and transport services via pipelines | Q21: 0.05 | R21: =Q21*R$16 -> 5670000
M22: Computer, electronic and optical products | N22: 0.03 | O22: =N22*O$16 -> 2259600
A23: of which 13a (half) | B23: 1750 | C23: =B23*F23 -> 1.0658498e+08 | D23: ='[1]GAP analysis Sc. 1'!$P$57 -> 0.060905704 | E23: ='[2]Conversion factors selected IV '!$O$89 -> 1 | F23: =D23*E23*1000000 -> 60905.704 | G23: ='LCoP 2030 MEDIUM'!E20 -> 1598.1345 | H23: =G23*F23 -> 97335504 | I23: ='LCoP 2030 MEDIUM'!H20 -> 0.13211308 | L23: =I23*H23 -> 12859293 | M23: ='LCoP 2030 MEDIUM'!F20 -> 0.50371231 | O23: =M23*H23 -> 49029091 | P23: ='LCoP 2030 MEDIUM'!G20 -> 0.36417461 | R23: =P23*H23 -> 35447120 | S23: =L23+O23+R23 -> 97335504
C24: =C23/C8 -> 0.034813661 | F24: Products of agriculture, hunting and related services | G24: =L27/L21 -> #DIV/0! | H24: domestic | I24: Straw | J24: Products of agriculture, hunting and related services | K24: ='Feedstock MIX per IVC'!G89 -> 104.52294 | L24: =K24*F$23 -> 6366043.2 | M24: Fabricated metal products | N24: 0.15 | O24: =N24*O$23 -> 7354363.7 | P24: Electricity, gas, steam and air conditioning | Q24: 0.15 | R24: =Q24*R$23 -> 5317067.9
F25: Food, beverages and tobacco products | G25: =L26/L23 -> 0.013872488 | H25: domestic | I25: Prunings & damaged crops | J25: Products of agriculture, hunting and related services | K25: ='Feedstock MIX per IVC'!G90 -> 6.0040708 | L25: =K25*F$23 -> 365682.16 | M25: Electrical equipment | N25: 0.02 | O25: =N25*O$23 -> 980581.83 | P25: Chemicals and chemical products | Q25: 0.25 | R25: =Q25*R$23 -> 8861779.9
F26: Products of forestry, logging and related services | G26: =L29/L23 -> 0.22886406 | H26: domestic | I26: Agroprocessing residues - maize cobs | J26: Food, beverages and tobacco products | K26: ='Feedstock MIX per IVC'!G91 -> 2.9289602 | L26: =K26*F$23 -> 178390.38 | M26: Machinery and equipment n.e.c. | N26: 0.45 | O26: =N26*O$23 -> 22063091 | P26: Legal and accounting services; services of head offices; management consultancy services | Q26: 0.2 | R26: =Q26*R$23 -> 7089423.9
F27: Paper and paper products | G27: =L30/L23 -> 0.20022694 | H27: domestic | I27: Lignocrops abandoned degraded | J27: Products of agriculture, hunting and related services | K27: ='Feedstock MIX per IVC'!G92 -> 4.8668638 | L27: =K27*F$23 -> 296419.76 | M27: Constructions and construction works | N27: 0.1 | O27: =N27*O$23 -> 4902909.1 | P27: Repair and installation services of machinery and equipment | Q27: 0.3 | R27: =Q27*R$23 -> 10634136
F28: Sewerage services; sewage sludge; waste collection, treatment and disposal services; materials recovery services; remediation services and other waste management services | G28: =L31/L23 -> 0 | H28: domestic | I28: Lignocrops inter & cover cropping | J28: Products of agriculture, hunting and related services | K28: ='Feedstock MIX per IVC'!G93 -> 2.2157284 | L28: =K28*F$23 -> 134950.5 | M28: Architectural and engineering services; technical testing and analysis services | N28: 0.25 | O28: =N28*O$23 -> 12257273 | P28: Land transport services and transport services via pipelines | Q28: 0.1 | R28: =Q28*R$23 -> 3544712
H29: domestic | I29: Primary forestry residues | J29: Products of forestry, logging and related services | K29: ='Feedstock MIX per IVC'!G94 -> 48.32109 | L29: =K29*F$23 -> 2943030 | M29: Computer, electronic and optical products | N29: 0.03 | O29: =N29*O$23 -> 1470872.7 | Q29: =SUM(Q24:Q28) -> 1
H30: domestic | I30: Secondary forest residues | J30: Paper and paper products | K30: ='Feedstock MIX per IVC'!G95 -> 42.274808 | L30: =K30*F$23 -> 2574776.9
H31: domestic | I31: Biowastes - Post consumer wood | J31: Sewerage services; sewage sludge; waste collection, treatment and disposal services; materials recovery services; remediation services and other waste management services | K31: ='Feedstock MIX per IVC'!G96 -> 0 | L31: =K31*F$23 -> 0
I32: SUM | L32: =SUM(L34:L42) -> 1.8846907e+09 | S32: =SUM(S34:S42) -> #REF!
I33: TOTALS domestic | M33: TOTALS | O33: =SUM(O34:O39) -> #REF! | P33: TOTALS | R33: =SUM(R34:R38) -> #REF! | S33: CHECKED; ALL FINE
J34: Products of agriculture, hunting and related services | L34: =SUMIF($J$17:$J$31, J34, $L$17:$L$31) -> 32073729 | M34: Fabricated metal products | O34: =O10+O17+#REF!+O24 -> #REF! | P34: Electricity, gas, steam and air conditioning | R34: =R10+R17+R24+#REF! -> #REF! | S34: =R34/$H$8 -> #REF!
J35: Products of forestry, logging and related services | L35: =SUMIF($J$17:$J$31, J35, $L$17:$L$31) -> 2943030 | M35: Electrical equipment | O35: =O11+O18+#REF!+O25 -> #REF! | P35: Chemicals and chemical products | R35: =R11+R18+R25+#REF! -> #REF! | S35: =R35/$H$8 -> #REF! | T35: =L32+O33+R33 -> #REF!
J36: Paper and paper products | L36: =SUMIF($J$17:$J$31, J36, $L$17:$L$31) -> 2574776.9 | M36: Machinery and equipment n.e.c. | O36: =O12+O19+#REF!+O26 -> #REF! | P36: Legal and accounting services; services of head offices; management consultancy services | R36: =R12+R19+R26+#REF! -> #REF! | S36: =R36/$H$8 -> #REF!
J37: Food, beverages and tobacco products | L37: =SUMIF($J$17:$J$31, J37, $L$17:$L$31) -> 178390.38 | M37: Constructions and construction works | O37: =O13+O20+#REF!+O27 -> #REF! | P37: Repair and installation services of machinery and equipment | R37: =R13+R20+R27+#REF! -> #REF! | S37: =R37/$H$8 -> #REF!
J38: Sewerage services; sewage sludge; waste collection, treatment and disposal services; materials recovery services; remediation services and other waste management services | L38: =SUMIF($J$17:$J$31, J38, $L$17:$L$31) -> 0 | M38: Architectural and engineering services; technical testing and analysis services | O38: =O14+O21+#REF!+O28 -> #REF! | P38: Land transport services and transport services via pipelines | R38: =R14+R21+R28+#REF! -> #REF! | S38: =R38/$H$8 -> #REF!
J39: Chemicals and chemical products | L39: =SUMIF($J$17:$J$31, J39, $L$17:$L$31) -> 22038110 | M39: Computer, electronic and optical products | O39: =O15+O22+#REF!+O29 -> #REF!
J40: Advanced biodiesel | L40: =SUMIF($J$17:$J$31, J40, $L$17:$L$31) -> 1.2488262e+08
I41: TOTALS imported
J42: Food, beverages and tobacco products | L42: =L10 -> 1.7e+09
A43: Advanced biogasoline
B44: =C44/1000000 -> 615.78122 | C44: =C45+C52+C59+C68 -> 6.1578122e+08 | D44: =D45+D52+D59+D68 -> 0.39452385 | F44: =F45+F52+F59+F68 -> 567056.66 | H44: =H45+H52+H59+H68 -> 7.1205405e+08 | L44: =L45+L52+L59+L68 -> 1.7054167e+08 | O44: =O45+O52+O59+O68 -> 2.6725193e+08 | R44: =R45+R52+R59+R68 -> 2.7426045e+08
A45: of which from IVC 5 | B45: 1000 | C45: =B45*F45 -> 2.5e+08 | D45: ='[1]GAP analysis Sc. 1'!$P$59 -> 0.16122098 | E45: ='[2]Conversion factors selected IV '!$O$17 -> 1.5506667 | F45: =D45*E45*1000000 -> 250000 | G45: ='LCoP 2030 MEDIUM'!E5 -> 1385.4252 | H45: =G45*F45 -> 3.4635631e+08 | I45: ='LCoP 2030 MEDIUM'!H5 -> 0.22695215 | L45: =I45*H45 -> 78606310 | M45: ='LCoP 2030 MEDIUM'!F5 -> 0.40059902 | O45: =M45*H45 -> 1.3875e+08 | P45: ='LCoP 2030 MEDIUM'!G5 -> 0.37244882 | R45: =P45*H45 -> 1.29e+08 | S45: =R45+O45+L45 -> 3.4635631e+08
F46: Products of agriculture, hunting and related services | G46: =SUMIF($J$46:$J$49,F46,$L$46:$L$49)/$L$45 -> 0.77548897 | H46: domestic | I46: Straw | J46: Products of agriculture, hunting and related services | K46: ='Feedstock MIX per IVC'!G13 -> 228.35941 | L46: =K46*F$45 -> 57089853 | M46: Fabricated metal products | N46: 0 | O46: =N46*O$45 -> 0 | P46: Electricity, gas, steam and air conditioning | Q46: 0.2 | R46: =Q46*R$45 -> 25800000
F47: Paper and paper products | G47: =SUMIF($J$46:$J$49,F47,$L$46:$L$49)/$L$45 -> 0.22451103 | H47: domestic | I47: Lignocrops abandoned degraded | J47: Products of agriculture, hunting and related services | K47: ='Feedstock MIX per IVC'!G14 -> 10.633017 | L47: =K47*F$45 -> 2658254.2 | M47: Electrical equipment | N47: 0.02 | O47: =N47*O$45 -> 2775000 | P47: Chemicals and chemical products | Q47: 0.5 | R47: =Q47*R$45 -> 64500000
H48: domestic | I48: Lignocrops inter & cover cropping | J48: Products of agriculture, hunting and related services | K48: ='Feedstock MIX per IVC'!G15 -> 4.8408745 | L48: =K48*F$45 -> 1210218.6 | M48: Machinery and equipment n.e.c. | N48: 0.5 | O48: =N48*O$45 -> 69375000 | P48: Legal and accounting services; services of head offices; management consultancy services | Q48: 0.15 | R48: =Q48*R$45 -> 19350000
H49: domestic | I49: Secondary forest residues | J49: Paper and paper products | K49: ='Feedstock MIX per IVC'!G16 -> 70.591935 | L49: =K49*F$45 -> 17647984 | M49: Constructions and construction works | N49: 0.15 | O49: =N49*O$45 -> 20812500 | P49: Repair and installation services of machinery and equipment | Q49: 0.1 | R49: =Q49*R$45 -> 12900000
M50: Architectural and engineering services; technical testing and analysis services | N50: 0.3 | O50: =N50*O$45 -> 41625000 | P50: Land transport services and transport services via pipelines | Q50: 0.05 | R50: =Q50*R$45 -> 6450000
M51: Computer, electronic and optical products | N51: 0.03 | O51: =N51*O$45 -> 4162500
A52: of which 12 (road) | B52: 1000 | C52: =B52*F52 -> 2.3584906e+08 | D52: ='[1]GAP analysis Sc. 1'!$P$60 -> 0.15209526 | E52: ='[2]Conversion factors selected IV '!$O$86 -> 1.5506667 | F52: =D52*E52*1000000 -> 235849.06 | G52: ='LCoP 2030 MEDIUM'!E18 -> 988.03814 | H52: =G52*F52 -> 2.3302786e+08 | I52: ='LCoP 2030 MEDIUM'!H18 -> 0.32087642 | L52: =I52*H52 -> 74773147 | M52: ='LCoP 2030 MEDIUM'!F18 -> 0.28136566 | O52: =M52*H52 -> 65566038 | P52: ='LCoP 2030 MEDIUM'!G18 -> 0.39775792 | R52: =P52*H52 -> 92688679 | S52: =R52+O52+L52 -> 2.3302786e+08
I53: Intermediate Bioenergy carriers (Syngas) | J53: Advanced biogas | K53: ='Feedstock MIX per IVC'!G85 -> 317.03814 | L53: =K53*F52 -> 74773147 | M53: Fabricated metal products | N53: 0 | O53: =N53*O$52 -> 0 | P53: Electricity, gas, steam and air conditioning | Q53: 0.2 | R53: =Q53*R$52 -> 18537736
M54: Electrical equipment | N54: 0.02 | O54: =N54*O$52 -> 1311320.8 | P54: Chemicals and chemical products | Q54: 0.5 | R54: =Q54*R$52 -> 46344340
M55: Machinery and equipment n.e.c. | N55: 0.5 | O55: =N55*O$52 -> 32783019 | P55: Legal and accounting services; services of head offices; management consultancy services | Q55: 0.15 | R55: =Q55*R$52 -> 13903302
M56: Constructions and construction works | N56: 0.15 | O56: =N56*O$52 -> 9834905.7 | P56: Repair and installation services of machinery and equipment | Q56: 0.1 | R56: =Q56*R$52 -> 9268867.9
M57: Architectural and engineering services; technical testing and analysis services | N57: 0.3 | O57: =N57*O$52 -> 19669811 | P57: Land transport services and transport services via pipelines | Q57: 0.05 | R57: =Q57*R$52 -> 4634434
M58: Computer, electronic and optical products | N58: 0.03 | O58: =N58*O$52 -> 1966981.1
A59: of which 13a (half) | B59: 1750 | C59: =B59*F59 -> 1.0658498e+08 | D59: ='[1]GAP analysis Sc. 1'!$P$61 -> 0.060905704 | E59: ='[2]Conversion factors selected IV '!$O$89 -> 1 | F59: =D59*E59*1000000 -> 60905.704 | G59: ='LCoP 2030 MEDIUM'!E20 -> 1598.1345 | H59: =G59*F59 -> 97335504 | I59: ='LCoP 2030 MEDIUM'!H20 -> 0.13211308 | L59: =I59*H59 -> 12859293 | M59: ='LCoP 2030 MEDIUM'!F20 -> 0.50371231 | O59: =M59*H59 -> 49029091 | P59: ='LCoP 2030 MEDIUM'!G20 -> 0.36417461 | R59: =P59*H59 -> 35447120 | S59: =R59+O59+L59 -> 97335504
F60: Products of agriculture, hunting and related services | G60: =SUMIF($J$60:$J$67,F60,$L$60:$L$67)/$L$59 -> 0.55703651 | H60: domestic | I60: Straw | J60: Products of agriculture, hunting and related services | K60: ='Feedstock MIX per IVC'!G89 -> 104.52294 | L60: =K60*F$59 -> 6366043.2 | M60: Fabricated metal products | N60: 0.15 | O60: =N60*O$59 -> 7354363.7 | P60: Electricity, gas, steam and air conditioning | Q60: 0.15 | R60: =Q60*R$59 -> 5317067.9
F61: Food, beverages and tobacco products | G61: =SUMIF($J$60:$J$67,F61,$L$60:$L$67)/$L$59 -> 0.013872488 | H61: domestic | I61: Prunings & damaged crops | J61: Products of agriculture, hunting and related services | K61: ='Feedstock MIX per IVC'!G90 -> 6.0040708 | L61: =K61*F$59 -> 365682.16 | M61: Electrical equipment | N61: 0.02 | O61: =N61*O$59 -> 980581.83 | P61: Chemicals and chemical products | Q61: 0.25 | R61: =Q61*R$59 -> 8861779.9
F62: Products of forestry, logging and related services | G62: =SUMIF($J$60:$J$67,F62,$L$60:$L$67)/$L$59 -> 0.22886406 | H62: domestic | I62: Agroprocessing residues - maize cobs | J62: Food, beverages and tobacco products | K62: ='Feedstock MIX per IVC'!G91 -> 2.9289602 | L62: =K62*F$59 -> 178390.38 | M62: Machinery and equipment n.e.c. | N62: 0.45 | O62: =N62*O$59 -> 22063091 | P62: Legal and accounting services; services of head offices; management consultancy services | Q62: 0.2 | R62: =Q62*R$59 -> 7089423.9
F63: Paper and paper products | G63: =SUMIF($J$60:$J$67,F63,$L$60:$L$67)/$L$59 -> 0.20022694 | H63: domestic | I63: Lignocrops abandoned degraded | J63: Products of agriculture, hunting and related services | K63: ='Feedstock MIX per IVC'!G92 -> 4.8668638 | L63: =K63*F$59 -> 296419.76 | M63: Constructions and construction works | N63: 0.1 | O63: =N63*O$59 -> 4902909.1 | P63: Repair and installation services of machinery and equipment | Q63: 0.3 | R63: =Q63*R$59 -> 10634136
F64: Sewerage services; sewage sludge; waste collection, treatment and disposal services; materials recovery services; remediation services and other waste management services | G64: =SUMIF($J$60:$J$67,F64,$L$60:$L$67)/$L$59 -> 0 | H64: domestic | I64: Lignocrops inter & cover cropping | J64: Products of agriculture, hunting and related services | K64: ='Feedstock MIX per IVC'!G93 -> 2.2157284 | L64: =K64*F$59 -> 134950.5 | M64: Architectural and engineering services; technical testing and analysis services | N64: 0.25 | O64: =N64*O$59 -> 12257273 | P64: Land transport services and transport services via pipelines | Q64: 0.1 | R64: =Q64*R$59 -> 3544712
G65: =SUM(G60:G64) -> 1 | H65: domestic | I65: Primary forestry residues | J65: Products of forestry, logging and related services | K65: ='Feedstock MIX per IVC'!G94 -> 48.32109 | L65: =K65*F$59 -> 2943030 | M65: Computer, electronic and optical products | N65: 0.03 | O65: =N65*O$59 -> 1470872.7
H66: domestic | I66: Secondary forest residues | J66: Paper and paper products | K66: ='Feedstock MIX per IVC'!G95 -> 42.274808 | L66: =K66*F$59 -> 2574776.9
H67: domestic | I67: Biowastes - Post consumer wood | J67: Sewerage services; sewage sludge; waste collection, treatment and disposal services; materials recovery services; remediation services and other waste management services | K67: ='Feedstock MIX per IVC'!G96 -> 0 | L67: =K67*F$59 -> 0
A68: of which 13b (road) | B68: 1150 | C68: =B68*F68 -> 23347186 | D68: ='[1]GAP analysis Sc. 1'!$P$62 -> 0.020301901 | E68: ='[2]Conversion factors selected IV '!$O$125 -> 1 | F68: =D68*E68*1000000 -> 20301.901 | G68: ='LCoP 2030 MEDIUM'!$E$22 -> 1740.4464 | H68: =G68*F68 -> 35334371 | I68: ='LCoP 2030 MEDIUM'!H$22 -> 0.12177705 | L68: =I68*H68 -> 4302915.4 | M68: ='LCoP 2030 MEDIUM'!F22 -> 0.39357718 | O68: =M68*H68 -> 13906802 | P68: ='LCoP 2030 MEDIUM'!G22 -> 0.48464577 | R68: =P68*H68 -> 17124654 | S68: =L68+O68+R68 -> 35334371
F69: Products of agriculture, hunting and related services | G69: =SUMIF($J$69:$J$76,F69,$L$69:$L$76)/$L$68 -> 0.5549025 | H69: domestic | I69: Straw | J69: Products of agriculture, hunting and related services | K69: ='Feedstock MIX per IVC'!G89 -> 104.52294 | L69: =K69*F$68 -> 2122014.4 | M69: Fabricated metal products | N69: 0.15 | O69: =N69*O$68 -> 2086020.3 | P69: Electricity, gas, steam and air conditioning | Q69: 0.15 | R69: =Q69*R$68 -> 2568698.1
F70: Food, beverages and tobacco products | G70: =SUMIF($J$69:$J$76,F70,$L$69:$L$76)/$L$68 -> 0.013819342 | H70: domestic | I70: Prunings & damaged crops | J70: Products of agriculture, hunting and related services | K70: ='Feedstock MIX per IVC'!G90 -> 6.0040708 | L70: =K70*F$68 -> 121894.05 | M70: Electrical equipment | N70: 0.02 | O70: =N70*O$68 -> 278136.05 | P70: Chemicals and chemical products | Q70: 0.25 | R70: =Q70*R$68 -> 4281163.4
F71: Products of forestry, logging and related services | G71: =SUMIF($J$69:$J$76,F71,$L$69:$L$76)/$L$68 -> 0.22798728 | H71: domestic | I71: Agroprocessing residues - maize cobs | J71: Food, beverages and tobacco products | K71: ='Feedstock MIX per IVC'!G91 -> 2.9289602 | L71: =K71*F$68 -> 59463.461 | M71: Machinery and equipment n.e.c. | N71: 0.45 | O71: =N71*O$68 -> 6258061 | P71: Legal and accounting services; services of head offices; management consultancy services | Q71: 0.2 | R71: =Q71*R$68 -> 3424930.7
F72: Paper and paper products | G72: =SUMIF($J$69:$J$76,F72,$L$69:$L$76)/$L$68 -> 0.19945987 | H72: domestic | I72: Lignocrops abandoned degraded | J72: Products of agriculture, hunting and related services | K72: ='Feedstock MIX per IVC'!G92 -> 4.8668638 | L72: =K72*F$68 -> 98806.587 | M72: Constructions and construction works | N72: 0.1 | O72: =N72*O$68 -> 1390680.2 | P72: Repair and installation services of machinery and equipment | Q72: 0.3 | R72: =Q72*R$68 -> 5137396.1
F73: Sewerage services; sewage sludge; waste collection, treatment and disposal services; materials recovery services; remediation services and other waste management services | G73: =SUMIF($J$69:$J$76,F73,$L$69:$L$76)/$L$68 -> 0 | H73: domestic | I73: Lignocrops inter & cover cropping | J73: Products of agriculture, hunting and related services | K73: ='Feedstock MIX per IVC'!G93 -> 2.2157284 | L73: =K73*F$68 -> 44983.499 | M73: Architectural and engineering services; technical testing and analysis services | N73: 0.25 | O73: =N73*O$68 -> 3476700.6 | P73: Land transport services and transport services via pipelines | Q73: 0.1 | R73: =Q73*R$68 -> 1712465.4
G74: =SUM(G69:G73) -> 0.996169 | H74: domestic | I74: Primary forestry residues | J74: Products of forestry, logging and related services | K74: ='Feedstock MIX per IVC'!G94 -> 48.32109 | L74: =K74*F$68 -> 981010 | M74: Computer, electronic and optical products | N74: 0.03 | O74: =N74*O$68 -> 417204.07
H75: domestic | I75: Secondary forest residues | J75: Paper and paper products | K75: ='Feedstock MIX per IVC'!G95 -> 42.274808 | L75: =K75*F$68 -> 858258.97
H76: domestic | I76: Biowastes - Post consumer wood | J76: Sewerage services; sewage sludge; waste collection, treatment and disposal services; materials recovery services; remediation services and other waste management services | K76: ='Feedstock MIX per IVC'!G96 -> 0 | L76: =K76*F$68 -> 0
I78: TOTALS domestic | L78: =SUM(L79:L84) -> 1.7052518e+08 | M78: TOTALS | O78: =SUM(O79:O84) -> 2.6725193e+08 | P78: TOTALS | R78: =SUM(R79:R83) -> 2.7426045e+08 | S78: =SUM(S79:S83) -> 0.38516803 | T78: =#REF!+#REF!+S78 -> #REF! | U78: ALLL CHECKED AND FINE
J79: Products of agriculture, hunting and related services | L79: =SUMIF($J$46:$J$76, J79, $L$46:$L$76) -> 70509120 | M79: Fabricated metal products | O79: =SUMIF($M$46:$M$74, M79, $O$46:$O$74) -> 9440384.1 | P79: Electricity, gas, steam and air conditioning | R79: =SUMIF($P$46:$P$73, P79, $R$46:$R$73) -> 52223502 | S79: =R79/$H$44 -> 0.073342047
J80: Products of forestry, logging and related services | L80: =SUMIF($J$46:$J$76, J80, $L$46:$L$76) -> 3924040 | M80: Electrical equipment | O80: =SUMIF($M$46:$M$74, M80, $O$46:$O$74) -> 5345038.6 | P80: Chemicals and chemical products | R80: =SUMIF($P$46:$P$73, P80, $R$46:$R$73) -> 1.2398728e+08 | S80: =R80/$H$44 -> 0.17412622
J81: Paper and paper products | L81: =SUMIF($J$46:$J$76, J81, $L$46:$L$76) -> 21081020 | M81: Machinery and equipment n.e.c. | O81: =SUMIF($M$46:$M$74, M81, $O$46:$O$74) -> 1.3047917e+08 | P81: Legal and accounting services; services of head offices; management consultancy services | R81: =SUMIF($P$46:$P$73, P81, $R$46:$R$73) -> 43767657 | S81: =R81/$H$44 -> 0.061466762
J82: Food, beverages and tobacco products | L82: =SUMIF($J$46:$J$76, J82, $L$46:$L$76) -> 237853.84 | M82: Constructions and construction works | O82: =SUMIF($M$46:$M$74, M82, $O$46:$O$74) -> 36940995 | P82: Repair and installation services of machinery and equipment | R82: =SUMIF($P$46:$P$73, P82, $R$46:$R$73) -> 37940400 | S82: =R82/$H$44 -> 0.053283034
J83: Sewerage services; sewage sludge; waste collection, treatment and disposal services; materials recovery services; remediation services and other waste management services | L83: =SUMIF($J$46:$J$76, J83, $L$46:$L$76) -> 0 | M83: Architectural and engineering services; technical testing and analysis services | O83: =SUMIF($M$46:$M$74, M83, $O$46:$O$74) -> 77028785 | P83: Land transport services and transport services via pipelines | R83: =SUMIF($P$46:$P$73, P83, $R$46:$R$73) -> 16341611 | S83: =R83/$H$44 -> 0.022949959
J84: Advanced biogas | L84: =SUMIF($J$46:$J$76, J84, $L$46:$L$76) -> 74773147 | M84: Computer, electronic and optical products | O84: =SUMIF($M$46:$M$74, M84, $O$46:$O$74) -> 8017557.9
A85: Advanced biogas | D85: Note: in Scenario 1 in 2030, this is only IVC 7 because IVC 9a is used as input for IVC 12
B86: =C86/1000000 -> 4159.8022 | C86: =C87+C97 -> 4.1598022e+09 | D86: =D87 -> 3.75 | F86: =F87 -> 3137589.9
A87: IVC 7 | B87: 1275 | C87: =B87*F87 -> 4.0004272e+09 | D87: ='[1]GAP analysis Sc. 1'!$P$64+'[1]GAP analysis Sc. 1'!$P$75 -> 3.75 | E87: ='[2]Conversion factors selected IV '!$O$29 -> 0.83669065 | F87: =D87*E87*1000000 -> 3137589.9 | G87: ='LCoP 2030 MEDIUM'!E10 -> 1024.4185 | H87: =G87*F87 -> 3.2142051e+09 | I87: ='LCoP 2030 MEDIUM'!H10 -> -0.020579023 | L87: =I87*H87 -> -66145201 | M87: ='LCoP 2030 MEDIUM'!F10 -> 0.59057897 | O87: =M87*H87 -> 1.8982419e+09 | P87: ='LCoP 2030 MEDIUM'!G10 -> 0.43000006 | R87: =P87*H87 -> 1.3821084e+09 | S87: =L87+O87+R87 -> 3.2142051e+09
C88: =C87/C86 -> 0.96168688 | G88: Food, beverages and tobacco products | H88: =SUMIF($J$88:$J$96,G88,$L$88:$L$96)/$L$87*(-1) -> 0.18587856 | I88: Prunings & damaged crops (olive stones excluded) | J88: Products of agriculture, hunting and related services | K88: ='Feedstock MIX per IVC'!G25 -> 0.84774671 | L88: =K88*F$87 -> 2659881.5 | M88: Fabricated metal products | N88: 0.05 | O88: =N88*O$87 -> 94912095 | P88: Electricity, gas, steam and air conditioning | Q88: 0.2 | R88: =Q88*R$87 -> 2.7642167e+08
G89: Products of agriculture, hunting and related services | H89: =SUMIF($J$88:$J$96,G89,$L$88:$L$96)/$L$87*(-1) -> 0.78770016 | I89: Lignocrops abandoned degraded | J89: Products of agriculture, hunting and related services | K89: ='Feedstock MIX per IVC'!G26 -> 0.6871784 | L89: =K89*F$87 -> 2156084 | M89: Electrical equipment | N89: 0.02 | O89: =N89*O$87 -> 37964838 | P89: Chemicals and chemical products | Q89: 0.5 | R89: =Q89*R$87 -> 6.9105418e+08
G90: Sewerage services; sewage sludge; waste collection, treatment and disposal services; materials recovery services; remediation services and other waste management services | H90: =SUMIF($J$88:$J$96,G90,$L$88:$L$96)/$L$87*(-1) -> -2.0072067 | I90: Lignocrops inter & cover cropping | J90: Products of agriculture, hunting and related services | K90: ='Feedstock MIX per IVC'!G27 -> 0.31285048 | L90: =K90*F$87 -> 981596.52 | M90: Machinery and equipment n.e.c. | N90: 0.4 | O90: =N90*O$87 -> 7.5929676e+08 | P90: Legal and accounting services; services of head offices; management consultancy services | Q90: 0.15 | R90: =Q90*R$87 -> 2.0731625e+08
G91: Advanced biodiesel | H91: =SUMIF($J$88:$J$96,G91,$L$88:$L$96)/$L$87 -> 0 | I91: Agroprocessing residues | J91: Food, beverages and tobacco products | K91: ='Feedstock MIX per IVC'!G28 -> 3.9186047 | L91: =K91*F$87 -> 12294975 | M91: Constructions and construction works | N91: 0.3 | O91: =N91*O$87 -> 5.6947257e+08 | P91: Repair and installation services of machinery and equipment | Q91: 0.1 | R91: =Q91*R$87 -> 1.3821084e+08
G92: Chemical and chemical products | H92: =SUMIF($J$88:$J$96,G92,$L$88:$L$96)/$L$87*(-1) -> 0.033628027 | I92: Straw | J92: Products of agriculture, hunting and related services | K92: ='Feedstock MIX per IVC'!G29 -> 14.75815 | L92: =K92*F$87 -> 46305023 | M92: Architectural and engineering services; technical testing and analysis services | N92: 0.2 | O92: =N92*O$87 -> 3.7964838e+08 | P92: Land transport services and transport services via pipelines | Q92: 0.05 | R92: =Q92*R$87 -> 69105418
H93: =SUM(H88:H92) -> -1 | I93: Manure | J93: Products of agriculture, hunting and related services | K93: ='Feedstock MIX per IVC'!G30 -> 0 | L93: =K93*F$87 -> 0 | M93: Computer, electronic and optical products | N93: 0.03 | O93: =N93*O$87 -> 56947257
I94: Sewage sludge | J94: Sewerage services; sewage sludge; waste collection, treatment and disposal services; materials recovery services; remediation services and other waste management services | K94: ='Feedstock MIX per IVC'!G31 -> 0 | L94: =K94*F$87 -> 0 | N94: =SUM(N88:N93) -> 1 | O94: =SUM(O88:O93) -> 1.8982419e+09
I95: Biowastes (post consumer woods excluded) | J95: Sewerage services; sewage sludge; waste collection, treatment and disposal services; materials recovery services; remediation services and other waste management services | K95: ='Feedstock MIX per IVC'!G32 -> -42.314992 | L95: =K95*F$87 -> -1.3276709e+08
I96: Intermediate Bioenergy carrier (crude glycerine) | J96: Chemical and chemical products | K96: ='Feedstock MIX per IVC'!G33 -> 0.70893032 | L96: =K96*F$87 -> 2224332.6
A97: IVC 9a | B97: 1275 | C97: =B97*F97 -> 1.59375e+08 | D97: ='[1]GAP analysis Sc. 1'!$K$13 -> 0.14939811 | E97: ='[2]Conversion factors selected IV '!$O$52 -> 0.83669065 | F97: =D97*E97*1000000 -> 125000 | G97: ='LCoP 2030 MEDIUM'!E14 -> 1369.4799 | H97: =G97*F97 -> 1.7118499e+08 | I97: ='LCoP 2030 MEDIUM'!H14 -> 0.15296312 | L97: =I97*H97 -> 26184989 | M97: ='LCoP 2030 MEDIUM'!F14 -> 0.58416337 | O97: =M97*H97 -> 1e+08 | P97: ='LCoP 2030 MEDIUM'!G14 -> 0.26287352 | R97: 2.9932641e+08
C98: =C97/C86 -> 0.03831312 | G98: Sewerage services; sewage sludge; waste collection, treatment and disposal services; materials recovery services; remediation services and other waste management services | H98: =(SUMIF($J$102:$J$111,G98,$L$102:$L$111)/$L$101) -> 0 | I98: Straw | J98: Products of agriculture, hunting and related services | K98: ='Feedstock MIX per IVC'!G50 -> 104.88963 | L98: =K98*$F$97 -> 13111203 | M98: Fabricated metal products | N98: 0 | O98: =N98*O$101 -> 0 | P98: Electricity, gas, steam and air conditioning | Q98: 0.25 | R98: =Q98*R$101 -> 74831601
C99: (all as feedstock for IVC 12) | G99: Food, beverages and tobacco products | H99: =(SUMIF($J$102:$J$111,G99,$L$102:$L$111)/$L$101) -> 0 | I99: Prunings & damaged crops | J99: Products of agriculture, hunting and related services | K99: ='Feedstock MIX per IVC'!G51 -> 6.0251342 | L99: =K99*$F$97 -> 753141.78 | M99: Electrical equipment | N99: 0.02 | O99: =N99*O$101 -> 1.2644636e+08 | P99: Chemicals and chemical products | Q99: 0.15 | R99: =Q99*R$101 -> 44898961
G100: Products of agriculture, hunting and related services | H100: =(SUMIF($J$102:$J$111,G100,$L$102:$L$111)/$L$101) -> 2.4181251 | I100: Sewage sludge | J100: Sewerage services; sewage sludge; waste collection, treatment and disposal services; materials recovery services; remediation services and other waste management services | K100: ='Feedstock MIX per IVC'!G52 -> 0 | L100: =K100*$F$97 -> 0 | M100: Machinery and equipment n.e.c. | N100: 0.55 | O100: =N100*O$101 -> 3.4772748e+09 | P100: Legal and accounting services; services of head offices; management consultancy services | Q100: 0.3 | R100: =Q100*R$101 -> 89797922
G101: Products of forestry, logging and related services | H101: =(SUMIF($J$102:$J$111,G101,$L$102:$L$111)/$L$101) -> 15.380568 | I101: Agroprocessing residues - maize cobs | J101: Food, beverages and tobacco products | K101: ='Feedstock MIX per IVC'!G53 -> 2.9392356 | L101: =K101*$F$97 -> 367404.45 | M101: Constructions and construction works | N101: 0.1 | O101: =N101*O$101 -> 6.3223178e+08 | P101: Repair and installation services of machinery and equipment | Q101: 0.3 | R101: =Q101*R$101 -> 89797922
...

Sheet 2030 costs Sc 2
A1: Contribution of each IVC to final product in Scenario (2) 2030
A2: Assumptions:
A3: technical capacity = tcp | E3: feedstock availability: 2030 high
B5: Market value | C5: Makret value of overall amount produced | D5: produced in Mtoe | E5: Conversion factor [t/toe] | F5: produced in t | G5: Cost of production [€/t] | H5: Money spent on each IVC | I5: Feedstock share of costs | J5: Eurostat sector | K5: money [€] spent on each feedtsock when producing 1t of product | L5: Absolute feedstock costs [€] | M5: CAPEX share of costs | N5: CAPEX distribution | O5: Absoluet CAPEX [€] | P5: OPEX share of costs | R5: Absolute OPEX [€] | S5: TOTAL production costs
A6: Sum ALL advanced | D6: =D8+D48+D90+D123+D173 -> 18.590301
A7: Advanced biodiesel
A8: TOTAL | B8: =C8/1000000 -> 9549.6752 | C8: =C28+C9+C16 -> 9.5496752e+09 | D8: =D28+D9+D16 -> 5.6702449 | F8: =F28+F9+F16 -> 5456957.3 | H8: =H28+H9+H16 -> 1.2899645e+10 | L8: =L28+L9+L16 -> 1.6003873e+09 | O8: =O9+O16+O28 -> 6.7243056e+09 | R8: =R9+R16+R28 -> 4.5749518e+09
A9: of which IVC 2 HVO | B9: 1750 | C9: =B9*F9 -> 5.1963933e+08 | D9: ='[1]GAP analysis Sc. 2'!$N$123 -> 0.31205736 | E9: ='[2]Conversion factors selected IV '!$O$7 -> 0.95154545 | F9: =D9*E9*1000000 -> 296936.76 | G9: ='LCoP 2030 HIGH'!E3 -> 1281.9315 | H9: =G9*F9 -> 3.8065259e+08 | I9: ='LCoP 2030 HIGH'!H3 -> 0.47423088 | L9: =I9*H9 -> 1.8051721e+08 | M9: ='LCoP 2030 HIGH'!F3 -> 0.2098396 | O9: =M9*H9 -> 79875988 | P9: ='LCoP 2030 HIGH'!G3 -> 0.31592951 | R9: =P9*H9 -> 1.2025939e+08 | S9: =L9+O9+R9 -> 3.8065259e+08
C10: =C9/C8 -> 0.054414345 | F10: Products of agriculture, hunting and related services | G10: =(SUMIF($J$10:$J$12,F10,$L$10:$L$12)/$L$9) -> 0.21075509 | I10: Tall oil | J10: Products of agriculture, hunting and related services | K10: ='Feedstock MIX per IVC'!J6 -> 128.12466 | L10: =K10*F$9 -> 38044922 | M10: Fabricated metal products | N10: 0.05 | O10: =N10*O$9 -> 3993799.4 | P10: Electricity, gas, steam and air conditioning | Q10: 0.35 | R10: =Q10*R$9 -> 42090786
F11: Advanced biodiesel | G11: =(SUMIF($J$10:$J$12,F11,$L$10:$L$12)/$L$9)/2 -> 0.33542909 | I11: FPBO (Intermediate bioenergy carrier) | J11: Advanced biodiesel | K11: ='Feedstock MIX per IVC'!J7*0.85 -> 407.83583 | L11: =K11*F$9 -> 1.2110145e+08 | M11: Electrical equipment | N11: 0.02 | O11: =N11*O$9 -> 1597519.8 | P11: Chemicals and chemical products | Q11: 0.25 | R11: =Q11*R$9 -> 30064847
F12: Chemicals and chemical products | G12: =(SUMIF($J$10:$J$12,F12,$L$10:$L$12)/$L$9) -> 0.11838674 | I12: biocrude (Intermediate Bioenergy carrier) | J12: Chemicals and chemical products | K12: ='Feedstock MIX per IVC'!J7*0.15 -> 71.971029 | L12: =K12*F$9 -> 21370844 | M12: Machinery and equipment n.e.c. | N12: 0.45 | O12: =N12*O$9 -> 35944195 | P12: Legal and accounting services; services of head offices; management consultancy services | Q12: 0.2 | R12: =Q12*R$9 -> 24051877
F13: Advanced biogasoline | G13: =G11 -> 0.33542909 | M13: Constructions and construction works | N13: 0.15 | O13: =N13*O$9 -> 11981398 | P13: Repair and installation services of machinery and equipment | Q13: 0.15 | R13: =Q13*R$9 -> 18038908
G14: =SUM(G10:G13) -> 1 | M14: Architectural and engineering services; technical testing and analysis services | N14: 0.3 | O14: =N14*O$9 -> 23962796 | P14: Land transport services and transport services via pipelines | Q14: 0.05 | R14: =Q14*R$9 -> 6012969.4
I15: Sum | L15: =SUM(L10:L12) -> 1.8051721e+08 | M15: Computer, electronic and optical products | N15: 0.03 | O15: =N15*O$9 -> 2396279.6
A16: of which IVC 11a (road) | B16: 1750 | C16: =B16*F16 -> 6.8102703e+09 | D16: ='[1]GAP analysis Sc. 2'!$N$124 -> 4.08975 | E16: ='[2]Conversion factors selected IV '!$O$64 -> 0.95154545 | F16: =D16*E16*1000000 -> 3891583 | G16: ='LCoP 2030 HIGH'!E16 -> 2696.299 | H16: =G16*F16 -> 1.0492871e+10 | I16: ='LCoP 2030 HIGH'!H16 -> 0.109891 | L16: =I16*H16 -> 1.1530721e+09 | M16: ='LCoP 2030 HIGH'!F16 -> 0.5359198 | O16: =M16*H16 -> 5.6233375e+09 | P16: ='LCoP 2030 HIGH'!G16 -> 0.35418921 | R16: =P16*H16 -> 3.7164618e+09 | S16: =L16+O16+R16 -> 1.0492871e+10
C17: =C16/C8 -> 0.71314156 | F17: Products of agriculture, hunting and related services | G17: =(SUMIF($J$17:$J$26,F17,$L$17:$L$26)/$L$16) -> 0.62196372 | I17: Straw | J17: Products of agriculture, hunting and related services | K17: ='Feedstock MIX per IVC'!J63 -> 161.99072 | L17: =K17*F$16 -> 6.3040032e+08 | M17: Fabricated metal products | N17: 0 | O17: =N17*O$16 -> 0 | P17: Electricity, gas, steam and air conditioning | Q17: 0.25 | R17: =Q17*R$16 -> 9.2911545e+08
F18: Products of forestry, logging and related services | G18: =(SUMIF($J$17:$J$26,F18,$L$17:$L$26)/$L$16) -> 0.1487034 | I18: Prunings & damaged crops | J18: Products of agriculture, hunting and related services | K18: ='Feedstock MIX per IVC'!J64 -> 8.4731123 | L18: =K18*F$16 -> 32973820 | M18: Electrical equipment | N18: 0.02 | O18: =N18*O$16 -> 1.1246675e+08 | P18: Chemicals and chemical products | Q18: 0.15 | R18: =Q18*R$16 -> 5.5746927e+08
F19: Paper and paper products | G19: =(SUMIF($J$17:$J$26,F19,$L$17:$L$26)/$L$16) -> 0.18227674 | I19: Sewage sludge | J19: Sewerage services; sewage sludge; waste collection, treatment and disposal services; materials recovery services; remediation services and other waste management services | K19: ='Feedstock MIX per IVC'!J65 -> 0 | L19: =K19*F$16 -> 0 | M19: Machinery and equipment n.e.c. | N19: 0.55 | O19: =N19*O$16 -> 3.0928356e+09 | P19: Legal and accounting services; services of head offices; management consultancy services | Q19: 0.3 | R19: =Q19*R$16 -> 1.1149385e+09
F20: Food, beverages and tobacco products | G20: =(SUMIF($J$17:$J$26,F20,$L$17:$L$26)/$L$16) -> 0.014502397 | I20: Agroprocessing residues - maize cobs | J20: Food, beverages and tobacco products | K20: ='Feedstock MIX per IVC'!J66 -> 4.2970453 | L20: =K20*F$16 -> 16722309 | M20: Constructions and construction works | N20: 0.1 | O20: =N20*O$16 -> 5.6233375e+08 | P20: Repair and installation services of machinery and equipment | Q20: 0.3 | R20: =Q20*R$16 -> 1.1149385e+09
F21: Sewerage services; sewage sludge; waste collection, treatment and disposal services; materials recovery services; remediation services and other waste management services | G21: =(SUMIF($J$17:$J$26,F21,$L$17:$L$26)/$L$16) -> 0 | I21: Lignocrops abandoned degraded | J21: Products of agriculture, hunting and related services | K21: ='Feedstock MIX per IVC'!J67 -> 8.1190082 | L21: =K21*F$16 -> 31595795 | M21: Architectural and engineering services; technical testing and analysis services | N21: 0.3 | O21: =N21*O$16 -> 1.6870012e+09 | P21: Land transport services and transport services via pipelines | Q21: 0 | R21: =Q21*R$16 -> 0
F22: Advanced biodiesel | G22: =(SUMIF($J$17:$J$26,F22,$L$17:$L$26)/$L$16)/2 -> 0.016276872 | I22: Lignocrops inter & cover cropping | J22: Products of agriculture, hunting and related services | K22: ='Feedstock MIX per IVC'!J68 -> 5.7043807 | L22: =K22*F$16 -> 22199071 | M22: Computer, electronic and optical products | N22: 0.03 | O22: =N22*O$16 -> 1.6870012e+08
F23: Chemicals and chemical products | G23: =(SUMIF($J$17:$J$26,F23,$L$17:$L$26)/$L$16) -> 0 | I23: Primary forestry residues | J23: Products of forestry, logging and related services | K23: ='Feedstock MIX per IVC'!J69 -> 44.060666 | L23: =K23*F$16 -> 1.7146574e+08
F24: Advanced biogasoline | G24: =G22 -> 0.016276872 | I24: Secondary forest residues | J24: Paper and paper products | K24: ='Feedstock MIX per IVC'!J70 -> 54.008411 | L24: =K24*F$16 -> 2.1017822e+08
G25: =SUM(G17:G24) -> 1 | I25: Biowastes - Post consumer wood | J25: Sewerage services; sewage sludge; waste collection, treatment and disposal services; materials recovery services; remediation services and other waste management services | K25: ='Feedstock MIX per IVC'!J71 -> 0 | L25: =K25*F$16 -> 0
I26: Intermediate Bioenergy carriers (FPBO with lower quality ) | J26: Advanced biodiesel | K26: ='Feedstock MIX per IVC'!J72 -> 9.6456413 | L26: =K26*F$16 -> 37536814
I27: Sum | L27: =SUM(L17:L26) -> 1.1530721e+09
A28: of which 13a (half) | B28: 1750 | C28: =B28*F28 -> 2219765625 | D28: ='[1]GAP analysis Sc. 2'!$N$125 -> 1.2684375 | E28: ='[2]Conversion factors selected IV '!$O$89 -> 1 | F28: =D28*E28*1000000 -> 1268437.5 | G28: ='LCoP 2030 HIGH'!E20 -> 1597.336 | H28: =G28*F28 -> 2.0261209e+09 | I28: ='LCoP 2030 HIGH'!H20 -> 0.13167923 | L28: =I28*H28 -> 2.6679804e+08 | M28: ='LCoP 2030 HIGH'!F20 -> 0.50396411 | O28: =M28*H28 -> 1.0210922e+09 | P28: ='LCoP 2030 HIGH'!G20 -> 0.36435666 | R28: =P28*H28 -> 738230625 | S28: =L28+O28+R28 -> 2.0261209e+09
C29: =C28/C8 -> 0.2324441 | F29: Products of agriculture, hunting and related services | G29: =(SUMIF($J$29:$J$36,F29,$L$29:$L$36)/$L$28) -> 0.62730453 | I29: Straw | J29: Products of agriculture, hunting and related services | K29: ='Feedstock MIX per IVC'!J89 -> 115.98101 | L29: =K29*F$28 -> 1.4711467e+08 | M29: Fabricated metal products | N29: 0.15 | O29: =N29*O$28 -> 1.5316383e+08 | P29: Electricity, gas, steam and air conditioning | Q29: 0.15 | R29: =Q29*R$28 -> 1.1073459e+08
F30: Products of forestry, logging and related services | G30: =(SUMIF($J$29:$J$36,F30,$L$29:$L$36)/$L$28) -> 0.16087373 | I30: Prunings & damaged crops | J30: Products of agriculture, hunting and related services | K30: ='Feedstock MIX per IVC'!J90 -> 6.0665214 | L30: =K30*F$28 -> 7695003.3 | M30: Electrical equipment | N30: 0.02 | O30: =N30*O$28 -> 20421844 | P30: Chemicals and chemical products | Q30: 0.25 | R30: =Q30*R$28 -> 1.8455766e+08
F31: Paper and paper products | G31: =(SUMIF($J$29:$J$36,F31,$L$29:$L$36)/$L$28) -> 0.19719481 | I31: Agroprocessing residues - maize cobs | J31: Food, beverages and tobacco products | K31: ='Feedstock MIX per IVC'!J91 -> 3.0765693 | L31: =K31*F$28 -> 3902435.9 | M31: Machinery and equipment n.e.c. | N31: 0.45 | O31: =N31*O$28 -> 4.5949148e+08 | P31: Legal and accounting services; services of head offices; management consultancy services | Q31: 0.2 | R31: =Q31*R$28 -> 147646125
F32: Food, beverages and tobacco products | G32: =(SUMIF($J$29:$J$36,F32,$L$29:$L$36)/$L$28) -> 0.014626929 | I32: Lignocrops abandoned degraded | J32: Products of agriculture, hunting and related services | K32: ='Feedstock MIX per IVC'!J92 -> 5.8129924 | L32: =K32*F$28 -> 7373417.5 | M32: Constructions and construction works | N32: 0.1 | O32: =N32*O$28 -> 1.0210922e+08 | P32: Repair and installation services of machinery and equipment | Q32: 0.3 | R32: =Q32*R$28 -> 2.2146919e+08
F33: Sewerage services; sewage sludge; waste collection, treatment and disposal services; materials recovery services; remediation services and other waste management services | G33: =(SUMIF($J$29:$J$36,F33,$L$29:$L$36)/$L$28) -> 0 | I33: Lignocrops inter & cover cropping | J33: Products of agriculture, hunting and related services | K33: ='Feedstock MIX per IVC'!J93 -> 4.0841838 | L33: =K33*F$28 -> 5180531.9 | M33: Architectural and engineering services; technical testing and analysis services | N33: 0.25 | O33: =N33*O$28 -> 2.5527305e+08 | P33: Land transport services and transport services via pipelines | Q33: 0.1 | R33: =Q33*R$28 -> 73823062
F34: Advanced biodiesel | G34: =(SUMIF($J$29:$J$36,F34,$L$29:$L$36)/$L$28) -> 0 | I34: Primary forestry residues | J34: Products of forestry, logging and related services | K34: ='Feedstock MIX per IVC'!J94 -> 33.837534 | L34: =K34*F$28 -> 42920797 | M34: Computer, electronic and optical products | N34: 0.03 | O34: =N34*O$28 -> 30632766 | Q34: =SUM(Q29:Q33) -> 1
F35: Chemicals and chemical products | G35: =(SUMIF($J$29:$J$36,F35,$L$29:$L$36)/$L$28) -> 0 | I35: Secondary forest residues | J35: Paper and paper products | K35: ='Feedstock MIX per IVC'!J95 -> 41.477163 | L35: =K35*F$28 -> 52611189
G36: =SUM(G29:G35) -> 1 | I36: Biowastes - Post consumer wood | J36: Sewerage services; sewage sludge; waste collection, treatment and disposal services; materials recovery services; remediation services and other waste management services | K36: ='Feedstock MIX per IVC'!J96 -> 0 | L36: =K36*F$28 -> 0
I37: SUM | L37: =SUM(L29:L36) -> 2.6679804e+08
I38: TOTALS domestic | M38: TOTALS | O38: =SUM(O39:O44) -> 6.7243056e+09 | P38: TOTALS | R38: =SUM(R39:R43) -> 4.5749518e+09 | S38: =SUM(S39:S43) -> 0.35465719
J39: Products of agriculture, hunting and related services | L39: =SUMIF($J$10:$J$36,J39,$L$10:$L$36) -> 9.2257755e+08 | M39: Fabricated metal products | O39: =SUMIF($M$10:$M$36,M39,$O$10:$O$36) -> 1.5715763e+08 | P39: Electricity, gas, steam and air conditioning | R39: =SUMIF($P$10:$P$36,P39,$R$10:$R$36) -> 1.0819408e+09 | S39: =R39/$H$8 -> 0.083873691
J40: Products of forestry, logging and related services | L40: =SUMIF($J$10:$J$36,J40,$L$10:$L$36) -> 2.1438654e+08 | M40: Electrical equipment | O40: =SUMIF($M$10:$M$36,M40,$O$10:$O$36) -> 1.3448611e+08 | P40: Chemicals and chemical products | R40: =SUMIF($P$10:$P$36,P40,$R$10:$R$36) -> 7.7209177e+08 | S40: =R40/$H$8 -> 0.059853723
J41: Paper and paper products | L41: =SUMIF($J$10:$J$36,J41,$L$10:$L$36) -> 2.6278941e+08 | M41: Machinery and equipment n.e.c. | O41: =SUMIF($M$10:$M$36,M41,$O$10:$O$36) -> 3.5882713e+09 | P41: Legal and accounting services; services of head offices; management consultancy services | R41: =SUMIF($P$10:$P$36,P41,$R$10:$R$36) -> 1.2866365e+09 | S41: =R41/$H$8 -> 0.099742013
J42: Food, beverages and tobacco products | L42: =SUMIF($J$10:$J$36,J42,$L$10:$L$36) -> 20624745 | M42: Constructions and construction works | O42: =SUMIF($M$10:$M$36,M42,$O$10:$O$36) -> 6.7642436e+08 | P42: Repair and installation services of machinery and equipment | R42: =SUMIF($P$10:$P$36,P42,$R$10:$R$36) -> 1.3544466e+09 | S42: =R42/$H$8 -> 0.10499875
J43: Sewerage services; sewage sludge; waste collection, treatment and disposal services; materials recovery services; remediation services and other waste management services | L43: =SUMIF($J$10:$J$36,J43,$L$10:$L$36) -> 0 | M43: Architectural and engineering services; technical testing and analysis services | O43: =SUMIF($M$10:$M$36,M43,$O$10:$O$36) -> 1.9662371e+09 | P43: Land transport services and transport services via pipelines | R43: =SUMIF($P$10:$P$36,P43,$R$10:$R$36) -> 79836032 | S43: =R43/$H$8 -> 0.0061890101
J44: Advanced biodiesel | L44: =SUMIF($J$10:$J$36,J44,$L$10:$L$36) -> 1.5863826e+08 | M44: Computer, electronic and optical products | O44: =SUMIF($M$10:$M$36,M44,$O$10:$O$36) -> 2.0172917e+08
J45: Chemicals and chemical products | L45: =SUMIF($J$10:$J$36,J45,$L$10:$L$36) -> 21370844
I46: SUM | L46: =SUM(L39:L45) -> 1.6003873e+09
A47: Advanced biogasoline
B48: =C48/1000000 -> 10469.28 | C48: =C49+C56+C63+C72 -> 1.046928e+10 | D48: =D49+D56+D63+D72 -> 6.8069123 | F48: =F49+F56+F63+F72 -> 9391108.3 | H48: =H49+H56+H63+H72 -> 1.2139178e+10 | L48: =L49+L56+L63+L72 -> 2.7490109e+09 | O48: =O49+O56+O63+O72 -> 4.6312349e+09 | R48: =R49+R56+R63+R72 -> 4.7589326e+09
A49: of which from IVC 5 | B49: 1000 | C49: =B49*F49 -> 3.6385229e+09 | D49: ='[1]GAP analysis Sc. 2'!$N$127 -> 2.3464249 | E49: ='[2]Conversion factors selected IV '!$O$17 -> 1.5506667 | F49: =D49*E49*1000000 -> 3638522.9 | G49: ='LCoP 2030 HIGH'!E5 -> 1387.0526 | H49: =G49*F49 -> 5.0468228e+09 | I49: ='LCoP 2030 HIGH'!H5 -> 0.22785916 | L49: =I49*H49 -> 1.1499648e+09 | M49: ='LCoP 2030 HIGH'!F5 -> 0.40012901 | O49: =M49*H49 -> 2.0193802e+09 | P49: ='LCoP 2030 HIGH'!G5 -> 0.37201183 | R49: =P49*H49 -> 1.8774778e+09 | S49: =R49+O49+L49 -> 5.0468228e+09
C50: =C49/C48 -> 0.3475428 | F50: Products of agriculture, hunting and related services | G50: =SUMIF($J$50:$J$54,F50,$L$50:$L$53)/$L$49 -> 0.79882414 | H50: domestic | I50: Straw | J50: Products of agriculture, hunting and related services | K50: ='Feedstock MIX per IVC'!J13 -> 232.61998 | L50: =K50*F$49 -> 8.4639314e+08 | M50: Fabricated metal products | N50: 0 | O50: =N50*O$49 -> 0 | P50: Electricity, gas, steam and air conditioning | Q50: 0.2 | R50: =Q50*R$49 -> 3.7549556e+08
F51: Paper and paper products | G51: =SUMIF($J$50:$J$54,F51,$L$50:$L$53)/$L$49 -> 0.20117586 | H51: domestic | I51: Lignocrops abandoned degraded | J51: Products of agriculture, hunting and related services | K51: ='Feedstock MIX per IVC'!J14 -> 11.658962 | L51: =K51*F$49 -> 42421399 | M51: Electrical equipment | N51: 0.02 | O51: =N51*O$49 -> 40387604 | P51: Chemicals and chemical products | Q51: 0.5 | R51: =Q51*R$49 -> 9.3873891e+08
H52: domestic | I52: Lignocrops inter & cover cropping | J52: Products of agriculture, hunting and related services | K52: ='Feedstock MIX per IVC'!J15 -> 8.1915371 | L52: =K52*F$49 -> 29805095 | M52: Machinery and equipment n.e.c. | N52: 0.5 | O52: =N52*O$49 -> 1.0096901e+09 | P52: Legal and accounting services; services of head offices; management consultancy services | Q52: 0.15 | R52: =Q52*R$49 -> 2.8162167e+08
H53: domestic | I53: Secondary forest residues | J53: Paper and paper products | K53: ='Feedstock MIX per IVC'!J16 -> 63.582165 | L53: =K53*F$49 -> 2.3134516e+08 | M53: Constructions and construction works | N53: 0.15 | O53: =N53*O$49 -> 3.0290703e+08 | P53: Repair and installation services of machinery and equipment | Q53: 0.1 | R53: =Q53*R$49 -> 1.8774778e+08
M54: Architectural and engineering services; technical testing and analysis services | N54: 0.3 | O54: =N54*O$49 -> 6.0581406e+08 | P54: Land transport services and transport services via pipelines | Q54: 0.05 | R54: =Q54*R$49 -> 93873891
M55: Computer, electronic and optical products | N55: 0.03 | O55: =N55*O$49 -> 60581406
A56: of which 12 (road) | B56: 1000 | C56: =B56*F56 -> 3.6385229e+09 | D56: ='[1]GAP analysis Sc. 2'!$N$128 -> 2.3464249 | E56: ='[2]Conversion factors selected IV '!$O$86 -> 1.5506667 | F56: =D56*E56*1000000 -> 3638522.9 | G56: ='LCoP 2030 HIGH'!E18 -> 988.03814 | H56: =G56*F56 -> 3.5949994e+09 | I56: ='LCoP 2030 HIGH'!H18 -> 0.32087642 | L56: =I56*H56 -> 1.1535505e+09 | M56: ='LCoP 2030 HIGH'!F18 -> 0.28136566 | O56: =M56*H56 -> 1.0115094e+09 | P56: ='LCoP 2030 HIGH'!G18 -> 0.39775792 | R56: =P56*H56 -> 1.4299395e+09 | S56: =R56+O56+L56 -> 3.5949994e+09
C57: =C56/C48 -> 0.3475428 | I57: Intermediate Bioenergy carriers (Syngas) | J57: Advanced biogas | K57: ='Feedstock MIX per IVC'!J85 -> 317.03814 | L57: =K57*F56 -> 1.1535505e+09 | M57: Fabricated metal products | N57: 0 | O57: =N57*O$56 -> 0 | P57: Electricity, gas, steam and air conditioning | Q57: 0.2 | R57: =Q57*R$56 -> 2.859879e+08
M58: Electrical equipment | N58: 0.02 | O58: =N58*O$56 -> 20230187 | P58: Chemicals and chemical products | Q58: 0.5 | R58: =Q58*R$56 -> 7.1496975e+08
M59: Machinery and equipment n.e.c. | N59: 0.5 | O59: =N59*O$56 -> 5.0575468e+08 | P59: Legal and accounting services; services of head offices; management consultancy services | Q59: 0.15 | R59: =Q59*R$56 -> 2.1449093e+08
M60: Constructions and construction works | N60: 0.15 | O60: =N60*O$56 -> 1.5172641e+08 | P60: Repair and installation services of machinery and equipment | Q60: 0.1 | R60: =Q60*R$56 -> 1.4299395e+08
M61: Architectural and engineering services; technical testing and analysis services | N61: 0.3 | O61: =N61*O$56 -> 3.0345281e+08 | P61: Land transport services and transport services via pipelines | Q61: 0.05 | R61: =Q61*R$56 -> 71496975
M62: Computer, electronic and optical products | N62: 0.03 | O62: =N62*O$56 -> 30345281
A63: of which 13a (half) | B63: 1750 | C63: =B63*F63 -> 2219765625 | D63: ='[1]GAP analysis Sc. 2'!$N$125 -> 1.2684375 | E63: ='[2]Conversion factors selected IV '!$O$89 -> 1 | F63: =D63*E63*1000000 -> 1268437.5 | G63: ='LCoP 2030 HIGH'!E20 -> 1597.336 | H63: =G63*F63 -> 2.0261209e+09 | I63: ='LCoP 2030 HIGH'!H20 -> 0.13167923 | L63: =I63*H63 -> 2.6679804e+08 | M63: ='LCoP 2030 HIGH'!F20 -> 0.50396411 | O63: =M63*H63 -> 1.0210922e+09 | P63: ='LCoP 2030 HIGH'!G20 -> 0.36435666 | R63: =P63*H63 -> 738230625 | S63: =L63+O63+R63 -> 2.0261209e+09
C64: =C63/C48 -> 0.21202658 | F64: Food, beverages and tobacco products | G64: =SUMIF($J$64:$J$71,F64,$L$64:$L$71)/$L$63 -> 0.014626929 | H64: domestic | I64: Straw | J64: Products of agriculture, hunting and related services | K64: ='Feedstock MIX per IVC'!J89 -> 115.98101 | L64: =K64*F$63 -> 1.4711467e+08 | M64: Fabricated metal products | N64: 0.15 | O64: =N64*O$63 -> 1.5316383e+08 | P64: Electricity, gas, steam and air conditioning | Q64: 0.15 | R64: =Q64*R$63 -> 1.1073459e+08
F65: Products of agriculture, hunting and related services | G65: =SUMIF($J$64:$J$71,F65,$L$64:$L$71)/$L$63 -> 0.62730453 | H65: domestic | I65: Prunings & damaged crops | J65: Products of agriculture, hunting and related services | K65: ='Feedstock MIX per IVC'!J90 -> 6.0665214 | L65: =K65*F$63 -> 7695003.3 | M65: Electrical equipment | N65: 0.02 | O65: =N65*O$63 -> 20421844 | P65: Chemicals and chemical products | Q65: 0.25 | R65: =Q65*R$63 -> 1.8455766e+08
F66: Products of forestry, logging and related services | G66: =SUMIF($J$64:$J$71,F66,$L$64:$L$71)/$L$63 -> 0.16087373 | H66: domestic | I66: Agroprocessing residues - maize cobs | J66: Food, beverages and tobacco products | K66: ='Feedstock MIX per IVC'!J91 -> 3.0765693 | L66: =K66*F$63 -> 3902435.9 | M66: Machinery and equipment n.e.c. | N66: 0.45 | O66: =N66*O$63 -> 4.5949148e+08 | P66: Legal and accounting services; services of head offices; management consultancy services | Q66: 0.2 | R66: =Q66*R$63 -> 147646125
F67: Paper and paper products | G67: =SUMIF($J$64:$J$71,F67,$L$64:$L$71)/$L$63 -> 0.19719481 | H67: domestic | I67: Lignocrops abandoned degraded | J67: Products of agriculture, hunting and related services | K67: ='Feedstock MIX per IVC'!J92 -> 5.8129924 | L67: =K67*F$63 -> 7373417.5 | M67: Constructions and construction works | N67: 0.1 | O67: =N67*O$63 -> 1.0210922e+08 | P67: Repair and installation services of machinery and equipment | Q67: 0.3 | R67: =Q67*R$63 -> 2.2146919e+08
F68: Sewerage services; sewage sludge; waste collection, treatment and disposal services; materials recovery services; remediation services and other waste management services | G68: =SUMIF($J$64:$J$71,F68,$L$64:$L$71)/$L$63 -> 0 | H68: domestic | I68: Lignocrops inter & cover cropping | J68: Products of agriculture, hunting and related services | K68: ='Feedstock MIX per IVC'!J93 -> 4.0841838 | L68: =K68*F$63 -> 5180531.9 | M68: Architectural and engineering services; technical testing and analysis services | N68: 0.25 | O68: =N68*O$63 -> 2.5527305e+08 | P68: Land transport services and transport services via pipelines | Q68: 0.1 | R68: =Q68*R$63 -> 73823062
G69: =SUM(G64:G68) -> 1 | H69: domestic | I69: Primary forestry residues | J69: Products of forestry, logging and related services | K69: ='Feedstock MIX per IVC'!J94 -> 33.837534 | L69: =K69*F$63 -> 42920797 | M69: Computer, electronic and optical products | N69: 0.03 | O69: =N69*O$63 -> 30632766
H70: domestic | I70: Secondary forest residues | J70: Paper and paper products | K70: ='Feedstock MIX per IVC'!J95 -> 41.477163 | L70: =K70*F$63 -> 52611189
H71: domestic | I71: Biowastes - Post consumer wood | J71: Sewerage services; sewage sludge; waste collection, treatment and disposal services; materials recovery services; remediation services and other waste management services | K71: ='Feedstock MIX per IVC'!J96 -> 0 | L71: =K71*F$63 -> 0
A72: of which 13b (road) | B72: 1150 | C72: =B72*F72 -> 9.7246875e+08 | D72: ='[1]GAP analysis Sc. 2'!$N$130 -> 0.845625 | E72: ='[2]Conversion factors selected IV '!$O$125 -> 1 | F72: =D72*E72*1000000 -> 845625 | G72: ='LCoP 2030 HIGH'!E22 -> 1739.8201 | H72: =G72*F72 -> 1.4712354e+09 | I72: ='LCoP 2030 HIGH'!H22 -> 0.12146089 | L72: =I72*H72 -> 1.7869756e+08 | M72: ='LCoP 2030 HIGH'!F22 -> 0.39371887 | O72: =M72*H72 -> 5.7925313e+08 | P72: ='LCoP 2030 HIGH'!G22 -> 0.48482024 | R72: =P72*H72 -> 7.1328469e+08 | S72: =L72+O72+R72 -> 1.4712354e+09
C73: =C72/C48 -> 0.092887833 | F73: Food, beverages and tobacco products | G73: =SUMIF($J$73:$J$80,F73,$L$73:$L$80)/$L$72 -> 0.01423356 | H73: domestic | I73: Straw | J73: Products of agriculture, hunting and related services | K73: ='Feedstock MIX per IVC'!J107 -> 113.38995 | L73: =K73*F$72 -> 95885373 | M73: Fabricated metal products | N73: 0.15 | O73: =N73*O$72 -> 86887969 | P73: Electricity, gas, steam and air conditioning | Q73: 0.15 | R73: =Q73*R$72 -> 1.069927e+08
F74: Products of agriculture, hunting and related services | G74: =SUMIF($J$73:$J$80,F74,$L$73:$L$80)/$L$72 -> 0.6373276 | H74: domestic | I74: Prunings & damaged crops | J74: Products of agriculture, hunting and related services | K74: ='Feedstock MIX per IVC'!J108 -> 5.9309927 | L74: =K74*F$72 -> 5015395.7 | M74: Electrical equipment | N74: 0.02 | O74: =N74*O$72 -> 11585063 | P74: Chemicals and chemical products | Q74: 0.25 | R74: =Q74*R$72 -> 1.7832117e+08
F75: Products of forestry, logging and related services | G75: =SUMIF($J$73:$J$80,F75,$L$73:$L$80)/$L$72 -> 0.15654728 | H75: domestic | I75: Agroprocessing residues - maize cobs | J75: Food, beverages and tobacco products | K75: ='Feedstock MIX per IVC'!J109 -> 3.0078374 | L75: =K75*F$72 -> 2543502.5 | M75: Machinery and equipment n.e.c. | N75: 0.45 | O75: =N75*O$72 -> 2.6066391e+08 | P75: Legal and accounting services; services of head offices; management consultancy services | Q75: 0.2 | R75: =Q75*R$72 -> 1.4265694e+08
F76: Paper and paper products | G76: =SUMIF($J$73:$J$80,F76,$L$73:$L$80)/$L$72 -> 0.19189156 | H76: domestic | I76: Lignocrops abandoned degraded | J76: Products of agriculture, hunting and related services | K76: ='Feedstock MIX per IVC'!J110 -> 11.366255 | L76: =K76*F$72 -> 9611589.5 | M76: Constructions and construction works | N76: 0.1 | O76: =N76*O$72 -> 57925313 | P76: Repair and installation services of machinery and equipment | Q76: 0.3 | R76: =Q76*R$72 -> 2.1398541e+08
F77: Sewerage services; sewage sludge; waste collection, treatment and disposal services; materials recovery services; remediation services and other waste management services | G77: =SUMIF($J$73:$J$80,F77,$L$73:$L$80)/$L$72 -> 0 | H77: domestic | I77: Lignocrops inter & cover cropping | J77: Products of agriculture, hunting and related services | K77: ='Feedstock MIX per IVC'!J111 -> 3.9929413 | L77: =K77*F$72 -> 3376531 | M77: Architectural and engineering services; technical testing and analysis services | N77: 0.25 | O77: =N77*O$72 -> 1.4481328e+08 | P77: Land transport services and transport services via pipelines | Q77: 0.1 | R77: =Q77*R$72 -> 71328469
G78: =SUM(G73:G77) -> 1 | H78: domestic | I78: Primary forestry residues | J78: Products of forestry, logging and related services | K78: ='Feedstock MIX per IVC'!J112 -> 33.081588 | L78: =K78*F$72 -> 27974618 | M78: Computer, electronic and optical products | N78: 0.03 | O78: =N78*O$72 -> 17377594
H79: domestic | I79: Secondary forest residues | J79: Paper and paper products | K79: ='Feedstock MIX per IVC'!J113 -> 40.550545 | L79: =K79*F$72 -> 34290554
H80: domestic | I80: Biowastes - Post consumer wood | J80: Sewerage services; sewage sludge; waste collection, treatment and disposal services; materials recovery services; remediation services and other waste management services | K80: ='Feedstock MIX per IVC'!J114 -> 0 | L80: =K80*F$72 -> 0
I82: TOTALS domestic | L82: =SUM(L83:L88) -> 2.7490109e+09 | M82: TOTALS | O82: =SUM(O83:O88) -> 4.6312349e+09 | P82: TOTALS | R82: =SUM(R83:R87) -> 4.7589326e+09 | S82: =SUM(S83:S87) -> 0.39203086
J83: Products of agriculture, hunting and related services | L83: =SUMIF($J$50:$J$80, J83, $L$50:$L$80) -> 1.1998721e+09 | M83: Fabricated metal products | O83: =SUMIF($M$50:$M$78, M83, $O$50:$O$78) -> 2.400518e+08 | P83: Electricity, gas, steam and air conditioning | R83: =SUMIF($P$50:$P$77, P83, $R$50:$R$77) -> 8.7921076e+08 | S83: =R83/$H$48 -> 0.072427534
J84: Products of forestry, logging and related services | L84: =SUMIF($J$50:$J$80, J84, $L$50:$L$80) -> 70895414 | M84: Electrical equipment | O84: =SUMIF($M$50:$M$78, M84, $O$50:$O$78) -> 92624698 | P84: Chemicals and chemical products | R84: =SUMIF($P$50:$P$77, P84, $R$50:$R$77) -> 2.0165875e+09 | S84: =R84/$H$48 -> 0.16612224
J85: Paper and paper products | L85: =SUMIF($J$50:$J$80, J85, $L$50:$L$80) -> 3.1824691e+08 | M85: Machinery and equipment n.e.c. | O85: =SUMIF($M$50:$M$78, M85, $O$50:$O$78) -> 2.2356002e+09 | P85: Legal and accounting services; services of head offices; management consultancy services | R85: =SUMIF($P$50:$P$77, P85, $R$50:$R$77) -> 7.8641566e+08 | S85: =R85/$H$48 -> 0.064783269
J86: Food, beverages and tobacco products | L86: =SUMIF($J$50:$J$80, J86, $L$50:$L$80) -> 6445938.4 | M86: Constructions and construction works | O86: =SUMIF($M$50:$M$78, M86, $O$50:$O$78) -> 6.1466797e+08 | P86: Repair and installation services of machinery and equipment | R86: =SUMIF($P$50:$P$77, P86, $R$50:$R$77) -> 7.6619633e+08 | S86: =R86/$H$48 -> 0.063117642
J87: Sewerage services; sewage sludge; waste collection, treatment and disposal services; materials recovery services; remediation services and other waste management services | L87: =SUMIF($J$50:$J$80, J87, $L$50:$L$80) -> 0 | M87: Architectural and engineering services; technical testing and analysis services | O87: =SUMIF($M$50:$M$78, M87, $O$50:$O$78) -> 1.3093532e+09 | P87: Land transport services and transport services via pipelines | R87: =SUMIF($P$50:$P$77, P87, $R$50:$R$77) -> 3.105224e+08 | S87: =R87/$H$48 -> 0.025580182
J88: Advanced biogas | L88: =SUMIF($J$50:$J$80, J88, $L$50:$L$80) -> 1.1535505e+09 | M88: Computer, electronic and optical products | O88: =SUMIF($M$50:$M$78, M88, $O$50:$O$78) -> 1.3893705e+08
A89: Advanced biogas
B90: =C90/1000000 -> 26710.404 | C90: =C91+C101 -> 2.6710404e+10 | D90: =D92+D102 -> 1.4537189 | F90: =F91+F101 -> 20949336 | L90: =L91+L101 -> 2.5196009e+09 | O90: =O91+O101 -> 1.5112858e+10 | R90: =R91+R101 -> 4.0189779e+09
A91: IVC 7 | B91: 1275 | C91: =B91*F91 -> 1.0766301e+10 | D91: ='[1]GAP analysis Sc. 2'!$M$132 -> 10.09233 | E91: ='[2]Conversion factors selected IV '!$O$29 -> 0.83669065 | F91: =D91*E91*1000000 -> 8444157.8 | G91: ='LCoP 2030 HIGH'!E10 -> 1029.7035 | H91: =G91*F91 -> 8.6949786e+09 | I91: ='LCoP 2030 HIGH'!H10 -> -0.015340841 | L91: =I91*H91 -> -1.3338829e+08 | M91: ='LCoP 2030 HIGH'!F10 -> 0.58754778 | O91: =M91*H91 -> 5.1087154e+09 | P91: ='LCoP 2030 HIGH'!G10 -> 0.42779306 | R91: =P91*H91 -> 3.7196515e+09 | S91: =L91+O91+R91 -> 8.6949786e+09
C92: for cosnumption | D92: ='[1]GAP analysis Sc. 2'!$N$132 -> 1.0837488 | F92: Food, beverages and tobacco products | G92: =SUMIF($J$92:$J$100,F92,$L$92:$L$100)/$L$91 -> -0.2706585 | I92: Prunings & damaged crops (olive stones excluded) | J92: Products of agriculture, hunting and related services | K92: ='Feedstock MIX per IVC'!J25 -> 0.89326983 | L92: =K92*F$91 -> 7542911.3 | M92: Fabricated metal products | N92: 0.05 | O92: =N92*O$91 -> 2.5543577e+08 | P92: Electricity, gas, steam and air conditioning | Q92: 0.2 | R92: =Q92*R$91 -> 7.439303e+08
C93: as feedstock for IVC 8b | D93: =D91-D92 -> 9.0085808 | F93: Products of agriculture, hunting and related services | G93: =SUMIF($J$92:$J$100,F93,$L$92:$L$100)/$L$91 -> -1.2300084 | I93: Lignocrops abandoned degraded | J93: Products of agriculture, hunting and related services | K93: ='Feedstock MIX per IVC'!J26 -> 0.85601008 | L93: =K93*F$91 -> 7228284.2 | M93: Electrical equipment | N93: 0.02 | O93: =N93*O$91 -> 1.0217431e+08 | P93: Chemicals and chemical products | Q93: 0.5 | R93: =Q93*R$91 -> 1.8598257e+09
F94: Chemical and chemical products | G94: =SUMIF($J$92:$J$100,F94,$L$92:$L$100)/$L$91 -> -0.032776531 | I94: Lignocrops inter & cover cropping | J94: Products of agriculture, hunting and related services | K94: ='Feedstock MIX per IVC'!J27 -> 0.60142905 | L94: =K94*F$91 -> 5078561.8 | M94: Machinery and equipment n.e.c. | N94: 0.4 | O94: =N94*O$91 -> 2.0434862e+09 | P94: Legal and accounting services; services of head offices; management consultancy services | Q94: 0.15 | R94: =Q94*R$91 -> 5.5794772e+08
F95: Sewerage services; sewage sludge; waste collection, treatment and disposal services; materials recovery services; remediation services and other waste management services | G95: =SUMIF($J$92:$J$100,F95,$L$92:$L$100)/$L$91 -> 2.5334435 | I95: Agroprocessing residues | J95: Food, beverages and tobacco products | K95: ='Feedstock MIX per IVC'!J28 -> 4.2754617 | L95: =K95*F$91 -> 36102673 | M95: Constructions and construction works | N95: 0.3 | O95: =N95*O$91 -> 1.5326146e+09 | P95: Repair and installation services of machinery and equipment | Q95: 0.1 | R95: =Q95*R$91 -> 3.7196515e+08
G96: =SUM(G92:G95) -> 1 | I96: Straw | J96: Products of agriculture, hunting and related services | K96: ='Feedstock MIX per IVC'!J29 -> 17.079141 | L96: =K96*F$91 -> 1.4421896e+08 | M96: Architectural and engineering services; technical testing and analysis services | N96: 0.2 | O96: =N96*O$91 -> 1.0217431e+09 | P96: Land transport services and transport services via pipelines | Q96: 0.05 | R96: =Q96*R$91 -> 1.8598257e+08
I97: Manure | J97: Products of agriculture, hunting and related services | K97: ='Feedstock MIX per IVC'!J30 -> 0 | L97: =K97*F$91 -> 0 | M97: Computer, electronic and optical products | N97: 0.03 | O97: =N97*O$91 -> 1.5326146e+08
I98: Sewage sludge | J98: Sewerage services; sewage sludge; waste collection, treatment and disposal services; materials recovery services; remediation services and other waste management services | K98: ='Feedstock MIX per IVC'!J31 -> 0 | L98: =K98*F$91 -> 0 | N98: =SUM(N92:N97) -> 1
I99: Biowastes (post consumer woods excluded) | J99: Sewerage services; sewage sludge; waste collection, treatment and disposal services; materials recovery services; remediation services and other waste management services | K99: ='Feedstock MIX per IVC'!J32 -> -40.019584 | L99: =K99*F$91 -> -3.3793168e+08
H100: ?? | I100: Intermediate Bioenergy carrier (crude glycerine) | J100: Chemical and chemical products | K100: ='Feedstock MIX per IVC'!J33 -> 0.51775505 | L100: =K100*F$91 -> 4372005.3
A101: IVC 9a | B101: 1275 | C101: =B101*F101 -> 1.5944102e+10 | D101: ='[1]GAP analysis Sc. 2'!$M$144 -> 14.946 | E101: ='[2]Conversion factors selected IV '!$O$52 -> 0.83669065 | F101: =D101*E101*1000000 -> 12505178 | G101: ='LCoP 2030 HIGH'!E14 -> 1372.1512 | H101: =G101*F101 -> 1.7158996e+10 | I101: ='LCoP 2030 HIGH'!H14 -> 0.15461215 | L101: =I101*H101 -> 2.6529892e+09 | M101: ='LCoP 2030 HIGH'!F14 -> 0.58302611 | O101: =M101*H101 -> 1.0004143e+10 | P101: ='LCoP 2030 HIGH'!G14 -> 0.26236175 | R101: 2.9932641e+08
C102: for consumption | D102: ='[1]GAP analysis Sc. 2'!$N$144 -> 0.36997008 | F102: Food, beverages and tobacco products | G102: =SUMIF($J$102:$J$111,F102,$L$102:$L$111)/$L$101 -> 0.014721565 | I102: Straw | J102: Products of agriculture, hunting and related services | K102: ='Feedstock MIX per IVC'!J50 -> 117.73884 | L102: =K102*F$101 -> 1.4723452e+09 | M102: Fabricated metal products | N102: 0 | O102: =N102*O$101 -> 0 | P102: Electricity, gas, steam and air conditioning | Q102: 0.25 | R102: =Q102*R$101 -> 74831601
...

Sheet 2030 costs Sc 3
A1: Contribution of each IVC to final product in Scenario (3) 2030
A2: Assumptions:
A3: technical capacity = no constraints | E3: feedstock availability: 2030 high
D5: produced in Mtoe | E5: Conversion factor [t/toe] | F5: produced in t | G5: Cost of production [€/t] | H5: Money spent on each IVC | I5: Feedstock share of costs | J5: Eurostat sector | K5: money [€] spent on each feedtsock when producing 1t of product | L5: Absolute feedstock costs [€] | M5: CAPEX share of costs | N5: CAPEX distribution | O5: Absoluet CAPEX [€] | P5: OPEX share of costs | R5: Absolute OPEX [€] | S5: TOTAL production costs
A6: Sum ALL advanced | B6: Market price [€(t] | C6: Makret value of overall amount produced | D6: =D8+D48+D90+D123+D163 -> 102.37541
A7: Advanced biodiesel
A8: TOTAL | D8: =D28+D9+D16 -> 10.021837 | F8: =F28+F9+F16 -> 9715725.4 | H8: =H28+H9+H16 -> 2.1491397e+10 | L8: =L28+L9+L16 -> 2.7000504e+09 | O8: =O9+O16+O28 -> 1.1141155e+10 | R8: =R9+R16+R28 -> 7.6501915e+09
A9: of which IVC 2 HVO | B9: 1750 | C9: =B9*F9 -> 7.8465261e+08 | D9: ='[1]GAP analysis Sc. 3'!$J$27 -> 0.47120494 | E9: ='[2]Conversion factors selected IV '!$O$7 -> 0.95154545 | F9: =D9*E9*1000000 -> 448372.92 | G9: ='LCoP 2030 HIGH'!E3 -> 1281.9315 | H9: =G9*F9 -> 5.7478338e+08 | I9: ='LCoP 2030 HIGH'!H3 -> 0.47423088 | L9: =I9*H9 -> 2.7258003e+08 | M9: ='LCoP 2030 HIGH'!F3 -> 0.2098396 | O9: =M9*H9 -> 1.2061232e+08 | P9: ='LCoP 2030 HIGH'!G3 -> 0.31592951 | R9: =P9*H9 -> 1.8159103e+08 | S9: =L9+O9+R9 -> 5.7478338e+08
G10: Products of agriculture, hunting and related services | H10: =L10/L9 -> 0.21075509 | I10: Tall oil | J10: Products of agriculture, hunting and related services | K10: ='Feedstock MIX per IVC'!J6 -> 128.12466 | L10: =K10*F$9 -> 57447629 | M10: Fabricated metal products | N10: 0.05 | O10: =N10*O$9 -> 6030615.8 | P10: Electricity, gas, steam and air conditioning | Q10: 0.35 | R10: =Q10*R$9 -> 63556862
G11: Advanced biodiesel | H11: =L11/L9 -> 0.67085817 | I11: FPBO (Intermediate bioenergy carrier) | J11: Advanced biodiesel | K11: ='Feedstock MIX per IVC'!J7*0.85 -> 407.83583 | L11: =K11*F$9 -> 1.8286254e+08 | M11: Electrical equipment | N11: 0.02 | O11: =N11*O$9 -> 2412246.3 | P11: Chemicals and chemical products | Q11: 0.25 | R11: =Q11*R$9 -> 45397758
G12: Chemicals and chemical products | H12: =L12/L9 -> 0.11838674 | I12: biocrude (Intermediate Bioenergy carrier) | J12: Chemicals and chemical products | K12: ='Feedstock MIX per IVC'!J7*0.15 -> 71.971029 | L12: =K12*F$9 -> 32269860 | M12: Machinery and equipment n.e.c. | N12: 0.45 | O12: =N12*O$9 -> 54275542 | P12: Legal and accounting services; services of head offices; management consultancy services | Q12: 0.2 | R12: =Q12*R$9 -> 36318207
M13: Constructions and construction works | N13: 0.15 | O13: =N13*O$9 -> 18091847 | P13: Repair and installation services of machinery and equipment | Q13: 0.15 | R13: =Q13*R$9 -> 27238655
M14: Architectural and engineering services; technical testing and analysis services | N14: 0.3 | O14: =N14*O$9 -> 36183695 | P14: Land transport services and transport services via pipelines | Q14: 0.05 | R14: =Q14*R$9 -> 9079551.7
I15: Sum | L15: =SUM(L10:L12) -> 2.7258003e+08 | M15: Computer, electronic and optical products | N15: 0.03 | O15: =N15*O$9 -> 3618369.5
A16: of which IVC 11a (road) | B16: 1750 | C16: =B16*F16 -> 9.7352608e+09 | D16: ='[1]GAP analysis Sc. 3'!$J$28 -> 5.8462853 | E16: ='[2]Conversion factors selected IV '!$O$64 -> 0.95154545 | F16: =D16*E16*1000000 -> 5563006.2 | G16: ='LCoP 2030 HIGH'!E16 -> 2696.299 | H16: =G16*F16 -> 1.4999528e+10 | I16: ='LCoP 2030 HIGH'!H16 -> 0.109891 | L16: =I16*H16 -> 1.6483131e+09 | M16: ='LCoP 2030 HIGH'!F16 -> 0.5359198 | O16: =M16*H16 -> 8.0385439e+09 | P16: ='LCoP 2030 HIGH'!G16 -> 0.35418921 | R16: =P16*H16 -> 5.3126709e+09 | S16: =L16+O16+R16 -> 1.4999528e+10
G17: Sewerage services; sewage sludge; waste collection, treatment and disposal services; materials recovery services; remediation services and other waste management services | H17: =SUMIF($J$17:$J$26,G17,$L$17:$L$26)/$L$16 -> 0 | I17: Straw | J17: Products of agriculture, hunting and related services | K17: ='Feedstock MIX per IVC'!J63 -> 161.99072 | L17: =K17*F$16 -> 9.0115536e+08 | M17: Fabricated metal products | N17: 0 | O17: =N17*O$16 -> 0 | P17: Electricity, gas, steam and air conditioning | Q17: 0.25 | R17: =Q17*R$16 -> 1.3281677e+09
G18: Food, beverages and tobacco products | H18: =SUMIF($J$17:$J$26,G18,$L$17:$L$26)/$L$16 -> 0.014502397 | I18: Prunings & damaged crops | J18: Products of agriculture, hunting and related services | K18: ='Feedstock MIX per IVC'!J64 -> 8.4731123 | L18: =K18*F$16 -> 47135976 | M18: Electrical equipment | N18: 0.02 | O18: =N18*O$16 -> 1.6077088e+08 | P18: Chemicals and chemical products | Q18: 0.15 | R18: =Q18*R$16 -> 7.9690063e+08
G19: Products of agriculture, hunting and related services | H19: =SUMIF($J$17:$J$26,G19,$L$17:$L$26)/$L$16 -> 0.62196372 | I19: Sewage sludge | J19: Sewerage services; sewage sludge; waste collection, treatment and disposal services; materials recovery services; remediation services and other waste management services | K19: ='Feedstock MIX per IVC'!J65 -> 0 | L19: =K19*F$16 -> 0 | M19: Machinery and equipment n.e.c. | N19: 0.55 | O19: =N19*O$16 -> 4.4211992e+09 | P19: Legal and accounting services; services of head offices; management consultancy services | Q19: 0.3 | R19: =Q19*R$16 -> 1.5938013e+09
G20: Products of forestry, logging and related services | H20: =SUMIF($J$17:$J$26,G20,$L$17:$L$26)/$L$16 -> 0.1487034 | I20: Agroprocessing residues - maize cobs | J20: Food, beverages and tobacco products | K20: ='Feedstock MIX per IVC'!J66 -> 4.2970453 | L20: =K20*F$16 -> 23904490 | M20: Constructions and construction works | N20: 0.1 | O20: =N20*O$16 -> 8.0385439e+08 | P20: Repair and installation services of machinery and equipment | Q20: 0.3 | R20: =Q20*R$16 -> 1.5938013e+09
G21: Paper and paper products | H21: =SUMIF($J$17:$J$26,G21,$L$17:$L$26)/$L$16 -> 0.18227674 | I21: Lignocrops abandoned degraded | J21: Products of agriculture, hunting and related services | K21: ='Feedstock MIX per IVC'!J67 -> 8.1190082 | L21: =K21*F$16 -> 45166093 | M21: Architectural and engineering services; technical testing and analysis services | N21: 0.3 | O21: =N21*O$16 -> 2.4115632e+09 | P21: Land transport services and transport services via pipelines | Q21: 0 | R21: =Q21*R$16 -> 0
G22: Advanced biodiesel | H22: =SUMIF($J$17:$J$26,G22,$L$17:$L$26)/$L$16 -> 0.032553744 | I22: Lignocrops inter & cover cropping | J22: Products of agriculture, hunting and related services | K22: ='Feedstock MIX per IVC'!J68 -> 5.7043807 | L22: =K22*F$16 -> 31733505 | M22: Computer, electronic and optical products | N22: 0.03 | O22: =N22*O$16 -> 2.4115632e+08
H23: =SUM(H17:H22) -> 1 | I23: Primary forestry residues | J23: Products of forestry, logging and related services | K23: ='Feedstock MIX per IVC'!J69 -> 44.060666 | L23: =K23*F$16 -> 2.4510976e+08
I24: Secondary forest residues | J24: Paper and paper products | K24: ='Feedstock MIX per IVC'!J70 -> 54.008411 | L24: =K24*F$16 -> 3.0044913e+08
I25: Biowastes - Post consumer wood | J25: Sewerage services; sewage sludge; waste collection, treatment and disposal services; materials recovery services; remediation services and other waste management services | K25: ='Feedstock MIX per IVC'!J71 -> 0 | L25: =K25*F$16 -> 0
I26: Intermediate Bioenergy carriers (FPBO with lower quality ) | J26: Advanced biodiesel | K26: ='Feedstock MIX per IVC'!J72 -> 9.6456413 | L26: =K26*F$16 -> 53658762
I27: Sum | L27: =SUM(L17:L26) -> 1.6483131e+09
A28: of which 13a (half) | B28: 1750 | C28: =B28*F28 -> 6.4826061e+09 | D28: ='[1]GAP analysis Sc. 3'!$J$29 -> 3.7043463 | E28: ='[2]Conversion factors selected IV '!$O$89 -> 1 | F28: =D28*E28*1000000 -> 3704346.3 | G28: ='LCoP 2030 HIGH'!E20 -> 1597.336 | H28: =G28*F28 -> 5.9170857e+09 | I28: ='LCoP 2030 HIGH'!H20 -> 0.13167923 | L28: =I28*H28 -> 7.791573e+08 | M28: ='LCoP 2030 HIGH'!F20 -> 0.50396411 | O28: =M28*H28 -> 2.9819988e+09 | P28: ='LCoP 2030 HIGH'!G20 -> 0.36435666 | R28: =P28*H28 -> 2.1559296e+09 | S28: =L28+O28+R28 -> 5.9170857e+09
G29: Sewerage services; sewage sludge; waste collection, treatment and disposal services; materials recovery services; remediation services and other waste management services | H29: =SUMIF($J$29:$J$36,G29,$L$29:$L$36)/$L$28 -> 0 | I29: Straw | J29: Products of agriculture, hunting and related services | K29: ='Feedstock MIX per IVC'!J89 -> 115.98101 | L29: =K29*F$28 -> 4.2963384e+08 | M29: Fabricated metal products | N29: 0.15 | O29: =N29*O$28 -> 4.4729982e+08 | P29: Electricity, gas, steam and air conditioning | Q29: 0.15 | R29: =Q29*R$28 -> 3.2338943e+08
G30: Food, beverages and tobacco products | H30: =SUMIF($J$29:$J$36,G30,$L$29:$L$36)/$L$28 -> 0.014626929 | I30: Prunings & damaged crops | J30: Products of agriculture, hunting and related services | K30: ='Feedstock MIX per IVC'!J90 -> 6.0665214 | L30: =K30*F$28 -> 22472496 | M30: Electrical equipment | N30: 0.02 | O30: =N30*O$28 -> 59639976 | P30: Chemicals and chemical products | Q30: 0.25 | R30: =Q30*R$28 -> 5.3898239e+08
G31: Products of agriculture, hunting and related services | H31: =SUMIF($J$29:$J$36,G31,$L$29:$L$36)/$L$28 -> 0.62730453 | I31: Agroprocessing residues - maize cobs | J31: Food, beverages and tobacco products | K31: ='Feedstock MIX per IVC'!J91 -> 3.0765693 | L31: =K31*F$28 -> 11396678 | M31: Machinery and equipment n.e.c. | N31: 0.45 | O31: =N31*O$28 -> 1.3418995e+09 | P31: Legal and accounting services; services of head offices; management consultancy services | Q31: 0.2 | R31: =Q31*R$28 -> 4.3118591e+08
G32: Products of forestry, logging and related services | H32: =SUMIF($J$29:$J$36,G32,$L$29:$L$36)/$L$28 -> 0.16087373 | I32: Lignocrops abandoned degraded | J32: Products of agriculture, hunting and related services | K32: ='Feedstock MIX per IVC'!J92 -> 5.8129924 | L32: =K32*F$28 -> 21533337 | M32: Constructions and construction works | N32: 0.1 | O32: =N32*O$28 -> 2.9819988e+08 | P32: Repair and installation services of machinery and equipment | Q32: 0.3 | R32: =Q32*R$28 -> 6.4677887e+08
G33: Paper and paper products | H33: =SUMIF($J$29:$J$36,G33,$L$29:$L$36)/$L$28 -> 0.19719481 | I33: Lignocrops inter & cover cropping | J33: Products of agriculture, hunting and related services | K33: ='Feedstock MIX per IVC'!J93 -> 4.0841838 | L33: =K33*F$28 -> 15129231 | M33: Architectural and engineering services; technical testing and analysis services | N33: 0.25 | O33: =N33*O$28 -> 7.454997e+08 | P33: Land transport services and transport services via pipelines | Q33: 0.1 | R33: =Q33*R$28 -> 2.1559296e+08
G34: Advanced biodiesel | I34: Primary forestry residues | J34: Products of forestry, logging and related services | K34: ='Feedstock MIX per IVC'!J94 -> 33.837534 | L34: =K34*F$28 -> 1.2534594e+08 | M34: Computer, electronic and optical products | N34: 0.03 | O34: =N34*O$28 -> 89459964 | Q34: =SUM(Q29:Q33) -> 1
H35: =SUM(H29:H34) -> 1 | I35: Secondary forest residues | J35: Paper and paper products | K35: ='Feedstock MIX per IVC'!J95 -> 41.477163 | L35: =K35*F$28 -> 1.5364578e+08
I36: Biowastes - Post consumer wood | J36: Sewerage services; sewage sludge; waste collection, treatment and disposal services; materials recovery services; remediation services and other waste management services | K36: ='Feedstock MIX per IVC'!J96 -> 0 | L36: =K36*F$28 -> 0
I37: SUM | L37: =SUM(L29:L36) -> 7.791573e+08
I38: TOTALS domestic | M38: TOTALS | O38: =SUM(O39:O44) -> 1.2874578e+10 | P38: TOTALS | R38: =SUM(R39:R43) -> 9.7847053e+09
J39: Products of agriculture, hunting and related services | L39: =SUMIF($J$10:$J$190, J39, $L$10:$L$191) -> 2.629848e+09 | M39: Fabricated metal products | O39: =SUMIF($M$10:$M$188, M39, $O$10:$O$188) -> 7.1334382e+08 | P39: Electricity, gas, steam and air conditioning | R39: =SUMIF($P$10:$P$187, P39, $R$10:$R$187) -> 2.0352911e+09
J40: Products of forestry, logging and related services | L40: =SUMIF($J$10:$J$190, J40, $L$10:$L$191) -> 6.0581107e+08 | M40: Electrical equipment | O40: =SUMIF($M$10:$M$188, M40, $O$10:$O$188) -> 2.5749155e+08 | P40: Chemicals and chemical products | R40: =SUMIF($P$10:$P$187, P40, $R$10:$R$187) -> 1.9149092e+09
J41: Paper and paper products | L41: =SUMIF($J$10:$J$190, J41, $L$10:$L$191) -> 7.4258735e+08 | M41: Machinery and equipment n.e.c. | O41: =SUMIF($M$10:$M$188, M41, $O$10:$O$188) -> 6.5974143e+09 | P41: Legal and accounting services; services of head offices; management consultancy services | R41: =SUMIF($P$10:$P$187, P41, $R$10:$R$187) -> 2.4882081e+09
J42: Food, beverages and tobacco products | L42: =SUMIF($J$10:$J$190, J42, $L$10:$L$191) -> 58939524 | M42: Constructions and construction works | O42: =SUMIF($M$10:$M$188, M42, $O$10:$O$188) -> 1.2934884e+09 | P42: Repair and installation services of machinery and equipment | R42: =SUMIF($P$10:$P$187, P42, $R$10:$R$187) -> 2.9081729e+09
J43: Sewerage services; sewage sludge; waste collection, treatment and disposal services; materials recovery services; remediation services and other waste management services | L43: =SUMIF($J$10:$J$190, J43, $L$10:$L$191) -> 0 | M43: Architectural and engineering services; technical testing and analysis services | O43: =SUMIF($M$10:$M$188, M43, $O$10:$O$188) -> 3.6266022e+09 | P43: Land transport services and transport services via pipelines | R43: =SUMIF($P$10:$P$187, P43, $R$10:$R$187) -> 4.3812389e+08
J44: Advanced biodiesel | L44: =SUMIF($J$10:$J$190, J44, $L$10:$L$191) -> 2.365213e+08 | M44: Computer, electronic and optical products | O44: =SUMIF($M$10:$M$188, M44, $O$10:$O$188) -> 3.8623733e+08
J45: Chemicals and chemical products | L45: =SUMIF($J$10:$J$190, J45, $L$10:$L$191) -> 32269860
I46: SUM | L46: =SUM(L39:L45) -> 4.3059771e+09
A47: Advanced biogasoline
C48: =C49+C56+C63+C72 -> 3.7929669e+10 | D48: =D49+D56+D63+D72 -> 25.938202 | F48: =F49+F56+F63+F72 -> 34016962 | L48: =L49+L56+L63+L72 -> 9.5820851e+09 | O48: =O49+O56+O63+O72 -> 1.667488e+10 | R48: =R49+R56+R63+R72 -> 1.8447407e+10
A49: of which from IVC 5 | B49: 1000 | C49: =B49*F49 -> 7.8983376e+09 | D49: ='[1]GAP analysis Sc. 3'!$J$31 -> 5.0935109 | E49: ='[2]Conversion factors selected IV '!$O$17 -> 1.5506667 | F49: =D49*E49*1000000 -> 7898337.6 | G49: ='LCoP 2030 HIGH'!E5 -> 1387.0526 | H49: =G49*F49 -> 1.095541e+10 | I49: ='LCoP 2030 HIGH'!H5 -> 0.22785916 | L49: =I49*H49 -> 2.4962905e+09 | M49: ='LCoP 2030 HIGH'!F5 -> 0.40012901 | O49: =M49*H49 -> 4.3835774e+09 | P49: ='LCoP 2030 HIGH'!G5 -> 0.37201183 | R49: =P49*H49 -> 4.0755422e+09 | S49: =R49+O49+L49 -> 1.095541e+10
C50: =C49/C48 -> 0.2082364 | F50: Products of agriculture, hunting and related services | G50: =(SUMIF($J$50:$J$53, F50,$L$50:$L$53)/$L$49) -> 0.79882414 | H50: domestic | I50: Straw | J50: Products of agriculture, hunting and related services | K50: ='Feedstock MIX per IVC'!J13 -> 232.61998 | L50: =K50*F$49 -> 1.8373112e+09 | M50: Fabricated metal products | N50: 0 | O50: =N50*O$49 -> 0 | P50: Electricity, gas, steam and air conditioning | Q50: 0.2 | R50: =Q50*R$49 -> 8.1510844e+08
F51: Paper and paper products | G51: =(SUMIF($J$50:$J$53, F51,$L$50:$L$53)/$L$49) -> 0.20117586 | H51: domestic | I51: Lignocrops abandoned degraded | J51: Products of agriculture, hunting and related services | K51: ='Feedstock MIX per IVC'!J14 -> 11.658962 | L51: =K51*F$49 -> 92086416 | M51: Electrical equipment | N51: 0.02 | O51: =N51*O$49 -> 87671548 | P51: Chemicals and chemical products | Q51: 0.5 | R51: =Q51*R$49 -> 2.0377711e+09
H52: domestic | I52: Lignocrops inter & cover cropping | J52: Products of agriculture, hunting and related services | K52: ='Feedstock MIX per IVC'!J15 -> 8.1915371 | L52: =K52*F$49 -> 64699525 | M52: Machinery and equipment n.e.c. | N52: 0.5 | O52: =N52*O$49 -> 2.1917887e+09 | P52: Legal and accounting services; services of head offices; management consultancy services | Q52: 0.15 | R52: =Q52*R$49 -> 6.1133133e+08
H53: domestic | I53: Secondary forest residues | J53: Paper and paper products | K53: ='Feedstock MIX per IVC'!J16 -> 63.582165 | L53: =K53*F$49 -> 5.021934e+08 | M53: Constructions and construction works | N53: 0.15 | O53: =N53*O$49 -> 6.5753661e+08 | P53: Repair and installation services of machinery and equipment | Q53: 0.1 | R53: =Q53*R$49 -> 4.0755422e+08
M54: Architectural and engineering services; technical testing and analysis services | N54: 0.3 | O54: =N54*O$49 -> 1.3150732e+09 | P54: Land transport services and transport services via pipelines | Q54: 0.05 | R54: =Q54*R$49 -> 2.0377711e+08
M55: Computer, electronic and optical products | N55: 0.03 | O55: =N55*O$49 -> 1.3150732e+08
A56: of which 12 (road) | B56: 1000 | C56: =B56*F56 -> 1.4851294e+10 | D56: ='[1]GAP analysis Sc. 3'!$J$32 -> 9.577361 | E56: ='[2]Conversion factors selected IV '!$O$86 -> 1.5506667 | F56: =D56*E56*1000000 -> 14851294 | G56: ='LCoP 2030 HIGH'!E18 -> 988.03814 | H56: =G56*F56 -> 1.4673645e+10 | I56: ='LCoP 2030 HIGH'!H18 -> 0.32087642 | L56: =I56*H56 -> 4.7084268e+09 | M56: ='LCoP 2030 HIGH'!F18 -> 0.28136566 | O56: =M56*H56 -> 4.1286599e+09 | P56: ='LCoP 2030 HIGH'!G18 -> 0.39775792 | R56: =P56*H56 -> 5.8365587e+09 | S56: =R56+O56+L56 -> 1.4673645e+10
G57: Advanced biogas | H57: 1 | I57: Intermediate Bioenergy carriers (Syngas) | J57: Advanced biogas | K57: ='Feedstock MIX per IVC'!J85 -> 317.03814 | L57: =K57*F56 -> 4.7084268e+09 | M57: Fabricated metal products | N57: 0 | O57: =N57*O$56 -> 0 | P57: Electricity, gas, steam and air conditioning | Q57: 0.2 | R57: =Q57*R$56 -> 1.1673117e+09
M58: Electrical equipment | N58: 0.02 | O58: =N58*O$56 -> 82573197 | P58: Chemicals and chemical products | Q58: 0.5 | R58: =Q58*R$56 -> 2.9182794e+09
M59: Machinery and equipment n.e.c. | N59: 0.5 | O59: =N59*O$56 -> 2.0643299e+09 | P59: Legal and accounting services; services of head offices; management consultancy services | Q59: 0.15 | R59: =Q59*R$56 -> 8.7548381e+08
M60: Constructions and construction works | N60: 0.15 | O60: =N60*O$56 -> 6.1929898e+08 | P60: Repair and installation services of machinery and equipment | Q60: 0.1 | R60: =Q60*R$56 -> 5.8365587e+08
M61: Architectural and engineering services; technical testing and analysis services | N61: 0.3 | O61: =N61*O$56 -> 1.238598e+09 | P61: Land transport services and transport services via pipelines | Q61: 0.05 | R61: =Q61*R$56 -> 2.9182794e+08
M62: Computer, electronic and optical products | N62: 0.03 | O62: =N62*O$56 -> 1.238598e+08
A63: of which 13a (half) | B63: 1750 | C63: =B63*F63 -> 6.4826061e+09 | D63: ='[1]GAP analysis Sc. 3'!$J$33 -> 3.7043463 | E63: ='[2]Conversion factors selected IV '!$O$89 -> 1 | F63: =D63*E63*1000000 -> 3704346.3 | G63: ='LCoP 2030 HIGH'!E20 -> 1597.336 | H63: =G63*F63 -> 5.9170857e+09 | I63: ='LCoP 2030 HIGH'!H20 -> 0.13167923 | L63: =I63*H63 -> 7.791573e+08 | M63: ='LCoP 2030 HIGH'!F20 -> 0.50396411 | O63: =M63*H63 -> 2.9819988e+09 | P63: ='LCoP 2030 HIGH'!G20 -> 0.36435666 | R63: =P63*H63 -> 2.1559296e+09 | S63: =L63+O63+R63 -> 5.9170857e+09
F64: Sewerage services; sewage sludge; waste collection, treatment and disposal services; materials recovery services; remediation services and other waste management services | G64: =(SUMIF($J$64:$J$71, F64,$L$64:$L$71)/$L$63) -> 0 | H64: domestic | I64: Straw | J64: Products of agriculture, hunting and related services | K64: ='Feedstock MIX per IVC'!J89 -> 115.98101 | L64: =K64*F$63 -> 4.2963384e+08 | M64: Fabricated metal products | N64: 0.15 | O64: =N64*O$63 -> 4.4729982e+08 | P64: Electricity, gas, steam and air conditioning | Q64: 0.15 | R64: =Q64*R$63 -> 3.2338943e+08
F65: Food, beverages and tobacco products | G65: =(SUMIF($J$64:$J$71, F65,$L$64:$L$71)/$L$63) -> 0.014626929 | H65: domestic | I65: Prunings & damaged crops | J65: Products of agriculture, hunting and related services | K65: ='Feedstock MIX per IVC'!J90 -> 6.0665214 | L65: =K65*F$63 -> 22472496 | M65: Electrical equipment | N65: 0.02 | O65: =N65*O$63 -> 59639976 | P65: Chemicals and chemical products | Q65: 0.25 | R65: =Q65*R$63 -> 5.3898239e+08
F66: Products of agriculture, hunting and related services | G66: =(SUMIF($J$64:$J$71, F66,$L$64:$L$71)/$L$63) -> 0.62730453 | H66: domestic | I66: Agroprocessing residues - maize cobs | J66: Food, beverages and tobacco products | K66: ='Feedstock MIX per IVC'!J91 -> 3.0765693 | L66: =K66*F$63 -> 11396678 | M66: Machinery and equipment n.e.c. | N66: 0.45 | O66: =N66*O$63 -> 1.3418995e+09 | P66: Legal and accounting services; services of head offices; management consultancy services | Q66: 0.2 | R66: =Q66*R$63 -> 4.3118591e+08
F67: Products of forestry, logging and related services | G67: =(SUMIF($J$64:$J$71, F67,$L$64:$L$71)/$L$63) -> 0.16087373 | H67: domestic | I67: Lignocrops abandoned degraded | J67: Products of agriculture, hunting and related services | K67: ='Feedstock MIX per IVC'!J92 -> 5.8129924 | L67: =K67*F$63 -> 21533337 | M67: Constructions and construction works | N67: 0.1 | O67: =N67*O$63 -> 2.9819988e+08 | P67: Repair and installation services of machinery and equipment | Q67: 0.3 | R67: =Q67*R$63 -> 6.4677887e+08
F68: Paper and paper products | G68: =(SUMIF($J$64:$J$71, F68,$L$64:$L$71)/$L$63) -> 0.19719481 | H68: domestic | I68: Lignocrops inter & cover cropping | J68: Products of agriculture, hunting and related services | K68: ='Feedstock MIX per IVC'!J93 -> 4.0841838 | L68: =K68*F$63 -> 15129231 | M68: Architectural and engineering services; technical testing and analysis services | N68: 0.25 | O68: =N68*O$63 -> 7.454997e+08 | P68: Land transport services and transport services via pipelines | Q68: 0.1 | R68: =Q68*R$63 -> 2.1559296e+08
F69: Advanced biodiesel | G69: =(SUMIF($J$64:$J$71, F69,$L$64:$L$71)/$L$63) -> 0 | H69: domestic | I69: Primary forestry residues | J69: Products of forestry, logging and related services | K69: ='Feedstock MIX per IVC'!J94 -> 33.837534 | L69: =K69*F$63 -> 1.2534594e+08 | M69: Computer, electronic and optical products | N69: 0.03 | O69: =N69*O$63 -> 89459964
G70: =SUM(G64:G69) -> 1 | H70: domestic | I70: Secondary forest residues | J70: Paper and paper products | K70: ='Feedstock MIX per IVC'!J95 -> 41.477163 | L70: =K70*F$63 -> 1.5364578e+08
H71: domestic | I71: Biowastes - Post consumer wood | J71: Sewerage services; sewage sludge; waste collection, treatment and disposal services; materials recovery services; remediation services and other waste management services | K71: ='Feedstock MIX per IVC'!J96 -> 0 | L71: =K71*F$63 -> 0
A72: of which 13b (road) | B72: 1150 | C72: =B72*F72 -> 8.6974312e+09 | D72: ='[1]GAP analysis Sc. 3'!$J$34 -> 7.5629836 | E72: ='[2]Conversion factors selected IV '!$O$125 -> 1 | F72: =D72*E72*1000000 -> 7562983.6 | G72: ='LCoP 2030 HIGH'!E22 -> 1739.8201 | H72: =G72*F72 -> 1.3158231e+10 | I72: ='LCoP 2030 HIGH'!H22 -> 0.12146089 | L72: =I72*H72 -> 1.5982105e+09 | M72: ='LCoP 2030 HIGH'!F22 -> 0.39371887 | O72: =M72*H72 -> 5.1806438e+09 | P72: ='LCoP 2030 HIGH'!G22 -> 0.48482024 | R72: =P72*H72 -> 6.3793767e+09 | S72: =L72+O72+R72 -> 1.3158231e+10
F73: Sewerage services; sewage sludge; waste collection, treatment and disposal services; materials recovery services; remediation services and other waste management services | G73: =(SUMIF($J$73:$J$80, F73,$L$73:$L$80)/$L$72) -> 0 | H73: domestic | I73: Straw | J73: Products of agriculture, hunting and related services | K73: ='Feedstock MIX per IVC'!J107 -> 113.38995 | L73: =K73*F$72 -> 8.5756631e+08 | M73: Fabricated metal products | N73: 0.15 | O73: =N73*O$72 -> 7.7709657e+08 | P73: Electricity, gas, steam and air conditioning | Q73: 0.15 | R73: =Q73*R$72 -> 9.569065e+08
F74: Food, beverages and tobacco products | G74: =(SUMIF($J$73:$J$80, F74,$L$73:$L$80)/$L$72) -> 0.01423356 | H74: domestic | I74: Prunings & damaged crops | J74: Products of agriculture, hunting and related services | K74: ='Feedstock MIX per IVC'!J108 -> 5.9309927 | L74: =K74*F$72 -> 44856000 | M74: Electrical equipment | N74: 0.02 | O74: =N74*O$72 -> 1.0361288e+08 | P74: Chemicals and chemical products | Q74: 0.25 | R74: =Q74*R$72 -> 1.5948442e+09
F75: Products of agriculture, hunting and related services | G75: =(SUMIF($J$73:$J$80, F75,$L$73:$L$80)/$L$72) -> 0.6373276 | H75: domestic | I75: Agroprocessing residues - maize cobs | J75: Food, beverages and tobacco products | K75: ='Feedstock MIX per IVC'!J109 -> 3.0078374 | L75: =K75*F$72 -> 22748225 | M75: Machinery and equipment n.e.c. | N75: 0.45 | O75: =N75*O$72 -> 2.3312897e+09 | P75: Legal and accounting services; services of head offices; management consultancy services | Q75: 0.2 | R75: =Q75*R$72 -> 1.2758753e+09
F76: Products of forestry, logging and related services | G76: =(SUMIF($J$73:$J$80, F76,$L$73:$L$80)/$L$72) -> 0.15654728 | H76: domestic | I76: Lignocrops abandoned degraded | J76: Products of agriculture, hunting and related services | K76: ='Feedstock MIX per IVC'!J110 -> 11.366255 | L76: =K76*F$72 -> 85962801 | M76: Constructions and construction works | N76: 0.1 | O76: =N76*O$72 -> 5.1806438e+08 | P76: Repair and installation services of machinery and equipment | Q76: 0.3 | R76: =Q76*R$72 -> 1.913813e+09
F77: Paper and paper products | G77: =(SUMIF($J$73:$J$80, F77,$L$73:$L$80)/$L$72) -> 0.19189156 | H77: domestic | I77: Lignocrops inter & cover cropping | J77: Products of agriculture, hunting and related services | K77: ='Feedstock MIX per IVC'!J111 -> 3.9929413 | L77: =K77*F$72 -> 30198550 | M77: Architectural and engineering services; technical testing and analysis services | N77: 0.25 | O77: =N77*O$72 -> 1.2951609e+09 | P77: Land transport services and transport services via pipelines | Q77: 0.1 | R77: =Q77*R$72 -> 6.3793767e+08
F78: Advanced biodiesel | G78: =(SUMIF($J$73:$J$80, F78,$L$73:$L$80)/$L$72) -> 0 | H78: domestic | I78: Primary forestry residues | J78: Products of forestry, logging and related services | K78: ='Feedstock MIX per IVC'!J112 -> 33.081588 | L78: =K78*F$72 -> 2.5019551e+08 | M78: Computer, electronic and optical products | N78: 0.03 | O78: =N78*O$72 -> 1.5541931e+08
G79: =SUM(G73:G78) -> 1 | H79: domestic | I79: Secondary forest residues | J79: Paper and paper products | K79: ='Feedstock MIX per IVC'!J113 -> 40.550545 | L79: =K79*F$72 -> 3.066831e+08
H80: domestic | I80: Biowastes - Post consumer wood | J80: Sewerage services; sewage sludge; waste collection, treatment and disposal services; materials recovery services; remediation services and other waste management services | K80: ='Feedstock MIX per IVC'!J114 -> 0 | L80: =K80*F$72 -> 0
I82: TOTALS domestic | L82: =SUM(L83:L88) -> 9.5820851e+09 | M82: TOTALS | O82: =SUM(O83:O88) -> 1.667488e+10 | P82: TOTALS | R82: =SUM(R83:R87) -> 1.8447407e+10
J83: Products of agriculture, hunting and related services | L83: =SUMIF($J$50:$J$80, J83, $L$50:$L$80) -> 3.5014497e+09 | M83: Fabricated metal products | O83: =SUMIF($M$50:$M$78, M83, $O$50:$O$78) -> 1.2243964e+09 | P83: Electricity, gas, steam and air conditioning | R83: =SUMIF($P$50:$P$77, P83, $R$50:$R$77) -> 3.2627161e+09
J84: Products of forestry, logging and related services | L84: =SUMIF($J$50:$J$80, J84, $L$50:$L$80) -> 3.7554145e+08 | M84: Electrical equipment | O84: =SUMIF($M$50:$M$78, M84, $O$50:$O$78) -> 3.334976e+08 | P84: Chemicals and chemical products | R84: =SUMIF($P$50:$P$77, P84, $R$50:$R$77) -> 7.089877e+09
J85: Paper and paper products | L85: =SUMIF($J$50:$J$80, J85, $L$50:$L$80) -> 9.6252228e+08 | M85: Machinery and equipment n.e.c. | O85: =SUMIF($M$50:$M$78, M85, $O$50:$O$78) -> 7.9293078e+09 | P85: Legal and accounting services; services of head offices; management consultancy services | R85: =SUMIF($P$50:$P$77, P85, $R$50:$R$77) -> 3.1938764e+09
J86: Food, beverages and tobacco products | L86: =SUMIF($J$50:$J$80, J86, $L$50:$L$80) -> 34144903 | M86: Constructions and construction works | O86: =SUMIF($M$50:$M$78, M86, $O$50:$O$78) -> 2.0930998e+09 | P86: Repair and installation services of machinery and equipment | R86: =SUMIF($P$50:$P$77, P86, $R$50:$R$77) -> 3.551802e+09
J87: Sewerage services; sewage sludge; waste collection, treatment and disposal services; materials recovery services; remediation services and other waste management services | L87: =SUMIF($J$50:$J$80, J87, $L$50:$L$80) -> 0 | M87: Architectural and engineering services; technical testing and analysis services | O87: =SUMIF($M$50:$M$78, M87, $O$50:$O$78) -> 4.5943318e+09 | P87: Land transport services and transport services via pipelines | R87: =SUMIF($P$50:$P$77, P87, $R$50:$R$77) -> 1.3491357e+09
J88: Advanced biogas | L88: =SUMIF($J$50:$J$80, J88, $L$50:$L$80) -> 4.7084268e+09 | M88: Computer, electronic and optical products | O88: =SUMIF($M$50:$M$78, M88, $O$50:$O$78) -> 5.0024639e+08
A89: Advanced biogas
C90: =C91+C101 -> 5.1658114e+10 | D90: =D91+D101 -> 48.424311 | L90: =L91+L101 -> 1.1614334e+09 | O90: =O91+O101 -> 2.6053346e+10 | R90: =R91+R101 -> 1.4665472e+10
A91: IVC 7 | B91: 1275 | C91: =B91*F91 -> 4.158192e+10 | D91: ='[1]GAP analysis Sc. 3'!$J$36 -> 38.978887 | E91: ='[2]Conversion factors selected IV '!$O$29 -> 0.83669065 | F91: =D91*E91*1000000 -> 32613270 | G91: ='LCoP 2030 HIGH'!E10 -> 1029.7035 | H91: =G91*F91 -> 3.3581998e+10 | I91: ='LCoP 2030 HIGH'!H10 -> -0.015340841 | L91: =I91*H91 -> -5.151761e+08 | M91: ='LCoP 2030 HIGH'!F10 -> 0.58754778 | O91: =M91*H91 -> 1.9731029e+10 | P91: ='LCoP 2030 HIGH'!G10 -> 0.42779306 | R91: =P91*H91 -> 1.4366146e+10 | S91: =L91+O91+R91 -> 3.3581998e+10
G92: Food, beverages and tobacco products | H92: =(SUMIF($J$92:$J$100,G92,$L$92:$L$100)/$L$91) -> -0.2706585 | I92: Prunings & damaged crops (olive stones excluded) | J92: Products of agriculture, hunting and related services | K92: ='Feedstock MIX per IVC'!J25 -> 0.89326983 | L92: =K92*F$91 -> 29132450 | M92: Fabricated metal products | N92: 0.05 | O92: =N92*O$91 -> 9.8655143e+08 | P92: Electricity, gas, steam and air conditioning | Q92: 0.2 | R92: =Q92*R$91 -> 2.8732291e+09
G93: Products of agriculture, hunting and related services | H93: =(SUMIF($J$92:$J$100,G93,$L$92:$L$100)/$L$91) -> -1.2300084 | I93: Lignocrops abandoned degraded | J93: Products of agriculture, hunting and related services | K93: ='Feedstock MIX per IVC'!J26 -> 0.85601008 | L93: =K93*F$91 -> 27917288 | M93: Electrical equipment | N93: 0.02 | O93: =N93*O$91 -> 3.9462057e+08 | P93: Chemicals and chemical products | Q93: 0.5 | R93: =Q93*R$91 -> 7.1830728e+09
G94: Sewerage services; sewage sludge; waste collection, treatment and disposal services; materials recovery services; remediation services and other waste management services | H94: =(SUMIF($J$92:$J$100,G94,$L$92:$L$100)/$L$91) -> 2.5334435 | I94: Lignocrops inter & cover cropping | J94: Products of agriculture, hunting and related services | K94: ='Feedstock MIX per IVC'!J27 -> 0.60142905 | L94: =K94*F$91 -> 19614568 | M94: Machinery and equipment n.e.c. | N94: 0.4 | O94: =N94*O$91 -> 7.8924114e+09 | P94: Legal and accounting services; services of head offices; management consultancy services | Q94: 0.15 | R94: =Q94*R$91 -> 2.1549218e+09
G95: Chemical and chemical products | H95: =(SUMIF($J$92:$J$100,G95,$L$92:$L$100)/$L$91) -> -0.032776531 | I95: Agroprocessing residues | J95: Food, beverages and tobacco products | K95: ='Feedstock MIX per IVC'!J28 -> 4.2754617 | L95: =K95*F$91 -> 1.3943679e+08 | M95: Constructions and construction works | N95: 0.3 | O95: =N95*O$91 -> 5.9193086e+09 | P95: Repair and installation services of machinery and equipment | Q95: 0.1 | R95: =Q95*R$91 -> 1.4366146e+09
H96: =SUM(H92:H95) -> 1 | I96: Straw | J96: Products of agriculture, hunting and related services | K96: ='Feedstock MIX per IVC'!J29 -> 17.079141 | L96: =K96*F$91 -> 5.5700665e+08 | M96: Architectural and engineering services; technical testing and analysis services | N96: 0.2 | O96: =N96*O$91 -> 3.9462057e+09 | P96: Land transport services and transport services via pipelines | Q96: 0.05 | R96: =Q96*R$91 -> 7.1830728e+08
I97: Manure | J97: Products of agriculture, hunting and related services | K97: ='Feedstock MIX per IVC'!J30 -> 0 | L97: =K97*F$91 -> 0 | M97: Computer, electronic and optical products | N97: 0.03 | O97: =N97*O$91 -> 5.9193086e+08
I98: Sewage sludge | J98: Sewerage services; sewage sludge; waste collection, treatment and disposal services; materials recovery services; remediation services and other waste management services | K98: ='Feedstock MIX per IVC'!J31 -> 0 | L98: =K98*F$91 -> 0 | N98: =SUM(N92:N97) -> 1
I99: Biowastes (post consumer woods excluded) | J99: Sewerage services; sewage sludge; waste collection, treatment and disposal services; materials recovery services; remediation services and other waste management services | K99: ='Feedstock MIX per IVC'!J32 -> -40.019584 | L99: =K99*F$91 -> -1.3051695e+09
I100: Intermediate Bioenergy carrier (crude glycerine) | J100: Chemical and chemical products | K100: ='Feedstock MIX per IVC'!J33 -> 0.51775505 | L100: =K100*F$91 -> 16885685
A101: IVC 9a | B101: 1275 | C101: =B101*F101 -> 1.0076194e+10 | D101: ='[1]GAP analysis Sc. 3'!$J$37 -> 9.4454233 | E101: ='[2]Conversion factors selected IV '!$O$52 -> 0.83669065 | F101: =D101*E101*1000000 -> 7902897.3 | G101: ='LCoP 2030 HIGH'!E14 -> 1372.1512 | H101: =G101*F101 -> 1.084397e+10 | I101: ='LCoP 2030 HIGH'!H14 -> 0.15461215 | L101: =I101*H101 -> 1.6766095e+09 | M101: ='LCoP 2030 HIGH'!F14 -> 0.58302611 | O101: =M101*H101 -> 6.3223178e+09 | P101: ='LCoP 2030 HIGH'!G14 -> 0.26236175 | R101: 2.9932641e+08
G102: Sewerage services; sewage sludge; waste collection, treatment and disposal services; materials recovery services; remediation services and other waste management services | H102: =(SUMIF($J$102:$J$111,G102,$L$102:$L$111)/$L$101) -> 0 | I102: Straw | J102: Products of agriculture, hunting and related services | K102: ='Feedstock MIX per IVC'!J50 -> 117.73884 | L102: =K102*F$101 -> 9.3047796e+08 | M102: Fabricated metal products | N102: 0 | O102: =N102*O$101 -> 0 | P102: Electricity, gas, steam and air conditioning | Q102: 0.25 | R102: =Q102*R$101 -> 74831601
...

Sheet 2035 costs Sc 1
A1: Contribution of each IVC to final product in Scenario (1) 2035
A2: Assumptions:
A3: technical capacity = cmc | E3: feedstock availability: 2035 with 2030 medium and 2050 high
A4: assuming the feedstock split from 2030 medium
D5: produced in Mtoe | E5: Conversion factor [t/toe] | F5: produced in t | G5: Cost of production [€/t] | H5: Money spent on each IVC | I5: Feedstock share of costs | J5: Eurostat sector | K5: money [€] spent on each feedtsock when producing 1t of product | L5: Absolute feedstock costs [€] | M5: CAPEX share of costs | N5: CAPEX distribution | O5: Absoluet CAPEX [€] | P5: OPEX share of costs | R5: Absolute OPEX [€] | S5: TOTAL production costs
A6: SUMME ALL advanced | D6: =D8+D42+D84+D96+D129 -> 7.2164117 | F6: =F8+F42+F84+F96+F129 -> 8134018.7
A7: Advanced biodiesel
A8: TOTAL | C8: =C9+C23+C16 -> 4.0839384e+09 | D8: =D9+D23+D41+D16 -> 2.4737706 | F8: =F9+F23+F16 -> 2675247.4 | L8: =L9+L16+L23 -> 2.3752912e+09 | O8: =O9+O16+O23 -> 3.9723084e+08 | R8: =R9+R16+R23 -> 8.244265e+08
A9: of which IVC 1 | B9: 1450 | C9: =B9*F9 -> 2.8890987e+09 | D9: ='[1]GAP analysis Sc. 1'!$C$64 -> 1.7608156 | E9: ='[2]Conversion factors selected IV '!$O$4 -> 1.1315676 | F9: =D9*E9*1000000 -> 1992481.9 | G9: ='LCoP 2030 MEDIUM'!E2 -> 1350 | H9: =G9*F9 -> 2.6898505e+09 | I9: ='LCoP 2030 MEDIUM'!H2 -> 0.74074074 | L9: =I9*H9 -> 1.9924819e+09 | M9: ='LCoP 2030 MEDIUM'!F2 -> 0.061481481 | O9: =M9*H9 -> 1.6537599e+08 | P9: ='LCoP 2030 MEDIUM'!G2 -> 0.19777778 | R9: =P9*H9 -> 5.3199265e+08 | S9: =L9+O9+R9 -> 2.6898505e+09
C10: =C9/$C$8 -> 0.70742954 | H10: imported | I10: POME | J10: Food, beverages and tobacco products | K10: ='Feedstock MIX per IVC'!F8 -> 1 | L10: =L9 -> 1.9924819e+09 | M10: Fabricated metal products | N10: 0.05 | O10: =N10*O$9 -> 8268799.7 | P10: Electricity, gas, steam and air conditioning | Q10: 0.35 | R10: =Q10*R$9 -> 1.8619743e+08
M11: Electrical equipment | N11: 0.02 | O11: =N11*O$9 -> 3307519.9 | P11: Chemicals and chemical products | Q11: 0.25 | R11: =Q11*R$9 -> 1.3299816e+08
M12: Machinery and equipment n.e.c. | N12: 0.45 | O12: =N12*O$9 -> 74419197 | P12: Legal and accounting services; services of head offices; management consultancy services | Q12: 0.2 | R12: =Q12*R$9 -> 1.0639853e+08
M13: Constructions and construction works | N13: 0.15 | O13: =N13*O$9 -> 24806399 | P13: Repair and installation services of machinery and equipment | Q13: 0.15 | R13: =Q13*R$9 -> 79798898
M14: Architectural and engineering services; technical testing and analysis services | N14: 0.3 | O14: =N14*O$9 -> 49612798 | P14: Land transport services and transport services via pipelines | Q14: 0.05 | R14: =Q14*R$9 -> 26599633
M15: Computer, electronic and optical products | N15: 0.03 | O15: =N15*O$9 -> 4961279.8
A16: of which IVC 2 HVO | B16: 1750 | C16: =B16*F16 -> 1.0375e+09 | D16: ='[1]GAP analysis Sc. 1'!$C$65 -> 0.62304658 | E16: ='[2]Conversion factors selected IV '!$O$7 -> 0.95154545 | F16: =D16*E16*1000000 -> 592857.14 | G16: ='LCoP 2030 MEDIUM'!E3 -> 1287.6835 | H16: =G16*F16 -> 7.6341233e+08 | I16: ='LCoP 2030 MEDIUM'!H3 -> 0.47657943 | L16: =I16*H16 -> 3.6382662e+08 | M16: ='LCoP 2030 MEDIUM'!F3 -> 0.20890227 | O16: =M16*H16 -> 1.5947857e+08 | P16: ='LCoP 2030 MEDIUM'!G3 -> 0.31451829 | R16: =P16*H16 -> 2.4010714e+08 | S16: =L16+O16+R16 -> 7.6341233e+08
C17: =C16/$C$8 -> 0.25404399 | H17: imported | I17: POME | J17: Food, beverages and tobacco products | L17: =L16 -> 3.6382662e+08 | M17: Fabricated metal products | N17: 0.05 | O17: =N17*O$16 -> 7973928.6 | P17: Electricity, gas, steam and air conditioning | Q17: 0.35 | R17: =Q17*R$16 -> 84037500
M18: Electrical equipment | N18: 0.02 | O18: =N18*O$16 -> 3189571.4 | P18: Chemicals and chemical products | Q18: 0.25 | R18: =Q18*R$16 -> 60026786
M19: Machinery and equipment n.e.c. | N19: 0.45 | O19: =N19*O$16 -> 71765357 | P19: Legal and accounting services; services of head offices; management consultancy services | Q19: 0.2 | R19: =Q19*R$16 -> 48021429
M20: Constructions and construction works | N20: 0.15 | O20: =N20*O$16 -> 23921786 | P20: Repair and installation services of machinery and equipment | Q20: 0.15 | R20: =Q20*R$16 -> 36016071
M21: Architectural and engineering services; technical testing and analysis services | N21: 0.3 | O21: =N21*O$16 -> 47843571 | P21: Land transport services and transport services via pipelines | Q21: 0.05 | R21: =Q21*R$16 -> 12005357
M22: Computer, electronic and optical products | N22: 0.03 | O22: =N22*O$16 -> 4784357.1
A23: of which 13a (half) | B23: 1750 | C23: =B23*F23 -> 1.5733973e+08 | D23: ='[1]GAP analysis Sc. 1'!$C$66 -> 0.08990842 | E23: ='[2]Conversion factors selected IV '!$O$89 -> 1 | F23: =D23*E23*1000000 -> 89908.42 | G23: ='LCoP 2030 MEDIUM'!E20 -> 1598.1345 | H23: =G23*F23 -> 1.4368574e+08 | I23: ='LCoP 2030 MEDIUM'!H20 -> 0.13211308 | L23: =I23*H23 -> 18982766 | M23: ='LCoP 2030 MEDIUM'!F20 -> 0.50371231 | O23: =M23*H23 -> 72376278 | P23: ='LCoP 2030 MEDIUM'!G20 -> 0.36417461 | R23: =P23*H23 -> 52326700 | S23: =L23+O23+R23 -> 1.4368574e+08
C24: =C23/$C$8 -> 0.038526471 | F24: Products of agriculture, hunting and related services | G24: =SUMIF($J$24:$J$31,F24,$L$24:$L$31)/$L$23 -> 0.55703651 | H24: domestic | I24: Straw | J24: Products of agriculture, hunting and related services | K24: ='Feedstock MIX per IVC'!G89 -> 104.52294 | L24: =K24*F$23 -> 9397492.3 | M24: Fabricated metal products | N24: 0.15 | O24: =N24*O$23 -> 10856442 | P24: Electricity, gas, steam and air conditioning | Q24: 0.15 | R24: =Q24*R$23 -> 7849005
F25: Products of forestry, logging and related services | G25: =SUMIF($J$24:$J$31,F25,$L$24:$L$31)/$L$23 -> 0.22886406 | H25: domestic | I25: Prunings & damaged crops | J25: Products of agriculture, hunting and related services | K25: ='Feedstock MIX per IVC'!G90 -> 6.0040708 | L25: =K25*F$23 -> 539816.52 | M25: Electrical equipment | N25: 0.02 | O25: =N25*O$23 -> 1447525.6 | P25: Chemicals and chemical products | Q25: 0.25 | R25: =Q25*R$23 -> 13081675
F26: Paper and paper products | G26: =SUMIF($J$24:$J$31,F26,$L$24:$L$31)/$L$23 -> 0.20022694 | H26: domestic | I26: Agroprocessing residues - maize cobs | J26: Food, beverages and tobacco products | K26: ='Feedstock MIX per IVC'!G91 -> 2.9289602 | L26: =K26*F$23 -> 263338.18 | M26: Machinery and equipment n.e.c. | N26: 0.45 | O26: =N26*O$23 -> 32569325 | P26: Legal and accounting services; services of head offices; management consultancy services | Q26: 0.2 | R26: =Q26*R$23 -> 10465340
F27: Food, beverages and tobacco products | G27: =SUMIF($J$24:$J$31,F27,$L$24:$L$31)/$L$23 -> 0.013872488 | H27: domestic | I27: Lignocrops abandoned degraded | J27: Products of agriculture, hunting and related services | K27: ='Feedstock MIX per IVC'!G92 -> 4.8668638 | L27: =K27*F$23 -> 437572.03 | M27: Constructions and construction works | N27: 0.1 | O27: =N27*O$23 -> 7237627.8 | P27: Repair and installation services of machinery and equipment | Q27: 0.3 | R27: =Q27*R$23 -> 15698010
F28: Sewerage services; sewage sludge; waste collection, treatment and disposal services; materials recovery services; remediation services and other waste management services | G28: =SUMIF($J$24:$J$31,F28,$L$24:$L$31)/$L$23 -> 0 | H28: domestic | I28: Lignocrops inter & cover cropping | J28: Products of agriculture, hunting and related services | K28: ='Feedstock MIX per IVC'!G93 -> 2.2157284 | L28: =K28*F$23 -> 199212.64 | M28: Architectural and engineering services; technical testing and analysis services | N28: 0.25 | O28: =N28*O$23 -> 18094069 | P28: Land transport services and transport services via pipelines | Q28: 0.1 | R28: =Q28*R$23 -> 5232670
G29: =SUM(G24:G28) -> 1 | H29: domestic | I29: Primary forestry residues | J29: Products of forestry, logging and related services | K29: ='Feedstock MIX per IVC'!G94 -> 48.32109 | L29: =K29*F$23 -> 4344472.8 | M29: Computer, electronic and optical products | N29: 0.03 | O29: =N29*O$23 -> 2171288.3 | Q29: =SUM(Q24:Q28) -> 1
H30: domestic | I30: Secondary forest residues | J30: Paper and paper products | K30: ='Feedstock MIX per IVC'!G95 -> 42.274808 | L30: =K30*F$23 -> 3800861.1
H31: domestic | I31: Biowastes - Post consumer wood | J31: Sewerage services; sewage sludge; waste collection, treatment and disposal services; materials recovery services; remediation services and other waste management services | K31: ='Feedstock MIX per IVC'!G96 -> 0 | L31: =K31*F$23 -> 0
I33: TOTALS domestic | M33: TOTALS | O33: =SUM(O34:O39) -> 3.9723084e+08 | P33: TOTALS | R33: =SUM(R34:R38) -> 8.244265e+08
J34: Products of agriculture, hunting and related services | L34: =L24+L25+L27+L28 -> 10574094 | M34: Fabricated metal products | O34: =O10+O17+O24 -> 27099170 | P34: Electricity, gas, steam and air conditioning | R34: =R10+R17+R24 -> 2.7808393e+08
J35: Products of forestry, logging and related services | L35: =L29 -> 4344472.8 | M35: Electrical equipment | O35: =O11+O18+O25 -> 7944616.9 | P35: Chemicals and chemical products | R35: =R11+R18+R25 -> 2.0610662e+08
J36: Paper and paper products | L36: 0 | M36: Machinery and equipment n.e.c. | O36: =O12+O19+O26 -> 1.7875388e+08 | P36: Legal and accounting services; services of head offices; management consultancy services | R36: =R12+R19+R26 -> 1.648853e+08
J37: Food, beverages and tobacco products | L37: =L26 -> 263338.18 | M37: Constructions and construction works | O37: =O13+O20+O27 -> 55965813 | P37: Repair and installation services of machinery and equipment | R37: =R13+R20+R27 -> 1.3151298e+08
J38: Sewerage services; sewage sludge; waste collection, treatment and disposal services; materials recovery services; remediation services and other waste management services | L38: =L31 -> 0 | M38: Architectural and engineering services; technical testing and analysis services | O38: =O14+O21+O28 -> 1.1555044e+08 | P38: Land transport services and transport services via pipelines | R38: =R14+R21+R28 -> 43837660
I39: TOTALS imported | M39: Computer, electronic and optical products | O39: =O15+O22+O29 -> 11916925
J40: Products of agriculture, hunting and related services | L40: =L10+L17 -> 2.3563085e+09
A41: Advanced biogasoline
C42: =C43+C50+C57+C66 -> 9.3680595e+08 | D42: =D43+D50+D57+D66 -> 0.59662031 | F42: =F43+F50+F57+F66 -> 867025.41 | L42: =L43+L50+L57+L66 -> 2.6277942e+08 | O42: =O43+O50+O57+O66 -> 3.9371759e+08 | R42: =R43+R50+R57+R66 -> 4.0871774e+08
A43: of which from IVC 5 | B43: 1000 | C43: =B43*F43 -> 3.5714286e+08 | D43: ='[1]GAP analysis Sc. 1'!$C$68 -> 0.23031569 | E43: ='[2]Conversion factors selected IV '!$O$17 -> 1.5506667 | F43: =D43*E43*1000000 -> 357142.86 | G43: ='LCoP 2030 MEDIUM'!E5 -> 1385.4252 | H43: =G43*F43 -> 4.9479473e+08 | I43: ='LCoP 2030 MEDIUM'!H5 -> 0.22695215 | L43: =I43*H43 -> 1.1229473e+08 | M43: ='LCoP 2030 MEDIUM'!F5 -> 0.40059902 | O43: =M43*H43 -> 1.9821429e+08 | P43: ='LCoP 2030 MEDIUM'!G5 -> 0.37244882 | R43: =P43*H43 -> 1.8428571e+08 | S43: =R43+O43+L43 -> 4.9479473e+08
C44: =C43/$C$42 -> 0.38123462 | F44: Products of agriculture, hunting and related services | G44: =SUMIF($J$44:$J$47,F44,$L$44:$L$47)/$L$43 -> 0.77548897 | H44: domestic | I44: Straw | J44: Products of agriculture, hunting and related services | K44: ='Feedstock MIX per IVC'!G13 -> 228.35941 | L44: =K44*F$43 -> 81556934 | M44: Fabricated metal products | N44: 0 | O44: =N44*O$43 -> 0 | P44: Electricity, gas, steam and air conditioning | Q44: 0.2 | R44: =Q44*R$43 -> 36857143
F45: Paper and paper products | G45: =SUMIF($J$44:$J$47,F45,$L$44:$L$47)/$L$43 -> 0.22451103 | H45: domestic | I45: Lignocrops abandoned degraded | J45: Products of agriculture, hunting and related services | K45: ='Feedstock MIX per IVC'!G14 -> 10.633017 | L45: =K45*F$43 -> 3797505.9 | M45: Electrical equipment | N45: 0.02 | O45: =N45*O$43 -> 3964285.7 | P45: Chemicals and chemical products | Q45: 0.5 | R45: =Q45*R$43 -> 92142857
H46: domestic | I46: Lignocrops inter & cover cropping | J46: Products of agriculture, hunting and related services | K46: ='Feedstock MIX per IVC'!G15 -> 4.8408745 | L46: =K46*F$43 -> 1728883.8 | M46: Machinery and equipment n.e.c. | N46: 0.5 | O46: =N46*O$43 -> 99107143 | P46: Legal and accounting services; services of head offices; management consultancy services | Q46: 0.15 | R46: =Q46*R$43 -> 27642857
H47: domestic | I47: Secondary forest residues | J47: Paper and paper products | K47: ='Feedstock MIX per IVC'!G16 -> 70.591935 | L47: =K47*F$43 -> 25211405 | M47: Constructions and construction works | N47: 0.15 | O47: =N47*O$43 -> 29732143 | P47: Repair and installation services of machinery and equipment | Q47: 0.1 | R47: =Q47*R$43 -> 18428571
M48: Architectural and engineering services; technical testing and analysis services | N48: 0.3 | O48: =N48*O$43 -> 59464286 | P48: Land transport services and transport services via pipelines | Q48: 0.05 | R48: =Q48*R$43 -> 9214285.7
M49: Computer, electronic and optical products | N49: 0.03 | O49: =N49*O$43 -> 5946428.6
A50: of which 12 (road) | B50: 1000 | C50: =B50*F50 -> 4.0431267e+08 | D50: ='[1]GAP analysis Sc. 1'!$C$69 -> 0.26073474 | E50: ='[2]Conversion factors selected IV '!$O$86 -> 1.5506667 | F50: =D50*E50*1000000 -> 404312.67 | G50: ='LCoP 2030 MEDIUM'!E18 -> 988.03814 | H50: =G50*F50 -> 3.9947634e+08 | I50: ='LCoP 2030 MEDIUM'!H18 -> 0.32087642 | L50: =I50*H50 -> 1.2818254e+08 | M50: ='LCoP 2030 MEDIUM'!F18 -> 0.28136566 | O50: =M50*H50 -> 1.1239892e+08 | P50: ='LCoP 2030 MEDIUM'!G18 -> 0.39775792 | R50: =P50*H50 -> 1.5889488e+08 | S50: =R50+O50+L50 -> 3.9947634e+08
C51: =C50/$C$42 -> 0.43158636 | I51: Intermediate Bioenergy carriers (Syngas) | J51: Advanced biogas | K51: ='Feedstock MIX per IVC'!G85 -> 317.03814 | L51: =K51*F50 -> 1.2818254e+08 | M51: Fabricated metal products | N51: 0 | O51: =N51*O$50 -> 0 | P51: Electricity, gas, steam and air conditioning | Q51: 0.2 | R51: =Q51*R$50 -> 31778976
M52: Electrical equipment | N52: 0.02 | O52: =N52*O$50 -> 2247978.4 | P52: Chemicals and chemical products | Q52: 0.5 | R52: =Q52*R$50 -> 79447439
M53: Machinery and equipment n.e.c. | N53: 0.5 | O53: =N53*O$50 -> 56199461 | P53: Legal and accounting services; services of head offices; management consultancy services | Q53: 0.15 | R53: =Q53*R$50 -> 23834232
M54: Constructions and construction works | N54: 0.15 | O54: =N54*O$50 -> 16859838 | P54: Repair and installation services of machinery and equipment | Q54: 0.1 | R54: =Q54*R$50 -> 15889488
M55: Architectural and engineering services; technical testing and analysis services | N55: 0.3 | O55: =N55*O$50 -> 33719677 | P55: Land transport services and transport services via pipelines | Q55: 0.05 | R55: =Q55*R$50 -> 7944743.9
M56: Computer, electronic and optical products | N56: 0.03 | O56: =N56*O$50 -> 3371967.7
A57: of which 13a (half) | B57: 1750 | C57: =B57*F57 -> 1.5733973e+08 | D57: ='[1]GAP analysis Sc. 1'!$C$70 -> 0.08990842 | E57: ='[2]Conversion factors selected IV '!$O$89 -> 1 | F57: =D57*E57*1000000 -> 89908.42 | G57: ='LCoP 2030 MEDIUM'!E20 -> 1598.1345 | H57: =G57*F57 -> 1.4368574e+08 | I57: ='LCoP 2030 MEDIUM'!H20 -> 0.13211308 | L57: =I57*H57 -> 18982766 | M57: ='LCoP 2030 MEDIUM'!F20 -> 0.50371231 | O57: =M57*H57 -> 72376278 | P57: ='LCoP 2030 MEDIUM'!G20 -> 0.36417461 | R57: =P57*H57 -> 52326700 | S57: =R57+O57+L57 -> 1.4368574e+08
C58: =C57/$C$42 -> 0.16795339 | F58: Products of agriculture, hunting and related services | G58: =SUMIF($J$58:$J$65,F58,$L$58:$L$65)/$L$57 -> 0.55703651 | H58: domestic | I58: Straw | J58: Products of agriculture, hunting and related services | K58: ='Feedstock MIX per IVC'!G89 -> 104.52294 | L58: =K58*F$57 -> 9397492.3 | M58: Fabricated metal products | N58: 0.15 | O58: =N58*O$57 -> 10856442 | P58: Electricity, gas, steam and air conditioning | Q58: 0.15 | R58: =Q58*R$57 -> 7849005
F59: Products of forestry, logging and related services | G59: =SUMIF($J$58:$J$65,F59,$L$58:$L$65)/$L$57 -> 0.22886406 | H59: domestic | I59: Prunings & damaged crops | J59: Products of agriculture, hunting and related services | K59: ='Feedstock MIX per IVC'!G90 -> 6.0040708 | L59: =K59*F$57 -> 539816.52 | M59: Electrical equipment | N59: 0.02 | O59: =N59*O$57 -> 1447525.6 | P59: Chemicals and chemical products | Q59: 0.25 | R59: =Q59*R$57 -> 13081675
F60: Paper and paper products | G60: =SUMIF($J$58:$J$65,F60,$L$58:$L$65)/$L$57 -> 0.20022694 | H60: domestic | I60: Agroprocessing residues - maize cobs | J60: Food, beverages and tobacco products | K60: ='Feedstock MIX per IVC'!G91 -> 2.9289602 | L60: =K60*F$57 -> 263338.18 | M60: Machinery and equipment n.e.c. | N60: 0.45 | O60: =N60*O$57 -> 32569325 | P60: Legal and accounting services; services of head offices; management consultancy services | Q60: 0.2 | R60: =Q60*R$57 -> 10465340
F61: Food, beverages and tobacco products | G61: =SUMIF($J$58:$J$65,F61,$L$58:$L$65)/$L$57 -> 0.013872488 | H61: domestic | I61: Lignocrops abandoned degraded | J61: Products of agriculture, hunting and related services | K61: ='Feedstock MIX per IVC'!G92 -> 4.8668638 | L61: =K61*F$57 -> 437572.03 | M61: Constructions and construction works | N61: 0.1 | O61: =N61*O$57 -> 7237627.8 | P61: Repair and installation services of machinery and equipment | Q61: 0.3 | R61: =Q61*R$57 -> 15698010
F62: Sewerage services; sewage sludge; waste collection, treatment and disposal services; materials recovery services; remediation services and other waste management services | G62: =SUMIF($J$58:$J$65,F62,$L$58:$L$65)/$L$57 -> 0 | H62: domestic | I62: Lignocrops inter & cover cropping | J62: Products of agriculture, hunting and related services | K62: ='Feedstock MIX per IVC'!G93 -> 2.2157284 | L62: =K62*F$57 -> 199212.64 | M62: Architectural and engineering services; technical testing and analysis services | N62: 0.25 | O62: =N62*O$57 -> 18094069 | P62: Land transport services and transport services via pipelines | Q62: 0.1 | R62: =Q62*R$57 -> 5232670
F63: Advanced biogas | G63: =SUMIF($J$58:$J$65,F63,$L$58:$L$65)/$L$57 -> 0 | H63: domestic | I63: Primary forestry residues | J63: Products of forestry, logging and related services | K63: ='Feedstock MIX per IVC'!G94 -> 48.32109 | L63: =K63*F$57 -> 4344472.8 | M63: Computer, electronic and optical products | N63: 0.03 | O63: =N63*O$57 -> 2171288.3
G64: =SUM(G58:G63) -> 1 | H64: domestic | I64: Secondary forest residues | J64: Paper and paper products | K64: ='Feedstock MIX per IVC'!G95 -> 42.274808 | L64: =K64*F$57 -> 3800861.1
H65: domestic | I65: Biowastes - Post consumer wood | J65: Sewerage services; sewage sludge; waste collection, treatment and disposal services; materials recovery services; remediation services and other waste management services | K65: ='Feedstock MIX per IVC'!G96 -> 0 | L65: =K65*F$57 -> 0
A66: of which 13b (road) | B66: 1150 | C66: =B66*F66 -> 18010687 | D66: ='[1]GAP analysis Sc. 1'!$C$71 -> 0.015661467 | E66: ='[2]Conversion factors selected IV '!$O$125 -> 1 | F66: =D66*E66*1000000 -> 15661.467 | G66: ='LCoP 2030 MEDIUM'!$E$22 -> 1740.4464 | H66: =G66*F66 -> 27257944 | I66: ='LCoP 2030 MEDIUM'!H$22 -> 0.12177705 | L66: =I66*H66 -> 3319391.9 | M66: ='LCoP 2030 MEDIUM'!F22 -> 0.39357718 | O66: =M66*H66 -> 10728105 | P66: ='LCoP 2030 MEDIUM'!G22 -> 0.48464577 | R66: =P66*H66 -> 13210447 | S66: =L66+O66+R66 -> 27257944
C67: =C66/$C$42 -> 0.019225632 | F67: Products of agriculture, hunting and related services | G67: =SUMIF($J$67:$J$74,F67,$L$67:$L$74)/$L$66 -> 0.5549025 | H67: domestic | I67: Straw | J67: Products of agriculture, hunting and related services | K67: ='Feedstock MIX per IVC'!G89 -> 104.52294 | L67: =K67*F$66 -> 1636982.5 | M67: Fabricated metal products | N67: 0.15 | O67: =N67*O$66 -> 1609215.7 | P67: Electricity, gas, steam and air conditioning | Q67: 0.15 | R67: =Q67*R$66 -> 1981567.1
F68: Products of forestry, logging and related services | G68: =SUMIF($J$67:$J$74,F68,$L$67:$L$74)/$L$66 -> 0.22798728 | H68: domestic | I68: Prunings & damaged crops | J68: Products of agriculture, hunting and related services | K68: ='Feedstock MIX per IVC'!G90 -> 6.0040708 | L68: =K68*F$66 -> 94032.554 | M68: Electrical equipment | N68: 0.02 | O68: =N68*O$66 -> 214562.09 | P68: Chemicals and chemical products | Q68: 0.25 | R68: =Q68*R$66 -> 3302611.8
F69: Paper and paper products | G69: =SUMIF($J$67:$J$74,F69,$L$67:$L$74)/$L$66 -> 0.19945987 | H69: domestic | I69: Agroprocessing residues - maize cobs | J69: Food, beverages and tobacco products | K69: ='Feedstock MIX per IVC'!G91 -> 2.9289602 | L69: =K69*F$66 -> 45871.813 | M69: Machinery and equipment n.e.c. | N69: 0.45 | O69: =N69*O$66 -> 4827647.1 | P69: Legal and accounting services; services of head offices; management consultancy services | Q69: 0.2 | R69: =Q69*R$66 -> 2642089.4
F70: Food, beverages and tobacco products | G70: =SUMIF($J$67:$J$74,F70,$L$67:$L$74)/$L$66 -> 0.013819342 | H70: domestic | I70: Lignocrops abandoned degraded | J70: Products of agriculture, hunting and related services | K70: ='Feedstock MIX per IVC'!G92 -> 4.8668638 | L70: =K70*F$66 -> 76222.224 | M70: Constructions and construction works | N70: 0.1 | O70: =N70*O$66 -> 1072810.5 | P70: Repair and installation services of machinery and equipment | Q70: 0.3 | R70: =Q70*R$66 -> 3963134.1
F71: Sewerage services; sewage sludge; waste collection, treatment and disposal services; materials recovery services; remediation services and other waste management services | G71: =SUMIF($J$67:$J$74,F71,$L$67:$L$74)/$L$66 -> 0 | H71: domestic | I71: Lignocrops inter & cover cropping | J71: Products of agriculture, hunting and related services | K71: ='Feedstock MIX per IVC'!G93 -> 2.2157284 | L71: =K71*F$66 -> 34701.556 | M71: Architectural and engineering services; technical testing and analysis services | N71: 0.25 | O71: =N71*O$66 -> 2682026.2 | P71: Land transport services and transport services via pipelines | Q71: 0.1 | R71: =Q71*R$66 -> 1321044.7
F72: Advanced biogas | G72: =SUMIF($J$67:$J$74,F72,$L$67:$L$74)/$L$66 -> 0 | H72: domestic | I72: Primary forestry residues | J72: Products of forestry, logging and related services | K72: ='Feedstock MIX per IVC'!G94 -> 48.32109 | L72: =K72*F$66 -> 756779.14 | M72: Computer, electronic and optical products | N72: 0.03 | O72: =N72*O$66 -> 321843.14
G73: =SUM(G67:G72) -> 0.996169 | H73: domestic | I73: Secondary forest residues | J73: Paper and paper products | K73: ='Feedstock MIX per IVC'!G95 -> 42.274808 | L73: =K73*F$66 -> 662085.49
H74: domestic | I74: Biowastes - Post consumer wood | J74: Sewerage services; sewage sludge; waste collection, treatment and disposal services; materials recovery services; remediation services and other waste management services | K74: ='Feedstock MIX per IVC'!G96 -> 0 | L74: =K74*F$66 -> 0
I76: TOTALS domestic | L76: =SUM(L77:L82) -> 2.6276671e+08 | M76: TOTALS | O76: =SUM(O77:O82) -> 3.9371759e+08 | P76: TOTALS | R76: =SUM(R77:R81) -> 4.0871774e+08
J77: Products of agriculture, hunting and related services | L77: =L44+L45+L46+L58+L59+L61+L62+L67+L68+L70+L71 -> 99499356 | M77: Fabricated metal products | O77: =O44+O51+O58+O67 -> 12465657 | P77: Electricity, gas, steam and air conditioning | R77: =R44+R51+R58+R67 -> 78466691
J78: Products of forestry, logging and related services | L78: =L72+L63 -> 5101252 | M78: Electrical equipment | O78: =O45+O52+O59+O68 -> 7874351.8 | P78: Chemicals and chemical products | R78: =R45+R52+R59+R68 -> 1.8797458e+08
J79: Paper and paper products | L79: =L64+L47+L73 -> 29674352 | M79: Machinery and equipment n.e.c. | O79: =O46+O53+O60+O69 -> 1.9270358e+08 | P79: Legal and accounting services; services of head offices; management consultancy services | R79: =R46+R53+R60+R69 -> 64584518
J80: Food, beverages and tobacco products | L80: =L60+L69 -> 309210 | M80: Constructions and construction works | O80: =O47+O54+O61+O70 -> 54902419 | P80: Repair and installation services of machinery and equipment | R80: =R47+R54+R61+R70 -> 53979204
J81: Sewerage services; sewage sludge; waste collection, treatment and disposal services; materials recovery services; remediation services and other waste management services | L81: =L65+L74 -> 0 | M81: Architectural and engineering services; technical testing and analysis services | O81: =O48+O55+O62+O71 -> 1.1396006e+08 | P81: Land transport services and transport services via pipelines | R81: =R48+R55+R62+R71 -> 23712744
J82: Advanced biogas | L82: =L51 -> 1.2818254e+08 | M82: Computer, electronic and optical products | O82: =O49+O56+O63+O72 -> 11811528
A83: Advanced biogas
C84: =C85 -> 2.1202287e+09 | D84: =D85 -> 1.9875022 | F84: =F85 -> 1662924.5
A85: IVC 7 | B85: 1275 | C85: =B85*F85 -> 2.1202287e+09 | D85: ='[1]GAP analysis Sc. 1'!$C$73+'[1]GAP analysis Sc. 1'!$C$82 -> 1.9875022 | E85: ='[2]Conversion factors selected IV '!$O$29 -> 0.83669065 | F85: =D85*E85*1000000 -> 1662924.5 | G85: ='LCoP 2030 MEDIUM'!E10 -> 1024.4185 | H85: =G85*F85 -> 1.7035305e+09 | I85: ='LCoP 2030 MEDIUM'!H10 -> -0.020579023 | L85: =I85*H85 -> -35056995 | M85: ='LCoP 2030 MEDIUM'!F10 -> 0.59057897 | O85: =M85*H85 -> 1.0060693e+09 | P85: ='LCoP 2030 MEDIUM'!G10 -> 0.43000006 | R85: =P85*H85 -> 7.3251823e+08 | S85: =L85+O85+R85 -> 1.7035305e+09
C86: =100% -> 1 | F86: Food, beverages and tobacco products | G86: =SUMIF($J$86:$J$94,F86,$L$86:$L$94)/$L$85 -> -0.18587856 | I86: Prunings & damaged crops (olive stones excluded) | J86: Products of agriculture, hunting and related services | K86: ='Feedstock MIX per IVC'!G25 -> 0.84774671 | L86: =K86*F$85 -> 1409738.8 | M86: Fabricated metal products | N86: 0.05 | O86: =N86*O$85 -> 50303465 | P86: Electricity, gas, steam and air conditioning | Q86: 0.2 | R86: =Q86*R$85 -> 1.4650365e+08
F87: Products of agriculture, hunting and related services | G87: =SUMIF($J$86:$J$94,F87,$L$86:$L$94)/$L$85 -> -0.78770016 | I87: Lignocrops abandoned degraded | J87: Products of agriculture, hunting and related services | K87: ='Feedstock MIX per IVC'!G26 -> 0.6871784 | L87: =K87*F$85 -> 1142725.8 | M87: Electrical equipment | N87: 0.02 | O87: =N87*O$85 -> 20121386 | P87: Chemicals and chemical products | Q87: 0.5 | R87: =Q87*R$85 -> 3.6625912e+08
F88: Sewerage services; sewage sludge; waste collection, treatment and disposal services; materials recovery services; remediation services and other waste management services | G88: =SUMIF($J$86:$J$94,F88,$L$86:$L$94)/$L$85 -> 2.0072067 | I88: Lignocrops inter & cover cropping | J88: Products of agriculture, hunting and related services | K88: ='Feedstock MIX per IVC'!G27 -> 0.31285048 | L88: =K88*F$85 -> 520246.73 | M88: Machinery and equipment n.e.c. | N88: 0.4 | O88: =N88*O$85 -> 4.0242772e+08 | P88: Legal and accounting services; services of head offices; management consultancy services | Q88: 0.15 | R88: =Q88*R$85 -> 1.0987773e+08
I89: Agroprocessing residues | J89: Food, beverages and tobacco products | K89: ='Feedstock MIX per IVC'!G28 -> 3.9186047 | L89: =K89*F$85 -> 6516343.7 | M89: Constructions and construction works | N89: 0.3 | O89: =N89*O$85 -> 3.0182079e+08 | P89: Repair and installation services of machinery and equipment | Q89: 0.1 | R89: =Q89*R$85 -> 73251823
I90: Straw | J90: Products of agriculture, hunting and related services | K90: ='Feedstock MIX per IVC'!G29 -> 14.75815 | L90: =K90*F$85 -> 24541689 | M90: Architectural and engineering services; technical testing and analysis services | N90: 0.2 | O90: =N90*O$85 -> 2.0121386e+08 | P90: Land transport services and transport services via pipelines | Q90: 0.05 | R90: =Q90*R$85 -> 36625912
I91: Manure | J91: Products of agriculture, hunting and related services | K91: ='Feedstock MIX per IVC'!G30 -> 0 | L91: =K91*F$85 -> 0 | M91: Computer, electronic and optical products | N91: 0.03 | O91: =N91*O$85 -> 30182079
I92: Sewage sludge | J92: Sewerage services; sewage sludge; waste collection, treatment and disposal services; materials recovery services; remediation services and other waste management services | K92: ='Feedstock MIX per IVC'!G31 -> 0 | L92: =K92*F$85 -> 0 | N92: =SUM(N86:N91) -> 1
I93: Biowastes (post consumer woods excluded) | J93: Sewerage services; sewage sludge; waste collection, treatment and disposal services; materials recovery services; remediation services and other waste management services | K93: ='Feedstock MIX per IVC'!G32 -> -42.314992 | L93: =K93*F$85 -> -70366636
H94: ?? | I94: Intermediate Bioenergy carrier (crude glycerine) | J94: Chemical and chemical products | K94: ='Feedstock MIX per IVC'!G33 -> 0.70893032 | L94: =K94*F$85 -> 1178897.6
A95: Advanced bio-kerosene
C96: =C97+C104+C116 -> 3.2136616e+09 | D96: =D97+D104+D116 -> 1.3853744 | F96: =F97+F104+F116 -> 1350278
A97: IVC 2 HEFA | B97: 2380 | C97: =B97*F97 -> 2.8806698e+09 | D97: ='[1]GAP analysis Sc. 1'!$C$85 -> 1.2430905 | E97: ='[2]Conversion factors selected IV '!$O$78 -> 0.97367442 | F97: =D97*E97*1000000 -> 1210365.4 | G97: ='LCoP 2030 MEDIUM'!E4 -> 1811.2944 | H97: =G97*F97 -> 2.1923282e+09 | I97: ='LCoP 2030 MEDIUM'!H4 -> 0.47992993 | L97: =I97*H97 -> 1.0521639e+09 | M97: ='LCoP 2030 MEDIUM'!F4 -> 0.20758635 | O97: =M97*H97 -> 4.5509741e+08 | P97: ='LCoP 2030 MEDIUM'!G4 -> 0.31248371 | R97: =P97*H97 -> 6.8506684e+08 | S97: =L97+O97+R97 -> 2.1923282e+09
C98: =C97/$C$96 -> 0.89638242 | F98: Products of agriculture, hunting and related services | G98: =SUMIF($J$98:$J$101,F98,$L$98:$L$101)/$L$97 -> 0.56992974 | I98: Oil crops abandoned, degraded, intercropping | J98: Products of agriculture, hunting and related services | K98: ='Feedstock MIX per IVC'!G9 -> 353.01402 | L98: =K98*F$97 -> 4.2727597e+08 | M98: Fabricated metal products | N98: 0.05 | O98: =N98*O$97 -> 22754870 | P98: Electricity, gas, steam and air conditioning | Q98: 0.35 | R98: =Q98*R$97 -> 2.397734e+08
F99: Advanced biodiesel | G99: =SUMIF($J$98:$J$101,F99,$L$98:$L$101)/$L$97 -> 0.21503513 | I99: Tall oil | J99: Products of agriculture, hunting and related services | K99: ='Feedstock MIX per IVC'!G10 -> 142.42272 | L99: =K99*F$97 -> 1.7238354e+08 | M99: Electrical equipment | N99: 0.02 | O99: =N99*O$97 -> 9101948.2 | P99: Chemicals and chemical products | Q99: 0.25 | R99: =Q99*R$97 -> 1.7126671e+08
F100: Chemical and chemical products | G100: =SUMIF($J$98:$J$101,F100,$L$98:$L$101)/$L$97 -> 0.21503513 | I100: FPBO (Intermediate bioenergy carrier) | J100: Advanced biodiesel | K100: ='Feedstock MIX per IVC'!G11/2 -> 186.92883 | L100: =K100*F$97 -> 2.262522e+08 | M100: Machinery and equipment n.e.c. | N100: 0.45 | O100: =N100*O$97 -> 2.0479383e+08 | P100: Legal and accounting services; services of head offices; management consultancy services | Q100: 0.2 | R100: =Q100*R$97 -> 1.3701337e+08
G101: =SUM(G98:G100) -> 1 | I101: Biocrude (Intermediate Bioenergy carrier) | J101: Chemical and chemical products | K101: ='Feedstock MIX per IVC'!G11/2 -> 186.92883 | L101: =K101*F$97 -> 2.262522e+08 | M101: Constructions and construction works | N101: 0.15 | O101: =N101*O$97 -> 68264611 | P101: Repair and installation services of machinery and equipment | Q101: 0.15 | R101: =Q101*R$97 -> 1.0276003e+08
M102: Architectural and engineering services; technical testing and analysis services | N102: 0.3 | O102: =N102*O$97 -> 1.3652922e+08 | P102: Land transport services and transport services via pipelines | Q102: 0.05 | R102: =Q102*R$97 -> 34253342
...

Sheet 2035 costs Scenario 2
A1: Contribution of each IVC to final product in Scenario (2) 2035
A2: Assumptions:
A3: technical capacity = tcp | E3: feedstock availability: 2030 high
D5: produced in Mtoe | E5: Conversion factor [t/toe] | F5: produced in t | G5: Cost of production [€/t] | H5: Money spent on each IVC | I5: Feedstock share of costs | J5: Eurostat sector | K5: money [€] spent on each feedtsock when producing 1t of product | L5: Absolute feedstock costs [€] | M5: CAPEX share of costs | N5: CAPEX distribution | O5: Absoluet CAPEX [€] | P5: OPEX share of costs | R5: Absolute OPEX [€] | S5: TOTAL production costs
A6: ALL advanced biofuels | B6: Market price | C6: Market value of amount produced | D6: =D8+D45+D87+D122+D169 -> 21.196679
A7: Advanced biodiesel
A8: TOTAL | C8: =C9+C16+C27 -> 1.7066997e+10 | D8: =D9+D16+D27 -> 10.13233 | E8: =E9+E16+E27 -> 2.9030909 | F8: =F9+F16+F27 -> 9752569.6 | L8: =L9+L16+L27 -> 2.8221219e+09 | O8: =O9+O16+O27 -> 1.2134223e+10 | R8: =R9+R16+R27 -> 8.2287735e+09
A9: of which IVC 2 HVO | B9: 1750 | C9: =B9*F9 -> 7.2845283e+08 | D9: ='[1]GAP analysis Sc. 2'!$C$123 -> 0.43745547 | E9: ='[2]Conversion factors selected IV '!$O$7 -> 0.95154545 | F9: =D9*E9*1000000 -> 416258.76 | G9: ='LCoP 2030 HIGH'!E3 -> 1281.9315 | H9: =G9*F9 -> 5.3361523e+08 | I9: ='LCoP 2030 HIGH'!H3 -> 0.47423088 | L9: =I9*H9 -> 2.5305682e+08 | M9: ='LCoP 2030 HIGH'!F3 -> 0.2098396 | O9: =M9*H9 -> 1.1197361e+08 | P9: ='LCoP 2030 HIGH'!G3 -> 0.31592951 | R9: =P9*H9 -> 1.685848e+08 | S9: =L9+O9+R9 -> 5.3361523e+08
C10: =C9/$C$8 -> 0.042681958 | H10: domestic | I10: Tall oil | J10: Products of agriculture, hunting and related services | L10: =L9 -> 2.5305682e+08 | M10: Fabricated metal products | N10: 0.05 | O10: =N10*O$9 -> 5598680.3 | P10: Electricity, gas, steam and air conditioning | Q10: 0.35 | R10: =Q10*R$9 -> 59004680
I11: FPBO (Intermediate bioenergy carrier) | M11: Electrical equipment | N11: 0.02 | O11: =N11*O$9 -> 2239472.1 | P11: Chemicals and chemical products | Q11: 0.25 | R11: =Q11*R$9 -> 42146200
I12: biocrude (Intermediate Bioenergy carrier) | M12: Machinery and equipment n.e.c. | N12: 0.45 | O12: =N12*O$9 -> 50388123 | P12: Legal and accounting services; services of head offices; management consultancy services | Q12: 0.2 | R12: =Q12*R$9 -> 33716960
M13: Constructions and construction works | N13: 0.15 | O13: =N13*O$9 -> 16796041 | P13: Repair and installation services of machinery and equipment | Q13: 0.15 | R13: =Q13*R$9 -> 25287720
M14: Architectural and engineering services; technical testing and analysis services | N14: 0.3 | O14: =N14*O$9 -> 33592082 | P14: Land transport services and transport services via pipelines | Q14: 0.05 | R14: =Q14*R$9 -> 8429239.9
M15: Computer, electronic and optical products | N15: 0.03 | O15: =N15*O$9 -> 3359208.2
A16: of which IVC 11a (road) | B16: 1750 | C16: =B16*F16 -> 1.2322514e+10 | D16: ='[1]GAP analysis Sc. 2'!$C$124 -> 7.4 | E16: ='[2]Conversion factors selected IV '!$O$64 -> 0.95154545 | F16: =D16*E16*1000000 -> 7041436.4 | G16: ='LCoP 2030 HIGH'!E16 -> 2696.299 | H16: =G16*F16 -> 1.8985818e+10 | I16: ='LCoP 2030 HIGH'!H16 -> 0.109891 | L16: =I16*H16 -> 2.0863704e+09 | M16: ='LCoP 2030 HIGH'!F16 -> 0.5359198 | O16: =M16*H16 -> 1.0174876e+10 | P16: ='LCoP 2030 HIGH'!G16 -> 0.35418921 | R16: =P16*H16 -> 6.7245717e+09 | S16: =L16+O16+R16 -> 1.8985818e+10
C17: =C16/$C$8 -> 0.72200832 | G17: Products of agriculture, hunting and related services | H17: =SUMIF($J$17:$J$26,G17,$L$17:$L$26)/$L$16 -> 0.62196372 | I17: Straw | J17: Products of agriculture, hunting and related services | K17: ='Feedstock MIX per IVC'!J63 -> 161.99072 | L17: =K17*F$16 -> 1.1406473e+09 | M17: Fabricated metal products | N17: 0 | O17: =N17*O$16 -> 0 | P17: Electricity, gas, steam and air conditioning | Q17: 0.25 | R17: =Q17*R$16 -> 1.6811429e+09
G18: Products of forestry, logging and related services | H18: =SUMIF($J$17:$J$26,G18,$L$17:$L$26)/$L$16 -> 0.1487034 | I18: Prunings & damaged crops | J18: Products of agriculture, hunting and related services | K18: ='Feedstock MIX per IVC'!J64 -> 8.4731123 | L18: =K18*F$16 -> 59662881 | M18: Electrical equipment | N18: 0.02 | O18: =N18*O$16 -> 2.0349751e+08 | P18: Chemicals and chemical products | Q18: 0.15 | R18: =Q18*R$16 -> 1.0086858e+09
G19: Paper and paper products | H19: =SUMIF($J$17:$J$26,G19,$L$17:$L$26)/$L$16 -> 0.18227674 | I19: Sewage sludge | J19: Sewerage services; sewage sludge; waste collection, treatment and disposal services; materials recovery services; remediation services and other waste management services | K19: ='Feedstock MIX per IVC'!J65 -> 0 | L19: =K19*F$16 -> 0 | M19: Machinery and equipment n.e.c. | N19: 0.55 | O19: =N19*O$16 -> 5.5961816e+09 | P19: Legal and accounting services; services of head offices; management consultancy services | Q19: 0.3 | R19: =Q19*R$16 -> 2.0173715e+09
G20: Food, beverages and tobacco products | H20: =SUMIF($J$17:$J$26,G20,$L$17:$L$26)/$L$16 -> 0.014502397 | I20: Agroprocessing residues - maize cobs | J20: Food, beverages and tobacco products | K20: ='Feedstock MIX per IVC'!J66 -> 4.2970453 | L20: =K20*F$16 -> 30257371 | M20: Constructions and construction works | N20: 0.1 | O20: =N20*O$16 -> 1.0174876e+09 | P20: Repair and installation services of machinery and equipment | Q20: 0.3 | R20: =Q20*R$16 -> 2.0173715e+09
G21: Sewerage services; sewage sludge; waste collection, treatment and disposal services; materials recovery services; remediation services and other waste management services | H21: =SUMIF($J$17:$J$26,G21,$L$17:$L$26)/$L$16 -> 0 | I21: Lignocrops abandoned degraded | J21: Products of agriculture, hunting and related services | K21: ='Feedstock MIX per IVC'!J67 -> 8.1190082 | L21: =K21*F$16 -> 57169480 | M21: Architectural and engineering services; technical testing and analysis services | N21: 0.3 | O21: =N21*O$16 -> 3.0524627e+09 | P21: Land transport services and transport services via pipelines | Q21: 0 | R21: =Q21*R$16 -> 0
G22: Advanced biodiesel | H22: =SUMIF($J$17:$J$26,G22,$L$17:$L$26)/$L$16/2 -> 0.016276872 | I22: Lignocrops inter & cover cropping | J22: Products of agriculture, hunting and related services | K22: ='Feedstock MIX per IVC'!J68 -> 5.7043807 | L22: =K22*F$16 -> 40167034 | M22: Computer, electronic and optical products | N22: 0.03 | O22: =N22*O$16 -> 3.0524627e+08
G23: Advanced biogasoline | H23: =H22 -> 0.016276872 | I23: Primary forestry residues | J23: Products of forestry, logging and related services | K23: ='Feedstock MIX per IVC'!J69 -> 44.060666 | L23: =K23*F$16 -> 3.1025038e+08
H24: =SUM(H17:H22) -> 0.98372313 | I24: Secondary forest residues | J24: Paper and paper products | K24: ='Feedstock MIX per IVC'!J70 -> 54.008411 | L24: =K24*F$16 -> 3.8029679e+08
