Workbook

Sheet Prices per feedstock & per IVC
A1: This sheet is mostly redundant since the price data is in th "feedstock MIX price per IVC " sheet. But references and Eurostat mapping in here
A2: Prices of feedstocks
B4: Eurostat sector | C4: Share per feedstock of overall feedstock mix (2030 medium) | D4: Share per feedstock of overall feedstock mix (2030 high) | E4: Price estimate [€/t] | F4: Source | G4: Share distribution of feedstocks within IVC 2030 | H4: Share distribution of feedstocks within IVC 2050 | I4: share feedstock costs | J4: CAPEX [€/t] | K4: share CAPEX | L4: OPEX [€/t] | M4: share OPEX | N4: OVERALL costs
A5: IVC 1 | E5: 520 | I5: =E5/N5 -> 0.59770115 | J5: 83 | K5: =J5/N5 -> 0.095402299 | L5: 267 | M5: =L5/N5 -> 0.30689655 | N5: =E5+J5+L5 -> 870
A6: Oil crops abandoned, degraded, intercropping | B6: A01: Products of agriculture, hunting and related services | D6: 1 | E6: 520 €/t | F6: Study 2, p. 124 | G6: 1 | H6: 1
A7: IVC 2 - HVO | C7: =SUM(C8:C10) -> 1 | D7: =SUM(D8:D10) -> 1 | E7: =D8*E8+D10*E10 -> 87.837631 | I7: =E7/N7 -> 0.11529705 | J7: 269 | K7: =J7/N7 -> 0.35309361 | L7: 405 | M7: =L7/N7 -> 0.53160934 | N7: =E7+J7+L7 -> 761.83763
A8: Oil crops abandoned, degraded, intercropping | B8: A01: Products of agriculture, hunting and related services | C8: 0 | D8: 0 | E8: 520 | F8: Study 2, p. 124
A9: Tall Oil | C9: ='[1]Availabilities EU Austria'!$N$13/'[1]Availabilities EU Austria'!$N$10 -> 0.063011547 | D9: ='[1]Availabilities EU Austria'!$Q$13/'[1]Availabilities EU Austria'!$Q$10 -> 0.089199177 | E9: ??
A10: Intermediate Bioenergy carriers (biocrude, FPBO) | B10: C20: Chemicals and chemical products | C10: =('[1]Availabilities EU Austria'!$N$15+'[1]Availabilities EU Austria'!$N$14)/'[1]Availabilities EU Austria'!$N$10 -> 0.93698845 | D10: =('[1]Availabilities EU Austria'!$Q$14+'[1]Availabilities EU Austria'!$Q$15)/'[1]Availabilities EU Austria'!$Q$10 -> 0.91080082 | E10: 96.44 | F10: CHECK
A11: IVC 2 - HEFA | C11: =SUM(C12:C14) -> 1 | D11: =SUM(D12:D14) -> 1 | E11: =D12*E12+D14*E14 -> 137.72093 | I11: =E11/N11 -> 0.12755234 | J11: 376 | K11: =J11/N11 -> 0.34823813 | L11: 566 | M11: =L11/N11 -> 0.52420953 | N11: =E11+J11+L11 -> 1079.7209
A12: Oil crops abandoned, degraded, intercropping | B12: A01: Products of agriculture, hunting and related services | C12: ='[1]Availabilities EU Austria'!$N$21/'[1]Availabilities EU Austria'!$N$16 -> 0.072434801 | D12: ='[1]Availabilities EU Austria'!$Q$21/'[1]Availabilities EU Austria'!$Q$16 -> 0.11542722 | E12: 520 | F12: Study 2, p. 124
A13: Tall oil | C13: ='[1]Availabilities EU Austria'!$N$23/'[1]Availabilities EU Austria'!$N$16 -> 0.058447318 | D13: ='[1]Availabilities EU Austria'!$Q$23/'[1]Availabilities EU Austria'!$Q$16 -> 0.078903164 | E13: ?
A14: Intermediate Bioenergy carriers (biocrude, FPBO) | B14: C20: Chemicals and chemical products | C14: =('[1]Availabilities EU Austria'!$N$24+'[1]Availabilities EU Austria'!$N$25)/'[1]Availabilities EU Austria'!$N$16 -> 0.86911788 | D14: =('[1]Availabilities EU Austria'!$Q$24+'[1]Availabilities EU Austria'!$Q$25)/'[1]Availabilities EU Austria'!$Q$16 -> 0.80566962 | E14: 96.44
A15: IVC 5 | C15: =SUM(C16:C19) -> 1 | D15: =SUM(D16:D19) -> 1 | E15: =D16*E16+D17*E17+D18*E18+D19*E19 -> 60.376239
A16: Straw | B16: A01: Products of agriculture, hunting and related services | C16: ='[1]Availabilities EU Austria'!$N$27/'[1]Availabilities EU Austria'!$N$26 -> 0.73688393 | D16: ='[1]Availabilities EU Austria'!$Q$27/'[1]Availabilities EU Austria'!$Q$26 -> 0.74789495 | E16: 58 | F16: Study 2, p. 97
A17: Lignocrops abandoned degraded | B17: A01: Products of agriculture, hunting and related services | C17: ='[1]Availabilities EU Austria'!$N$28/'[1]Availabilities EU Austria'!$N$26 -> 0.028841348 | D17: ='[1]Availabilities EU Austria'!$Q$28/'[1]Availabilities EU Austria'!$Q$26 -> 0.031508836 | E17: 69 | F17: Study 2, p. 193
A18: Lignocrops inter & cover cropping | B18: A01: Products of agriculture, hunting and related services | C18: ='[1]Availabilities EU Austria'!$N$29/'[1]Availabilities EU Austria'!$N$26 -> 0.013130549 | D18: ='[1]Availabilities EU Austria'!$Q$29/'[1]Availabilities EU Austria'!$Q$26 -> 0.022137974 | E18: 69 | F18: Study 2, p. 193
A19: Secondary forest residues | B19: C17 Paper and paper products (en) | C19: ='[1]Availabilities EU Austria'!$N$30/'[1]Availabilities EU Austria'!$N$26 -> 0.22114418 | D19: ='[1]Availabilities EU Austria'!$Q$30/'[1]Availabilities EU Austria'!$Q$26 -> 0.19845824 | E19: 67
A20: IVC 6 | E20: =D21*E21 -> 96.44
A21: Intermediate Bioenergy carrier (ethanol, methanol) | B21: C20: Chemicals and chemical products | C21: 1 | D21: 1 | E21: 96.44
A22: IVC 7 | C22: =SUM(C23:C31) -> 1 | D22: =SUM(D23:D31) -> 1 | E22: =D23*E23+D24*E24+D25*E25+D26*E26+D27*E27+D28*E28+D29*E29+D30*E30+D31*E31 -> 30.965299
A23: Prunings & damaged crops (olive stones excluded) | B23: A01: Products of agriculture, hunting and related services | C23: ='[1]Availabilities EU Austria'!$N$41/'[1]Availabilities EU Austria'!$N$40 -> 0.030601718 | D23: ='[1]Availabilities EU Austria'!$Q$41/'[1]Availabilities EU Austria'!$Q$40 -> 0.03010511 | E23: 44 | F23: Study 2, p. 111
A24: Lignocrops abandoned degraded | B24: A01: Products of agriculture, hunting and related services | C24: ='[1]Availabilities EU Austria'!$N$42/'[1]Availabilities EU Austria'!$N$40 -> 0.018454385 | D24: ='[1]Availabilities EU Austria'!$Q$42/'[1]Availabilities EU Austria'!$Q$40 -> 0.021462821 | E24: 69 | F24: Study 2, p. 193 | G24: =0.21/2 -> 0.105
A25: Lignocrops inter & cover cropping | B25: A01: Products of agriculture, hunting and related services | C25: ='[1]Availabilities EU Austria'!$N$43/'[1]Availabilities EU Austria'!$N$40 -> 0.0084016949 | D25: ='[1]Availabilities EU Austria'!$Q$43/'[1]Availabilities EU Austria'!$Q$40 -> 0.015079687 | E25: 69 | F25: Study 2, p. 193 | G25: =0.21/2 -> 0.105
A26: Agroprocessing residues | B26: CPA_C10-12 (Food, beverages and tobacco products) | C26: ='[1]Availabilities EU Austria'!$N$44/'[1]Availabilities EU Austria'!$N$40 -> 0.023575445 | D26: ='[1]Availabilities EU Austria'!$Q$44/'[1]Availabilities EU Austria'!$Q$40 -> 0.024015373 | E26: 44 | F26: Study 2, p. 111 | G26: 0.24
A27: Straw | B27: A01: Products of agriculture, hunting and related services (en); A01.1: non-perennial crops | C27: ='[1]Availabilities EU Austria'!$N$45/'[1]Availabilities EU Austria'!$N$40 -> 0.47150152 | D27: ='[1]Availabilities EU Austria'!$Q$45/'[1]Availabilities EU Austria'!$Q$40 -> 0.50944236 | E27: 58
A28: Manure | B28: A01: Products of agriculture, hunting and related services; A01.4: Live animals and animal products | C28: ='[1]Availabilities EU Austria'!$N$46/'[1]Availabilities EU Austria'!$N$40 -> 0.347493 | D28: ='[1]Availabilities EU Austria'!$Q$46/'[1]Availabilities EU Austria'!$Q$40 -> 0.3159246 | E28: 0 | G28: 0.32
A29: Sewage sludge | B29: Sewerage services; sewage sludge; waste collection, treatment and disposal services; materials recovery services; remediation services and other waste management services | C29: ='[1]Availabilities EU Austria'!$N$47/'[1]Availabilities EU Austria'!$N$40 -> 0.031761184 | D29: ='[1]Availabilities EU Austria'!$Q$47/'[1]Availabilities EU Austria'!$Q$40 -> 0.024204717 | E29: 0
A30: Biowastes (post consumer woods excluded) | B30: Sewerage services; sewage sludge; waste collection, treatment and disposal services; materials recovery services; remediation services and other waste management services | C30: ='[1]Availabilities EU Austria'!$N$48/'[1]Availabilities EU Austria'!$N$40 -> 0.065902037 | D30: ='[1]Availabilities EU Austria'!$Q$48/'[1]Availabilities EU Austria'!$Q$40 -> 0.05819089 | E30: =-(55+70)/2 -> -62.5 | F30: Study 2, annex 4, page 40 | H30: wird hier das Minuszeichen richtig in die Formel übernommen?
A31: Intermediate Bioenergy carrier (crude glycerine) | B31: C20: Chemicals and chemical products | C31: ='[1]Availabilities EU Austria'!$N$49/'[1]Availabilities EU Austria'!$N$40 -> 0.0023090105 | D31: ='[1]Availabilities EU Austria'!$Q$49/'[1]Availabilities EU Austria'!$Q$40 -> 0.0015744344 | E31: 96.44 | F31: CETO 2026, p. 29
A32: IVC 8a | C32: =SUM(C33:C42) -> 1 | D32: =SUM(D33:D42) -> 1 | E32: =D33*E33+D34*E34+D35*E35+D36*E36+D37*E37+D38*E38+D39*E39+D40*E40+D41*E41+D42*E42 -> 57.287316
A33: Straw | B33: A01: Products of agriculture, hunting and related services (en); A01.1: non-perennial crops | C33: ='[1]Availabilities EU Austria'!$N$51/'[1]Availabilities EU Austria'!$N$50 -> 0.5178381 | D33: ='[1]Availabilities EU Austria'!$Q$51/'[1]Availabilities EU Austria'!$Q$50 -> 0.56804069 | E33: 58
A34: Prunings & damaged crops | B34: A01: Products of agriculture, hunting and related services | C34: ='[1]Availabilities EU Austria'!$N$52/'[1]Availabilities EU Austria'!$N$50 -> 0.033609087 | D34: ='[1]Availabilities EU Austria'!$Q$52/'[1]Availabilities EU Austria'!$Q$50 -> 0.033570732 | E34: 44
A35: Sewage sludge | B35: E: WATER SUPPLY; SEWERAGE, WASTE MANAGEMENT AND REMEDIATION SERVICES (en); E37: Sewage services, sewage sludge | C35: ='[1]Availabilities EU Austria'!$N$53/'[1]Availabilities EU Austria'!$N$50 -> 0.034882499 | D35: ='[1]Availabilities EU Austria'!$Q$53/'[1]Availabilities EU Austria'!$Q$50 -> 0.026988851 | E35: 0 | F35: CHECK
A36: Agroprocessing residues - maize cobs | B36: CPA_C10-12 (Food, beverages and tobacco products) | C36: ='[1]Availabilities EU Austria'!$N$54/'[1]Availabilities EU Austria'!$N$50 -> 0.013662908 | D36: ='[1]Availabilities EU Austria'!$Q$54/'[1]Availabilities EU Austria'!$Q$50 -> 0.014187521 | E36: 44
A37: Lignocrops abandoned degraded | B37: A01: Products of agriculture, hunting and related services | C37: ='[1]Availabilities EU Austria'!$N$55/'[1]Availabilities EU Austria'!$N$50 -> 0.020267981 | D37: ='[1]Availabilities EU Austria'!$Q$55/'[1]Availabilities EU Austria'!$Q$50 -> 0.02393157 | E37: 69
A38: Lignocrops inter & cover cropping | B38: A01: Products of agriculture, hunting and related services | C38: ='[1]Availabilities EU Austria'!$N$56/'[1]Availabilities EU Austria'!$N$50 -> 0.0092273673 | D38: ='[1]Availabilities EU Austria'!$Q$56/'[1]Availabilities EU Austria'!$Q$50 -> 0.01681422 | E38: 69
A39: Primary forestry residues | B39: A02: Products of forestry, logging and related services (en) | C39: ='[1]Availabilities EU Austria'!$N$57/'[1]Availabilities EU Austria'!$N$50 -> 0.14802813 | D39: ='[1]Availabilities EU Austria'!$Q$57/'[1]Availabilities EU Austria'!$Q$50 -> 0.10247464 | E39: 69 | F39: CHECK
A40: Secondary forest residues | B40: C MANUFACTURED PRODUCTS, C17: Paper and paper products (en) | C40: ='[1]Availabilities EU Austria'!$N$58/'[1]Availabilities EU Austria'!$N$50 -> 0.15540695 | D40: ='[1]Availabilities EU Austria'!$Q$58/'[1]Availabilities EU Austria'!$Q$50 -> 0.15073288 | E40: 69 | F40: CHECK
A41: Biowastes - Post consumer wood | B41: E WATER SUPPLY; SEWERAGE, WASTE MANAGEMENT AND REMEDIATION SERVICES (en) | C41: ='[1]Availabilities EU Austria'!$N$59/'[1]Availabilities EU Austria'!$N$50 -> 0.046552014 | D41: ='[1]Availabilities EU Austria'!$Q$59/'[1]Availabilities EU Austria'!$Q$50 -> 0.042968416 | E41: 0 | F41: CHECK
A42: Intermediate Bioenergy carrier (FPBO with lower quality) | B42: C20: Chemicals and chemical products | C42: ='[1]Availabilities EU Austria'!$N$60/'[1]Availabilities EU Austria'!$N$50 -> 0.020524961 | D42: ='[1]Availabilities EU Austria'!$Q$60/'[1]Availabilities EU Austria'!$Q$50 -> 0.020290488 | E42: 96.44
A43: IVC 8b | E43: =D44*E44 -> 96.44
A44: Intermediate Bioenergy carrier (biomethane) | B44: A01: Products of agriculture, hunting and related services | C44: 1 | D44: =100% -> 1 | E44: 96.44
A45: IVC 8c | E45: =D46*E46 -> 96.44
A46: e-biofuel feedstocks (biogenic CO2 and hydrogen from electrolysis) | B46: C20: Chemicals and chemical products | C46: 1 | D46: 1 | E46: 96.44
A47: IVC 9a | C47: =SUM(C48:C57) -> 1 | D47: =SUM(D48:D57) -> 1 | E47: =D48*E48+D49*E49+D50*E50+D51*E51+D52*E52+D53*E53+D54*E54+D55*E55+D56*E56+D57*E57 -> 57.287316
A48: Straw | B48: A01: Products of agriculture, hunting and related services | C48: ='[1]Availabilities EU Austria'!$N$70/'[1]Availabilities EU Austria'!$N$69 -> 0.5178381 | D48: ='[1]Availabilities EU Austria'!$Q$70/'[1]Availabilities EU Austria'!$Q$69 -> 0.56804069 | E48: 58
A49: Prunings & damaged crops | B49: A01: Products of agriculture, hunting and related services | C49: ='[1]Availabilities EU Austria'!$N$71/'[1]Availabilities EU Austria'!$N$69 -> 0.033609087 | D49: ='[1]Availabilities EU Austria'!$Q$71/'[1]Availabilities EU Austria'!$Q$69 -> 0.033570732 | E49: 44
A50: Sewage sludge | B50: E: WATER SUPPLY; SEWERAGE, WASTE MANAGEMENT AND REMEDIATION SERVICES (en); E37: Sewage services, sewage sludge | C50: ='[1]Availabilities EU Austria'!$N$72/'[1]Availabilities EU Austria'!$N$69 -> 0.034882499 | D50: ='[1]Availabilities EU Austria'!$Q$72/'[1]Availabilities EU Austria'!$Q$69 -> 0.026988851 | E50: 0 | F50: CHECK
A51: Agroprocessing residues - maize cobs | B51: CPA_C10-12 (Food, beverages and tobacco products) | C51: ='[1]Availabilities EU Austria'!$N$73/'[1]Availabilities EU Austria'!$N$69 -> 0.013662908 | D51: ='[1]Availabilities EU Austria'!$Q$73/'[1]Availabilities EU Austria'!$Q$69 -> 0.014187521 | E51: 44
A52: Lignocrops abandoned degraded | B52: A01: Products of agriculture, hunting and related services | C52: ='[1]Availabilities EU Austria'!$N$74/'[1]Availabilities EU Austria'!$N$69 -> 0.020267981 | D52: ='[1]Availabilities EU Austria'!$Q$74/'[1]Availabilities EU Austria'!$Q$69 -> 0.02393157 | E52: 69
A53: Lignocrops inter & cover cropping | B53: A01: Products of agriculture, hunting and related services | C53: ='[1]Availabilities EU Austria'!$N$75/'[1]Availabilities EU Austria'!$N$69 -> 0.0092273673 | D53: ='[1]Availabilities EU Austria'!$Q$75/'[1]Availabilities EU Austria'!$Q$69 -> 0.01681422 | E53: 69
A54: Primary forestry residues | B54: A02: Products of forestry, logging and related services (en) | C54: ='[1]Availabilities EU Austria'!$N$76/'[1]Availabilities EU Austria'!$N$69 -> 0.14802813 | D54: ='[1]Availabilities EU Austria'!$Q$76/'[1]Availabilities EU Austria'!$Q$69 -> 0.10247464 | E54: 69 | F54: CHECK
A55: Secondary forest residues | B55: C MANUFACTURED PRODUCTS, C17: Paper and paper products (en) | C55: ='[1]Availabilities EU Austria'!$N$77/'[1]Availabilities EU Austria'!$N$69 -> 0.15540695 | D55: ='[1]Availabilities EU Austria'!$Q$77/'[1]Availabilities EU Austria'!$Q$69 -> 0.15073288 | E55: 69 | F55: CHECK
A56: Biowastes - Post consumer wood | B56: E WATER SUPPLY; SEWERAGE, WASTE MANAGEMENT AND REMEDIATION SERVICES (en) | C56: ='[1]Availabilities EU Austria'!$N$78/'[1]Availabilities EU Austria'!$N$69 -> 0.046552014 | D56: ='[1]Availabilities EU Austria'!$Q$78/'[1]Availabilities EU Austria'!$Q$69 -> 0.042968416 | E56: 0 | F56: CHECK
A57: Intermediate Bioenergy carriers (FPBO with lower quality ) | B57: C20: Chemicals and chemical products | C57: ='[1]Availabilities EU Austria'!$N$79/'[1]Availabilities EU Austria'!$N$69 -> 0.020524961 | D57: ='[1]Availabilities EU Austria'!$Q$79/'[1]Availabilities EU Austria'!$Q$69 -> 0.020290488 | E57: 96.44
A58: IVC 9b | E58: =D59*E59 -> 96.44
A59: e-biofuel feedstocks (biogenic CO2 and hydrogen from electrolysis) | B59: C20: Chemicals and chemical products | D59: 1 | E59: 96.44
A60: IVC 11a | C60: =SUM(C61:C70) -> 1 | D60: =SUM(D61:D70) -> 1 | E60: =D61*E61+D62*E62+D63*E63+D64*E64+D65*E65+D66*E66+D67*E67+D68*E68+D69*E69+D70*E70 -> 57.287316
A61: Straw | B61: A01: Products of agriculture, hunting and related services | C61: ='[1]Availabilities EU Austria'!$N$105/'[1]Availabilities EU Austria'!$N$104 -> 0.5178381 | D61: ='[1]Availabilities EU Austria'!$Q$105/'[1]Availabilities EU Austria'!$Q$104 -> 0.56804069 | E61: 58
A62: Prunings & damaged crops | B62: A01: Products of agriculture, hunting and related services | C62: ='[1]Availabilities EU Austria'!$N$106/'[1]Availabilities EU Austria'!$N$104 -> 0.033609087 | D62: ='[1]Availabilities EU Austria'!$Q$106/'[1]Availabilities EU Austria'!$Q$104 -> 0.033570732 | E62: 44
A63: Sewage sludge | B63: E: WATER SUPPLY; SEWERAGE, WASTE MANAGEMENT AND REMEDIATION SERVICES (en); E37: Sewage services, sewage sludge | C63: ='[1]Availabilities EU Austria'!$N$107/'[1]Availabilities EU Austria'!$N$104 -> 0.034882499 | D63: ='[1]Availabilities EU Austria'!$Q$107/'[1]Availabilities EU Austria'!$Q$104 -> 0.026988851 | E63: 0 | F63: CHECK
A64: Agroprocessing residues - maize cobs | B64: CPA_C10-12 (Food, beverages and tobacco products) | C64: ='[1]Availabilities EU Austria'!$N$108/'[1]Availabilities EU Austria'!$N$104 -> 0.013662908 | D64: ='[1]Availabilities EU Austria'!$Q$108/'[1]Availabilities EU Austria'!$Q$104 -> 0.014187521 | E64: 44
A65: Lignocrops abandoned degraded | B65: A01: Products of agriculture, hunting and related services | C65: ='[1]Availabilities EU Austria'!$N$109/'[1]Availabilities EU Austria'!$N$104 -> 0.020267981 | D65: ='[1]Availabilities EU Austria'!$Q$109/'[1]Availabilities EU Austria'!$Q$104 -> 0.02393157 | E65: 69
A66: Lignocrops inter & cover cropping | B66: A01: Products of agriculture, hunting and related services | C66: ='[1]Availabilities EU Austria'!$N$110/'[1]Availabilities EU Austria'!$N$104 -> 0.0092273673 | D66: ='[1]Availabilities EU Austria'!$Q$110/'[1]Availabilities EU Austria'!$Q$104 -> 0.01681422 | E66: 69
A67: Primary forestry residues | B67: A02: Products of forestry, logging and related services (en) | C67: ='[1]Availabilities EU Austria'!$N$111/'[1]Availabilities EU Austria'!$N$104 -> 0.14802813 | D67: ='[1]Availabilities EU Austria'!$Q$111/'[1]Availabilities EU Austria'!$Q$104 -> 0.10247464 | E67: 69 | F67: CHECK
A68: Secondary forest residues | B68: C MANUFACTURED PRODUCTS, C17: Paper and paper products (en) | C68: ='[1]Availabilities EU Austria'!$N$112/'[1]Availabilities EU Austria'!$N$104 -> 0.15540695 | D68: ='[1]Availabilities EU Austria'!$Q$112/'[1]Availabilities EU Austria'!$Q$104 -> 0.15073288 | E68: 69 | F68: CHECK
A69: Biowastes - Post consumer wood | B69: E WATER SUPPLY; SEWERAGE, WASTE MANAGEMENT AND REMEDIATION SERVICES (en) | C69: ='[1]Availabilities EU Austria'!$N$113/'[1]Availabilities EU Austria'!$N$104 -> 0.046552014 | D69: ='[1]Availabilities EU Austria'!$Q$113/'[1]Availabilities EU Austria'!$Q$104 -> 0.042968416 | E69: 0 | F69: CHECK
A70: Intermediate Bioenergy carriers (FPBO with lower quality ) | C70: ='[1]Availabilities EU Austria'!$N$114/'[1]Availabilities EU Austria'!$N$104 -> 0.020524961 | D70: ='[1]Availabilities EU Austria'!$Q$114/'[1]Availabilities EU Austria'!$Q$104 -> 0.020290488 | E70: 96.44
A71: IVC 12 | E71: =D72*E72 -> 96.44
A72: Intermediate Bioenergy carriers (Syngas) | C72: 1 | D72: 1 | E72: 96.44
A73: IVC13a | C73: =SUM(C74:C81) -> 1 | D73: =SUM(D74:D81) -> #REF! | E73: =D74*E74+D75*E75+D76*E76+D77*E77+D78*E78+D79*E79+D80*E80+D81*E81 -> #REF!
A74: Straw | B74: A01: Products of agriculture, hunting and related services | C74: ='[1]Availabilities EU Austria'!$N$120/'[1]Availabilities EU Austria'!$N$119 -> 0.5482132 | D74: ='[1]Availabilities EU Austria'!#REF!/'[1]Availabilities EU Austria'!#REF! -> #REF! | E74: 58
A75: Prunings & damaged crops | B75: A01: Products of agriculture, hunting and related services | C75: ='[1]Availabilities EU Austria'!$N$121/'[1]Availabilities EU Austria'!$N$119 -> 0.035580513 | D75: ='[1]Availabilities EU Austria'!#REF!/'[1]Availabilities EU Austria'!#REF! -> #REF! | E75: 44
A76: Agroprocessing residues - maize cobs | B76: CPA_C10-12 (Food, beverages and tobacco products) | C76: ='[1]Availabilities EU Austria'!$N$122/'[1]Availabilities EU Austria'!$N$119 -> 0.01446434 | D76: ='[1]Availabilities EU Austria'!#REF!/'[1]Availabilities EU Austria'!#REF! -> #REF! | E76: 44
A77: Lignocrops abandoned degraded | B77: A01: Products of agriculture, hunting and related services | C77: ='[1]Availabilities EU Austria'!$N$123/'[1]Availabilities EU Austria'!$N$119 -> 0.02145685 | D77: ='[1]Availabilities EU Austria'!#REF!/'[1]Availabilities EU Austria'!#REF! -> #REF! | E77: 69
A78: Lignocrops inter & cover cropping | B78: A01: Products of agriculture, hunting and related services | C78: ='[1]Availabilities EU Austria'!$N$124/'[1]Availabilities EU Austria'!$N$119 -> 0.0097686219 | D78: ='[1]Availabilities EU Austria'!#REF!/'[1]Availabilities EU Austria'!#REF! -> #REF! | E78: 69
A79: Primary forestry residues | B79: A02: Products of forestry, logging and related services (en) | C79: ='[1]Availabilities EU Austria'!$N$125/'[1]Availabilities EU Austria'!$N$119 -> 0.1567111 | D79: ='[1]Availabilities EU Austria'!#REF!/'[1]Availabilities EU Austria'!#REF! -> #REF! | E79: 67
A80: Secondary forest residues | B80: C MANUFACTURED PRODUCTS, C17: Paper and paper products (en) | C80: ='[1]Availabilities EU Austria'!$N$126/'[1]Availabilities EU Austria'!$N$119 -> 0.16452273 | D80: ='[1]Availabilities EU Austria'!#REF!/'[1]Availabilities EU Austria'!#REF! -> #REF! | E80: 67
A81: Biowastes - Post consumer wood | B81: E WATER SUPPLY; SEWERAGE, WASTE MANAGEMENT AND REMEDIATION SERVICES (en) | C81: ='[1]Availabilities EU Austria'!$N$127/'[1]Availabilities EU Austria'!$N$119 -> 0.04928264 | D81: ='[1]Availabilities EU Austria'!#REF!/'[1]Availabilities EU Austria'!#REF! -> #REF! | E81: 0 | F81: CHECK

Sheet LCoP CONVENTIONAL
B1: TOTAL absolute costs [€/ t product] | C1: Feedstock share | E1: Absolute feedstock costs [€/t product] | F1: CAPEX share | H1: Absolute CAPEX | I1: OPEX share | K1: Absolute OPEX
A2: Conventional biodiesel
A3: transesterification of food/feed crops | B3: 800 | C3: 0.75 | D3: money [€] spent on each feedtsock when producing 1t of product | E3: =C3*B3 -> 600 | F3: 0.065 | G3: =SUM(G4:G8) -> 1 | H3: =F3*B3 -> 52 | I3: 0.185 | J3: =SUM(J4:J9) -> 1 | K3: =I3*B3 -> 148
B4: primarily EU | C4: Rapeseed oil | D4: ='Feedtstocks only CONVENTIONAL'!I4 -> 354.464 | E4: 0.76 | F4: Machinery and equipment | G4: 0.45 | H4: =G4*$H$3 -> 23.4 | I4: Chemical and chemical products | J4: 0.3 | K4: =J4*$K$3 -> 44.4
B5: imported | C5: Soybean oil | D5: ='Feedtstocks only CONVENTIONAL'!I5 -> 74.624 | E5: 0.16 | F5: Architectural and engineering services | G5: 0.3 | H5: =G5*$H$3 -> 15.6 | I5: Electricity, gas, steam & AC | J5: 0.2 | K5: =J5*$K$3 -> 29.6
B6: primarily EU | C6: Sunflower oil | D6: ='Feedtstocks only CONVENTIONAL'!I6 -> 18.656 | E6: 0.04 | F6: Constructions and construction works | G6: 0.15 | H6: =G6*$H$3 -> 7.8 | I6: Legal and accounting services; services of head offices; management consultancy services | J6: 0.25 | K6: =J6*$K$3 -> 37
B7: imported | C7: Palm oil | D7: ='Feedtstocks only CONVENTIONAL'!I7 -> 18.333333 | E7: 0.04 | F7: Fabricated metal products | G7: 0.07 | H7: =G7*$H$3 -> 3.64 | I7: Repair and installation services | J7: 0.15 | K7: =J7*$K$3 -> 22.2
F8: Computer, electronic and optical products | G8: 0.03 | H8: =G8*$H$3 -> 1.56 | I8: Land transport services and transport services via pipelines | J8: 0.1 | K8: =J8*$K$3 -> 14.8
I9: Waste management services | J9: 0 | K9: =J9*$K$3 -> 0
A10: transesterification of cover crops from marginal lands | B10: =E10+H10+K10 -> 1253 | C10: =E10/B10 -> 0.72067039 | E10: 903 | F10: =H10/B10 -> 0.066241022 | G10: =SUM(G11:G15) -> 1 | H10: 83 | I10: =K10/B10 -> 0.21308859 | J10: =SUM(J11:J16) -> 1 | K10: 267
F11: Machinery and equipment | G11: 0.48 | H11: =G11*$H$10 -> 39.84 | I11: Chemical and chemical products | J11: 0.25 | K11: =J11*$K$10 -> 66.75
F12: Architectural and engineering services | G12: 0.3 | H12: =G12*$H$10 -> 24.9 | I12: Electricity, gas, steam & AC | J12: 0.15 | K12: =J12*$K$10 -> 40.05
F13: Constructions and construction works | G13: 0.12 | H13: =G13*$H$10 -> 9.96 | I13: Legal and accounting services; services of head offices; management consultancy services | J13: 0.2 | K13: =J13*$K$10 -> 53.4
F14: Fabricated metal products | G14: 0.07 | H14: =G14*$H$10 -> 5.81 | I14: Repair and installation services | J14: 0.15 | K14: =J14*$K$10 -> 40.05
F15: Computer, electronic and optical products | G15: 0.03 | H15: =G15*$H$10 -> 2.49 | I15: Land transport services and transport services via pipelines | J15: 0.25 | K15: =J15*$K$10 -> 66.75
I16: Waste management services | J16: 0 | K16: =J16*$K$10 -> 0
A17: transesterification of UCO and AF | B17: 1253 | C17: =E17/$B$17 -> 0.72067039 | E17: 903 | F17: =$H$17/$B$17 -> 0.066241022 | G17: =SUM(G18:G22) -> 1 | H17: 83 | I17: =K17/B17 -> 0.21308859 | J17: =SUM(J18:J23) -> 1 | K17: 267
C18: UCO imported | D18: =0.6618*0.6 -> 0.39708 | E18: =D18*$E$17 -> 358.56324 | F18: Machinery and equipment | G18: 0.5 | H18: =G18*$H$17 -> 41.5 | I18: Chemical and chemical products | J18: 0.25 | K18: =J18*K$17 -> 66.75
C19: UCO domestic | D19: =0.6618*0.4 -> 0.26472 | E19: =D19*$E$17 -> 239.04216 | F19: Architectural and engineering services | G19: 0.3 | H19: =G19*$H$17 -> 24.9 | I19: Electricity, gas, steam & AC | J19: 0.15 | K19: =J19*K$17 -> 40.05
C20: Animal Fat | D20: 0.3382 | E20: =D20*$E$17 -> 305.3946 | F20: Constructions and construction works | G20: 0.1 | H20: =G20*$H$17 -> 8.3 | I20: Legal and accounting services; services of head offices; management consultancy services | J20: 0.2 | K20: =J20*K$17 -> 53.4
F21: Fabricated metal products | G21: 0.07 | H21: =G21*$H$17 -> 5.81 | I21: Repair and installation services | J21: 0.2 | K21: =J21*K$17 -> 53.4
F22: Computer, electronic and optical products | G22: 0.03 | H22: =G22*$H$17 -> 2.49 | I22: Land transport services and transport services via pipelines | J22: 0.1 | K22: =J22*K$17 -> 26.7
I23: Waste management services | J23: 0.1 | K23: =J23*K$17 -> 26.7
A24: hydrotreatment of food/feed crops | B24: =E24+H24+K24 -> 900 | C24: =E24/B24 -> 0.66666667 | E24: 600 | F24: =H24/B24 -> 0.11111111 | G24: =SUM(G25:G29) -> 1 | H24: 100 | I24: =K24/B24 -> 0.22222222 | J24: =SUM(J25:J30) -> 1 | K24: 200
F25: Machinery and equipment | G25: 0.55 | H25: =G25*$H$24 -> 55 | I25: Chemical and chemical products | J25: 0.4 | K25: =J25*$K$24 -> 80
F26: Architectural and engineering services | G26: 0.25 | H26: =G26*$H$24 -> 25 | I26: Electricity, gas, steam & AC | J26: 0.2 | K26: =J26*$K$24 -> 40
F27: Constructions and construction works | G27: 0.1 | H27: =G27*$H$24 -> 10 | I27: Legal and accounting services; services of head offices; management consultancy services | J27: 0.2 | K27: =J27*$K$24 -> 40
F28: Fabricated metal products | G28: 0.07 | H28: =G28*$H$24 -> 7 | I28: Repair and installation services | J28: 0.15 | K28: =J28*$K$24 -> 30
F29: Computer, electronic and optical products | G29: 0.03 | H29: =G29*$H$24 -> 3 | I29: Land transport services and transport services via pipelines | J29: 0.05 | K29: =J29*$K$24 -> 10
I30: Waste management services | J30: 0 | K30: =J30*$K$24 -> 0
A31: hydrotreatment of cover crops from marginal lands (non-aviation part) | B31: =E31+H31+K31 -> 1203 | C31: =E31/B31 -> 0.75062344 | E31: 903 | F31: =H31/$B$31 -> 0.08312552 | G31: =SUM(G32:G36) -> 1 | H31: 100 | I31: =K31/$B$31 -> 0.16625104 | J31: =SUM(J32:J37) -> 1 | K31: 200
F32: Machinery and equipment | G32: 0.58 | H32: =G32*$H$31 -> 58 | I32: Chemical and chemical products | J32: 0.35 | K32: =J32*$K$31 -> 70
F33: Architectural and engineering services | G33: 0.25 | H33: =G33*$H$31 -> 25 | I33: Electricity, gas, steam & AC | J33: 0.15 | K33: =J33*$K$31 -> 30
F34: Constructions and construction works | G34: 0.08 | H34: =G34*$H$31 -> 8 | I34: Legal and accounting services; services of head offices; management consultancy services | J34: 0.18 | K34: =J34*$K$31 -> 36
F35: Fabricated metal products | G35: 0.06 | H35: =G35*$H$31 -> 6 | I35: Repair and installation services | J35: 0.15 | K35: =J35*$K$31 -> 30
F36: Computer, electronic and optical products | G36: 0.03 | H36: =G36*$H$31 -> 3 | I36: Land transport services and transport services via pipelines | J36: 0.17 | K36: =J36*$K$31 -> 34
I37: Waste management services | J37: 0 | K37: =J37*$K$31 -> 0
A38: HVO (road) hydrotreatment of UCO and AF | B38: =E38+H38+K38 -> 2016 | C38: =E38/$B$38 -> 0.6656746 | E38: 1342 | F38: =H38/$B$38 -> 0.13343254 | G38: =SUM(G39:G43) -> 1 | H38: 269 | I38: =K38/$B$38 -> 0.20089286 | J38: =SUM(J39:J44) -> 1 | K38: 405
B39: 60% imported | C39: UCO | F39: Machinery and equipment | G39: 0.6 | H39: =G39*$H$38 -> 161.4 | I39: Chemical and chemical products | J39: 0.15 | K39: =J39*K$38 -> 60.75
B40: domestic | C40: Animal fat | F40: Architectural and engineering services | G40: 0.25 | H40: =G40*$H$38 -> 67.25 | I40: Electricity, gas, steam & AC | J40: 0.4 | K40: =J40*K$38 -> 162
F41: Constructions and construction works | G41: 0.07 | H41: =G41*$H$38 -> 18.83 | I41: Legal and accounting services; services of head offices; management consultancy services | J41: 0.2 | K41: =J41*K$38 -> 81
F42: Fabricated metal products | G42: 0.05 | H42: =G42*$H$38 -> 13.45 | I42: Repair and installation services | J42: 0.15 | K42: =J42*K$38 -> 60.75
F43: Computer, electronic and optical products | G43: 0.03 | H43: =G43*$H$38 -> 8.07 | I43: Land transport services and transport services via pipelines | J43: 0.1 | K43: =J43*K$38 -> 40.5
I44: Waste management services | J44: 0 | K44: =J44*K$38 -> 0
A45: HEFA (aviation) hydrotreatment of UCO and AF | B45: =E45+H45+K45 -> 2903 | C45: =E45/$B$45 -> 0.6755081 | E45: 1961 | F45: =H45/$B$45 -> 0.12952118 | G45: =SUM(G46:G50) -> 1 | H45: 376 | I45: =K45/$B$45 -> 0.19497072 | J45: =SUM(J46:J51) -> 1 | K45: 566
B46: 60% imported | C46: UCO | F46: Machinery and equipment | G46: 0.6 | H46: =G46*$H$45 -> 225.6 | I46: Chemical and chemical products | J46: 0.15 | K46: =J46*K$45 -> 84.9
B47: domestic | C47: Animal fat | F47: Architectural and engineering services | G47: 0.25 | H47: =G47*$H$45 -> 94 | I47: Electricity, gas, steam & AC | J47: 0.4 | K47: =J47*K$45 -> 226.4
F48: Constructions and construction works | G48: 0.07 | H48: =G48*$H$45 -> 26.32 | I48: Legal and accounting services; services of head offices; management consultancy services | J48: 0.2 | K48: =J48*K$45 -> 113.2
F49: Fabricated metal products | G49: 0.05 | H49: =G49*$H$45 -> 18.8 | I49: Repair and installation services | J49: 0.15 | K49: =J49*K$45 -> 84.9
F50: Computer, electronic and optical products | G50: 0.03 | H50: =G50*$H$45 -> 11.28 | I50: Land transport services and transport services via pipelines | J50: 0.1 | K50: =J50*K$45 -> 56.6
I51: Waste management services | J51: 0 | K51: =J51*K$45 -> 0
A52: Conventional biogasoline (Ethanol)
A53: ethanol fermentation of food/ feed crops | B53: 903.57 | C53: 0.7 | D53: source: CETO 2026 report, p. 28 | E53: =C53*B53 -> 632.499 | F53: 0.1 | H53: =F53*B53 -> 90.357 | I53: 0.2 | J53: =SUM(J54:J59) -> 1 | K53: =I53*B53 -> 180.714
C54: Wheat kernels | D54: 0.17 | F54: Machinery and equipment | G54: 0.5 | H54: =G54*$H$53 -> 45.1785 | I54: Chemical and chemical products | J54: 0.15 | K54: =J54*K$53 -> 27.1071
C55: Corn kernels | D55: 0.43 | F55: Architectural and engineering services | G55: 0.25 | H55: =G55*$H$53 -> 22.58925 | I55: Electricity, gas, steam & AC | J55: 0.4 | K55: =J55*K$53 -> 72.2856
C56: triticale | D56: 0.09 | F56: Constructions and construction works | G56: 0.15 | H56: =G56*$H$53 -> 13.55355 | I56: Legal and accounting services; services of head offices; management consultancy services | J56: 0.2 | K56: =J56*K$53 -> 36.1428
C57: Barley kernels | D57: 0.03 | F57: Fabricated metal products | G57: 0.07 | H57: =G57*$H$53 -> 6.32499 | I57: Repair and installation services | J57: 0.15 | K57: =J57*K$53 -> 27.1071
C58: Rye Kernels | D58: 0.02 | F58: Computer, electronic and optical products | G58: 0.03 | H58: =G58*$H$53 -> 2.71071 | I58: Land transport services and transport services via pipelines | J58: 0.1 | K58: =J58*K$53 -> 18.0714
C59: Sugar Beets | D59: 0.26 | I59: Waste management services | J59: 0 | K59: =J59*K$53 -> 0

Sheet 2023 costs
A1: 2023 | B1: marrket price | C1: market value asbolute [€/t] | D1: in Mtoe | E1: Conversion factor [t/toe] | F1: in t | G1: Cost of production [€/t] | H1: Cost spent per IVC | I1: Feedstock share of costs | J1: Eurostat sector | K1: money [€] spent on each feedtsock when producing 1t of product | L1: Absolute feedstock costs [€] | M1: CAPEX share of costs | N1: CAPEX distribution | O1: Absoluet CAPEX [€] | P1: OPEX share of costs | R1: Absolute OPEX [€] | S1: ENTIRE production costs
A2: Advanced biodiesel
A3: TOTAL | C3: =SUM(C4:C18) -> 2.1386098e+09 | D3: =D4+D11+D18 -> 1.3 | F3: =SUM(F4:F18) -> 1443203.4 | H3: =SUM(H4:H18) -> 1.894285e+09 | L3: =L4+L11+L18 -> 1.4277665e+09 | O3: =O4+O11+O18 -> 1.5900413e+08 | R3: =R4+R11+R18 -> 3.0751437e+08 | S3: =L3+R3 -> 1.7352809e+09
A4: of which IVC 1 | B4: 1450 | C4: =B4*F4 -> 1.8704812e+09 | D4: 1.14 | E4: ='[1]Conversion factors selected IV '!$O$4 -> 1.1315676 | F4: =D4*E4*1000000 -> 1289987 | G4: ='LCoP 2030 MEDIUM'!E2 -> 1283.25 | H4: =F4*G4 -> 1.6553759e+09 | I4: ='LCoP 2030 MEDIUM'!H2 -> 0.77927138 | L4: =I4*H4 -> 1.289987e+09 | M4: ='LCoP 2030 MEDIUM'!F2 -> 0.064679525 | O4: =M4*H4 -> 1.0706892e+08 | P4: ='LCoP 2030 MEDIUM'!G2 -> 0.15604909 | R4: =P4*H4 -> 2.583199e+08 | S4: =L4+O4+R4 -> 1.6553759e+09
H5: imported | I5: POME | J5: Food, beverages and tobacco products | K5: 850 | L5: =K5*F4 -> 1.096489e+09 | M5: Fabricated metal products | N5: 0.05 | O5: =N5*O$4 -> 5353446.2 | P5: Electricity, gas, steam and air conditioning | Q5: 0.35 | R5: =Q5*R$4 -> 90411966
M6: Electrical equipment | N6: 0.02 | O6: =N6*O$4 -> 2141378.5 | P6: Chemicals and chemical products | Q6: 0.25 | R6: =Q6*R$4 -> 64579976
M7: Machinery and equipment n.e.c. | N7: 0.45 | O7: =N7*O$4 -> 48181015 | P7: Legal and accounting services; services of head offices; management consultancy services | Q7: 0.2 | R7: =Q7*R$4 -> 51663980
M8: Constructions and construction works | N8: 0.15 | O8: =N8*O$4 -> 16060338 | P8: Repair and installation services of machinery and equipment | Q8: 0.15 | R8: =Q8*R$4 -> 38747985
M9: Architectural and engineering services; technical testing and analysis services | N9: 0.3 | O9: =N9*O$4 -> 32120677 | P9: Land transport services and transport services via pipelines | Q9: 0.05 | R9: =Q9*R$4 -> 12915995
M10: Computer, electronic and optical products | N10: 0.03 | O10: =N10*O$4 -> 3212067.7 | Q10: =SUM(Q5:Q9) -> 1 | R10: =SUM(R5:R9) -> 2.583199e+08
A11: of which IVC 2 | B11: 1750 | C11: =B11*F11 -> 2.3312864e+08 | D11: 0.14 | E11: ='[1]Conversion factors selected IV '!$O$7 -> 0.95154545 | F11: =D11*E11*1000000 -> 133216.36 | G11: ='LCoP 2030 MEDIUM'!E23 -> 1572.75 | H11: =F11*G11 -> 2.0951604e+08 | I11: ='LCoP 2030 MEDIUM'!H23 -> 0.63582896 | L11: =I11*H11 -> 1.3321636e+08 | M11: ='LCoP 2030 MEDIUM'!F23 -> 0.17103799 | N11: =SUM(N12:N17) -> 1 | O11: =M11*H11 -> 35835202 | P11: ='LCoP 2030 MEDIUM'!G23 -> 0.19313305 | R11: =P11*H11 -> 40464470 | S11: =L11+O11+R11 -> 2.0951604e+08
H12: imported | I12: POME | J12: Food, beverages and tobacco products | K12: 850 | L12: =K12*F11 -> 1.1323391e+08 | M12: Fabricated metal products | N12: 0.05 | O12: =N12*O$11 -> 1791760.1 | P12: Electricity, gas, steam and air conditioning | Q12: 0.35 | R12: =Q12*R$11 -> 14162565
M13: Electrical equipment | N13: 0.02 | O13: =N13*O$11 -> 716704.04 | P13: Chemicals and chemical products | Q13: 0.25 | R13: =Q13*R$11 -> 10116118
M14: Machinery and equipment n.e.c. | N14: 0.45 | O14: =N14*O$11 -> 16125841 | P14: Legal and accounting services; services of head offices; management consultancy services | Q14: 0.2 | R14: =Q14*R$11 -> 8092894.1
M15: Constructions and construction works | N15: 0.15 | O15: =N15*O$11 -> 5375280.3 | P15: Repair and installation services of machinery and equipment | Q15: 0.15 | R15: =Q15*R$11 -> 6069670.6
M16: Architectural and engineering services; technical testing and analysis services | N16: 0.3 | O16: =N16*O$11 -> 10750561 | P16: Land transport services and transport services via pipelines | Q16: 0.05 | R16: =Q16*R$11 -> 2023223.5
M17: Computer, electronic and optical products | N17: 0.03 | O17: =N17*O$11 -> 1075056.1 | Q17: =SUM(Q12:Q16) -> 1 | R17: =SUM(R12:R16) -> 40464470
A18: of which IVC 13a | B18: 1750 | C18: =B18*F18 -> 35000000 | D18: 0.02 | E18: ='[1]Conversion factors selected IV '!$O$98 -> 1 | F18: =D18*E18*1000000 -> 20000 | G18: ='LCoP 2030 MEDIUM'!E19 -> 1469.6575 | H18: =F18*G18 -> 29393151 | I18: ='LCoP 2030 MEDIUM'!H19 -> 0.15524537 | L18: =SUM(L19:L26) -> 4563150.7 | M18: ='LCoP 2030 MEDIUM'!F19 -> 0.54774666 | O18: =M18*H18 -> 16100000 | P18: ='LCoP 2030 MEDIUM'!G19 -> 0.29700797 | R18: =P18*H18 -> 8730000 | S18: =L18+O18+R18 -> 29393151
A19: I am assuming the feedstock split to be as in 2030 medium | G19: of which | H19: domestic | I19: Straw | J19: Products of agriculture, hunting and related services | K19: ='Feedstock MIX per IVC'!G84 -> 117.13778 | L19: =K19*F$18 -> 2342755.5 | M19: Fabricated metal products | N19: 0.15 | O19: =N19*O$18 -> 2415000 | P19: Electricity, gas, steam and air conditioning | Q19: 0.15 | R19: =Q19*R$18 -> 1309500
H20: domestic | I20: Prunings & damaged crops | J20: Products of agriculture, hunting and related services | K20: ='Feedstock MIX per IVC'!G85 -> 6.0040708 | L20: =K20*F$18 -> 120081.42 | M20: Electrical equipment | N20: 0.02 | O20: =N20*O$18 -> 322000 | P20: Chemicals and chemical products | Q20: 0.25 | R20: =Q20*R$18 -> 2182500
H21: domestic | I21: Agroprocessing residues - maize cobs | J21: Food, beverages and tobacco products | K21: ='Feedstock MIX per IVC'!G86 -> 2.9289602 | L21: =K21*F$18 -> 58579.204 | M21: Machinery and equipment n.e.c. | N21: 0.45 | O21: =N21*O$18 -> 7245000 | P21: Legal and accounting services; services of head offices; management consultancy services | Q21: 0.2 | R21: =Q21*R$18 -> 1746000
H22: domestic | I22: Lignocrops abandoned degraded | J22: Products of agriculture, hunting and related services | K22: ='Feedstock MIX per IVC'!G87 -> 4.8668638 | L22: =K22*F$18 -> 97337.275 | M22: Constructions and construction works | N22: 0.1 | O22: =N22*O$18 -> 1610000 | P22: Repair and installation services of machinery and equipment | Q22: 0.3 | R22: =Q22*R$18 -> 2619000
H23: domestic | I23: Lignocrops inter & cover cropping | J23: Products of agriculture, hunting and related services | K23: ='Feedstock MIX per IVC'!G88 -> 2.2157284 | L23: =K23*F$18 -> 44314.568 | M23: Architectural and engineering services; technical testing and analysis services | N23: 0.25 | O23: =N23*O$18 -> 4025000 | P23: Land transport services and transport services via pipelines | Q23: 0.1 | R23: =Q23*R$18 -> 873000
H24: domestic | I24: Primary forestry residues | J24: Products of forestry, logging and related services | K24: ='Feedstock MIX per IVC'!G89 -> 48.32109 | L24: =K24*F$18 -> 966421.8 | M24: Computer, electronic and optical products | N24: 0.03 | O24: =N24*O$18 -> 483000 | Q24: =SUM(Q19:Q23) -> 1 | R24: =SUM(R19:R23) -> 8730000
H25: domestic | I25: Secondary forest residues | J25: Paper and paper products | K25: ='Feedstock MIX per IVC'!G90 -> 41.012873 | L25: =K25*F$18 -> 820257.46
H26: domestic | I26: Biowastes - Post consumer wood | J26: Sewerage services; sewage sludge; waste collection, treatment and disposal services; materials recovery services; remediation services and other waste management services | K26: ='Feedstock MIX per IVC'!G91 -> 5.6701708 | L26: =K26*F$18 -> 113403.42 | M26: =K26*F$18 -> 113403.42
J28: TOTALS domestic | L28: =SUM(L29:L34) -> 4563150.7 | M28: TOTALS | O28: =SUM(O29:O34) -> 1.5900413e+08 | R28: =SUM(R29:R33) -> 3.0751437e+08 | S28: =S4+S11+S18 -> 1.894285e+09
J29: Products of agriculture, hunting and related services | L29: =L19+L20+L22+L23 -> 2604488.8 | M29: Fabricated metal products | O29: =O5+O12+O19 -> 9560206.3 | P29: Electricity, gas, steam and air conditioning | R29: =R5+R12+R19 -> 1.0588403e+08
J30: Paper and paper products | L30: =L25 -> 820257.46 | M30: Electrical equipment | O30: =O6+O13+O20 -> 3180082.5 | P30: Chemicals and chemical products | R30: =R6+R13+R20 -> 76878593
G31: or does that rather come from a biofuels sector directly? | J31: Chemicals and chemical products | L31: =L13 -> 0 | M31: Machinery and equipment n.e.c. | O31: =O7+O14+O21 -> 71551856 | P31: Legal and accounting services; services of head offices; management consultancy services | R31: =R7+R14+R21 -> 61502875
J32: Food, beverages and tobacco products | L32: =L21 -> 58579.204 | M32: Constructions and construction works | O32: =O8+O15+O22 -> 23045619 | P32: Repair and installation services of machinery and equipment | R32: =R8+R15+R22 -> 47436656
J33: Sewerage services; sewage sludge; waste collection, treatment and disposal services; materials recovery services; remediation services and other waste management services | L33: =L26 -> 113403.42 | M33: Architectural and engineering services; technical testing and analysis services | O33: =O9+O16+O23 -> 46896238 | P33: Land transport services and transport services via pipelines | R33: =R9+R16+R23 -> 15812219
J34: Products of forestry, logging and related services | L34: =L24 -> 966421.8 | M34: Computer, electronic and optical products | O34: =O10+O17+O24 -> 4770123.8
J35: TOTAL imported | L35: =L36 -> 1.2097229e+09
J36: Food, beverages and tobacco products | L36: =L12+L5 -> 1.2097229e+09
J37: ALL | L37: =L35+L28 -> 1.214286e+09 | M37: =L28+L37+O28+R28 -> 1.6853677e+09 | N37: =M37/1000000 -> 1685.3677
A38: Advanced biogasoline
A39: TOTAL | C39: =SUM(C40:C47) -> 2.3658667e+08 | D39: =SUM(D40:D47) -> 0.15 | F39: =SUM(F40:F47) -> 221586.67 | H39: =SUM(H40:H47) -> 2.8780279e+08 | L39: =L40+L47 -> 73078152 | O39: =O40+O47 -> 127980600 | R39: =R40+R47 -> 86744040
A40: of which IVC 5 | B40: 1000 | C40: =B40*F40 -> 2.0158667e+08 | D40: 0.13 | E40: ='[1]Conversion factors selected IV '!$O$18 -> 1.5506667 | F40: =D40*E40*1000000 -> 201586.67 | G40: ='LCoP 2030 MEDIUM'!E5 -> 1281.8786 | H40: =F40*G40 -> 2.5840964e+08 | I40: ='LCoP 2030 MEDIUM'!H5 -> 0.26514104 | L40: =I40*H40 -> 68515002 | M40: ='LCoP 2030 MEDIUM'!F5 -> 0.4329583 | O40: =M40*H40 -> 111880600 | P40: ='LCoP 2030 MEDIUM'!G5 -> 0.30190065 | R40: =P40*H40 -> 78014040 | S40: =L40+O40+R40 -> 2.5840964e+08
H41: domestic | I41: Straw | J41: Products of agriculture, hunting and related services | K41: ='Feedstock MIX per IVC'!G13 -> 255.92003 | L41: =K41*F$40 -> 51590066 | M41: Fabricated metal products | N41: 0 | O41: =N41*O$40 -> 0 | P41: Electricity, gas, steam and air conditioning | Q41: 0.2 | R41: =Q41*R$40 -> 15602808
H42: domestic | I42: Lignocrops abandoned degraded | J42: Products of agriculture, hunting and related services | K42: ='Feedstock MIX per IVC'!G14 -> 10.633017 | L42: =K42*F$40 -> 2143474.4 | M42: Electrical equipment | N42: 0.02 | O42: =N42*O$40 -> 2237612 | P42: Chemicals and chemical products | Q42: 0.5 | R42: =Q42*R$40 -> 39007020
H43: domestic | I43: Lignocrops inter & cover cropping | J43: Products of agriculture, hunting and related services | K43: ='Feedstock MIX per IVC'!G15 -> 4.8408745 | L43: =K43*F$40 -> 975855.76 | M43: Machinery and equipment n.e.c. | N43: 0.5 | O43: =N43*O$40 -> 55940300 | P43: Legal and accounting services; services of head offices; management consultancy services | Q43: 0.15 | R43: =Q43*R$40 -> 11702106
H44: domestic | I44: Secondary forest residues | J44: Paper and paper products | K44: ='Feedstock MIX per IVC'!G16 -> 68.484713 | L44: =K44*F$40 -> 13805605 | M44: Constructions and construction works | N44: 0.15 | O44: =N44*O$40 -> 16782090 | P44: Repair and installation services of machinery and equipment | Q44: 0.1 | R44: =Q44*R$40 -> 7801404
M45: Architectural and engineering services; technical testing and analysis services | N45: 0.3 | O45: =N45*O$40 -> 33564180 | P45: Land transport services and transport services via pipelines | Q45: 0.05 | R45: =Q45*R$40 -> 3900702
M46: Computer, electronic and optical products | N46: 0.03 | O46: =N46*O$40 -> 3356418 | Q46: =SUM(Q41:Q45) -> 1 | R46: =SUM(R41:R45) -> 78014040
A47: of which IVC 13a | B47: 1750 | C47: =B47*F47 -> 35000000 | D47: =0.04/2 -> 0.02 | E47: ='[1]Conversion factors selected IV '!$O$89 -> 1 | F47: =D47*E47*1000000 -> 20000 | G47: ='LCoP 2030 MEDIUM'!E19 -> 1469.6575 | H47: =F47*G47 -> 29393151 | I47: ='LCoP 2030 MEDIUM'!H19 -> 0.15524537 | K47: =SUM(K48:K55) -> 228.15753 | L47: =I47*H47 -> 4563150.7 | M47: ='LCoP 2030 MEDIUM'!F19 -> 0.54774666 | O47: =M47*H47 -> 16100000 | P47: ='LCoP 2030 MEDIUM'!G19 -> 0.29700797 | R47: =P47*H47 -> 8730000 | S47: =L47+O47+R47 -> 29393151
H48: domestic | I48: Straw | J48: Products of agriculture, hunting and related services | K48: ='Feedstock MIX per IVC'!G84 -> 117.13778 | L48: =K48*$F$47 -> 2342755.5 | M48: Fabricated metal products | N48: 0.15 | O48: =N48*O$47 -> 2415000 | P48: Electricity, gas, steam and air conditioning | Q48: 0.15 | R48: =Q48*R$47 -> 1309500
H49: domestic | I49: Prunings & damaged crops | J49: Products of agriculture, hunting and related services | K49: ='Feedstock MIX per IVC'!G85 -> 6.0040708 | L49: =K49*$F$47 -> 120081.42 | M49: Electrical equipment | N49: 0.02 | O49: =N49*O$47 -> 322000 | P49: Chemicals and chemical products | Q49: 0.25 | R49: =Q49*R$47 -> 2182500
H50: domestic | I50: Agroprocessing residues - maize cobs | J50: Food, beverages and tobacco products | K50: ='Feedstock MIX per IVC'!G86 -> 2.9289602 | L50: =K50*$F$47 -> 58579.204 | M50: Machinery and equipment n.e.c. | N50: 0.45 | O50: =N50*O$47 -> 7245000 | P50: Legal and accounting services; services of head offices; management consultancy services | Q50: 0.2 | R50: =Q50*R$47 -> 1746000
H51: domestic | I51: Lignocrops abandoned degraded | J51: Products of agriculture, hunting and related services | K51: ='Feedstock MIX per IVC'!G87 -> 4.8668638 | L51: =K51*$F$47 -> 97337.275 | M51: Constructions and construction works | N51: 0.1 | O51: =N51*O$47 -> 1610000 | P51: Repair and installation services of machinery and equipment | Q51: 0.3 | R51: =Q51*R$47 -> 2619000
H52: domestic | I52: Lignocrops inter & cover cropping | J52: Products of agriculture, hunting and related services | K52: ='Feedstock MIX per IVC'!G88 -> 2.2157284 | L52: =K52*$F$47 -> 44314.568 | M52: Architectural and engineering services; technical testing and analysis services | N52: 0.25 | O52: =N52*O$47 -> 4025000 | P52: Land transport services and transport services via pipelines | Q52: 0.1 | R52: =Q52*R$47 -> 873000
H53: domestic | I53: Primary forestry residues | J53: Products of forestry, logging and related services | K53: ='Feedstock MIX per IVC'!G89 -> 48.32109 | L53: =K53*$F$47 -> 966421.8 | M53: Computer, electronic and optical products | N53: 0.03 | O53: =N53*O$47 -> 483000 | Q53: =SUM(Q48:Q52) -> 1 | R53: =SUM(R48:R52) -> 8730000
H54: domestic | I54: Secondary forest residues | J54: Paper and paper products | K54: ='Feedstock MIX per IVC'!G90 -> 41.012873 | L54: =K54*$F$47 -> 820257.46
H55: domestic | I55: Biowastes - Post consumer wood | J55: Sewerage services; sewage sludge; waste collection, treatment and disposal services; materials recovery services; remediation services and other waste management services | K55: ='Feedstock MIX per IVC'!G91 -> 5.6701708 | L55: =K55*$F$47 -> 113403.42
J56: TOTALS domestic | L56: =SUM(L57:L62) -> 73078152 | M56: TOTALS | O56: =O40+O47 -> 127980600 | R56: =SUM(R57:R61) -> 86744040
I57: of which | J57: Products of agriculture, hunting and related services | L57: =L41+L42+L43+L48+L49+L51+L52 -> 57313885 | M57: Fabricated metal products | O57: =O41+O48 -> 2415000 | P57: Electricity, gas, steam and air conditioning | R57: =R41+R48 -> 16912308
J58: Paper and paper products | L58: =L44+L54 -> 14625863 | M58: Electrical equipment | O58: =O42+O49 -> 2559612 | P58: Chemicals and chemical products | R58: =R42+R49 -> 41189520
J59: Chemicals and chemical products | L59: =0 -> 0 | M59: Machinery and equipment n.e.c. | O59: =O43+O50 -> 63185300 | P59: Legal and accounting services; services of head offices; management consultancy services | R59: =R43+R50 -> 13448106
J60: Food, beverages and tobacco products | L60: =L50 -> 58579.204 | M60: Constructions and construction works | O60: =O44+O51 -> 18392090 | P60: Repair and installation services of machinery and equipment | R60: =R44+R51 -> 10420404
J61: Sewerage services; sewage sludge; waste collection, treatment and disposal services; materials recovery services; remediation services and other waste management services | L61: =L55 -> 113403.42 | M61: Architectural and engineering services; technical testing and analysis services | O61: =O45+O52 -> 37589180 | P61: Land transport services and transport services via pipelines | R61: =R45+R52 -> 4773702
J62: Products of forestry, logging and related services | L62: =L53 -> 966421.8 | M62: Computer, electronic and optical products | O62: =O46+O53 -> 3839418
A63: Advanced biogas
A64: TOTAL | C64: =C65 -> 1.3868147e+08 | D64: 0.13 | F64: =F65 -> 108769.78 | H64: =H65 -> 99803999
A65: of which IVC 7 | B65: 1275 | C65: =B65*F65 -> 1.3868147e+08 | D65: 0.13 | E65: ='[1]Conversion factors selected IV '!$O$29 -> 0.83669065 | F65: =D65*E65*1000000 -> 108769.78 | G65: ='LCoP 2030 MEDIUM'!E9 -> 917.57099 | H65: =F65*G65 -> 99803999 | I65: ='LCoP 2030 MEDIUM'!H9 -> -0.01940341 | L65: =I65*H65 -> -1936537.9 | M65: ='LCoP 2030 MEDIUM'!F9 -> 0.65934953 | O65: =M65*H65 -> 65805719 | P65: ='LCoP 2030 MEDIUM'!G9 -> 0.36005388 | R65: =P65*H65 -> 35934817 | S65: =L65+O65+R65 -> 99803999
H66: domestic | I66: Prunings & damaged crops (olive stones excluded) | J66: Products of agriculture, hunting and related services | K66: ='Feedstock MIX per IVC'!G20 -> 0.84774671 | L66: =K66*$F$65 -> 92209.227 | M66: Fabricated metal products | N66: 0.05 | O66: =N66*$O$65 -> 3290286 | P66: Electricity, gas, steam and air conditioning | Q66: 0.2 | R66: =Q66*R$65 -> 7186963.5
H67: domestic | I67: Lignocrops abandoned degraded | J67: Products of agriculture, hunting and related services | K67: ='Feedstock MIX per IVC'!G21 -> 0.6871784 | L67: =K67*$F$65 -> 74744.246 | M67: Electrical equipment | N67: 0.02 | O67: =N67*$O$65 -> 1316114.4 | P67: Chemicals and chemical products | Q67: 0.5 | R67: =Q67*R$65 -> 17967409
H68: domestic | I68: Lignocrops inter & cover cropping | J68: Products of agriculture, hunting and related services | K68: ='Feedstock MIX per IVC'!G22 -> 0.31285048 | L68: =K68*$F$65 -> 34028.679 | M68: Machinery and equipment n.e.c. | N68: 0.4 | O68: =N68*$O$65 -> 26322288 | P68: Legal and accounting services; services of head offices; management consultancy services | Q68: 0.15 | R68: =Q68*R$65 -> 5390222.6
H69: domestic | I69: Agroprocessing residues | J69: Food, beverages and tobacco products | K69: ='Feedstock MIX per IVC'!G23 -> 3.9186047 | L69: =K69*$F$65 -> 426225.79 | M69: Constructions and construction works | N69: 0.3 | O69: =N69*$O$65 -> 19741716 | P69: Repair and installation services of machinery and equipment | Q69: 0.1 | R69: =Q69*R$65 -> 3593481.7
H70: domestic | I70: Straw | J70: Products of agriculture, hunting and related services | K70: ='Feedstock MIX per IVC'!G24 -> 16.539306 | L70: =K70*$F$65 -> 1798976.8 | M70: Architectural and engineering services; technical testing and analysis services | N70: 0.2 | O70: =N70*$O$65 -> 13161144 | P70: Land transport services and transport services via pipelines | Q70: 0.05 | R70: =Q70*R$65 -> 1796740.9
H71: domestic | I71: Manure | J71: Products of agriculture, hunting and related services | K71: ='Feedstock MIX per IVC'!G25 -> 0 | L71: =K71*$F$65 -> 0 | M71: Computer, electronic and optical products | N71: 0.03 | O71: =N71*$O$65 -> 1974171.6 | Q71: =SUM(Q66:Q70) -> 1 | R71: =Q71*R$65 -> 35934817
H72: domestic | I72: Sewage sludge | J72: Sewerage services; sewage sludge; waste collection, treatment and disposal services; materials recovery services; remediation services and other waste management services | K72: ='Feedstock MIX per IVC'!G26 -> 0 | L72: =K72*$F$65 -> 0 | N72: =SUM(N66:N71) -> 1 | O72: =SUM(O66:O71) -> 65805719
H73: domestic | I73: Biowastes (post consumer woods excluded) | J73: Sewerage services; sewage sludge; waste collection, treatment and disposal services; materials recovery services; remediation services and other waste management services | K73: ='Feedstock MIX per IVC'!G27 -> -42.314992 | L73: =K73*$F$65 -> -4602592.6
H74: domestic | I74: Intermediate Bioenergy carrier (crude glycerine) | J74: Chemical and chemical products | K74: ='Feedstock MIX per IVC'!G28 -> 2.2052996 | L74: =K74*$F$65 -> 239869.96
J75: TOTALS | L75: =SUM(L76:L80) -> -1936537.9 | M75: TOTALS | O75: =O65 -> 65805719 | R75: =R65 -> 35934817
I76: of which | J76: Products of agriculture, hunting and related services | L76: =L66+L67+L68+L70+L71 -> 1999958.9 | M76: Fabricated metal products | O76: =O66 -> 3290286 | P76: Electricity, gas, steam and air conditioning | R76: =R66 -> 7186963.5
J77: Paper and paper products | L77: =0 -> 0 | M77: Electrical equipment | O77: =O67 -> 1316114.4 | P77: Chemicals and chemical products | R77: =R67 -> 17967409
J78: Chemical and chemical products | L78: =L74 -> 239869.96 | M78: Machinery and equipment n.e.c. | O78: =O68 -> 26322288 | P78: Legal and accounting services; services of head offices; management consultancy services | R78: =R68 -> 5390222.6
J79: Food, beverages and tobacco products | L79: =L69 -> 426225.79 | M79: Constructions and construction works | O79: =O69 -> 19741716 | P79: Repair and installation services of machinery and equipment | R79: =R69 -> 3593481.7
J80: Sewerage services; sewage sludge; waste collection, treatment and disposal services; materials recovery services; remediation services and other waste management services | L80: =L72+L73 -> -4602592.6 | M80: Architectural and engineering services; technical testing and analysis services | O80: =O70 -> 13161144 | P80: Land transport services and transport services via pipelines | R80: =R70 -> 1796740.9
L81: =SUM(L76:L79) -> 2666054.7 | M81: Computer, electronic and optical products | O81: =O71 -> 1974171.6
A82: Conventional biodiesel
A83: TOTAL | C83: =SUM(C84:C98) -> 1.5963965e+10 | D83: =SUM(D84:D98) -> 12.938449 | E83: 1.1627907 | F83: =SUM(F84:F98) -> 13695614 | H83: =H84+H91+H98 -> 1.3041552e+10 | L83: =L84+L91+L98 -> 9.2778682e+09 | O83: =O84+O91+O98 -> 1.0604614e+09 | R83: =R84+R91+R98 -> 2.7032227e+09 | S83: =L83+R83 -> 1.1981091e+10
A84: transestification of food/ feed crops | B84: 1165.6261 | C84: =B84*F84 -> 6.0612559e+09 | D84: ='[2]GAP analysis Sc. 1'!$G$18 -> 4.5953951 | E84: ='[1]Conversion factors selected IV '!$O$4 -> 1.1315676 | F84: =D84*E84*1000000 -> 5200000 | G84: ='LCoP CONVENTIONAL'!$B$3 -> 800 | H84: =G84*F84 -> 4.16e+09 | I84: ='LCoP CONVENTIONAL'!$C$3 -> 0.75 | K84: =I84*G84 -> 600 | L84: =I84*H84 -> 3.12e+09 | M84: ='LCoP CONVENTIONAL'!$F$3 -> 0.065 | O84: =M84*H84 -> 2.704e+08 | P84: ='LCoP CONVENTIONAL'!$I$3 -> 0.185 | R84: =P84*H84 -> 7.696e+08
H85: domestic | I85: rapeseed oil | J85: Food, beverages and tobacco products | K85: ='Feedtstocks only CONVENTIONAL'!$J$4 -> 0.76052615 | L85: =K85*L$84 -> 2.3728416e+09 | M85: Machinery and equipment | N85: 0.45 | O85: =N85*$O$84 -> 1.2168e+08 | P85: Chemical and chemical products | Q85: 0.3 | R85: =Q85*R$84 -> 2.3088e+08
F86: NOTE: made of imported soybeans, pick up in discussion | H86: domestic | I86: soybean oil | J86: Food, beverages and tobacco products | K86: ='Feedtstocks only CONVENTIONAL'!$J$5 -> 0.16011077 | L86: =K86*L$84 -> 4.995456e+08 | M86: Architectural and engineering services | N86: 0.3 | O86: =N86*$O$84 -> 81120000 | P86: Electricity, gas, steam & AC | Q86: 0.2 | R86: =Q86*R$84 -> 1.5392e+08
H87: domestic | I87: sunflower oil | J87: Food, beverages and tobacco products | K87: ='Feedtstocks only CONVENTIONAL'!$J$6 -> 0.040027692 | L87: =K87*L$84 -> 1.248864e+08 | M87: Constructions and construction works | N87: 0.15 | O87: =N87*$O$84 -> 40560000 | P87: Legal and accounting services; services of head offices; management consultancy services | Q87: 0.25 | R87: =Q87*R$84 -> 1.924e+08
H88: imported | I88: palm oil | J88: Food, beverages and tobacco products | K88: ='Feedtstocks only CONVENTIONAL'!$J$7 -> 0.039335389 | L88: =K88*L$84 -> 1.2272641e+08 | M88: Fabricated metal products | N88: 0.07 | O88: =N88*$O$84 -> 18928000 | P88: Repair and installation services | Q88: 0.15 | R88: =Q88*R$84 -> 1.1544e+08
M89: Computer, electronic and optical products | N89: 0.03 | O89: =N89*$O$84 -> 8112000 | P89: Land transport services and transport services via pipelines | Q89: 0.1 | R89: =Q89*R$84 -> 76960000
P90: Sewerage services; sewage sludge; waste collection, treatment and disposal services; materials recovery services; remediation services and other waste management services | Q90: 0 | R90: =Q90*R$84 -> 0
A91: transestification of UCO and AF | B91: 1165.6261 | C91: =B91*F91 -> 4.0796915e+09 | D91: ='[2]GAP analysis Sc. 1'!$G$23 -> 3.0930544 | E91: ='[1]Conversion factors selected IV '!$O$4 -> 1.1315676 | F91: =D91*E91*1000000 -> 3500000 | G91: ='LCoP CONVENTIONAL'!$B$17 -> 1253 | H91: =G91*F91 -> 4385500000 | I91: ='LCoP CONVENTIONAL'!$C$17 -> 0.72067039 | K91: ='Feedtstocks only CONVENTIONAL'!I15 -> 853.09425 | L91: =H91*I91 -> 3160500000 | M91: ='LCoP CONVENTIONAL'!$F$17 -> 0.066241022 | O91: =M91*H91 -> 290500000 | P91: ='LCoP CONVENTIONAL'!$I$17 -> 0.21308859 | R91: =P91*H91 -> 934500000
H92: domestic | I92: UCO domestic | J92: Food, beverages and tobacco products | K92: ='Feedtstocks only CONVENTIONAL'!J37 -> 0.42676656 | L92: =K92*L91 -> 1.3487957e+09 | M92: Machinery and equipment | N92: 0.5 | O92: =N92*O$91 -> 145250000 | P92: Chemical and chemical products | Q92: 0.25 | R92: =Q92*R$91 -> 233625000 | S92: Electricity, gas, steam and air conditioning
H93: imported | I93: UCO imported | J93: Food, beverages and tobacco products | K93: ='Feedtstocks only CONVENTIONAL'!J38 -> 0.28451104 | L93: =K93*L91 -> 8.9919714e+08 | M93: Architectural and engineering services | N93: 0.3 | O93: =N93*O$91 -> 87150000 | P93: Electricity, gas, steam & AC | Q93: 0.15 | R93: =Q93*R$91 -> 140175000 | S93: Chemicals and chemical products
H94: domestic | I94: animal fats | J94: Food, beverages and tobacco products | K94: ='Feedtstocks only CONVENTIONAL'!J39 -> 0.2887224 | L94: =K94*L91 -> 9.1250714e+08 | M94: Constructions and construction works | N94: 0.1 | O94: =N94*O$91 -> 29050000 | P94: Legal and accounting services; services of head offices; management consultancy services | Q94: 0.2 | R94: =Q94*R$91 -> 186900000 | S94: Legal and accounting services; services of head offices; management consultancy services
K95: =SUM(K92:K94) -> 1 | L95: =SUM(L92:L94) -> 3160500000 | M95: Fabricated metal products | N95: 0.07 | O95: =N95*O$91 -> 20335000 | P95: Repair and installation services | Q95: 0.2 | R95: =Q95*R$91 -> 186900000 | S95: Repair and installation services of machinery and equipment
M96: Computer, electronic and optical products | N96: 0.03 | O96: =N96*O$91 -> 8715000 | P96: Land transport services and transport services via pipelines | Q96: 0.1 | R96: =Q96*R$91 -> 93450000 | S96: Land transport services and transport services via pipelines
K97: from: | P97: Sewerage services; sewage sludge; waste collection, treatment and disposal services; materials recovery services; remediation services and other waste management services | Q97: 0.1 | R97: =Q97*R$91 -> 93450000
A98: hydrotreatment of food/ feed crops | B98: 1165.6261 | C98: =B98*F98 -> 5.8230178e+09 | D98: 5.25 | E98: ='[1]Conversion factors selected IV '!$O$7 -> 0.95154545 | F98: =D98*E98*1000000 -> 4995613.6 | G98: ='LCoP CONVENTIONAL'!$B$24 -> 900 | H98: =G98*F98 -> 4.4960523e+09 | I98: ='LCoP CONVENTIONAL'!$C$24 -> 0.66666667 | K98: ='Feedtstocks only CONVENTIONAL'!I22 -> 466.07733 | L98: =I98*H98 -> 2.9973682e+09 | M98: ='LCoP CONVENTIONAL'!$F$24 -> 0.11111111 | O98: =M98*H98 -> 4.9956136e+08 | P98: ='LCoP CONVENTIONAL'!$I$24 -> 0.22222222 | R98: =P98*H98 -> 9.9912273e+08
H99: domestic | I99: rapeseed oil | J99: Food, beverages and tobacco products | K99: ='Feedtstocks only CONVENTIONAL'!J$4 -> 0.76052615 | L99: =K99*L$98 -> 2.2795769e+09 | M99: Machinery and equipment | N99: 0.55 | O99: =N99*O$98 -> 274758750 | P99: Chemical and chemical products | Q99: 0.4 | R99: =Q99*R$98 -> 3.9964909e+08
F100: NOTE: made of imported soybeans, pick up in discussion | H100: domestic | I100: soybean oil | J100: Food, beverages and tobacco products | K100: ='Feedtstocks only CONVENTIONAL'!J$5 -> 0.16011077 | L100: =K100*L$98 -> 4.7991092e+08 | M100: Architectural and engineering services | N100: 0.25 | O100: =N100*O$98 -> 1.2489034e+08 | P100: Electricity, gas, steam & AC | Q100: 0.2 | R100: =Q100*R$98 -> 1.9982455e+08
H101: domestic | I101: sunflower oil | J101: Food, beverages and tobacco products | K101: ='Feedtstocks only CONVENTIONAL'!J$6 -> 0.040027692 | L101: =K101*L$98 -> 1.1997773e+08 | M101: Constructions and construction works | N101: 0.1 | O101: =N101*O$98 -> 49956136 | P101: Legal and accounting services; services of head offices; management consultancy services | Q101: 0.2 | R101: =Q101*R$98 -> 1.9982455e+08
...

Sheet 2030 costs Sc 1
A1: Contribution of each IVC to final product in Scenario (1) 2030
A2: Assumptions:
A3: technical capacity = cmc | E3: feedstock availability: 2030 medium
A4: Market value of ALLL biofule production | C4: =C6+C196+C225+C274+C283 -> 3.5019596e+10
B5: market price [€/t] | C5: makret value of overall amount produced | D5: produced in Mtoe | E5: Conversion factor [t/toe] | F5: produced in t | G5: Cost of production [€/t] | H5: Money spent on each IVC | I5: Feedstock share of costs | J5: Eurostat sector | K5: money [€] spent on each feedtsock when producing 1t of product | L5: Absolute feedstock costs [€] | M5: CAPEX share of costs | N5: CAPEX distribution | O5: Absoluet CAPEX [€] | P5: OPEX share of costs | R5: Absolute OPEX [€] | S5: TOTAL production costs
A6: SUMME ALL advanced | C6: =C8+C44+C86+C120+C154 -> 8.6532415e+09 | D6: =D8+D44+D86+D120+D154 -> 5.494849
A7: Advanced biodiesel
A8: TOTAL | B8: =C8/1000000 -> 3061.585 | C8: =C9+C23+C16 -> 3.061585e+09 | D8: =D9+D16+D23 -> 1.8575045 | F8: =F9+F23+F16 -> 2040905.7 | H8: =H9+H23+H16 -> 2.7114055e+09 | L8: =L9+L16+L23 -> 1.9938961e+09 | O8: =O9+O16+O23 -> 2.6544909e+08 | R8: =R9+R16+R23 -> 4.5206034e+08
A9: of which IVC 1 | B9: 1450 | C9: =B9*F9 -> 2.465e+09 | D9: ='[2]GAP analysis Sc. 1'!$C$36+'[2]GAP analysis Sc. 1'!$C$50 -> 1.5023407 | E9: ='[1]Conversion factors selected IV '!$O$4 -> 1.1315676 | F9: =D9*E9*1000000 -> 1700000 | G9: ='LCoP 2030 MEDIUM'!E2 -> 1283.25 | H9: =G9*F9 -> 2.181525e+09 | I9: ='LCoP 2030 MEDIUM'!H2 -> 0.77927138 | L9: =I9*H9 -> 1.7e+09 | M9: ='LCoP 2030 MEDIUM'!F2 -> 0.064679525 | O9: =M9*H9 -> 1.411e+08 | P9: ='LCoP 2030 MEDIUM'!G2 -> 0.15604909 | R9: =P9*H9 -> 3.40425e+08 | S9: =SUM(S10:S15) -> 0 | T9: =L9+O9+R9 -> 2.181525e+09
C10: =C9/C8 -> 0.80513852 | H10: imported | I10: POME | J10: Food, beverages and tobacco products | K10: ='Feedstock MIX per IVC'!G4 -> 1000 | L10: =K10*F9 -> 1.7e+09 | M10: Fabricated metal products | N10: 0.05 | O10: =N10*O$9 -> 7055000 | P10: Electricity, gas, steam and air conditioning | Q10: 0.35 | R10: =Q10*R$9 -> 1.1914875e+08
M11: Electrical equipment | N11: 0.02 | O11: =N11*O$9 -> 2822000 | P11: Chemicals and chemical products | Q11: 0.25 | R11: =Q11*R$9 -> 85106250
M12: Machinery and equipment n.e.c. | N12: 0.45 | O12: =N12*O$9 -> 63495000 | P12: Legal and accounting services; services of head offices; management consultancy services | Q12: 0.2 | R12: =Q12*R$9 -> 68085000
M13: Constructions and construction works | N13: 0.15 | O13: =N13*O$9 -> 21165000 | P13: Repair and installation services of machinery and equipment | Q13: 0.15 | R13: =Q13*R$9 -> 51063750
M14: Architectural and engineering services; technical testing and analysis services | N14: 0.3 | O14: =N14*O$9 -> 42330000 | P14: Land transport services and transport services via pipelines | Q14: 0.05 | R14: =Q14*R$9 -> 17021250
M15: Computer, electronic and optical products | N15: 0.03 | O15: =N15*O$9 -> 4233000
A16: of which IVC 2 HVO | B16: 1750 | C16: =B16*F16 -> 4.9e+08 | D16: ='[2]GAP analysis Sc. 1'!$C$37+'[2]GAP analysis Sc. 1'!$C$51 -> 0.29425814 | E16: ='[1]Conversion factors selected IV '!$O$7 -> 0.95154545 | F16: =D16*E16*1000000 -> 280000 | G16: ='LCoP 2030 MEDIUM'!E23 -> 1572.75 | H16: =G16*F16 -> 4.4037e+08 | I16: ='LCoP 2030 MEDIUM'!H23 -> 0.63582896 | L16: =I16*H16 -> 2.8e+08 | M16: ='LCoP 2030 MEDIUM'!F23 -> 0.17103799 | O16: =M16*H16 -> 75320000 | P16: ='LCoP 2030 MEDIUM'!G23 -> 0.19313305 | R16: =P16*H16 -> 85050000 | S16: =L16+O16+R16 -> 4.4037e+08
C17: =C16/C8 -> 0.16004782 | H17: imported | I17: POME | J17: Food, beverages and tobacco products | K17: 1000 | L17: =K17*F16 -> 2.8e+08 | M17: Fabricated metal products | N17: 0.05 | O17: =N17*O$16 -> 3766000 | P17: Electricity, gas, steam and air conditioning | Q17: 0.35 | R17: =Q17*R$16 -> 29767500
M18: Electrical equipment | N18: 0.02 | O18: =N18*O$16 -> 1506400 | P18: Chemicals and chemical products | Q18: 0.25 | R18: =Q18*R$16 -> 21262500
M19: Machinery and equipment n.e.c. | N19: 0.45 | O19: =N19*O$16 -> 33894000 | P19: Legal and accounting services; services of head offices; management consultancy services | Q19: 0.2 | R19: =Q19*R$16 -> 17010000
M20: Constructions and construction works | N20: 0.15 | O20: =N20*O$16 -> 11298000 | P20: Repair and installation services of machinery and equipment | Q20: 0.15 | R20: =Q20*R$16 -> 12757500
M21: Architectural and engineering services; technical testing and analysis services | N21: 0.3 | O21: =N21*O$16 -> 22596000 | P21: Land transport services and transport services via pipelines | Q21: 0.05 | R21: =Q21*R$16 -> 4252500
M22: Computer, electronic and optical products | N22: 0.03 | O22: =N22*O$16 -> 2259600
A23: of which 13a (half) | B23: 1750 | C23: =B23*F23 -> 1.0658498e+08 | D23: ='[2]GAP analysis Sc. 1'!$C$38 -> 0.060905704 | E23: ='[1]Conversion factors selected IV '!$O$89 -> 1 | F23: =D23*E23*1000000 -> 60905.704 | G23: ='LCoP 2030 MEDIUM'!E19 -> 1469.6575 | H23: =G23*F23 -> 89510526 | I23: ='LCoP 2030 MEDIUM'!H19 -> 0.15524537 | L23: =I23*H23 -> 13896095 | M23: ='LCoP 2030 MEDIUM'!F19 -> 0.54774666 | O23: =M23*H23 -> 49029091 | P23: ='LCoP 2030 MEDIUM'!G19 -> 0.29700797 | R23: =P23*H23 -> 26585340 | S23: =L23+O23+R23 -> 89510526
C24: =C23/C8 -> 0.034813661 | F24: Products of agriculture, hunting and related services | G24: =SUMIF($J$24:$J$31,F24,$L$24:$L$31)/$L$23 -> 0.57076546 | H24: domestic | I24: Straw | J24: Products of agriculture, hunting and related services | K24: ='Feedstock MIX per IVC'!G84 -> 117.13778 | L24: =K24*F$23 -> 7134358.7 | M24: Fabricated metal products | N24: 0.15 | O24: =N24*O$23 -> 7354363.7 | P24: Electricity, gas, steam and air conditioning | Q24: 0.15 | R24: =Q24*R$23 -> 3987800.9
F25: Food, beverages and tobacco products | G25: =SUMIF($J$24:$J$31,F25,$L$24:$L$31)/$L$23 -> 0.012837447 | H25: domestic | I25: Prunings & damaged crops | J25: Products of agriculture, hunting and related services | K25: ='Feedstock MIX per IVC'!G85 -> 6.0040708 | L25: =K25*F$23 -> 365682.16 | M25: Electrical equipment | N25: 0.02 | O25: =N25*O$23 -> 980581.83 | P25: Chemicals and chemical products | Q25: 0.25 | R25: =Q25*R$23 -> 6646334.9
F26: Products of forestry, logging and related services | G26: =SUMIF($J$24:$J$31,F26,$L$24:$L$31)/$L$23 -> 0.21178827 | H26: domestic | I26: Agroprocessing residues - maize cobs | J26: Food, beverages and tobacco products | K26: ='Feedstock MIX per IVC'!G86 -> 2.9289602 | L26: =K26*F$23 -> 178390.38 | M26: Machinery and equipment n.e.c. | N26: 0.45 | O26: =N26*O$23 -> 22063091 | P26: Legal and accounting services; services of head offices; management consultancy services | Q26: 0.2 | R26: =Q26*R$23 -> 5317067.9
F27: Paper and paper products | G27: =SUMIF($J$24:$J$31,F27,$L$24:$L$31)/$L$23 -> 0.17975682 | H27: domestic | I27: Lignocrops abandoned degraded | J27: Products of agriculture, hunting and related services | K27: ='Feedstock MIX per IVC'!G87 -> 4.8668638 | L27: =K27*F$23 -> 296419.76 | M27: Constructions and construction works | N27: 0.1 | O27: =N27*O$23 -> 4902909.1 | P27: Repair and installation services of machinery and equipment | Q27: 0.3 | R27: =Q27*R$23 -> 7975601.9
F28: Sewerage services; sewage sludge; waste collection, treatment and disposal services; materials recovery services; remediation services and other waste management services | G28: =SUMIF($J$24:$J$31,F28,$L$24:$L$31)/$L$23 -> 0.024851999 | H28: domestic | I28: Lignocrops inter & cover cropping | J28: Products of agriculture, hunting and related services | K28: ='Feedstock MIX per IVC'!G88 -> 2.2157284 | L28: =K28*F$23 -> 134950.5 | M28: Architectural and engineering services; technical testing and analysis services | N28: 0.25 | O28: =N28*O$23 -> 12257273 | P28: Land transport services and transport services via pipelines | Q28: 0.1 | R28: =Q28*R$23 -> 2658534
G29: =SUM(G24:G28) -> 1 | H29: domestic | I29: Primary forestry residues | J29: Products of forestry, logging and related services | K29: ='Feedstock MIX per IVC'!G89 -> 48.32109 | L29: =K29*F$23 -> 2943030 | M29: Computer, electronic and optical products | N29: 0.03 | O29: =N29*O$23 -> 1470872.7 | Q29: =SUM(Q24:Q28) -> 1
H30: domestic | I30: Secondary forest residues | J30: Paper and paper products | K30: ='Feedstock MIX per IVC'!G90 -> 41.012873 | L30: =K30*F$23 -> 2497917.9
H31: domestic | I31: Biowastes - Post consumer wood | J31: Sewerage services; sewage sludge; waste collection, treatment and disposal services; materials recovery services; remediation services and other waste management services | K31: ='Feedstock MIX per IVC'!G91 -> 5.6701708 | L31: =K31*F$23 -> 345345.74
I32: SUM | L32: =SUM(L34:L42) -> 1.9938961e+09 | S32: =SUM(S34:S42) -> 0.16672546
I33: TOTALS domestic | M33: TOTALS | O33: =SUM(O34:O39) -> 2.6544909e+08 | P33: TOTALS | R33: =SUM(R34:R38) -> 4.5206034e+08 | S33: CHECKED; ALL FINE
J34: Products of agriculture, hunting and related services | L34: =SUMIF($J$17:$J$31, J34, $L$17:$L$31) -> 7931411.2 | M34: Fabricated metal products | O34: =SUMIF($M$10:$M$29,M34,$O$10:$O$29) -> 18175364 | P34: Electricity, gas, steam and air conditioning | R34: =SUMIF($P$10:$P$29,P34,$R$10:$R$29) -> 1.5290405e+08 | S34: =R34/$H$8 -> 0.056392911
J35: Products of forestry, logging and related services | L35: =SUMIF($J$17:$J$31, J35, $L$17:$L$31) -> 2943030 | M35: Electrical equipment | O35: =SUMIF($M$10:$M$29,M35,$O$10:$O$29) -> 5308981.8 | P35: Chemicals and chemical products | R35: =SUMIF($P$10:$P$29,P35,$R$10:$R$29) -> 1.1301508e+08 | S35: =R35/$H$8 -> 0.041681366 | T35: =L32+O33+R33 -> 2.7114055e+09
J36: Paper and paper products | L36: =SUMIF($J$17:$J$31, J36, $L$17:$L$31) -> 2497917.9 | M36: Machinery and equipment n.e.c. | O36: =SUMIF($M$10:$M$29,M36,$O$10:$O$29) -> 1.1945209e+08 | P36: Legal and accounting services; services of head offices; management consultancy services | R36: =SUMIF($P$10:$P$29,P36,$R$10:$R$29) -> 90412068 | S36: =R36/$H$8 -> 0.033345092
J37: Food, beverages and tobacco products | L37: =SUMIF($J$17:$J$31, J37, $L$17:$L$31) -> 2.8017839e+08 | M37: Constructions and construction works | O37: =SUMIF($M$10:$M$29,M37,$O$10:$O$29) -> 37365909 | P37: Repair and installation services of machinery and equipment | R37: =SUMIF($P$10:$P$29,P37,$R$10:$R$29) -> 71796852 | S37: =R37/$H$8 -> 0.02647957
J38: Sewerage services; sewage sludge; waste collection, treatment and disposal services; materials recovery services; remediation services and other waste management services | L38: =SUMIF($J$17:$J$31, J38, $L$17:$L$31) -> 345345.74 | M38: Architectural and engineering services; technical testing and analysis services | O38: =SUMIF($M$10:$M$29,M38,$O$10:$O$29) -> 77183273 | P38: Land transport services and transport services via pipelines | R38: =SUMIF($P$10:$P$29,P38,$R$10:$R$29) -> 23932284 | S38: =R38/$H$8 -> 0.0088265233
J39: Chemicals and chemical products | L39: =SUMIF($J$17:$J$31, J39, $L$17:$L$31) -> 0 | M39: Computer, electronic and optical products | O39: =SUMIF($M$10:$M$29,M39,$O$10:$O$29) -> 7963472.7
J40: Advanced biodiesel | L40: =SUMIF($J$17:$J$31, J40, $L$17:$L$31) -> 0
I41: TOTALS imported
J42: Food, beverages and tobacco products | L42: =L10 -> 1.7e+09
A43: Advanced biogasoline
B44: =C44/1000000 -> 615.78122 | C44: =C45+C52+C59+C68 -> 6.1578122e+08 | D44: =D45+D52+D59+D68 -> 0.39452385 | F44: =F45+F52+F59+F68 -> 567056.66 | H44: =H45+H52+H59+H68 -> 7.1645505e+08 | L44: =L45+L52+L59+L68 -> 2.4350778e+08 | O44: =O45+O52+O59+O68 -> 2.6725193e+08 | R44: =R45+R52+R59+R68 -> 2.0569534e+08
A45: of which from IVC 5 | B45: 1000 | C45: =B45*F45 -> 2.5e+08 | D45: ='[2]GAP analysis Sc. 1'!$C$40 -> 0.16122098 | E45: ='[1]Conversion factors selected IV '!$O$17 -> 1.5506667 | F45: =D45*E45*1000000 -> 250000 | G45: ='LCoP 2030 MEDIUM'!E5 -> 1281.8786 | H45: =G45*F45 -> 3.2046966e+08 | I45: ='LCoP 2030 MEDIUM'!H5 -> 0.26514104 | L45: =I45*H45 -> 84969659 | M45: ='LCoP 2030 MEDIUM'!F5 -> 0.4329583 | O45: =M45*H45 -> 1.3875e+08 | P45: ='LCoP 2030 MEDIUM'!G5 -> 0.30190065 | R45: =P45*H45 -> 96750000 | S45: =R45+O45+L45 -> 3.2046966e+08
C46: =C45/$C$44 -> 0.40598834 | F46: Products of agriculture, hunting and related services | G46: =SUMIF($J$46:$J$49,F46,$L$46:$L$49)/$L$45 -> 0.79850245 | H46: domestic | I46: Straw | J46: Products of agriculture, hunting and related services | K46: ='Feedstock MIX per IVC'!G13 -> 255.92003 | L46: =K46*F$45 -> 63980008 | M46: Fabricated metal products | N46: 0 | O46: =N46*O$45 -> 0 | P46: Electricity, gas, steam and air conditioning | Q46: 0.2 | R46: =Q46*R$45 -> 19350000
F47: Paper and paper products | G47: =SUMIF($J$46:$J$49,F47,$L$46:$L$49)/$L$45 -> 0.20149755 | H47: domestic | I47: Lignocrops abandoned degraded | J47: Products of agriculture, hunting and related services | K47: ='Feedstock MIX per IVC'!G14 -> 10.633017 | L47: =K47*F$45 -> 2658254.2 | M47: Electrical equipment | N47: 0.02 | O47: =N47*O$45 -> 2775000 | P47: Chemicals and chemical products | Q47: 0.5 | R47: =Q47*R$45 -> 48375000
H48: domestic | I48: Lignocrops inter & cover cropping | J48: Products of agriculture, hunting and related services | K48: ='Feedstock MIX per IVC'!G15 -> 4.8408745 | L48: =K48*F$45 -> 1210218.6 | M48: Machinery and equipment n.e.c. | N48: 0.5 | O48: =N48*O$45 -> 69375000 | P48: Legal and accounting services; services of head offices; management consultancy services | Q48: 0.15 | R48: =Q48*R$45 -> 14512500
H49: domestic | I49: Secondary forest residues | J49: Paper and paper products | K49: ='Feedstock MIX per IVC'!G16 -> 68.484713 | L49: =K49*F$45 -> 17121178 | M49: Constructions and construction works | N49: 0.15 | O49: =N49*O$45 -> 20812500 | P49: Repair and installation services of machinery and equipment | Q49: 0.1 | R49: =Q49*R$45 -> 9675000
M50: Architectural and engineering services; technical testing and analysis services | N50: 0.3 | O50: =N50*O$45 -> 41625000 | P50: Land transport services and transport services via pipelines | Q50: 0.05 | R50: =Q50*R$45 -> 4837500
M51: Computer, electronic and optical products | N51: 0.03 | O51: =N51*O$45 -> 4162500
A52: of which 12 (road) | B52: 1000 | C52: =B52*F52 -> 2.3584906e+08 | D52: ='[2]GAP analysis Sc. 1'!$C$41 -> 0.15209526 | E52: ='[1]Conversion factors selected IV '!$O$86 -> 1.5506667 | F52: =D52*E52*1000000 -> 235849.06 | G52: ='LCoP 2030 MEDIUM'!E17 -> 1166.35 | H52: =G52*F52 -> 2.7508255e+08 | I52: ='LCoP 2030 MEDIUM'!H17 -> 0.50893814 | L52: =I52*H52 -> 1.4e+08 | M52: ='LCoP 2030 MEDIUM'!F17 -> 0.23835041 | O52: =M52*H52 -> 65566038 | P52: ='LCoP 2030 MEDIUM'!G17 -> 0.25271145 | R52: =P52*H52 -> 69516509 | S52: =R52+O52+L52 -> 2.7508255e+08
C53: =C52/$C$44 -> 0.38300787 | F53: Advanced biogas | G53: 1 | I53: Intermediate Bioenergy carriers (Syngas) | J53: Advanced biogas | K53: ='Feedstock MIX per IVC'!G80 -> 593.6 | L53: =K53*F52 -> 1.4e+08 | M53: Fabricated metal products | N53: 0 | O53: =N53*O$52 -> 0 | P53: Electricity, gas, steam and air conditioning | Q53: 0.2 | R53: =Q53*R$52 -> 13903302
M54: Electrical equipment | N54: 0.02 | O54: =N54*O$52 -> 1311320.8 | P54: Chemicals and chemical products | Q54: 0.5 | R54: =Q54*R$52 -> 34758255
M55: Machinery and equipment n.e.c. | N55: 0.5 | O55: =N55*O$52 -> 32783019 | P55: Legal and accounting services; services of head offices; management consultancy services | Q55: 0.15 | R55: =Q55*R$52 -> 10427476
M56: Constructions and construction works | N56: 0.15 | O56: =N56*O$52 -> 9834905.7 | P56: Repair and installation services of machinery and equipment | Q56: 0.1 | R56: =Q56*R$52 -> 6951650.9
M57: Architectural and engineering services; technical testing and analysis services | N57: 0.3 | O57: =N57*O$52 -> 19669811 | P57: Land transport services and transport services via pipelines | Q57: 0.05 | R57: =Q57*R$52 -> 3475825.5
M58: Computer, electronic and optical products | N58: 0.03 | O58: =N58*O$52 -> 1966981.1
A59: of which 13a (half) | B59: 1750 | C59: =B59*F59 -> 1.0658498e+08 | D59: ='[2]GAP analysis Sc. 1'!$C$42 -> 0.060905704 | E59: ='[1]Conversion factors selected IV '!$O$89 -> 1 | F59: =D59*E59*1000000 -> 60905.704 | G59: ='LCoP 2030 MEDIUM'!E19 -> 1469.6575 | H59: =G59*F59 -> 89510526 | I59: ='LCoP 2030 MEDIUM'!H19 -> 0.15524537 | L59: =I59*H59 -> 13896095 | M59: ='LCoP 2030 MEDIUM'!F19 -> 0.54774666 | O59: =M59*H59 -> 49029091 | P59: ='LCoP 2030 MEDIUM'!G19 -> 0.29700797 | R59: =P59*H59 -> 26585340 | S59: =R59+O59+L59 -> 89510526
C60: =C59/$C$44 -> 0.17308904 | F60: Products of agriculture, hunting and related services | G60: =SUMIF($J$60:$J$67,F60,$L$60:$L$67)/$L$59 -> 0.57076546 | H60: domestic | I60: Straw | J60: Products of agriculture, hunting and related services | K60: ='Feedstock MIX per IVC'!G84 -> 117.13778 | L60: =K60*F$59 -> 7134358.7 | M60: Fabricated metal products | N60: 0.15 | O60: =N60*O$59 -> 7354363.7 | P60: Electricity, gas, steam and air conditioning | Q60: 0.15 | R60: =Q60*R$59 -> 3987800.9
F61: Food, beverages and tobacco products | G61: =SUMIF($J$60:$J$67,F61,$L$60:$L$67)/$L$59 -> 0.012837447 | H61: domestic | I61: Prunings & damaged crops | J61: Products of agriculture, hunting and related services | K61: ='Feedstock MIX per IVC'!G85 -> 6.0040708 | L61: =K61*F$59 -> 365682.16 | M61: Electrical equipment | N61: 0.02 | O61: =N61*O$59 -> 980581.83 | P61: Chemicals and chemical products | Q61: 0.25 | R61: =Q61*R$59 -> 6646334.9
F62: Products of forestry, logging and related services | G62: =SUMIF($J$60:$J$67,F62,$L$60:$L$67)/$L$59 -> 0.21178827 | H62: domestic | I62: Agroprocessing residues - maize cobs | J62: Food, beverages and tobacco products | K62: ='Feedstock MIX per IVC'!G86 -> 2.9289602 | L62: =K62*F$59 -> 178390.38 | M62: Machinery and equipment n.e.c. | N62: 0.45 | O62: =N62*O$59 -> 22063091 | P62: Legal and accounting services; services of head offices; management consultancy services | Q62: 0.2 | R62: =Q62*R$59 -> 5317067.9
F63: Paper and paper products | G63: =SUMIF($J$60:$J$67,F63,$L$60:$L$67)/$L$59 -> 0.17975682 | H63: domestic | I63: Lignocrops abandoned degraded | J63: Products of agriculture, hunting and related services | K63: ='Feedstock MIX per IVC'!G87 -> 4.8668638 | L63: =K63*F$59 -> 296419.76 | M63: Constructions and construction works | N63: 0.1 | O63: =N63*O$59 -> 4902909.1 | P63: Repair and installation services of machinery and equipment | Q63: 0.3 | R63: =Q63*R$59 -> 7975601.9
F64: Sewerage services; sewage sludge; waste collection, treatment and disposal services; materials recovery services; remediation services and other waste management services | G64: =SUMIF($J$60:$J$67,F64,$L$60:$L$67)/$L$59 -> 0.024851999 | H64: domestic | I64: Lignocrops inter & cover cropping | J64: Products of agriculture, hunting and related services | K64: ='Feedstock MIX per IVC'!G88 -> 2.2157284 | L64: =K64*F$59 -> 134950.5 | M64: Architectural and engineering services; technical testing and analysis services | N64: 0.25 | O64: =N64*O$59 -> 12257273 | P64: Land transport services and transport services via pipelines | Q64: 0.1 | R64: =Q64*R$59 -> 2658534
G65: =SUM(G60:G64) -> 1 | H65: domestic | I65: Primary forestry residues | J65: Products of forestry, logging and related services | K65: ='Feedstock MIX per IVC'!G89 -> 48.32109 | L65: =K65*F$59 -> 2943030 | M65: Computer, electronic and optical products | N65: 0.03 | O65: =N65*O$59 -> 1470872.7
H66: domestic | I66: Secondary forest residues | J66: Paper and paper products | K66: ='Feedstock MIX per IVC'!G90 -> 41.012873 | L66: =K66*F$59 -> 2497917.9
H67: domestic | I67: Biowastes - Post consumer wood | J67: Sewerage services; sewage sludge; waste collection, treatment and disposal services; materials recovery services; remediation services and other waste management services | K67: ='Feedstock MIX per IVC'!G91 -> 5.6701708 | L67: =K67*F$59 -> 345345.74
A68: of which 13b (road) | B68: 1150 | C68: =B68*F68 -> 23347186 | D68: ='[2]GAP analysis Sc. 1'!$C$43 -> 0.020301901 | E68: ='[1]Conversion factors selected IV '!$O$125 -> 1 | F68: =D68*E68*1000000 -> 20301.901 | G68: ='LCoP 2030 MEDIUM'!$E$21 -> 1546.2749 | H68: =G68*F68 -> 31392321 | I68: ='LCoP 2030 MEDIUM'!H$21 -> 0.14787146 | L68: =I68*H68 -> 4642028.4 | M68: ='LCoP 2030 MEDIUM'!F21 -> 0.44300013 | O68: =M68*H68 -> 13906802 | P68: ='LCoP 2030 MEDIUM'!G21 -> 0.40912841 | R68: =P68*H68 -> 12843490 | S68: =L68+O68+R68 -> 31392321
C69: =C68/$C$44 -> 0.037914742 | F69: Products of agriculture, hunting and related services | G69: =SUMIF($J$69:$J$76,F69,$L$69:$L$76)/$L$68 -> 0.56953631 | H69: domestic | I69: Straw | J69: Products of agriculture, hunting and related services | K69: ='Feedstock MIX per IVC'!G84 -> 117.13778 | L69: =K69*F$68 -> 2378119.6 | M69: Fabricated metal products | N69: 0.15 | O69: =N69*O$68 -> 2086020.3 | P69: Electricity, gas, steam and air conditioning | Q69: 0.15 | R69: =Q69*R$68 -> 1926523.5
F70: Food, beverages and tobacco products | G70: =SUMIF($J$69:$J$76,F70,$L$69:$L$76)/$L$68 -> 0.012809801 | H70: domestic | I70: Prunings & damaged crops | J70: Products of agriculture, hunting and related services | K70: ='Feedstock MIX per IVC'!G85 -> 6.0040708 | L70: =K70*F$68 -> 121894.05 | M70: Electrical equipment | N70: 0.02 | O70: =N70*O$68 -> 278136.05 | P70: Chemicals and chemical products | Q70: 0.25 | R70: =Q70*R$68 -> 3210872.6
F71: Products of forestry, logging and related services | G71: =SUMIF($J$69:$J$76,F71,$L$69:$L$76)/$L$68 -> 0.21133218 | H71: domestic | I71: Agroprocessing residues - maize cobs | J71: Food, beverages and tobacco products | K71: ='Feedstock MIX per IVC'!G86 -> 2.9289602 | L71: =K71*F$68 -> 59463.461 | M71: Machinery and equipment n.e.c. | N71: 0.45 | O71: =N71*O$68 -> 6258061 | P71: Legal and accounting services; services of head offices; management consultancy services | Q71: 0.2 | R71: =Q71*R$68 -> 2568698.1
F72: Paper and paper products | G72: =SUMIF($J$69:$J$76,F72,$L$69:$L$76)/$L$68 -> 0.17936971 | H72: domestic | I72: Lignocrops abandoned degraded | J72: Products of agriculture, hunting and related services | K72: ='Feedstock MIX per IVC'!G87 -> 4.8668638 | L72: =K72*F$68 -> 98806.587 | M72: Constructions and construction works | N72: 0.1 | O72: =N72*O$68 -> 1390680.2 | P72: Repair and installation services of machinery and equipment | Q72: 0.3 | R72: =Q72*R$68 -> 3853047.1
F73: Sewerage services; sewage sludge; waste collection, treatment and disposal services; materials recovery services; remediation services and other waste management services | G73: =SUMIF($J$69:$J$76,F73,$L$69:$L$76)/$L$68 -> 0.02479848 | H73: domestic | I73: Lignocrops inter & cover cropping | J73: Products of agriculture, hunting and related services | K73: ='Feedstock MIX per IVC'!G88 -> 2.2157284 | L73: =K73*F$68 -> 44983.499 | M73: Architectural and engineering services; technical testing and analysis services | N73: 0.25 | O73: =N73*O$68 -> 3476700.6 | P73: Land transport services and transport services via pipelines | Q73: 0.1 | R73: =Q73*R$68 -> 1284349
G74: =SUM(G69:G73) -> 0.99784648 | H74: domestic | I74: Primary forestry residues | J74: Products of forestry, logging and related services | K74: ='Feedstock MIX per IVC'!G89 -> 48.32109 | L74: =K74*F$68 -> 981010 | M74: Computer, electronic and optical products | N74: 0.03 | O74: =N74*O$68 -> 417204.07
H75: domestic | I75: Secondary forest residues | J75: Paper and paper products | K75: ='Feedstock MIX per IVC'!G90 -> 41.012873 | L75: =K75*F$68 -> 832639.3
H76: domestic | I76: Biowastes - Post consumer wood | J76: Sewerage services; sewage sludge; waste collection, treatment and disposal services; materials recovery services; remediation services and other waste management services | K76: ='Feedstock MIX per IVC'!G91 -> 5.6701708 | L76: =K76*F$68 -> 115115.25
I78: TOTALS domestic | L78: =SUM(L79:L84) -> 2.4349779e+08 | M78: TOTALS | O78: =SUM(O79:O84) -> 2.6725193e+08 | P78: TOTALS | R78: =SUM(R79:R83) -> 2.0569534e+08 | S78: =SUM(S79:S83) -> 0.28710153 | U78: ALLL CHECKED AND FINE
J79: Products of agriculture, hunting and related services | L79: =SUMIF($J$46:$J$76, J79, $L$46:$L$76) -> 78423696 | M79: Fabricated metal products | O79: =SUMIF($M$46:$M$74, M79, $O$46:$O$74) -> 9440384.1 | P79: Electricity, gas, steam and air conditioning | R79: =SUMIF($P$46:$P$73, P79, $R$46:$R$73) -> 39167626 | S79: =R79/$H$44 -> 0.054668644
J80: Products of forestry, logging and related services | L80: =SUMIF($J$46:$J$76, J80, $L$46:$L$76) -> 3924040 | M80: Electrical equipment | O80: =SUMIF($M$46:$M$74, M80, $O$46:$O$74) -> 5345038.6 | P80: Chemicals and chemical products | R80: =SUMIF($P$46:$P$73, P80, $R$46:$R$73) -> 92990462 | S80: =R80/$H$44 -> 0.12979246
J81: Paper and paper products | L81: =SUMIF($J$46:$J$76, J81, $L$46:$L$76) -> 20451735 | M81: Machinery and equipment n.e.c. | O81: =SUMIF($M$46:$M$74, M81, $O$46:$O$74) -> 1.3047917e+08 | P81: Legal and accounting services; services of head offices; management consultancy services | R81: =SUMIF($P$46:$P$73, P81, $R$46:$R$73) -> 32825742 | S81: =R81/$H$44 -> 0.04581689
J82: Food, beverages and tobacco products | L82: =SUMIF($J$46:$J$76, J82, $L$46:$L$76) -> 237853.84 | M82: Constructions and construction works | O82: =SUMIF($M$46:$M$74, M82, $O$46:$O$74) -> 36940995 | P82: Repair and installation services of machinery and equipment | R82: =SUMIF($P$46:$P$73, P82, $R$46:$R$73) -> 28455300 | S82: =R82/$H$44 -> 0.039716797
J83: Sewerage services; sewage sludge; waste collection, treatment and disposal services; materials recovery services; remediation services and other waste management services | L83: =SUMIF($J$46:$J$76, J83, $L$46:$L$76) -> 460460.99 | M83: Architectural and engineering services; technical testing and analysis services | O83: =SUMIF($M$46:$M$74, M83, $O$46:$O$74) -> 77028785 | P83: Land transport services and transport services via pipelines | R83: =SUMIF($P$46:$P$73, P83, $R$46:$R$73) -> 12256208 | S83: =R83/$H$44 -> 0.017106737
J84: Advanced biogas | L84: =SUMIF($J$46:$J$76, J84, $L$46:$L$76) -> 1.4e+08 | M84: Computer, electronic and optical products | O84: =SUMIF($M$46:$M$74, M84, $O$46:$O$74) -> 8017557.9
A85: Advanced biogas
B86: =C86/1000000 -> 1993.2809 | C86: =C87+C97 -> 1.9932809e+09 | D86: =D87+D97 -> 1.8685013 | F86: =F87 -> 1438357.6
A87: IVC 7 | B87: 1275 | C87: =B87*F87 -> 1.8339059e+09 | D87: ='[2]GAP analysis Sc. 1'!$D$45+'[2]GAP analysis Sc. 1'!$D$57+'[2]GAP analysis Sc. 1'!$E$55 -> 1.7191032 | E87: ='[1]Conversion factors selected IV '!$O$29 -> 0.83669065 | F87: =D87*E87*1000000 -> 1438357.6 | G87: ='LCoP 2030 MEDIUM'!E9 -> 917.57099 | H87: =G87*F87 -> 1.3197952e+09 | I87: ='LCoP 2030 MEDIUM'!H9 -> -0.01940341 | L87: =I87*H87 -> -25608527 | M87: ='LCoP 2030 MEDIUM'!F9 -> 0.65934953 | O87: =M87*H87 -> 8.7020633e+08 | P87: ='LCoP 2030 MEDIUM'!G9 -> 0.36005388 | R87: =P87*H87 -> 4.7519738e+08 | S87: =L87+O87+R87 -> 1.3197952e+09
C88: =C87/C86 -> 0.92004388 | G88: Food, beverages and tobacco products | H88: =SUMIF($J$88:$J$96,G88,$L$88:$L$96)/$L$87 -> -0.22009679 | I88: Prunings & damaged crops (olive stones excluded) | J88: Products of agriculture, hunting and related services | K88: ='Feedstock MIX per IVC'!G20 -> 0.84774671 | L88: =K88*F$87 -> 1219362.9 | M88: Fabricated metal products | N88: 0.05 | O88: =N88*O$87 -> 43510317 | P88: Electricity, gas, steam and air conditioning | Q88: 0.2 | R88: =Q88*R$87 -> 95039477
G89: Products of agriculture, hunting and related services | H89: =SUMIF($J$88:$J$96,G89,$L$88:$L$96)/$L$87 -> -1.0327497 | I89: Lignocrops abandoned degraded | J89: Products of agriculture, hunting and related services | K89: ='Feedstock MIX per IVC'!G21 -> 0.6871784 | L89: =K89*F$87 -> 988408.25 | M89: Electrical equipment | N89: 0.02 | O89: =N89*O$87 -> 17404127 | P89: Chemicals and chemical products | Q89: 0.5 | R89: =Q89*R$87 -> 2.3759869e+08
G90: Sewerage services; sewage sludge; waste collection, treatment and disposal services; materials recovery services; remediation services and other waste management services | H90: =SUMIF($J$88:$J$96,G90,$L$88:$L$96)/$L$87 -> 2.3767118 | I90: Lignocrops inter & cover cropping | J90: Products of agriculture, hunting and related services | K90: ='Feedstock MIX per IVC'!G22 -> 0.31285048 | L90: =K90*F$87 -> 449990.86 | M90: Machinery and equipment n.e.c. | N90: 0.4 | O90: =N90*O$87 -> 3.4808253e+08 | P90: Legal and accounting services; services of head offices; management consultancy services | Q90: 0.15 | R90: =Q90*R$87 -> 71279608
G91: Advanced biodiesel | H91: =SUMIF($J$88:$J$96,G91,$L$88:$L$96)/$L$87 -> 0 | I91: Agroprocessing residues | J91: Food, beverages and tobacco products | K91: ='Feedstock MIX per IVC'!G23 -> 3.9186047 | L91: =K91*F$87 -> 5636354.8 | M91: Constructions and construction works | N91: 0.3 | O91: =N91*O$87 -> 2.610619e+08 | P91: Repair and installation services of machinery and equipment | Q91: 0.1 | R91: =Q91*R$87 -> 47519738
G92: Chemical and chemical products | H92: =SUMIF($J$88:$J$96,G92,$L$88:$L$96)/$L$87 -> -0.12386536 | I92: Straw | J92: Products of agriculture, hunting and related services | K92: ='Feedstock MIX per IVC'!G24 -> 16.539306 | L92: =K92*F$87 -> 23789436 | M92: Architectural and engineering services; technical testing and analysis services | N92: 0.2 | O92: =N92*O$87 -> 1.7404127e+08 | P92: Land transport services and transport services via pipelines | Q92: 0.05 | R92: =Q92*R$87 -> 23759869
H93: =SUM(H88:H92) -> 1 | I93: Manure | J93: Products of agriculture, hunting and related services | K93: ='Feedstock MIX per IVC'!G25 -> 0 | L93: =K93*F$87 -> 0 | M93: Computer, electronic and optical products | N93: 0.03 | O93: =N93*O$87 -> 26106190
I94: Sewage sludge | J94: Sewerage services; sewage sludge; waste collection, treatment and disposal services; materials recovery services; remediation services and other waste management services | K94: ='Feedstock MIX per IVC'!G26 -> 0 | L94: =K94*F$87 -> 0 | N94: =SUM(N88:N93) -> 1 | O94: =SUM(O88:O93) -> 8.7020633e+08
I95: Biowastes (post consumer woods excluded) | J95: Sewerage services; sewage sludge; waste collection, treatment and disposal services; materials recovery services; remediation services and other waste management services | K95: ='Feedstock MIX per IVC'!G27 -> -42.314992 | L95: =K95*F$87 -> -60864090
I96: Intermediate Bioenergy carrier (crude glycerine) | J96: Chemical and chemical products | K96: ='Feedstock MIX per IVC'!G28 -> 2.2052996 | L96: =K96*F$87 -> 3172009.4
A97: IVC 9a | B97: 1275 | C97: =B97*F97 -> 1.59375e+08 | D97: ='[2]GAP analysis Sc. 1'!$K$13 -> 0.14939811 | E97: ='[1]Conversion factors selected IV '!$O$52 -> 0.83669065 | F97: =D97*E97*1000000 -> 125000 | G97: ='LCoP 2030 MEDIUM'!E13 -> 1303.9013 | H97: =G97*F97 -> 1.6298766e+08 | I97: ='LCoP 2030 MEDIUM'!H13 -> 0.17938575 | L97: =I97*H97 -> 29237665 | M97: ='LCoP 2030 MEDIUM'!F13 -> 0.61354336 | O97: =M97*H97 -> 1e+08 | P97: ='LCoP 2030 MEDIUM'!G13 -> 0.20707089 | R97: 2.9932641e+08
C98: =C97/C86 -> 0.079956116 | G98: Sewerage services; sewage sludge; waste collection, treatment and disposal services; materials recovery services; remediation services and other waste management services | H98: =(SUMIF($J$98:$J$107,G98,$L$98:$L$107)/$L$97) -> 0.026151275 | I98: Straw | J98: Products of agriculture, hunting and related services | K98: ='Feedstock MIX per IVC'!G45 -> 117.54872 | L98: =K98*$F$97 -> 14693590 | M98: Fabricated metal products | N98: 0 | O98: =N98*O$101 -> 0 | P98: Electricity, gas, steam and air conditioning | Q98: 0.25 | R98: =Q98*R$101 -> 0
C99: (all as feedstock for IVC 12) | G99: Food, beverages and tobacco products | H99: =(SUMIF($J$98:$J$107,G99,$L$98:$L$107)/$L$97) -> 0.012566135 | I99: Prunings & damaged crops | J99: Products of agriculture, hunting and related services | K99: ='Feedstock MIX per IVC'!G46 -> 6.0251342 | L99: =K99*$F$97 -> 753141.78 | M99: Electrical equipment | N99: 0.02 | O99: =N99*O$101 -> 0 | P99: Chemicals and chemical products | Q99: 0.15 | R99: =Q99*R$101 -> 0
G100: Products of agriculture, hunting and related services | H100: =(SUMIF($J$98:$J$107,G100,$L$98:$L$107)/$L$97) -> 0.55870268 | I100: Sewage sludge | J100: Sewerage services; sewage sludge; waste collection, treatment and disposal services; materials recovery services; remediation services and other waste management services | K100: ='Feedstock MIX per IVC'!G47 -> 0 | L100: =K100*$F$97 -> 0 | M100: Machinery and equipment n.e.c. | N100: 0.55 | O100: =N100*O$101 -> 0 | P100: Legal and accounting services; services of head offices; management consultancy services | Q100: 0.3 | R100: =Q100*R$101 -> 0
G101: Products of forestry, logging and related services | H101: =(SUMIF($J$98:$J$107,G101,$L$98:$L$107)/$L$97) -> 0.1932743 | I101: Agroprocessing residues - maize cobs | J101: Food, beverages and tobacco products | K101: ='Feedstock MIX per IVC'!G48 -> 2.9392356 | L101: =K101*$F$97 -> 367404.45 | M101: Constructions and construction works | N101: 0.1 | O101: =N101*O$101 -> 0 | P101: Repair and installation services of machinery and equipment | Q101: 0.3 | R101: =Q101*R$101 -> 0
...

Sheet Tabelle1
B1: Exiobase mapping
A2: Feedstock
A3: IVC 1 FAME
A4: Imported POME
A5: IVC 2 HVO
A6: Tall oil
A7: FPBO, biocrude
A8: IVC 2 HEFA | G8: Eindeutige Kategorien
A9: Oil crops abandoned | D9: Eindeutige Kategorien | E9: Eurostat sector | G9: Advanced biogasoline | H9: CPA_C20
A10: Tall oil | D10: {=_xlfn._xlws.SORT(_xlfn.UNIQUE(_xlfn._xlws.FILTER(A2:A119,(A2:A119<>"")*(UPPER(LEFT(TRIM(A2:A119),3))<>"IVC"))))} -> Agroprocessing residues | E10: Food, beverages and tobacco products | G10: {=_xlfn._xlws.SORT(_xlfn.UNIQUE(_xlfn._xlws.FILTER(E10:E35,E10:E35<>"")))} -> Advanced biodiesel | H10: CPA_C20
A11: FPBO, biocrude | D11: Agroprocessing residues - maize cobs | E11: Food, beverages and tobacco products | G11: Advanced biogas | H11: CPA_C20_Advanced_biogas
A12: IVC 5 Advanced Ethanol | D12: Biowastes - Post consumer wood | E12: Sewerage services; sewage sludge; waste collection, treatment and disposal services; materials recovery services; remediation services and other waste management services | G12: Advanced bio-HFO | H12: CPA_C20_advanced_bio_HFO
A13: Straw | D13: Biowastes (post consumer woods excluded) | E13: Sewerage services; sewage sludge; waste collection, treatment and disposal services; materials recovery services; remediation services and other waste management services | G13: Chemicals and chemical products | H13: CPA_C20_others
A14: Lignocrops abandoned degraded | D14: e-biofuel feedstocks (biogenic CO2 and hydrogen from electrolysis) | E14: Chemicals and chemical products | G14: Food, beverages and tobacco products | H14: CPA_C10-12
A15: Lignocrops inter & cover cropping | D15: Feedstock | G15: Paper and paper products | H15: CPA_C17
A16: Secondary forest residues | D16: FPBO, biocrude | E16: Chemicals and chemical products | G16: Products of agriculture, hunting and related services | H16: CPA_A01
A17: IVC 6 | D17: HEFA (with imported POME ) | E17: Advanced biodiesel | G17: Products of forestry, logging and related services | H17: CPA_A02
A18: Intermediate Bioenergy carrier (ethanol, methanol) | D18: Imported POME | E18: Food, beverages and tobacco products | G18: Sewerage services; sewage sludge; waste collection, treatment and disposal services; materials recovery services; remediation services and other waste management services | H18: CPA_E37-39
A19: IVC 7 (MCR + MSW) | D19: Intermediate Bioenergy carrier (biomethane) | E19: Advanced biogas
A20: Prunings & damaged crops (olive stones excluded) | D20: Intermediate Bioenergy carrier (crude glycerine) | E20: Chemicals and chemical products
A21: Lignocrops abandoned degraded | D21: Intermediate Bioenergy carrier (ethanol, methanol) | E21: Advanced bio-HFO
A22: Lignocrops inter & cover cropping | D22: Intermediate Bioenergy carrier (FPBO with lower quality) | E22: Advanced biodiesel
A23: Agroprocessing residues | D23: Intermediate Bioenergy carriers (FPBO with lower quality ) | E23: Advanced biodiesel
A24: Straw | D24: Intermediate Bioenergy carriers (Syngas) | E24: Advanced biogas
A25: Manure | D25: Lignocrops abandoned degraded | E25: Products of agriculture, hunting and related services
A26: Sewage sludge | D26: Lignocrops inter & cover cropping | E26: Products of agriculture, hunting and related services
A27: Biowastes (post consumer woods excluded) | D27: Manure | E27: Products of agriculture, hunting and related services
A28: Intermediate Bioenergy carrier (crude glycerine) | D28: Oil crops abandoned | E28: Products of agriculture, hunting and related services
A29: IVC 8a | D29: Primary forestry residues | E29: Products of forestry, logging and related services
A30: Straw | D30: Prunings & damaged crops | E30: Products of agriculture, hunting and related services
... A35: Lignocrops inter & cover cropping | D35: Tall oil | E35: Products of agriculture, hunting and related services
A36: Primary forestry residues
A37: Secondary forest residues
A38: Biowastes - Post consumer wood
A39: Intermediate Bioenergy carrier (FPBO with lower quality) | B39: Adv biodiesel, adv biogasoline
A40: IVC 8b
A41: Intermediate Bioenergy carrier (biomethane)
A42: IVC 8c
A43: e-biofuel feedstocks (biogenic CO2 and hydrogen from electrolysis)
A44: IVC 9a
A45: Straw
A46: Prunings & damaged crops
A47: Sewage sludge
A48: Agroprocessing residues - maize cobs
A49: Lignocrops abandoned degraded
A50: Lignocrops inter & cover cropping
A51: Primary forestry residues
... A53: Biowastes - Post consumer wood
A54: Intermediate Bioenergy carriers (FPBO with lower quality ) | B54: Adv biodiesel, adv biogasoline
A55: IVC 9b
A56: e-biofuel feedstocks (biogenic CO2 and hydrogen from electrolysis)
A57: IVC 11a (road, diesel)
A58: Straw
A59: Prunings & damaged crops
A60: Sewage sludge
A61: Agroprocessing residues - maize cobs
A62: Lignocrops abandoned degraded
A63: Lignocrops inter & cover cropping
A64: Primary forestry residues
A65: Secondary forest residues
A66: Biowastes - Post consumer wood
A67: Intermediate Bioenergy carriers (FPBO with lower quality ) | B67: Adv biodiesel, adv biogasoline
A68: IVC 11a (SAF)
A69: Straw
A70: Prunings & damaged crops
A71: Sewage sludge
A72: Agroprocessing residues - maize cobs
A73: Lignocrops abandoned degraded
A74: Lignocrops inter & cover cropping
A75: Primary forestry residues
A76: Secondary forest residues
A77: Biowastes - Post consumer wood
A78: Intermediate Bioenergy carriers (FPBO with lower quality ) | B78: Adv biodiesel, adv biogasoline
A79: IVC 12 (road)
A80: Intermediate Bioenergy carriers (Syngas)
A81: IVC 12 (aviation)
A82: Intermediate Bioenergy carriers (Syngas)
A83: IVC13a (road)
A84: Straw
A85: Prunings & damaged crops
A86: Agroprocessing residues - maize cobs
A87: Lignocrops abandoned degraded
A88: Lignocrops inter & cover cropping
A89: Primary forestry residues
A90: Secondary forest residues
... A119: HEFA (with imported POME )

Sheet 2030 costs Sc 2
A1: Contribution of each IVC to final product in Scenario (2) 2030
A2: Assumptions:
A3: technical capacity = tcp | E3: feedstock availability: 2030 high
C4: =C6+C201+C226 -> 5.5490742e+10
B5: Market value | C5: Makret value of overall amount produced | D5: produced in Mtoe | E5: Conversion factor [t/toe] | F5: produced in t | G5: Cost of production [€/t] | H5: Money spent on each IVC | I5: Feedstock share of costs | J5: Eurostat sector | K5: money [€] spent on each feedtsock when producing 1t of product | L5: Absolute feedstock costs [€] | M5: CAPEX share of costs | N5: CAPEX distribution | O5: Absoluet CAPEX [€] | P5: OPEX share of costs | R5: Absolute OPEX [€] | S5: TOTAL production costs
A6: Sum ALL advanced | C6: =C8+C48+C90+C123+C162 -> 3.7743028e+10 | D6: =D8+D48+D90+D123+D162 -> 24.505634
A7: Advanced biodiesel
A8: TOTAL | B8: =C8/1000000 -> 10212.747 | C8: =C28+C9+C16 -> 1.0212747e+10 | D8: =D28+D9+D16 -> 6.0684375 | F8: =F28+F9+F16 -> 5835855.7 | H8: =H28+H9+H16 -> 1.3293409e+10 | L8: =L28+L9+L16 -> 1.8473113e+09 | O8: =O9+O16+O28 -> 7.6210115e+09 | R8: =R9+R16+R28 -> 3.8250862e+09
A9: of which IVC 2 HVO | B9: 1750 | C9: =B9*F9 -> 0 | D9: ='[2]GAP analysis Sc. 2'!$C$38 -> 0 | E9: ='[1]Conversion factors selected IV '!$O$7 -> 0.95154545 | F9: =D9*E9*1000000 -> 0 | G9: ='LCoP 2030 HIGH'!E3 -> 2245.1729 | H9: =G9*F9 -> 0 | I9: ='LCoP 2030 HIGH'!H3 -> 0.74489715 | L9: =I9*H9 -> 0 | M9: ='LCoP 2030 HIGH'!F3 -> 0.1198126 | O9: =M9*H9 -> 0 | P9: ='LCoP 2030 HIGH'!G3 -> 0.13529025 | R9: =P9*H9 -> 0 | S9: =L9+O9+R9 -> 0
C10: =C9/C8 -> 0 | F10: Products of agriculture, hunting and related services | G10: =(SUMIF($J$10:$J$12,F10,$L$10:$L$12)/$L$9) -> #DIV/0! | I10: Tall oil | J10: Products of agriculture, hunting and related services | K10: ='Feedstock MIX per IVC'!J6 -> 179.86731 | L10: =K10*F$9 -> 0 | M10: Fabricated metal products | N10: 0.05 | O10: =N10*O$9 -> 0 | P10: Electricity, gas, steam and air conditioning | Q10: 0.35 | R10: =Q10*R$9 -> 0
F11: Advanced biodiesel | G11: =(SUMIF($J$10:$J$12,F11,$L$10:$L$12)/$L$9)/2 -> #DIV/0! | I11: FPBO (Intermediate bioenergy carrier) | J11: Advanced biodiesel | K11: ='Feedstock MIX per IVC'!J7*0.85 -> 1268.6722 | L11: =K11*F$9 -> 0 | M11: Electrical equipment | N11: 0.02 | O11: =N11*O$9 -> 0 | P11: Chemicals and chemical products | Q11: 0.25 | R11: =Q11*R$9 -> 0
F12: Chemicals and chemical products | G12: =(SUMIF($J$10:$J$12,F12,$L$10:$L$12)/$L$9) -> #DIV/0! | I12: biocrude (Intermediate Bioenergy carrier) | J12: Chemicals and chemical products | K12: ='Feedstock MIX per IVC'!J7*0.15 -> 223.88333 | L12: =K12*F$9 -> 0 | M12: Machinery and equipment n.e.c. | N12: 0.45 | O12: =N12*O$9 -> 0 | P12: Legal and accounting services; services of head offices; management consultancy services | Q12: 0.2 | R12: =Q12*R$9 -> 0
F13: Advanced biogasoline | G13: =G11 -> #DIV/0! | M13: Constructions and construction works | N13: 0.15 | O13: =N13*O$9 -> 0 | P13: Repair and installation services of machinery and equipment | Q13: 0.15 | R13: =Q13*R$9 -> 0
G14: =SUM(G10:G13) -> #DIV/0! | M14: Architectural and engineering services; technical testing and analysis services | N14: 0.3 | O14: =N14*O$9 -> 0 | P14: Land transport services and transport services via pipelines | Q14: 0.05 | R14: =Q14*R$9 -> 0
I15: Sum | L15: =SUM(L10:L12) -> 0 | M15: Computer, electronic and optical products | N15: 0.03 | O15: =N15*O$9 -> 0
A16: of which IVC 11a (road) | B16: 1750 | C16: =B16*F16 -> 7.9929818e+09 | D16: ='[2]GAP analysis Sc. 2'!$C$39 -> 4.8 | E16: ='[1]Conversion factors selected IV '!$O$64 -> 0.95154545 | F16: =D16*E16*1000000 -> 4567418.2 | G16: ='LCoP 2030 HIGH'!E15 -> 2502.2771 | H16: =G16*F16 -> 1.1428946e+10 | I16: ='LCoP 2030 HIGH'!H15 -> 0.13628669 | L16: =I16*H16 -> 1.5576132e+09 | M16: ='LCoP 2030 HIGH'!F15 -> 0.57747402 | O16: =M16*H16 -> 6.5999193e+09 | P16: ='LCoP 2030 HIGH'!G15 -> 0.28623929 | R16: =P16*H16 -> 3.2714133e+09 | S16: =L16+O16+R16 -> 1.1428946e+10
C17: =C16/C8 -> 0.78264756 | F17: Products of agriculture, hunting and related services | G17: =(SUMIF($J$17:$J$26,F17,$L$17:$L$26)/$L$16) -> 0.59771745 | I17: Straw | J17: Products of agriculture, hunting and related services | K17: ='Feedstock MIX per IVC'!J58 -> 181.54132 | L17: =K17*F$16 -> 8.2917513e+08 | M17: Fabricated metal products | N17: 0 | O17: =N17*O$16 -> 0 | P17: Electricity, gas, steam and air conditioning | Q17: 0.25 | R17: =Q17*R$16 -> 8.1785332e+08
F18: Products of forestry, logging and related services | G18: =(SUMIF($J$17:$J$26,F18,$L$17:$L$26)/$L$16) -> 0.12919991 | I18: Prunings & damaged crops | J18: Products of agriculture, hunting and related services | K18: ='Feedstock MIX per IVC'!J59 -> 8.4731123 | L18: =K18*F$16 -> 38700247 | M18: Electrical equipment | N18: 0.02 | O18: =N18*O$16 -> 1.3199839e+08 | P18: Chemicals and chemical products | Q18: 0.15 | R18: =Q18*R$16 -> 4.9071199e+08
F19: Paper and paper products | G19: =(SUMIF($J$17:$J$26,F19,$L$17:$L$26)/$L$16) -> 0.14918901 | I19: Sewage sludge | J19: Sewerage services; sewage sludge; waste collection, treatment and disposal services; materials recovery services; remediation services and other waste management services | K19: ='Feedstock MIX per IVC'!J60 -> 0 | L19: =K19*F$16 -> 0 | M19: Machinery and equipment n.e.c. | N19: 0.55 | O19: =N19*O$16 -> 3.6299556e+09 | P19: Legal and accounting services; services of head offices; management consultancy services | Q19: 0.3 | R19: =Q19*R$16 -> 9.8142398e+08
F20: Food, beverages and tobacco products | G20: =(SUMIF($J$17:$J$26,F20,$L$17:$L$26)/$L$16) -> 0.012600306 | I20: Agroprocessing residues - maize cobs | J20: Food, beverages and tobacco products | K20: ='Feedstock MIX per IVC'!J61 -> 4.2970453 | L20: =K20*F$16 -> 19626403 | M20: Constructions and construction works | N20: 0.1 | O20: =N20*O$16 -> 6.5999193e+08 | P20: Repair and installation services of machinery and equipment | Q20: 0.3 | R20: =Q20*R$16 -> 9.8142398e+08
F21: Sewerage services; sewage sludge; waste collection, treatment and disposal services; materials recovery services; remediation services and other waste management services | G21: =(SUMIF($J$17:$J$26,F21,$L$17:$L$26)/$L$16) -> 0.023308789 | I21: Lignocrops abandoned degraded | J21: Products of agriculture, hunting and related services | K21: ='Feedstock MIX per IVC'!J62 -> 8.1190082 | L21: =K21*F$16 -> 37082906 | M21: Architectural and engineering services; technical testing and analysis services | N21: 0.3 | O21: =N21*O$16 -> 1.9799758e+09 | P21: Land transport services and transport services via pipelines | Q21: 0 | R21: =Q21*R$16 -> 0
F22: Advanced biodiesel | G22: =(SUMIF($J$17:$J$26,F22,$L$17:$L$26)/$L$16)/2 -> 0.043992266 | I22: Lignocrops inter & cover cropping | J22: Products of agriculture, hunting and related services | K22: ='Feedstock MIX per IVC'!J63 -> 5.7043807 | L22: =K22*F$16 -> 26054292 | M22: Computer, electronic and optical products | N22: 0.03 | O22: =N22*O$16 -> 1.9799758e+08
F23: Chemicals and chemical products | G23: =(SUMIF($J$17:$J$26,F23,$L$17:$L$26)/$L$16) -> 0 | I23: Primary forestry residues | J23: Products of forestry, logging and related services | K23: ='Feedstock MIX per IVC'!J64 -> 44.060666 | L23: =K23*F$16 -> 2.0124349e+08
F24: Advanced biogasoline | G24: =G22 -> 0.043992266 | I24: Secondary forest residues | J24: Paper and paper products | K24: ='Feedstock MIX per IVC'!J65 -> 50.877489 | L24: =K24*F$16 -> 2.3237877e+08
G25: =SUM(G17:G24) -> 1 | I25: Biowastes - Post consumer wood | J25: Sewerage services; sewage sludge; waste collection, treatment and disposal services; materials recovery services; remediation services and other waste management services | K25: ='Feedstock MIX per IVC'!J66 -> 7.9489277 | L25: =K25*F$16 -> 36306077
I26: Intermediate Bioenergy carriers (FPBO with lower quality ) | J26: Advanced biodiesel | K26: ='Feedstock MIX per IVC'!J67 -> 30.005106 | L26: =K26*F$16 -> 1.3704586e+08
I27: Sum | L27: =SUM(L17:L26) -> 1.5576132e+09
A28: of which 13a (half) | B28: 1750 | C28: =B28*F28 -> 2219765625 | D28: ='[2]GAP analysis Sc. 2'!$C$40 -> 1.2684375 | E28: ='[1]Conversion factors selected IV '!$O$89 -> 1 | F28: =D28*E28*1000000 -> 1268437.5 | G28: ='LCoP 2030 HIGH'!E19 -> 1469.8897 | H28: =G28*F28 -> 1.8644632e+09 | I28: ='LCoP 2030 HIGH'!H19 -> 0.15537881 | L28: =I28*H28 -> 2.8969808e+08 | M28: ='LCoP 2030 HIGH'!F19 -> 0.54766013 | O28: =M28*H28 -> 1.0210922e+09 | P28: ='LCoP 2030 HIGH'!G19 -> 0.29696105 | R28: =P28*H28 -> 5.5367297e+08 | S28: =L28+O28+R28 -> 1.8644632e+09
C29: =C28/C8 -> 0.21735244 | F29: Products of agriculture, hunting and related services | G29: =(SUMIF($J$29:$J$36,F29,$L$29:$L$36)/$L$28) -> 0.63900608 | I29: Straw | J29: Products of agriculture, hunting and related services | K29: ='Feedstock MIX per IVC'!J84 -> 129.97872 | L29: =K29*F$28 -> 1.6486989e+08 | M29: Fabricated metal products | N29: 0.15 | O29: =N29*O$28 -> 1.5316383e+08 | P29: Electricity, gas, steam and air conditioning | Q29: 0.15 | R29: =Q29*R$28 -> 83050945
F30: Products of forestry, logging and related services | G30: =(SUMIF($J$29:$J$36,F30,$L$29:$L$36)/$L$28) -> 0.14815699 | I30: Prunings & damaged crops | J30: Products of agriculture, hunting and related services | K30: ='Feedstock MIX per IVC'!J85 -> 6.0665214 | L30: =K30*F$28 -> 7695003.3 | M30: Electrical equipment | N30: 0.02 | O30: =N30*O$28 -> 20421844 | P30: Chemicals and chemical products | Q30: 0.25 | R30: =Q30*R$28 -> 1.3841824e+08
F31: Paper and paper products | G31: =(SUMIF($J$29:$J$36,F31,$L$29:$L$36)/$L$28) -> 0.17618586 | I31: Agroprocessing residues - maize cobs | J31: Food, beverages and tobacco products | K31: ='Feedstock MIX per IVC'!J86 -> 3.0765693 | L31: =K31*F$28 -> 3902435.9 | M31: Machinery and equipment n.e.c. | N31: 0.45 | O31: =N31*O$28 -> 4.5949148e+08 | P31: Legal and accounting services; services of head offices; management consultancy services | Q31: 0.2 | R31: =Q31*R$28 -> 1.1073459e+08
F32: Food, beverages and tobacco products | G32: =(SUMIF($J$29:$J$36,F32,$L$29:$L$36)/$L$28) -> 0.0134707 | I32: Lignocrops abandoned degraded | J32: Products of agriculture, hunting and related services | K32: ='Feedstock MIX per IVC'!J87 -> 5.8129924 | L32: =K32*F$28 -> 7373417.5 | M32: Constructions and construction works | N32: 0.1 | O32: =N32*O$28 -> 1.0210922e+08 | P32: Repair and installation services of machinery and equipment | Q32: 0.3 | R32: =Q32*R$28 -> 1.6610189e+08
F33: Sewerage services; sewage sludge; waste collection, treatment and disposal services; materials recovery services; remediation services and other waste management services | G33: =(SUMIF($J$29:$J$36,F33,$L$29:$L$36)/$L$28) -> 0.023180367 | I33: Lignocrops inter & cover cropping | J33: Products of agriculture, hunting and related services | K33: ='Feedstock MIX per IVC'!J88 -> 4.0841838 | L33: =K33*F$28 -> 5180531.9 | M33: Architectural and engineering services; technical testing and analysis services | N33: 0.25 | O33: =N33*O$28 -> 2.5527305e+08 | P33: Land transport services and transport services via pipelines | Q33: 0.1 | R33: =Q33*R$28 -> 55367297
F34: Advanced biodiesel | G34: =(SUMIF($J$29:$J$36,F34,$L$29:$L$36)/$L$28) -> 0 | I34: Primary forestry residues | J34: Products of forestry, logging and related services | K34: ='Feedstock MIX per IVC'!J89 -> 33.837534 | L34: =K34*F$28 -> 42920797 | M34: Computer, electronic and optical products | N34: 0.03 | O34: =N34*O$28 -> 30632766 | Q34: =SUM(Q29:Q33) -> 1
F35: Chemicals and chemical products | G35: =(SUMIF($J$29:$J$36,F35,$L$29:$L$36)/$L$28) -> 0 | I35: Secondary forest residues | J35: Paper and paper products | K35: ='Feedstock MIX per IVC'!J90 -> 40.239039 | L35: =K35*F$28 -> 51040706
G36: =SUM(G29:G35) -> 1 | I36: Biowastes - Post consumer wood | J36: Sewerage services; sewage sludge; waste collection, treatment and disposal services; materials recovery services; remediation services and other waste management services | K36: ='Feedstock MIX per IVC'!J91 -> 5.2941575 | L36: =K36*F$28 -> 6715307.9
I37: SUM | L37: =SUM(L29:L36) -> 2.8969808e+08
I38: TOTALS domestic | M38: TOTALS | O38: =SUM(O39:O44) -> 7.6210115e+09 | P38: TOTALS | R38: =SUM(R39:R43) -> 3.8250862e+09 | S38: =SUM(S39:S43) -> 0.28774307
J39: Products of agriculture, hunting and related services | L39: =SUMIF($J$10:$J$36,J39,$L$10:$L$36) -> 1.1161314e+09 | M39: Fabricated metal products | O39: =SUMIF($M$10:$M$36,M39,$O$10:$O$36) -> 1.5316383e+08 | P39: Electricity, gas, steam and air conditioning | R39: =SUMIF($P$10:$P$36,P39,$R$10:$R$36) -> 9.0090426e+08 | S39: =R39/$H$8 -> 0.067770748
J40: Products of forestry, logging and related services | L40: =SUMIF($J$10:$J$36,J40,$L$10:$L$36) -> 2.4416429e+08 | M40: Electrical equipment | O40: =SUMIF($M$10:$M$36,M40,$O$10:$O$36) -> 1.5242023e+08 | P40: Chemicals and chemical products | R40: =SUMIF($P$10:$P$36,P40,$R$10:$R$36) -> 6.2913023e+08 | S40: =R40/$H$8 -> 0.047326478
J41: Paper and paper products | L41: =SUMIF($J$10:$J$36,J41,$L$10:$L$36) -> 2.8341947e+08 | M41: Machinery and equipment n.e.c. | O41: =SUMIF($M$10:$M$36,M41,$O$10:$O$36) -> 4.0894471e+09 | P41: Legal and accounting services; services of head offices; management consultancy services | R41: =SUMIF($P$10:$P$36,P41,$R$10:$R$36) -> 1.0921586e+09 | S41: =R41/$H$8 -> 0.082157901
J42: Food, beverages and tobacco products | L42: =SUMIF($J$10:$J$36,J42,$L$10:$L$36) -> 23528839 | M42: Constructions and construction works | O42: =SUMIF($M$10:$M$36,M42,$O$10:$O$36) -> 7.6210115e+08 | P42: Repair and installation services of machinery and equipment | R42: =SUMIF($P$10:$P$36,P42,$R$10:$R$36) -> 1.1475259e+09 | S42: =R42/$H$8 -> 0.08632292
J43: Sewerage services; sewage sludge; waste collection, treatment and disposal services; materials recovery services; remediation services and other waste management services | L43: =SUMIF($J$10:$J$36,J43,$L$10:$L$36) -> 43021385 | M43: Architectural and engineering services; technical testing and analysis services | O43: =SUMIF($M$10:$M$36,M43,$O$10:$O$36) -> 2.2352488e+09 | P43: Land transport services and transport services via pipelines | R43: =SUMIF($P$10:$P$36,P43,$R$10:$R$36) -> 55367297 | S43: =R43/$H$8 -> 0.0041650187
J44: Advanced biodiesel | L44: =SUMIF($J$10:$J$36,J44,$L$10:$L$36) -> 1.3704586e+08 | M44: Computer, electronic and optical products | O44: =SUMIF($M$10:$M$36,M44,$O$10:$O$36) -> 2.2863034e+08
J45: Chemicals and chemical products | L45: =SUMIF($J$10:$J$36,J45,$L$10:$L$36) -> 0
I46: SUM | L46: =SUM(L39:L45) -> 1.8473113e+09
A47: Advanced biogasoline
B48: =C48/1000000 -> 10469.28 | C48: =C49+C56+C63+C72 -> 1.046928e+10 | D48: =D49+D56+D63+D72 -> 6.8069123 | F48: =F49+F56+F63+F72 -> 9391108.3 | H48: =H49+H56+H63+H72 -> 1.2088793e+10 | L48: =L49+L56+L63+L72 -> 3.8883583e+09 | O48: =O49+O56+O63+O72 -> 4.6312349e+09 | R48: =R49+R56+R63+R72 -> 3.5691995e+09
A49: of which from IVC 5 | B49: 1000 | C49: =B49*F49 -> 3.6385229e+09 | D49: ='[2]GAP analysis Sc. 2'!$C$42 -> 2.3464249 | E49: ='[1]Conversion factors selected IV '!$O$17 -> 1.5506667 | F49: =D49*E49*1000000 -> 3638522.9 | G49: ='LCoP 2030 HIGH'!E5 -> 1284.2295 | H49: =G49*F49 -> 4.6726984e+09 | I49: ='LCoP 2030 HIGH'!H5 -> 0.26648625 | L49: =I49*H49 -> 1.2452099e+09 | M49: ='LCoP 2030 HIGH'!F5 -> 0.43216575 | O49: =M49*H49 -> 2.0193802e+09 | P49: ='LCoP 2030 HIGH'!G5 -> 0.30134801 | R49: =P49*H49 -> 1.4081084e+09 | S49: =R49+O49+L49 -> 4.6726984e+09
C50: =C49/C48 -> 0.3475428 | F50: Products of agriculture, hunting and related services | G50: =SUMIF($J$50:$J$54,F50,$L$50:$L$53)/$L$49 -> 0.81975782 | H50: domestic | I50: Straw | J50: Products of agriculture, hunting and related services | K50: ='Feedstock MIX per IVC'!J13 -> 260.69481 | L50: =K50*F$49 -> 9.4854404e+08 | M50: Fabricated metal products | N50: 0 | O50: =N50*O$49 -> 0 | P50: Electricity, gas, steam and air conditioning | Q50: 0.2 | R50: =Q50*R$49 -> 2.8162167e+08
F51: Paper and paper products | G51: =SUMIF($J$50:$J$54,F51,$L$50:$L$53)/$L$49 -> 0.18024218 | H51: domestic | I51: Lignocrops abandoned degraded | J51: Products of agriculture, hunting and related services | K51: ='Feedstock MIX per IVC'!J14 -> 11.658962 | L51: =K51*F$49 -> 42421399 | M51: Electrical equipment | N51: 0.02 | O51: =N51*O$49 -> 40387604 | P51: Chemicals and chemical products | Q51: 0.5 | R51: =Q51*R$49 -> 7.0405418e+08
H52: domestic | I52: Lignocrops inter & cover cropping | J52: Products of agriculture, hunting and related services | K52: ='Feedstock MIX per IVC'!J15 -> 8.1915371 | L52: =K52*F$49 -> 29805095 | M52: Machinery and equipment n.e.c. | N52: 0.5 | O52: =N52*O$49 -> 1.0096901e+09 | P52: Legal and accounting services; services of head offices; management consultancy services | Q52: 0.15 | R52: =Q52*R$49 -> 2.1121625e+08
H53: domestic | I53: Secondary forest residues | J53: Paper and paper products | K53: ='Feedstock MIX per IVC'!J16 -> 61.68419 | L53: =K53*F$49 -> 2.2443934e+08 | M53: Constructions and construction works | N53: 0.15 | O53: =N53*O$49 -> 3.0290703e+08 | P53: Repair and installation services of machinery and equipment | Q53: 0.1 | R53: =Q53*R$49 -> 1.4081084e+08
M54: Architectural and engineering services; technical testing and analysis services | N54: 0.3 | O54: =N54*O$49 -> 6.0581406e+08 | P54: Land transport services and transport services via pipelines | Q54: 0.05 | R54: =Q54*R$49 -> 70405418
M55: Computer, electronic and optical products | N55: 0.03 | O55: =N55*O$49 -> 60581406
A56: of which 12 (road) | B56: 1000 | C56: =B56*F56 -> 3.6385229e+09 | D56: ='[2]GAP analysis Sc. 2'!$C$43 -> 2.3464249 | E56: ='[1]Conversion factors selected IV '!$O$86 -> 1.5506667 | F56: =D56*E56*1000000 -> 3638522.9 | G56: ='LCoP 2030 HIGH'!E17 -> 1166.35 | H56: =G56*F56 -> 4.2437912e+09 | I56: ='LCoP 2030 HIGH'!H17 -> 0.50893814 | L56: =I56*H56 -> 2.1598272e+09 | M56: ='LCoP 2030 HIGH'!F17 -> 0.23835041 | O56: =M56*H56 -> 1.0115094e+09 | P56: ='LCoP 2030 HIGH'!G17 -> 0.25271145 | R56: =P56*H56 -> 1.0724546e+09 | S56: =R56+O56+L56 -> 4.2437912e+09
C57: =C56/C48 -> 0.3475428 | I57: Intermediate Bioenergy carriers (Syngas) | J57: Advanced biogas | K57: ='Feedstock MIX per IVC'!J80 -> 593.6 | L57: =K57*F56 -> 2.1598272e+09 | M57: Fabricated metal products | N57: 0 | O57: =N57*O$56 -> 0 | P57: Electricity, gas, steam and air conditioning | Q57: 0.2 | R57: =Q57*R$56 -> 2.1449093e+08
M58: Electrical equipment | N58: 0.02 | O58: =N58*O$56 -> 20230187 | P58: Chemicals and chemical products | Q58: 0.5 | R58: =Q58*R$56 -> 5.3622731e+08
M59: Machinery and equipment n.e.c. | N59: 0.5 | O59: =N59*O$56 -> 5.0575468e+08 | P59: Legal and accounting services; services of head offices; management consultancy services | Q59: 0.15 | R59: =Q59*R$56 -> 1.6086819e+08
M60: Constructions and construction works | N60: 0.15 | O60: =N60*O$56 -> 1.5172641e+08 | P60: Repair and installation services of machinery and equipment | Q60: 0.1 | R60: =Q60*R$56 -> 1.0724546e+08
M61: Architectural and engineering services; technical testing and analysis services | N61: 0.3 | O61: =N61*O$56 -> 3.0345281e+08 | P61: Land transport services and transport services via pipelines | Q61: 0.05 | R61: =Q61*R$56 -> 53622731
M62: Computer, electronic and optical products | N62: 0.03 | O62: =N62*O$56 -> 30345281
A63: of which 13a (half) | B63: 1750 | C63: =B63*F63 -> 2219765625 | D63: ='[2]GAP analysis Sc. 2'!$C$44 -> 1.2684375 | E63: ='[1]Conversion factors selected IV '!$O$89 -> 1 | F63: =D63*E63*1000000 -> 1268437.5 | G63: ='LCoP 2030 HIGH'!E19 -> 1469.8897 | H63: =G63*F63 -> 1.8644632e+09 | I63: ='LCoP 2030 HIGH'!H19 -> 0.15537881 | L63: =I63*H63 -> 2.8969808e+08 | M63: ='LCoP 2030 HIGH'!F19 -> 0.54766013 | O63: =M63*H63 -> 1.0210922e+09 | P63: ='LCoP 2030 HIGH'!G19 -> 0.29696105 | R63: =P63*H63 -> 5.5367297e+08 | S63: =L63+O63+R63 -> 1.8644632e+09
C64: =C63/C48 -> 0.21202658 | F64: Food, beverages and tobacco products | G64: =SUMIF($J$64:$J$71,F64,$L$64:$L$71)/$L$63 -> 0.0134707 | H64: domestic | I64: Straw | J64: Products of agriculture, hunting and related services | K64: ='Feedstock MIX per IVC'!J84 -> 129.97872 | L64: =K64*F$63 -> 1.6486989e+08 | M64: Fabricated metal products | N64: 0.15 | O64: =N64*O$63 -> 1.5316383e+08 | P64: Electricity, gas, steam and air conditioning | Q64: 0.15 | R64: =Q64*R$63 -> 83050945
F65: Products of agriculture, hunting and related services | G65: =SUMIF($J$64:$J$71,F65,$L$64:$L$71)/$L$63 -> 0.63900608 | H65: domestic | I65: Prunings & damaged crops | J65: Products of agriculture, hunting and related services | K65: ='Feedstock MIX per IVC'!J85 -> 6.0665214 | L65: =K65*F$63 -> 7695003.3 | M65: Electrical equipment | N65: 0.02 | O65: =N65*O$63 -> 20421844 | P65: Chemicals and chemical products | Q65: 0.25 | R65: =Q65*R$63 -> 1.3841824e+08
F66: Products of forestry, logging and related services | G66: =SUMIF($J$64:$J$71,F66,$L$64:$L$71)/$L$63 -> 0.14815699 | H66: domestic | I66: Agroprocessing residues - maize cobs | J66: Food, beverages and tobacco products | K66: ='Feedstock MIX per IVC'!J86 -> 3.0765693 | L66: =K66*F$63 -> 3902435.9 | M66: Machinery and equipment n.e.c. | N66: 0.45 | O66: =N66*O$63 -> 4.5949148e+08 | P66: Legal and accounting services; services of head offices; management consultancy services | Q66: 0.2 | R66: =Q66*R$63 -> 1.1073459e+08
F67: Paper and paper products | G67: =SUMIF($J$64:$J$71,F67,$L$64:$L$71)/$L$63 -> 0.17618586 | H67: domestic | I67: Lignocrops abandoned degraded | J67: Products of agriculture, hunting and related services | K67: ='Feedstock MIX per IVC'!J87 -> 5.8129924 | L67: =K67*F$63 -> 7373417.5 | M67: Constructions and construction works | N67: 0.1 | O67: =N67*O$63 -> 1.0210922e+08 | P67: Repair and installation services of machinery and equipment | Q67: 0.3 | R67: =Q67*R$63 -> 1.6610189e+08
F68: Sewerage services; sewage sludge; waste collection, treatment and disposal services; materials recovery services; remediation services and other waste management services | G68: =SUMIF($J$64:$J$71,F68,$L$64:$L$71)/$L$63 -> 0.023180367 | H68: domestic | I68: Lignocrops inter & cover cropping | J68: Products of agriculture, hunting and related services | K68: ='Feedstock MIX per IVC'!J88 -> 4.0841838 | L68: =K68*F$63 -> 5180531.9 | M68: Architectural and engineering services; technical testing and analysis services | N68: 0.25 | O68: =N68*O$63 -> 2.5527305e+08 | P68: Land transport services and transport services via pipelines | Q68: 0.1 | R68: =Q68*R$63 -> 55367297
G69: =SUM(G64:G68) -> 1 | H69: domestic | I69: Primary forestry residues | J69: Products of forestry, logging and related services | K69: ='Feedstock MIX per IVC'!J89 -> 33.837534 | L69: =K69*F$63 -> 42920797 | M69: Computer, electronic and optical products | N69: 0.03 | O69: =N69*O$63 -> 30632766
H70: domestic | I70: Secondary forest residues | J70: Paper and paper products | K70: ='Feedstock MIX per IVC'!J90 -> 40.239039 | L70: =K70*F$63 -> 51040706
H71: domestic | I71: Biowastes - Post consumer wood | J71: Sewerage services; sewage sludge; waste collection, treatment and disposal services; materials recovery services; remediation services and other waste management services | K71: ='Feedstock MIX per IVC'!J91 -> 5.2941575 | L71: =K71*F$63 -> 6715307.9
A72: of which 13b (road) | B72: 1150 | C72: =B72*F72 -> 9.7246875e+08 | D72: ='[2]GAP analysis Sc. 2'!$C$45 -> 0.845625 | E72: ='[1]Conversion factors selected IV '!$O$125 -> 1 | F72: =D72*E72*1000000 -> 845625 | G72: ='LCoP 2030 HIGH'!E21 -> 1546.5955 | H72: =G72*F72 -> 1.3078398e+09 | I72: ='LCoP 2030 HIGH'!H21 -> 0.14804809 | L72: =I72*H72 -> 1.9362319e+08 | M72: ='LCoP 2030 HIGH'!F21 -> 0.44290831 | O72: =M72*H72 -> 579253125 | P72: ='LCoP 2030 HIGH'!G21 -> 0.4090436 | R72: =P72*H72 -> 5.3496352e+08 | S72: =L72+O72+R72 -> 1.3078398e+09
C73: =C72/C48 -> 0.092887833 | F73: Food, beverages and tobacco products | G73: =SUMIF($J$73:$J$80,F73,$L$73:$L$80)/$L$72 -> 0.013136352 | H73: domestic | I73: Straw | J73: Products of agriculture, hunting and related services | K73: ='Feedstock MIX per IVC'!J102 -> 127.07494 | L73: =K73*F$72 -> 1.0745775e+08 | M73: Fabricated metal products | N73: 0.15 | O73: =N73*O$72 -> 86887969 | P73: Electricity, gas, steam and air conditioning | Q73: 0.15 | R73: =Q73*R$72 -> 80244527
F74: Products of agriculture, hunting and related services | G74: =SUMIF($J$73:$J$80,F74,$L$73:$L$80)/$L$72 -> 0.64796608 | H74: domestic | I74: Prunings & damaged crops | J74: Products of agriculture, hunting and related services | K74: ='Feedstock MIX per IVC'!J103 -> 5.9309927 | L74: =K74*F$72 -> 5015395.7 | M74: Electrical equipment | N74: 0.02 | O74: =N74*O$72 -> 11585062 | P74: Chemicals and chemical products | Q74: 0.25 | R74: =Q74*R$72 -> 1.3374088e+08
F75: Products of forestry, logging and related services | G75: =SUMIF($J$73:$J$80,F75,$L$73:$L$80)/$L$72 -> 0.14447968 | H75: domestic | I75: Agroprocessing residues - maize cobs | J75: Food, beverages and tobacco products | K75: ='Feedstock MIX per IVC'!J104 -> 3.0078374 | L75: =K75*F$72 -> 2543502.5 | M75: Machinery and equipment n.e.c. | N75: 0.45 | O75: =N75*O$72 -> 2.6066391e+08 | P75: Legal and accounting services; services of head offices; management consultancy services | Q75: 0.2 | R75: =Q75*R$72 -> 1.069927e+08
F76: Paper and paper products | G76: =SUMIF($J$73:$J$80,F76,$L$73:$L$80)/$L$72 -> 0.17181286 | H76: domestic | I76: Lignocrops abandoned degraded | J76: Products of agriculture, hunting and related services | K76: ='Feedstock MIX per IVC'!J105 -> 11.366255 | L76: =K76*F$72 -> 9611589.5 | M76: Constructions and construction works | N76: 0.1 | O76: =N76*O$72 -> 57925312 | P76: Repair and installation services of machinery and equipment | Q76: 0.3 | R76: =Q76*R$72 -> 1.6048905e+08
F77: Sewerage services; sewage sludge; waste collection, treatment and disposal services; materials recovery services; remediation services and other waste management services | G77: =SUMIF($J$73:$J$80,F77,$L$73:$L$80)/$L$72 -> 0.022605022 | H77: domestic | I77: Lignocrops inter & cover cropping | J77: Products of agriculture, hunting and related services | K77: ='Feedstock MIX per IVC'!J106 -> 3.9929413 | L77: =K77*F$72 -> 3376531 | M77: Architectural and engineering services; technical testing and analysis services | N77: 0.25 | O77: =N77*O$72 -> 1.4481328e+08 | P77: Land transport services and transport services via pipelines | Q77: 0.1 | R77: =Q77*R$72 -> 53496352
G78: =SUM(G73:G77) -> 1 | H78: domestic | I78: Primary forestry residues | J78: Products of forestry, logging and related services | K78: ='Feedstock MIX per IVC'!J107 -> 33.081588 | L78: =K78*F$72 -> 27974618 | M78: Computer, electronic and optical products | N78: 0.03 | O78: =N78*O$72 -> 17377594
H79: domestic | I79: Secondary forest residues | J79: Paper and paper products | K79: ='Feedstock MIX per IVC'!J108 -> 39.340081 | L79: =K79*F$72 -> 33266956
H80: domestic | I80: Biowastes - Post consumer wood | J80: Sewerage services; sewage sludge; waste collection, treatment and disposal services; materials recovery services; remediation services and other waste management services | K80: ='Feedstock MIX per IVC'!J109 -> 5.1758836 | L80: =K80*F$72 -> 4376856.6
I82: TOTALS domestic | L82: =SUM(L83:L88) -> 3.8883583e+09 | M82: TOTALS | O82: =SUM(O83:O88) -> 4.6312349e+09 | P82: TOTALS | R82: =SUM(R83:R87) -> 3.5691995e+09 | S82: =SUM(S83:S87) -> 0.29524863
J83: Products of agriculture, hunting and related services | L83: =SUMIF($J$50:$J$80, J83, $L$50:$L$80) -> 1.3313506e+09 | M83: Fabricated metal products | O83: =SUMIF($M$50:$M$78, M83, $O$50:$O$78) -> 2.400518e+08 | P83: Electricity, gas, steam and air conditioning | R83: =SUMIF($P$50:$P$77, P83, $R$50:$R$77) -> 6.5940807e+08 | S83: =R83/$H$48 -> 0.054547057
J84: Products of forestry, logging and related services | L84: =SUMIF($J$50:$J$80, J84, $L$50:$L$80) -> 70895414 | M84: Electrical equipment | O84: =SUMIF($M$50:$M$78, M84, $O$50:$O$78) -> 92624698 | P84: Chemicals and chemical products | R84: =SUMIF($P$50:$P$77, P84, $R$50:$R$77) -> 1.5124406e+09 | S84: =R84/$H$48 -> 0.12511097
J85: Paper and paper products | L85: =SUMIF($J$50:$J$80, J85, $L$50:$L$80) -> 3.08747e+08 | M85: Machinery and equipment n.e.c. | O85: =SUMIF($M$50:$M$78, M85, $O$50:$O$78) -> 2.2356002e+09 | P85: Legal and accounting services; services of head offices; management consultancy services | R85: =SUMIF($P$50:$P$77, P85, $R$50:$R$77) -> 5.8981175e+08 | S85: =R85/$H$48 -> 0.048789963
J86: Food, beverages and tobacco products | L86: =SUMIF($J$50:$J$80, J86, $L$50:$L$80) -> 6445938.4 | M86: Constructions and construction works | O86: =SUMIF($M$50:$M$78, M86, $O$50:$O$78) -> 6.1466797e+08 | P86: Repair and installation services of machinery and equipment | R86: =SUMIF($P$50:$P$77, P86, $R$50:$R$77) -> 5.7464724e+08 | S86: =R86/$H$48 -> 0.047535536
J87: Sewerage services; sewage sludge; waste collection, treatment and disposal services; materials recovery services; remediation services and other waste management services | L87: =SUMIF($J$50:$J$80, J87, $L$50:$L$80) -> 11092164 | M87: Architectural and engineering services; technical testing and analysis services | O87: =SUMIF($M$50:$M$78, M87, $O$50:$O$78) -> 1.3093532e+09 | P87: Land transport services and transport services via pipelines | R87: =SUMIF($P$50:$P$77, P87, $R$50:$R$77) -> 2.328918e+08 | S87: =R87/$H$48 -> 0.0192651
J88: Advanced biogas | L88: =SUMIF($J$50:$J$80, J88, $L$50:$L$80) -> 2.1598272e+09 | M88: Computer, electronic and optical products | O88: =SUMIF($M$50:$M$78, M88, $O$50:$O$78) -> 1.3893705e+08
A89: Advanced biogas
B90: =C90/1000000 -> 5897.7629 | C90: =C91+C101 -> 5.8977629e+09 | D90: =D91+D101 -> 5.5285623 | F90: =F91+F101 -> 4625696.4 | L90: =L91+L101 -> 5.1093829e+08 | O90: =O91+O101 -> 3.2417427e+09 | R90: =R91+R101 -> 1.0766639e+09
A91: IVC 7 | B91: 1275 | C91: =B91*F91 -> 2.9999404e+09 | D91: ='[2]GAP analysis Sc. 2'!$C$47+'[2]GAP analysis Sc. 2'!$J$52 -> 2.8121439 | E91: ='[1]Conversion factors selected IV '!$O$29 -> 0.83669065 | F91: =D91*E91*1000000 -> 2352894.5 | G91: ='LCoP 2030 HIGH'!E9 -> 922.73261 | H91: =G91*F91 -> 2.1710924e+09 | I91: ='LCoP 2030 HIGH'!H9 -> -0.013701038 | L91: =I91*H91 -> -29746220 | M91: ='LCoP 2030 HIGH'!F9 -> 0.65566124 | O91: =M91*H91 -> 1.4235012e+09 | P91: ='LCoP 2030 HIGH'!G9 -> 0.3580398 | R91: =P91*H91 -> 7.7733751e+08 | S91: =L91+O91+R91 -> 2.1710924e+09
C92: for cosnumption | D92: ='[2]GAP analysis Sc. 2'!$C$47 -> 1.0837488 | F92: Food, beverages and tobacco products | G92: =SUMIF($J$92:$J$100,F92,$L$92:$L$100)/$L$91 -> -0.33818449 | I92: Prunings & damaged crops (olive stones excluded) | J92: Products of agriculture, hunting and related services | K92: ='Feedstock MIX per IVC'!J20 -> 0.89326983 | L92: =K92*F$91 -> 2101769.6 | M92: Fabricated metal products | N92: 0.05 | O92: =N92*O$91 -> 71175058 | P92: Electricity, gas, steam and air conditioning | Q92: 0.2 | R92: =Q92*R$91 -> 1.554675e+08
C93: as feedstock for IVC 8b | D93: =D91-D92 -> 1.7283951 | F93: Products of agriculture, hunting and related services | G93: =SUMIF($J$92:$J$100,F93,$L$92:$L$100)/$L$91 -> -1.6999253 | I93: Lignocrops abandoned degraded | J93: Products of agriculture, hunting and related services | K93: ='Feedstock MIX per IVC'!J21 -> 0.85601008 | L93: =K93*F$91 -> 2014101.4 | M93: Electrical equipment | N93: 0.02 | O93: =N93*O$91 -> 28470023 | P93: Chemicals and chemical products | Q93: 0.5 | R93: =Q93*R$91 -> 3.8866875e+08
F94: Chemical and chemical products | G94: =SUMIF($J$92:$J$100,F94,$L$92:$L$100)/$L$91 -> -0.12739696 | I94: Lignocrops inter & cover cropping | J94: Products of agriculture, hunting and related services | K94: ='Feedstock MIX per IVC'!J22 -> 0.60142905 | L94: =K94*F$91 -> 1415099.1 | M94: Machinery and equipment n.e.c. | N94: 0.4 | O94: =N94*O$91 -> 5.6940046e+08 | P94: Legal and accounting services; services of head offices; management consultancy services | Q94: 0.15 | R94: =Q94*R$91 -> 1.1660063e+08
F95: Sewerage services; sewage sludge; waste collection, treatment and disposal services; materials recovery services; remediation services and other waste management services | G95: =SUMIF($J$92:$J$100,F95,$L$92:$L$100)/$L$91 -> 3.1655067 | I95: Agroprocessing residues | J95: Food, beverages and tobacco products | K95: ='Feedstock MIX per IVC'!J23 -> 4.2754617 | L95: =K95*F$91 -> 10059710 | M95: Constructions and construction works | N95: 0.3 | O95: =N95*O$91 -> 4.2705035e+08 | P95: Repair and installation services of machinery and equipment | Q95: 0.1 | R95: =Q95*R$91 -> 77733751
G96: =SUM(G92:G95) -> 1 | I96: Straw | J96: Products of agriculture, hunting and related services | K96: ='Feedstock MIX per IVC'!J24 -> 19.140417 | L96: =K96*F$91 -> 45035380 | M96: Architectural and engineering services; technical testing and analysis services | N96: 0.2 | O96: =N96*O$91 -> 2.8470023e+08 | P96: Land transport services and transport services via pipelines | Q96: 0.05 | R96: =Q96*R$91 -> 38866875
I97: Manure | J97: Products of agriculture, hunting and related services | K97: ='Feedstock MIX per IVC'!J25 -> 0 | L97: =K97*F$91 -> 0 | M97: Computer, electronic and optical products | N97: 0.03 | O97: =N97*O$91 -> 42705035
I98: Sewage sludge | J98: Sewerage services; sewage sludge; waste collection, treatment and disposal services; materials recovery services; remediation services and other waste management services | K98: ='Feedstock MIX per IVC'!J26 -> 0 | L98: =K98*F$91 -> 0 | N98: =SUM(N92:N97) -> 1
I99: Biowastes (post consumer woods excluded) | J99: Sewerage services; sewage sludge; waste collection, treatment and disposal services; materials recovery services; remediation services and other waste management services | K99: ='Feedstock MIX per IVC'!J27 -> -40.019584 | L99: =K99*F$91 -> -94161859
I100: Intermediate Bioenergy carrier (crude glycerine) | J100: Chemical and chemical products | K100: ='Feedstock MIX per IVC'!J28 -> 1.6106026 | L100: =K100*F$91 -> 3789577.9
A101: IVC 9a | B101: 1275 | C101: =B101*F101 -> 2.8978225e+09 | D101: ='[2]GAP analysis Sc. 2'!$C$56+'[2]GAP analysis Sc. 2'!$E$43 -> 2.7164185 | E101: ='[1]Conversion factors selected IV '!$O$52 -> 0.83669065 | F101: =D101*E101*1000000 -> 2272801.9 | G101: ='LCoP 2030 HIGH'!E13 -> 1307.8934 | H101: =G101*F101 -> 2.9725826e+09 | I101: ='LCoP 2030 HIGH'!H13 -> 0.18189049 | L101: =I101*H101 -> 5.4068451e+08 | M101: ='LCoP 2030 HIGH'!F13 -> 0.61167066 | O101: =M101*H101 -> 1.8182415e+09 | P101: ='LCoP 2030 HIGH'!G13 -> 0.20643885 | R101: 2.9932641e+08
...

Sheet 2030 costs Sc 3
A1: Contribution of each IVC to final product in Scenario (3) 2030
A2: Assumptions:
A3: technical capacity = no constraints | E3: feedstock availability: 2030 high
C4: =C6+C201+C227 -> 2.8570881e+11
A5: Sum ALL advanced | B5: Market price [€(t] | C5: Makret value of overall amount produced | D5: produced in Mtoe | E5: Conversion factor [t/toe] | F5: produced in t | G5: Cost of production [€/t] | H5: Money spent on each IVC | I5: Feedstock share of costs | J5: Eurostat sector | K5: money [€] spent on each feedtsock when producing 1t of product | L5: Absolute feedstock costs [€] | M5: CAPEX share of costs | N5: CAPEX distribution | O5: Absoluet CAPEX [€] | P5: OPEX share of costs | R5: Absolute OPEX [€] | S5: TOTAL production costs
C6: =C8+C48+C90+C123+C163 -> 2.4431698e+11 | D6: =D8+D48+D90+D123+D163 -> 167.03273
A7: Advanced biodiesel
A8: TOTAL | C8: =C28+C9+C16 -> 2.8899847e+10 | D8: =D28+D9+D16 -> 16.977868 | F8: =F28+F9+F16 -> 16514198 | H8: =H28+H9+H16 -> 3.355918e+10 | L8: =L28+L9+L16 -> 5.3942548e+09 | O8: =O9+O16+O28 -> 1.8594166e+10 | R8: =R9+R16+R28 -> 9.5707588e+09
A9: of which IVC 2 HVO | B9: 1750 | C9: =B9*F9 -> 7.8465261e+08 | D9: ='[3]Scenario 3 2030'!$O$9 -> 0.47120494 | E9: ='[1]Conversion factors selected IV '!$O$7 -> 0.95154545 | F9: =D9*E9*1000000 -> 448372.92 | G9: ='LCoP 2030 HIGH'!E3 -> 2245.1729 | H9: =G9*F9 -> 1.0066747e+09 | I9: ='LCoP 2030 HIGH'!H3 -> 0.74489715 | L9: =I9*H9 -> 7.4986913e+08 | M9: ='LCoP 2030 HIGH'!F3 -> 0.1198126 | O9: =M9*H9 -> 1.2061232e+08 | P9: ='LCoP 2030 HIGH'!G3 -> 0.13529025 | R9: =P9*H9 -> 1.3619328e+08 | S9: =L9+O9+R9 -> 1.0066747e+09
C10: =C9/$C$8 -> 0.027150753 | G10: Products of agriculture, hunting and related services | H10: =L10/L9 -> 0.10754894 | I10: Tall oil | J10: Products of agriculture, hunting and related services | K10: ='Feedstock MIX per IVC'!J6 -> 179.86731 | L10: =K10*F$9 -> 80647633 | M10: Fabricated metal products | N10: 0.05 | O10: =N10*O$9 -> 6030615.8 | P10: Electricity, gas, steam and air conditioning | Q10: 0.35 | R10: =Q10*R$9 -> 47667646
G11: Advanced biodiesel | H11: =L11/L9 -> 0.7585834 | I11: FPBO (Intermediate bioenergy carrier) | J11: Advanced biodiesel | K11: ='Feedstock MIX per IVC'!J7*0.85 -> 1268.6722 | L11: =K11*F$9 -> 5.6883827e+08 | M11: Electrical equipment | N11: 0.02 | O11: =N11*O$9 -> 2412246.3 | P11: Chemicals and chemical products | Q11: 0.25 | R11: =Q11*R$9 -> 34048319
G12: Chemicals and chemical products | H12: =L12/L9 -> 0.13386766 | I12: biocrude (Intermediate Bioenergy carrier) | J12: Chemicals and chemical products | K12: ='Feedstock MIX per IVC'!J7*0.15 -> 223.88333 | L12: =K12*F$9 -> 1.0038322e+08 | M12: Machinery and equipment n.e.c. | N12: 0.45 | O12: =N12*O$9 -> 54275542 | P12: Legal and accounting services; services of head offices; management consultancy services | Q12: 0.2 | R12: =Q12*R$9 -> 27238655
M13: Constructions and construction works | N13: 0.15 | O13: =N13*O$9 -> 18091847 | P13: Repair and installation services of machinery and equipment | Q13: 0.15 | R13: =Q13*R$9 -> 20428991
M14: Architectural and engineering services; technical testing and analysis services | N14: 0.3 | O14: =N14*O$9 -> 36183695 | P14: Land transport services and transport services via pipelines | Q14: 0.05 | R14: =Q14*R$9 -> 6809663.8
I15: Sum | L15: =SUM(L10:L12) -> 7.4986913e+08 | M15: Computer, electronic and optical products | N15: 0.03 | O15: =N15*O$9 -> 3618369.5
A16: of which IVC 11a (road) | B16: 1750 | C16: =B16*F16 -> 1.5149982e+10 | D16: ='[3]Scenario 3 2030'!$O$20+'[3]Scenario 3 2030'!$O$21*2 -> 9.0979706 | E16: ='[1]Conversion factors selected IV '!$O$64 -> 0.95154545 | F16: =D16*E16*1000000 -> 8657132.6 | G16: ='LCoP 2030 HIGH'!E15 -> 2502.2771 | H16: =G16*F16 -> 2.1662544e+10 | I16: ='LCoP 2030 HIGH'!H15 -> 0.13628669 | L16: =I16*H16 -> 2.9523164e+09 | M16: ='LCoP 2030 HIGH'!F15 -> 0.57747402 | O16: =M16*H16 -> 1.2509557e+10 | P16: ='LCoP 2030 HIGH'!G15 -> 0.28623929 | R16: =P16*H16 -> 6.2006712e+09 | S16: =L16+O16+R16 -> 2.1662544e+10
C17: =C16/$C$8 -> 0.52422361 | G17: Sewerage services; sewage sludge; waste collection, treatment and disposal services; materials recovery services; remediation services and other waste management services | H17: =SUMIF($J$17:$J$26,G17,$L$17:$L$26)/$L$16 -> 0.023308789 | I17: Straw | J17: Products of agriculture, hunting and related services | K17: ='Feedstock MIX per IVC'!J58 -> 181.54132 | L17: =K17*F$16 -> 1.5716273e+09 | M17: Fabricated metal products | N17: 0 | O17: =N17*O$16 -> 0 | P17: Electricity, gas, steam and air conditioning | Q17: 0.25 | R17: =Q17*R$16 -> 1.5501678e+09
G18: Food, beverages and tobacco products | H18: =SUMIF($J$17:$J$26,G18,$L$17:$L$26)/$L$16 -> 0.012600306 | I18: Prunings & damaged crops | J18: Products of agriculture, hunting and related services | K18: ='Feedstock MIX per IVC'!J59 -> 8.4731123 | L18: =K18*F$16 -> 73352857 | M18: Electrical equipment | N18: 0.02 | O18: =N18*O$16 -> 2.5019113e+08 | P18: Chemicals and chemical products | Q18: 0.15 | R18: =Q18*R$16 -> 9.3010068e+08
G19: Products of agriculture, hunting and related services | H19: =SUMIF($J$17:$J$26,G19,$L$17:$L$26)/$L$16 -> 0.59771745 | I19: Sewage sludge | J19: Sewerage services; sewage sludge; waste collection, treatment and disposal services; materials recovery services; remediation services and other waste management services | K19: ='Feedstock MIX per IVC'!J60 -> 0 | L19: =K19*F$16 -> 0 | M19: Machinery and equipment n.e.c. | N19: 0.55 | O19: =N19*O$16 -> 6.8802561e+09 | P19: Legal and accounting services; services of head offices; management consultancy services | Q19: 0.3 | R19: =Q19*R$16 -> 1.8602014e+09
G20: Products of forestry, logging and related services | H20: =SUMIF($J$17:$J$26,G20,$L$17:$L$26)/$L$16 -> 0.12919991 | I20: Agroprocessing residues - maize cobs | J20: Food, beverages and tobacco products | K20: ='Feedstock MIX per IVC'!J61 -> 4.2970453 | L20: =K20*F$16 -> 37200091 | M20: Constructions and construction works | N20: 0.1 | O20: =N20*O$16 -> 1.2509557e+09 | P20: Repair and installation services of machinery and equipment | Q20: 0.3 | R20: =Q20*R$16 -> 1.8602014e+09
G21: Paper and paper products | H21: =SUMIF($J$17:$J$26,G21,$L$17:$L$26)/$L$16 -> 0.14918901 | I21: Lignocrops abandoned degraded | J21: Products of agriculture, hunting and related services | K21: ='Feedstock MIX per IVC'!J62 -> 8.1190082 | L21: =K21*F$16 -> 70287331 | M21: Architectural and engineering services; technical testing and analysis services | N21: 0.3 | O21: =N21*O$16 -> 3.752867e+09 | P21: Land transport services and transport services via pipelines | Q21: 0 | R21: =Q21*R$16 -> 0
G22: Advanced biodiesel | H22: =SUMIF($J$17:$J$26,G22,$L$17:$L$26)/$L$16 -> 0.087984531 | I22: Lignocrops inter & cover cropping | J22: Products of agriculture, hunting and related services | K22: ='Feedstock MIX per IVC'!J63 -> 5.7043807 | L22: =K22*F$16 -> 49383580 | M22: Computer, electronic and optical products | N22: 0.03 | O22: =N22*O$16 -> 3.752867e+08
H23: =SUM(H17:H22) -> 1 | I23: Primary forestry residues | J23: Products of forestry, logging and related services | K23: ='Feedstock MIX per IVC'!J64 -> 44.060666 | L23: =K23*F$16 -> 3.8143903e+08
I24: Secondary forest residues | J24: Paper and paper products | K24: ='Feedstock MIX per IVC'!J65 -> 50.877489 | L24: =K24*F$16 -> 4.4045317e+08
I25: Biowastes - Post consumer wood | J25: Sewerage services; sewage sludge; waste collection, treatment and disposal services; materials recovery services; remediation services and other waste management services | K25: ='Feedstock MIX per IVC'!J66 -> 7.9489277 | L25: =K25*F$16 -> 68814921
I26: Intermediate Bioenergy carriers (FPBO with lower quality ) | J26: Advanced biodiesel | K26: ='Feedstock MIX per IVC'!J67 -> 30.005106 | L26: =K26*F$16 -> 2.5975818e+08
I27: Sum | L27: =SUM(L17:L26) -> 2.9523164e+09
A28: of which 13a (half) | B28: 1750 | C28: =B28*F28 -> 1.2965212e+10 | D28: ='[3]Scenario 3 2030'!$O$23/2+'[3]Scenario 3 2030'!$P$23/2 -> 7.4086926 | E28: ='[1]Conversion factors selected IV '!$O$89 -> 1 | F28: =D28*E28*1000000 -> 7408692.6 | G28: ='LCoP 2030 HIGH'!E19 -> 1469.8897 | H28: =G28*F28 -> 1.0889961e+10 | I28: ='LCoP 2030 HIGH'!H19 -> 0.15537881 | L28: =I28*H28 -> 1.6920692e+09 | M28: ='LCoP 2030 HIGH'!F19 -> 0.54766013 | O28: =M28*H28 -> 5.9639976e+09 | P28: ='LCoP 2030 HIGH'!G19 -> 0.29696105 | R28: =P28*H28 -> 3.2338943e+09 | S28: =L28+O28+R28 -> 1.0889961e+10
C29: =C28/$C$8 -> 0.44862564 | G29: Sewerage services; sewage sludge; waste collection, treatment and disposal services; materials recovery services; remediation services and other waste management services | H29: =SUMIF($J$29:$J$36,G29,$L$29:$L$36)/$L$28 -> 0.023180367 | I29: Straw | J29: Products of agriculture, hunting and related services | K29: ='Feedstock MIX per IVC'!J84 -> 129.97872 | L29: =K29*F$28 -> 9.629724e+08 | M29: Fabricated metal products | N29: 0.15 | O29: =N29*O$28 -> 8.9459964e+08 | P29: Electricity, gas, steam and air conditioning | Q29: 0.15 | R29: =Q29*R$28 -> 4.8508415e+08
G30: Food, beverages and tobacco products | H30: =SUMIF($J$29:$J$36,G30,$L$29:$L$36)/$L$28 -> 0.0134707 | I30: Prunings & damaged crops | J30: Products of agriculture, hunting and related services | K30: ='Feedstock MIX per IVC'!J85 -> 6.0665214 | L30: =K30*F$28 -> 44944993 | M30: Electrical equipment | N30: 0.02 | O30: =N30*O$28 -> 1.1927995e+08 | P30: Chemicals and chemical products | Q30: 0.25 | R30: =Q30*R$28 -> 8.0847358e+08
G31: Products of agriculture, hunting and related services | H31: =SUMIF($J$29:$J$36,G31,$L$29:$L$36)/$L$28 -> 0.63900608 | I31: Agroprocessing residues - maize cobs | J31: Food, beverages and tobacco products | K31: ='Feedstock MIX per IVC'!J86 -> 3.0765693 | L31: =K31*F$28 -> 22793357 | M31: Machinery and equipment n.e.c. | N31: 0.45 | O31: =N31*O$28 -> 2.6837989e+09 | P31: Legal and accounting services; services of head offices; management consultancy services | Q31: 0.2 | R31: =Q31*R$28 -> 6.4677887e+08
G32: Products of forestry, logging and related services | H32: =SUMIF($J$29:$J$36,G32,$L$29:$L$36)/$L$28 -> 0.14815699 | I32: Lignocrops abandoned degraded | J32: Products of agriculture, hunting and related services | K32: ='Feedstock MIX per IVC'!J87 -> 5.8129924 | L32: =K32*F$28 -> 43066674 | M32: Constructions and construction works | N32: 0.1 | O32: =N32*O$28 -> 5.9639976e+08 | P32: Repair and installation services of machinery and equipment | Q32: 0.3 | R32: =Q32*R$28 -> 9.701683e+08
G33: Paper and paper products | H33: =SUMIF($J$29:$J$36,G33,$L$29:$L$36)/$L$28 -> 0.17618586 | I33: Lignocrops inter & cover cropping | J33: Products of agriculture, hunting and related services | K33: ='Feedstock MIX per IVC'!J88 -> 4.0841838 | L33: =K33*F$28 -> 30258462 | M33: Architectural and engineering services; technical testing and analysis services | N33: 0.25 | O33: =N33*O$28 -> 1.4909994e+09 | P33: Land transport services and transport services via pipelines | Q33: 0.1 | R33: =Q33*R$28 -> 3.2338943e+08
G34: Advanced biodiesel | I34: Primary forestry residues | J34: Products of forestry, logging and related services | K34: ='Feedstock MIX per IVC'!J89 -> 33.837534 | L34: =K34*F$28 -> 2.5069189e+08 | M34: Computer, electronic and optical products | N34: 0.03 | O34: =N34*O$28 -> 1.7891993e+08 | Q34: =SUM(Q29:Q33) -> 1
H35: =SUM(H29:H34) -> 1 | I35: Secondary forest residues | J35: Paper and paper products | K35: ='Feedstock MIX per IVC'!J90 -> 40.239039 | L35: =K35*F$28 -> 2.9811867e+08
I36: Biowastes - Post consumer wood | J36: Sewerage services; sewage sludge; waste collection, treatment and disposal services; materials recovery services; remediation services and other waste management services | K36: ='Feedstock MIX per IVC'!J91 -> 5.2941575 | L36: =K36*F$28 -> 39222786
I37: SUM | L37: =SUM(L29:L36) -> 1.6920692e+09
I38: TOTALS domestic | M38: TOTALS | O38: =SUM(O39:O44) -> 0 | P38: TOTALS | R38: =SUM(R39:R43) -> 0
J39: Products of agriculture, hunting and related services | L39: =SUMIF($J$10:$J$190, J39, $L$10:$L$191) -> 0 | M39: Fabricated metal products | O39: =SUMIF($M$10:$M$188, M39, $O$10:$O$188) -> 0 | P39: Electricity, gas, steam and air conditioning | R39: =SUMIF($P$10:$P$187, P39, $R$10:$R$187) -> 0
J40: Products of forestry, logging and related services | L40: =SUMIF($J$10:$J$190, J40, $L$10:$L$191) -> 0 | M40: Electrical equipment | O40: =SUMIF($M$10:$M$188, M40, $O$10:$O$188) -> 0 | P40: Chemicals and chemical products | R40: =SUMIF($P$10:$P$187, P40, $R$10:$R$187) -> 0
J41: Paper and paper products | L41: =SUMIF($J$10:$J$190, J41, $L$10:$L$191) -> 0 | M41: Machinery and equipment n.e.c. | O41: =SUMIF($M$10:$M$188, M41, $O$10:$O$188) -> 0 | P41: Legal and accounting services; services of head offices; management consultancy services | R41: =SUMIF($P$10:$P$187, P41, $R$10:$R$187) -> 0
J42: Food, beverages and tobacco products | L42: =SUMIF($J$10:$J$190, J42, $L$10:$L$191) -> 0 | M42: Constructions and construction works | O42: =SUMIF($M$10:$M$188, M42, $O$10:$O$188) -> 0 | P42: Repair and installation services of machinery and equipment | R42: =SUMIF($P$10:$P$187, P42, $R$10:$R$187) -> 0
J43: Sewerage services; sewage sludge; waste collection, treatment and disposal services; materials recovery services; remediation services and other waste management services | L43: =SUMIF($J$10:$J$190, J43, $L$10:$L$191) -> 0 | M43: Architectural and engineering services; technical testing and analysis services | O43: =SUMIF($M$10:$M$188, M43, $O$10:$O$188) -> 0 | P43: Land transport services and transport services via pipelines | R43: =SUMIF($P$10:$P$187, P43, $R$10:$R$187) -> 0
J44: Advanced biodiesel | L44: =SUMIF($J$10:$J$190, J44, $L$10:$L$191) -> 0 | M44: Computer, electronic and optical products | O44: =SUMIF($M$10:$M$188, M44, $O$10:$O$188) -> 0
J45: Chemicals and chemical products | L45: =SUMIF($J$10:$J$190, J45, $L$10:$L$191) -> 0
I46: SUM | L46: =SUM(L39:L45) -> 0
A47: Advanced biogasoline
C48: =C49+C56+C63+C72 -> 5.8854358e+10 | D48: =D49+D56+D63+D72 -> 38.956015 | F48: =F49+F56+F63+F72 -> 52163391 | H48: =H49+H56+H63+H72 -> 6.6896446e+10 | L48: =L49+L56+L63+L72 -> 2.3515362e+10 | O48: =O49+O56+O63+O72 -> 2.3671777e+10 | R48: =R49+R56+R63+R72 -> 1.9709306e+10
A49: of which from IVC 5 | B49: 1000 | C49: =B49*F49 -> 7.8983376e+09 | D49: ='[3]Scenario 3 2030'!$E$9 -> 5.0935109 | E49: ='[1]Conversion factors selected IV '!$O$17 -> 1.5506667 | F49: =D49*E49*1000000 -> 7898337.6 | G49: ='LCoP 2030 HIGH'!E5 -> 1284.2295 | H49: =G49*F49 -> 1.0143278e+10 | I49: ='LCoP 2030 HIGH'!H5 -> 0.26648625 | L49: =I49*H49 -> 2.7030441e+09 | M49: ='LCoP 2030 HIGH'!F5 -> 0.43216575 | O49: =M49*H49 -> 4.3835774e+09 | P49: ='LCoP 2030 HIGH'!G5 -> 0.30134801 | R49: =P49*H49 -> 3.0566567e+09 | S49: =R49+O49+L49 -> 1.0143278e+10
C50: =C49/$C$48 -> 0.13420141 | F50: Products of agriculture, hunting and related services | G50: =(SUMIF($J$50:$J$53, F50,$L$50:$L$53)/$L$49) -> 0.81975782 | H50: domestic | I50: Straw | J50: Products of agriculture, hunting and related services | K50: ='Feedstock MIX per IVC'!J13 -> 260.69481 | L50: =K50*F$49 -> 2.0590556e+09 | M50: Fabricated metal products | N50: 0 | O50: =N50*O$49 -> 0 | P50: Electricity, gas, steam and air conditioning | Q50: 0.2 | R50: =Q50*R$49 -> 6.1133133e+08
F51: Paper and paper products | G51: =(SUMIF($J$50:$J$53, F51,$L$50:$L$53)/$L$49) -> 0.18024218 | H51: domestic | I51: Lignocrops abandoned degraded | J51: Products of agriculture, hunting and related services | K51: ='Feedstock MIX per IVC'!J14 -> 11.658962 | L51: =K51*F$49 -> 92086416 | M51: Electrical equipment | N51: 0.02 | O51: =N51*O$49 -> 87671548 | P51: Chemicals and chemical products | Q51: 0.5 | R51: =Q51*R$49 -> 1.5283283e+09
H52: domestic | I52: Lignocrops inter & cover cropping | J52: Products of agriculture, hunting and related services | K52: ='Feedstock MIX per IVC'!J15 -> 8.1915371 | L52: =K52*F$49 -> 64699525 | M52: Machinery and equipment n.e.c. | N52: 0.5 | O52: =N52*O$49 -> 2.1917887e+09 | P52: Legal and accounting services; services of head offices; management consultancy services | Q52: 0.15 | R52: =Q52*R$49 -> 4.584985e+08
H53: domestic | I53: Secondary forest residues | J53: Paper and paper products | K53: ='Feedstock MIX per IVC'!J16 -> 61.68419 | L53: =K53*F$49 -> 4.8720256e+08 | M53: Constructions and construction works | N53: 0.15 | O53: =N53*O$49 -> 6.5753661e+08 | P53: Repair and installation services of machinery and equipment | Q53: 0.1 | R53: =Q53*R$49 -> 3.0566567e+08
M54: Architectural and engineering services; technical testing and analysis services | N54: 0.3 | O54: =N54*O$49 -> 1.3150732e+09 | P54: Land transport services and transport services via pipelines | Q54: 0.05 | R54: =Q54*R$49 -> 1.5283283e+08
M55: Computer, electronic and optical products | N55: 0.03 | O55: =N55*O$49 -> 1.3150732e+08
A56: of which 12 (road) | B56: 1000 | C56: =B56*F56 -> 2.9293377e+10 | D56: ='[3]Scenario 3 2030'!$E$10 -> 18.890828 | E56: ='[1]Conversion factors selected IV '!$O$86 -> 1.5506667 | F56: =D56*E56*1000000 -> 29293377 | G56: ='LCoP 2030 HIGH'!E17 -> 1166.35 | H56: =G56*F56 -> 3.416633e+10 | I56: ='LCoP 2030 HIGH'!H17 -> 0.50893814 | L56: =I56*H56 -> 1.7388548e+10 | M56: ='LCoP 2030 HIGH'!F17 -> 0.23835041 | O56: =M56*H56 -> 8.1435587e+09 | P56: ='LCoP 2030 HIGH'!G17 -> 0.25271145 | R56: =P56*H56 -> 8.6342228e+09 | S56: =R56+O56+L56 -> 3.416633e+10
C57: =C56/$C$48 -> 0.49772656 | G57: Advanced biogas | H57: 1 | I57: Intermediate Bioenergy carriers (Syngas) | J57: Advanced biogas | K57: ='Feedstock MIX per IVC'!J80 -> 593.6 | L57: =K57*F56 -> 1.7388548e+10 | M57: Fabricated metal products | N57: 0 | O57: =N57*O$56 -> 0 | P57: Electricity, gas, steam and air conditioning | Q57: 0.2 | R57: =Q57*R$56 -> 1.7268446e+09
M58: Electrical equipment | N58: 0.02 | O58: =N58*O$56 -> 1.6287117e+08 | P58: Chemicals and chemical products | Q58: 0.5 | R58: =Q58*R$56 -> 4.3171114e+09
M59: Machinery and equipment n.e.c. | N59: 0.5 | O59: =N59*O$56 -> 4.0717794e+09 | P59: Legal and accounting services; services of head offices; management consultancy services | Q59: 0.15 | R59: =Q59*R$56 -> 1.2951334e+09
M60: Constructions and construction works | N60: 0.15 | O60: =N60*O$56 -> 1.2215338e+09 | P60: Repair and installation services of machinery and equipment | Q60: 0.1 | R60: =Q60*R$56 -> 8.6342228e+08
M61: Architectural and engineering services; technical testing and analysis services | N61: 0.3 | O61: =N61*O$56 -> 2.4430676e+09 | P61: Land transport services and transport services via pipelines | Q61: 0.05 | R61: =Q61*R$56 -> 4.3171114e+08
M62: Computer, electronic and optical products | N62: 0.03 | O62: =N62*O$56 -> 2.4430676e+08
A63: of which 13a (half) | B63: 1750 | C63: =B63*F63 -> 1.2965212e+10 | D63: ='[3]Scenario 3 2030'!$E$11+'[3]Scenario 3 2030'!$P$23/2 -> 7.4086926 | E63: ='[1]Conversion factors selected IV '!$O$89 -> 1 | F63: =D63*E63*1000000 -> 7408692.6 | G63: ='LCoP 2030 HIGH'!E19 -> 1469.8897 | H63: =G63*F63 -> 1.0889961e+10 | I63: ='LCoP 2030 HIGH'!H19 -> 0.15537881 | L63: =I63*H63 -> 1.6920692e+09 | M63: ='LCoP 2030 HIGH'!F19 -> 0.54766013 | O63: =M63*H63 -> 5.9639976e+09 | P63: ='LCoP 2030 HIGH'!G19 -> 0.29696105 | R63: =P63*H63 -> 3.2338943e+09 | S63: =L63+O63+R63 -> 1.0889961e+10
C64: =C63/$C$48 -> 0.22029315 | F64: Sewerage services; sewage sludge; waste collection, treatment and disposal services; materials recovery services; remediation services and other waste management services | G64: =(SUMIF($J$64:$J$71, F64,$L$64:$L$71)/$L$63) -> 0.023180367 | H64: domestic | I64: Straw | J64: Products of agriculture, hunting and related services | K64: ='Feedstock MIX per IVC'!J84 -> 129.97872 | L64: =K64*F$63 -> 9.629724e+08 | M64: Fabricated metal products | N64: 0.15 | O64: =N64*O$63 -> 8.9459964e+08 | P64: Electricity, gas, steam and air conditioning | Q64: 0.15 | R64: =Q64*R$63 -> 4.8508415e+08
F65: Food, beverages and tobacco products | G65: =(SUMIF($J$64:$J$71, F65,$L$64:$L$71)/$L$63) -> 0.0134707 | H65: domestic | I65: Prunings & damaged crops | J65: Products of agriculture, hunting and related services | K65: ='Feedstock MIX per IVC'!J85 -> 6.0665214 | L65: =K65*F$63 -> 44944993 | M65: Electrical equipment | N65: 0.02 | O65: =N65*O$63 -> 1.1927995e+08 | P65: Chemicals and chemical products | Q65: 0.25 | R65: =Q65*R$63 -> 8.0847358e+08
F66: Products of agriculture, hunting and related services | G66: =(SUMIF($J$64:$J$71, F66,$L$64:$L$71)/$L$63) -> 0.63900608 | H66: domestic | I66: Agroprocessing residues - maize cobs | J66: Food, beverages and tobacco products | K66: ='Feedstock MIX per IVC'!J86 -> 3.0765693 | L66: =K66*F$63 -> 22793357 | M66: Machinery and equipment n.e.c. | N66: 0.45 | O66: =N66*O$63 -> 2.6837989e+09 | P66: Legal and accounting services; services of head offices; management consultancy services | Q66: 0.2 | R66: =Q66*R$63 -> 6.4677887e+08
F67: Products of forestry, logging and related services | G67: =(SUMIF($J$64:$J$71, F67,$L$64:$L$71)/$L$63) -> 0.14815699 | H67: domestic | I67: Lignocrops abandoned degraded | J67: Products of agriculture, hunting and related services | K67: ='Feedstock MIX per IVC'!J87 -> 5.8129924 | L67: =K67*F$63 -> 43066674 | M67: Constructions and construction works | N67: 0.1 | O67: =N67*O$63 -> 5.9639976e+08 | P67: Repair and installation services of machinery and equipment | Q67: 0.3 | R67: =Q67*R$63 -> 9.701683e+08
F68: Paper and paper products | G68: =(SUMIF($J$64:$J$71, F68,$L$64:$L$71)/$L$63) -> 0.17618586 | H68: domestic | I68: Lignocrops inter & cover cropping | J68: Products of agriculture, hunting and related services | K68: ='Feedstock MIX per IVC'!J88 -> 4.0841838 | L68: =K68*F$63 -> 30258462 | M68: Architectural and engineering services; technical testing and analysis services | N68: 0.25 | O68: =N68*O$63 -> 1.4909994e+09 | P68: Land transport services and transport services via pipelines | Q68: 0.1 | R68: =Q68*R$63 -> 3.2338943e+08
F69: Advanced biodiesel | G69: =(SUMIF($J$64:$J$71, F69,$L$64:$L$71)/$L$63) -> 0 | H69: domestic | I69: Primary forestry residues | J69: Products of forestry, logging and related services | K69: ='Feedstock MIX per IVC'!J89 -> 33.837534 | L69: =K69*F$63 -> 2.5069189e+08 | M69: Computer, electronic and optical products | N69: 0.03 | O69: =N69*O$63 -> 1.7891993e+08
G70: =SUM(G64:G69) -> 1 | H70: domestic | I70: Secondary forest residues | J70: Paper and paper products | K70: ='Feedstock MIX per IVC'!J90 -> 40.239039 | L70: =K70*F$63 -> 2.9811867e+08
H71: domestic | I71: Biowastes - Post consumer wood | J71: Sewerage services; sewage sludge; waste collection, treatment and disposal services; materials recovery services; remediation services and other waste management services | K71: ='Feedstock MIX per IVC'!J91 -> 5.2941575 | L71: =K71*F$63 -> 39222786
A72: of which 13b (road) | B72: 1150 | C72: =B72*F72 -> 8.6974312e+09 | D72: ='[3]Scenario 3 2030'!$E$12 -> 7.5629836 | E72: ='[1]Conversion factors selected IV '!$O$125 -> 1 | F72: =D72*E72*1000000 -> 7562983.6 | G72: ='LCoP 2030 HIGH'!E21 -> 1546.5955 | H72: =G72*F72 -> 1.1696877e+10 | I72: ='LCoP 2030 HIGH'!H21 -> 0.14804809 | L72: =I72*H72 -> 1.7317003e+09 | M72: ='LCoP 2030 HIGH'!F21 -> 0.44290831 | O72: =M72*H72 -> 5.1806438e+09 | P72: ='LCoP 2030 HIGH'!G21 -> 0.4090436 | R72: =P72*H72 -> 4.7845325e+09 | S72: =L72+O72+R72 -> 1.1696877e+10
C73: =C72/$C$48 -> 0.14777888 | F73: Sewerage services; sewage sludge; waste collection, treatment and disposal services; materials recovery services; remediation services and other waste management services | G73: =(SUMIF($J$73:$J$80, F73,$L$73:$L$80)/$L$72) -> 0.022605022 | H73: domestic | I73: Straw | J73: Products of agriculture, hunting and related services | K73: ='Feedstock MIX per IVC'!J102 -> 127.07494 | L73: =K73*F$72 -> 9.6106569e+08 | M73: Fabricated metal products | N73: 0.15 | O73: =N73*O$72 -> 7.7709657e+08 | P73: Electricity, gas, steam and air conditioning | Q73: 0.15 | R73: =Q73*R$72 -> 7.1767988e+08
F74: Food, beverages and tobacco products | G74: =(SUMIF($J$73:$J$80, F74,$L$73:$L$80)/$L$72) -> 0.013136352 | H74: domestic | I74: Prunings & damaged crops | J74: Products of agriculture, hunting and related services | K74: ='Feedstock MIX per IVC'!J103 -> 5.9309927 | L74: =K74*F$72 -> 44856000 | M74: Electrical equipment | N74: 0.02 | O74: =N74*O$72 -> 1.0361288e+08 | P74: Chemicals and chemical products | Q74: 0.25 | R74: =Q74*R$72 -> 1.1961331e+09
F75: Products of agriculture, hunting and related services | G75: =(SUMIF($J$73:$J$80, F75,$L$73:$L$80)/$L$72) -> 0.64796608 | H75: domestic | I75: Agroprocessing residues - maize cobs | J75: Food, beverages and tobacco products | K75: ='Feedstock MIX per IVC'!J104 -> 3.0078374 | L75: =K75*F$72 -> 22748225 | M75: Machinery and equipment n.e.c. | N75: 0.45 | O75: =N75*O$72 -> 2.3312897e+09 | P75: Legal and accounting services; services of head offices; management consultancy services | Q75: 0.2 | R75: =Q75*R$72 -> 9.569065e+08
F76: Products of forestry, logging and related services | G76: =(SUMIF($J$73:$J$80, F76,$L$73:$L$80)/$L$72) -> 0.14447968 | H76: domestic | I76: Lignocrops abandoned degraded | J76: Products of agriculture, hunting and related services | K76: ='Feedstock MIX per IVC'!J105 -> 11.366255 | L76: =K76*F$72 -> 85962801 | M76: Constructions and construction works | N76: 0.1 | O76: =N76*O$72 -> 5.1806438e+08 | P76: Repair and installation services of machinery and equipment | Q76: 0.3 | R76: =Q76*R$72 -> 1.4353598e+09
F77: Paper and paper products | G77: =(SUMIF($J$73:$J$80, F77,$L$73:$L$80)/$L$72) -> 0.17181286 | H77: domestic | I77: Lignocrops inter & cover cropping | J77: Products of agriculture, hunting and related services | K77: ='Feedstock MIX per IVC'!J106 -> 3.9929413 | L77: =K77*F$72 -> 30198550 | M77: Architectural and engineering services; technical testing and analysis services | N77: 0.25 | O77: =N77*O$72 -> 1.2951609e+09 | P77: Land transport services and transport services via pipelines | Q77: 0.1 | R77: =Q77*R$72 -> 4.7845325e+08
F78: Advanced biodiesel | G78: =(SUMIF($J$73:$J$80, F78,$L$73:$L$80)/$L$72) -> 0 | H78: domestic | I78: Primary forestry residues | J78: Products of forestry, logging and related services | K78: ='Feedstock MIX per IVC'!J107 -> 33.081588 | L78: =K78*F$72 -> 2.5019551e+08 | M78: Computer, electronic and optical products | N78: 0.03 | O78: =N78*O$72 -> 1.5541931e+08
G79: =SUM(G73:G78) -> 1 | H79: domestic | I79: Secondary forest residues | J79: Paper and paper products | K79: ='Feedstock MIX per IVC'!J108 -> 39.340081 | L79: =K79*F$72 -> 2.9752839e+08
H80: domestic | I80: Biowastes - Post consumer wood | J80: Sewerage services; sewage sludge; waste collection, treatment and disposal services; materials recovery services; remediation services and other waste management services | K80: ='Feedstock MIX per IVC'!J109 -> 5.1758836 | L80: =K80*F$72 -> 39145123
I82: TOTALS domestic | L82: =SUM(L83:L88) -> 2.3515362e+10 | M82: TOTALS | O82: =SUM(O83:O88) -> 2.3671777e+10 | P82: TOTALS | R82: =SUM(R83:R87) -> 1.9709306e+10
J83: Products of agriculture, hunting and related services | L83: =SUMIF($J$50:$J$80, J83, $L$50:$L$80) -> 4.4191671e+09 | M83: Fabricated metal products | O83: =SUMIF($M$50:$M$78, M83, $O$50:$O$78) -> 1.6716962e+09 | P83: Electricity, gas, steam and air conditioning | R83: =SUMIF($P$50:$P$77, P83, $R$50:$R$77) -> 3.5409399e+09
J84: Products of forestry, logging and related services | L84: =SUMIF($J$50:$J$80, J84, $L$50:$L$80) -> 5.0088739e+08 | M84: Electrical equipment | O84: =SUMIF($M$50:$M$78, M84, $O$50:$O$78) -> 4.7343555e+08 | P84: Chemicals and chemical products | R84: =SUMIF($P$50:$P$77, P84, $R$50:$R$77) -> 7.8500464e+09
J85: Paper and paper products | L85: =SUMIF($J$50:$J$80, J85, $L$50:$L$80) -> 1.0828496e+09 | M85: Machinery and equipment n.e.c. | O85: =SUMIF($M$50:$M$78, M85, $O$50:$O$78) -> 1.1278657e+10 | P85: Legal and accounting services; services of head offices; management consultancy services | R85: =SUMIF($P$50:$P$77, P85, $R$50:$R$77) -> 3.3573173e+09
J86: Food, beverages and tobacco products | L86: =SUMIF($J$50:$J$80, J86, $L$50:$L$80) -> 45541582 | M86: Constructions and construction works | O86: =SUMIF($M$50:$M$78, M86, $O$50:$O$78) -> 2.9935346e+09 | P86: Repair and installation services of machinery and equipment | R86: =SUMIF($P$50:$P$77, P86, $R$50:$R$77) -> 3.574616e+09
J87: Sewerage services; sewage sludge; waste collection, treatment and disposal services; materials recovery services; remediation services and other waste management services | L87: =SUMIF($J$50:$J$80, J87, $L$50:$L$80) -> 78367909 | M87: Architectural and engineering services; technical testing and analysis services | O87: =SUMIF($M$50:$M$78, M87, $O$50:$O$78) -> 6.5443012e+09 | P87: Land transport services and transport services via pipelines | R87: =SUMIF($P$50:$P$77, P87, $R$50:$R$77) -> 1.3863867e+09
J88: Advanced biogas | L88: =SUMIF($J$50:$J$80, J88, $L$50:$L$80) -> 1.7388548e+10 | M88: Computer, electronic and optical products | O88: =SUMIF($M$50:$M$78, M88, $O$50:$O$78) -> 7.1015332e+08
A89: Advanced biogas
C90: =C91+C101 -> 7.3538062e+10 | D90: =D91+D101 -> 68.934571 | H90: =H91+H101 -> 5.9308138e+10 | L90: =L91+L101 -> 3.2307426e+09 | O90: =O91+O101 -> 3.7976661e+10 | R90: =R91+R101 -> 1.4132497e+10
A91: IVC 7 | B91: 1275 | C91: =B91*F91 -> 5.3385674e+10 | D91: ='[3]Scenario 3 2030'!$E$14 -> 50.043725 | E91: ='[1]Conversion factors selected IV '!$O$29 -> 0.83669065 | F91: =D91*E91*1000000 -> 41871117 | G91: ='LCoP 2030 HIGH'!E9 -> 922.73261 | H91: =G91*F91 -> 3.8635844e+10 | I91: ='LCoP 2030 HIGH'!H9 -> -0.013701038 | L91: =I91*H91 -> -5.2935117e+08 | M91: ='LCoP 2030 HIGH'!F9 -> 0.65566124 | O91: =M91*H91 -> 2.5332025e+10 | P91: ='LCoP 2030 HIGH'!G9 -> 0.3580398 | R91: =P91*H91 -> 1.383317e+10 | S91: =L91+O91+R91 -> 3.8635844e+10
G92: Food, beverages and tobacco products | H92: =(SUMIF($J$92:$J$100,G92,$L$92:$L$100)/$L$91) -> -0.33818449 | I92: Prunings & damaged crops (olive stones excluded) | J92: Products of agriculture, hunting and related services | K92: ='Feedstock MIX per IVC'!J20 -> 0.89326983 | L92: =K92*F$91 -> 37402205 | M92: Fabricated metal products | N92: 0.05 | O92: =N92*O$91 -> 1.2666013e+09 | P92: Electricity, gas, steam and air conditioning | Q92: 0.2 | R92: =Q92*R$91 -> 2.766634e+09
G93: Products of agriculture, hunting and related services | H93: =(SUMIF($J$92:$J$100,G93,$L$92:$L$100)/$L$91) -> -1.6999253 | I93: Lignocrops abandoned degraded | J93: Products of agriculture, hunting and related services | K93: ='Feedstock MIX per IVC'!J21 -> 0.85601008 | L93: =K93*F$91 -> 35842098 | M93: Electrical equipment | N93: 0.02 | O93: =N93*O$91 -> 5.0664051e+08 | P93: Chemicals and chemical products | Q93: 0.5 | R93: =Q93*R$91 -> 6.9165851e+09
G94: Sewerage services; sewage sludge; waste collection, treatment and disposal services; materials recovery services; remediation services and other waste management services | H94: =(SUMIF($J$92:$J$100,G94,$L$92:$L$100)/$L$91) -> 3.1655067 | I94: Lignocrops inter & cover cropping | J94: Products of agriculture, hunting and related services | K94: ='Feedstock MIX per IVC'!J22 -> 0.60142905 | L94: =K94*F$91 -> 25182506 | M94: Machinery and equipment n.e.c. | N94: 0.4 | O94: =N94*O$91 -> 1.013281e+10 | P94: Legal and accounting services; services of head offices; management consultancy services | Q94: 0.15 | R94: =Q94*R$91 -> 2.0749755e+09
G95: Chemical and chemical products | H95: =(SUMIF($J$92:$J$100,G95,$L$92:$L$100)/$L$91) -> -0.12739696 | I95: Agroprocessing residues | J95: Food, beverages and tobacco products | K95: ='Feedstock MIX per IVC'!J23 -> 4.2754617 | L95: =K95*F$91 -> 1.7901836e+08 | M95: Constructions and construction works | N95: 0.3 | O95: =N95*O$91 -> 7.5996076e+09 | P95: Repair and installation services of machinery and equipment | Q95: 0.1 | R95: =Q95*R$91 -> 1.383317e+09
H96: =SUM(H92:H95) -> 1 | I96: Straw | J96: Products of agriculture, hunting and related services | K96: ='Feedstock MIX per IVC'!J24 -> 19.140417 | L96: =K96*F$91 -> 8.0143062e+08 | M96: Architectural and engineering services; technical testing and analysis services | N96: 0.2 | O96: =N96*O$91 -> 5.0664051e+09 | P96: Land transport services and transport services via pipelines | Q96: 0.05 | R96: =Q96*R$91 -> 6.9165851e+08
I97: Manure | J97: Products of agriculture, hunting and related services | K97: ='Feedstock MIX per IVC'!J25 -> 0 | L97: =K97*F$91 -> 0 | M97: Computer, electronic and optical products | N97: 0.03 | O97: =N97*O$91 -> 7.5996076e+08
I98: Sewage sludge | J98: Sewerage services; sewage sludge; waste collection, treatment and disposal services; materials recovery services; remediation services and other waste management services | K98: ='Feedstock MIX per IVC'!J26 -> 0 | L98: =K98*F$91 -> 0 | N98: =SUM(N92:N97) -> 1
I99: Biowastes (post consumer woods excluded) | J99: Sewerage services; sewage sludge; waste collection, treatment and disposal services; materials recovery services; remediation services and other waste management services | K99: ='Feedstock MIX per IVC'!J27 -> -40.019584 | L99: =K99*F$91 -> -1.6756647e+09
I100: Intermediate Bioenergy carrier (crude glycerine) | J100: Chemical and chemical products | K100: ='Feedstock MIX per IVC'!J28 -> 1.6106026 | L100: =K100*F$91 -> 67437729
A101: IVC 9a | B101: 1275 | C101: =B101*F101 -> 2.0152388e+10 | D101: ='[3]Scenario 3 2030'!$G$16 -> 18.890847 | E101: ='[1]Conversion factors selected IV '!$O$52 -> 0.83669065 | F101: =D101*E101*1000000 -> 15805795 | G101: ='LCoP 2030 HIGH'!E13 -> 1307.8934 | H101: =G101*F101 -> 2.0672294e+10 | I101: ='LCoP 2030 HIGH'!H13 -> 0.18189049 | L101: =I101*H101 -> 3.7600937e+09 | M101: ='LCoP 2030 HIGH'!F13 -> 0.61167066 | O101: =M101*H101 -> 1.2644636e+10 | P101: ='LCoP 2030 HIGH'!G13 -> 0.20643885 | R101: 2.9932641e+08
...

Sheet Feedstock MIX per IVC
E1: 2030 medium | H1: 2030 high | K1: 2040 with 2030 medium and 2050 high | M1: 2040 with 2030 high and 2050 high | O1: 2050 high
A2: Feedstock | B2: Price of 1t of feedstock | C2: Converison factor [t product/ t feedstock] | D2: Feestock cost to produce 1t of fuel | E2: (Old) Share of feedstock 2030 medium (NOT taking into account feedstock split) | F2: NEW share of feedstock mix 2030 medium (taking into account the feedstock split in 2030) | G2: money [€] spent on each feedtsock when producing 1t of product (and weighted feedstock mix cost) | H2: (old) Share per feedstock 2030 high | I2: NEW share of feedstock mix 2030 high (taking into account the feedstock split in 2030) | J2: money [€] spent on each feedtsock when producing 1t of product (and weighted feedstock mix cost)
A3: IVC 1 FAME | G3: =G4 -> 1000
A4: Imported POME | B4: 1000 | C4: 1 | D4: =B4/C4 -> 1000 | E4: 1 | F4: 1 | G4: =D4*F4 -> 1000 | H4: 1 | I4: 1 | J4: =B4*I4 -> 1000 | K4: 1 | L4: =K4*D4 -> 1000 | M4: =(I4+O4)/2 -> 1 | N4: =M4*D4 -> 1000 | O4: 1
A5: IVC 2 HVO | F5: =SUM(F6:F7) -> 1 | G5: =SUM(G6:G7) -> 1757.1545 | J5: =J7+J6 -> 1672.4229 | K5: =SUM(K6:K7) -> 1 | L5: =SUM(L6:L7) -> 1797.9347 | M5: =SUM(M6:M7) -> 1 | N5: =SUM(N6:N7) -> 1755.5689 | O5: =SUM(O6:O7) -> 1 | P5: =SUM(P6:P7) -> 1838.7149
A6: Tall oil | B6: 730 | C6: ='[1]Conversion factors selected IV '!$O$9 -> 0.95154545 | D6: =B6/C6 -> 767.17302 | E6: ='[1]Availabilities EU Austria'!$N$13/'[1]Availabilities EU Austria'!$N$10 -> 0.063011547 | F6: ='[1]Availabilities EU Austria'!$AB$13/'[1]Availabilities EU Austria'!$AB$10 -> 0.16279945 | G6: =F6*D6 -> 124.89535 | H6: ='[1]Availabilities EU Austria'!$Q$13/'[1]Availabilities EU Austria'!$Q$10 -> 0.089199177 | I6: ='[1]Availabilities EU Austria'!$AC$13/'[1]Availabilities EU Austria'!$AC$10 -> 0.23445469 | J6: =I6*D6 -> 179.86731 | K6: =(F6+O6)/2 -> 0.12831274 | L6: =K6*D6 -> 98.438074 | M6: =(I6+O6)/2 -> 0.16414036 | N6: =M6*D6 -> 125.92406 | O6: ='[1]Availabilities EU Austria'!$X$13/'[1]Availabilities EU Austria'!$X$10 -> 0.093826032 | P6: =O6*D6 -> 71.9808
A7: FPBO, biocrude | B7: 300 | C7: ='[1]Conversion factors selected IV '!$G$10 -> 0.15387273 | D7: =B7/C7 -> 1949.6632 | E7: =('[1]Availabilities EU Austria'!$N$15+'[1]Availabilities EU Austria'!$N$14)/'[1]Availabilities EU Austria'!$N$10 -> 0.93698845 | F7: =('[1]Availabilities EU Austria'!$AB$14+'[1]Availabilities EU Austria'!$AB$15)/'[1]Availabilities EU Austria'!$AB$10 -> 0.83720055 | G7: =F7*D7 -> 1632.2591 | H7: =('[1]Availabilities EU Austria'!$Q$14+'[1]Availabilities EU Austria'!$Q$15)/'[1]Availabilities EU Austria'!$Q$10 -> 0.91080082 | I7: =('[1]Availabilities EU Austria'!$AC$14+'[1]Availabilities EU Austria'!$AC$15)/'[1]Availabilities EU Austria'!$AC$10 -> 0.76554531 | J7: =I7*D7 -> 1492.5555 | K7: =(F7+O7)/2 -> 0.87168726 | L7: =K7*D7 -> 1699.4966 | M7: =(I7+O7)/2 -> 0.83585964 | N7: =M7*D7 -> 1629.6448 | O7: =('[1]Availabilities EU Austria'!$X$14+'[1]Availabilities EU Austria'!$X$15)/'[1]Availabilities EU Austria'!$X$10 -> 0.90617397 | P7: =O7*D7 -> 1766.7341
A8: IVC 2 HEFA | F8: =SUM(F9:F11) -> 1 | G8: =SUM(G9:G11) -> 1658.4116 | I8: =SUM(I9:I11) -> 1 | J8: =SUM(J9:J11) -> 1555.6028 | K8: =SUM(K9:K11) -> 1 | L8: =SUM(L9:L11) -> 1682.7582 | M8: =SUM(M9:M11) -> 1 | N8: =SUM(N9:N11) -> 1631.3538 | O8: =SUM(O9:O11) -> 1 | P8: =SUM(P9:P11) -> 1707.1048
A9: Oil crops abandoned | B9: 520 | C9: ='[1]Conversion factors selected IV '!$G$12 -> 0.42350471 | D9: =B9/C9 -> 1227.8494 | E9: ='[1]Availabilities EU Austria'!$N$21/'[1]Availabilities EU Austria'!$N$16 -> 0.072434801 | F9: ='[1]Availabilities EU Austria'!$AB$21/'[1]Availabilities EU Austria'!$AB$16 -> 0.28750596 | G9: =D9*F9 -> 353.01402 | H9: ='[1]Availabilities EU Austria'!$Q$21/'[1]Availabilities EU Austria'!$Q$16 -> 0.11542722 | I9: ='[1]Availabilities EU Austria'!$AC$21/'[1]Availabilities EU Austria'!$AC$16 -> 0.4068683 | J9: =D9*I9 -> 499.57299 | K9: =(F9+O9)/2 -> 0.24357775 | L9: =K9*D9 -> 299.07679 | M9: =(I9+O9)/2 -> 0.30325892 | N9: =M9*D9 -> 372.35628 | O9: ='[1]Availabilities EU Austria'!$AD$21/'[1]Availabilities EU Austria'!$AD$16 -> 0.19964954 | P9: =O9*D9 -> 245.13956
A10: Tall oil | B10: 520 | C10: ='[1]Conversion factors selected IV '!$G$12 -> 0.42350471 | D10: =B10/C10 -> 1227.8494 | E10: ='[1]Availabilities EU Austria'!$N$23/'[1]Availabilities EU Austria'!$N$16 -> 0.058447318 | F10: ='[1]Availabilities EU Austria'!$AB$23/'[1]Availabilities EU Austria'!$AB$16 -> 0.11599364 | G10: =D10*F10 -> 142.42272 | H10: ='[1]Availabilities EU Austria'!$Q$23/'[1]Availabilities EU Austria'!$Q$16 -> 0.078903164 | I10: ='[1]Availabilities EU Austria'!$AC$23/'[1]Availabilities EU Austria'!$AC$16 -> 0.13906251 | J10: =D10*I10 -> 170.74781 | K10: =(F10+O10)/2 -> 0.12619211 | L10: =K10*D10 -> 154.94491 | M10: =(I10+O10)/2 -> 0.13772655 | N10: =M10*D10 -> 169.10745 | O10: ='[1]Availabilities EU Austria'!$AD$23/'[1]Availabilities EU Austria'!$AD$16 -> 0.13639058 | P10: =O10*D10 -> 167.46709
A11: FPBO, biocrude | B11: 300 | C11: ='[1]Conversion factors selected IV '!$G$15 -> 0.15387273 | D11: =B11/C11 -> 1949.6632 | E11: =('[1]Availabilities EU Austria'!$N$24+'[1]Availabilities EU Austria'!$N$25)/'[1]Availabilities EU Austria'!$N$16 -> 0.86911788 | F11: =('[1]Availabilities EU Austria'!$AB$24+'[1]Availabilities EU Austria'!$AB$25)/'[1]Availabilities EU Austria'!$AB$16 -> 0.5965004 | G11: =D11*F11 -> 1162.9749 | H11: =('[1]Availabilities EU Austria'!$Q$24+'[1]Availabilities EU Austria'!$Q$25)/'[1]Availabilities EU Austria'!$Q$16 -> 0.80566962 | I11: =('[1]Availabilities EU Austria'!$AC$24+'[1]Availabilities EU Austria'!$AC$25)/'[1]Availabilities EU Austria'!$AC$16 -> 0.45406919 | J11: =D11*I11 -> 885.28201 | K11: =(F11+O11)/2 -> 0.63023014 | L11: =K11*D11 -> 1228.7365 | M11: =(I11+O11)/2 -> 0.55901454 | N11: =M11*D11 -> 1089.8901 | O11: =('[1]Availabilities EU Austria'!$AD$24+'[1]Availabilities EU Austria'!$AD$25)/'[1]Availabilities EU Austria'!$AD$16 -> 0.66395988 | P11: =O11*D11 -> 1294.4982
A12: IVC 5 Advanced Ethanol | F12: =SUM(F13:F16) -> 1 | G12: =SUM(G13:G16) -> 339.87864 | H12: =SUM(H13:H16) -> 1 | I12: =SUM(I13:I16) -> 1 | J12: =SUM(J13:J16) -> 342.2295 | K12: =SUM(K13:K16) -> 1 | L12: =SUM(L13:L16) -> 344.58151 | M12: =SUM(M13:M16) -> 1 | ... P12: =SUM(P13:P16) -> 349.28439
A13: Straw | B13: 65 | C13: ='[1]Conversion factors selected IV '!$G$17 -> 0.18050496 | D13: =B13/C13 -> 360.10091 | E13: ='[1]Availabilities EU Austria'!$N$27/'[1]Availabilities EU Austria'!$N$26 -> 0.73688393 | F13: ='[1]Availabilities EU Austria'!$AB$27/'[1]Availabilities EU Austria'!$AB$26 -> 0.71068978 | G13: =D13*F13 -> 255.92003 | H13: ='[1]Availabilities EU Austria'!$Q$27/'[1]Availabilities EU Austria'!$Q$26 -> 0.74789495 | I13: ='[1]Availabilities EU Austria'!$AC27/'[1]Availabilities EU Austria'!$AC$26 -> 0.72394933 | J13: =D13*I13 -> 260.69481 | K13: =(F13+O13)/2 -> 0.64236331 | L13: =K13*D13 -> 231.31561 | M13: =(I13+O13)/2 -> 0.64899309 | N13: =M13*D13 -> 233.703 | O13: ='[1]Availabilities EU Austria'!$AD$27/'[1]Availabilities EU Austria'!$AD$26 -> 0.57403685 | P13: =O13*D13 -> 206.71119
A14: Lignocrops abandoned degraded | B14: 69 | C14: ='[1]Conversion factors selected IV '!$G$18 -> 0.18050496 | D14: =B14/C14 -> 382.26096 | E14: ='[1]Availabilities EU Austria'!$N$28/'[1]Availabilities EU Austria'!$N$26 -> 0.028841348 | F14: ='[1]Availabilities EU Austria'!$AB$28/'[1]Availabilities EU Austria'!$AB$26 -> 0.027816119 | G14: =D14*F14 -> 10.633017 | H14: ='[1]Availabilities EU Austria'!$Q$28/'[1]Availabilities EU Austria'!$Q$26 -> 0.031508836 | I14: ='[1]Availabilities EU Austria'!$AC28/'[1]Availabilities EU Austria'!$AC$26 -> 0.030500006 | J14: =D14*I14 -> 11.658962 | K14: =(F14+O14)/2 -> 0.11275526 | L14: =K14*D14 -> 43.101936 | M14: =(I14+O14)/2 -> 0.11409721 | N14: =M14*D14 -> 43.614908 | O14: ='[1]Availabilities EU Austria'!$AD$28/'[1]Availabilities EU Austria'!$AD$26 -> 0.19769441 | P14: =O14*D14 -> 75.570855
A15: Lignocrops inter & cover cropping | B15: 69 | C15: ='[1]Conversion factors selected IV '!$G$19 -> 0.18050496 | D15: =B15/C15 -> 382.26096 | E15: ='[1]Availabilities EU Austria'!$N$29/'[1]Availabilities EU Austria'!$N$26 -> 0.013130549 | F15: ='[1]Availabilities EU Austria'!$AB$29/'[1]Availabilities EU Austria'!$AB$26 -> 0.012663795 | G15: =D15*F15 -> 4.8408745 | H15: ='[1]Availabilities EU Austria'!$Q$29/'[1]Availabilities EU Austria'!$Q$26 -> 0.022137974 | I15: ='[1]Availabilities EU Austria'!$AC29/'[1]Availabilities EU Austria'!$AC$26 -> 0.021429175 | J15: =D15*I15 -> 8.1915371 | K15: =(F15+O15)/2 -> 0.02584302 | L15: =K15*D15 -> 9.8787776 | M15: =(I15+O15)/2 -> 0.03022571 | N15: =M15*D15 -> 11.554109 | O15: ='[1]Availabilities EU Austria'!$AD$29/'[1]Availabilities EU Austria'!$AD$26 -> 0.039022244 | P15: =O15*D15 -> 14.916681
A16: Secondary forest residues | B16: 65 | C16: ='[1]Conversion factors selected IV '!$G$20 -> 0.23616906 | D16: =B16/C16 -> 275.22657 | E16: ='[1]Availabilities EU Austria'!$N$30/'[1]Availabilities EU Austria'!$N$26 -> 0.22114418 | F16: ='[1]Availabilities EU Austria'!$AB$30/'[1]Availabilities EU Austria'!$AB$26 -> 0.24883031 | G16: =D16*F16 -> 68.484713 | H16: ='[1]Availabilities EU Austria'!$Q$30/'[1]Availabilities EU Austria'!$Q$26 -> 0.19845824 | I16: ='[1]Availabilities EU Austria'!$AC30/'[1]Availabilities EU Austria'!$AC$26 -> 0.22412149 | J16: =D16*I16 -> 61.68419 | K16: =(F16+O16)/2 -> 0.21903841 | L16: =K16*D16 -> 60.285189 | M16: =(I16+O16)/2 -> 0.206684 | N16: =M16*D16 -> 56.884928 | O16: ='[1]Availabilities EU Austria'!$AD$30/'[1]Availabilities EU Austria'!$AD$26 -> 0.1892465 | P16: =O16*D16 -> 52.085666
A17: IVC 6 | G17: =G18 -> 1063.8298 | H17: =H18 -> 1 | I17: =I18 -> 1 | J17: =J18 -> 1063.8298 | K17: =K18 -> 1 | L17: =L18 -> 1063.8298 | M17: =M18 -> 1 | N17: =N18 -> 1063.8298
A18: Intermediate Bioenergy carrier (ethanol, methanol) | B18: 500 | C18: ='[1]Conversion factors selected IV '!$G$27 -> 0.47 | D18: =B18/C18 -> 1063.8298 | E18: 1 | F18: 1 | G18: =D18*F18 -> 1063.8298 | H18: 1 | I18: =100% -> 1 | J18: =D18 -> 1063.8298 | K18: =(F18+O18)/2 -> 1 | L18: =K18*D18 -> 1063.8298 | M18: =(I18+O18)/2 -> 1 | N18: =M18*D18 -> 1063.8298 | O18: 1 | P18: 205.19149
A19: IVC 7 (MCR + MSW) | E19: =SUM(E20:E28) -> 2 | F19: =SUM(F20:F28) -> 1 | G19: =SUM(G20:G28) -> -17.804006 | H19: =SUM(H20:H28) -> 1 | I19: =SUM(I20:I28) -> 1 | J19: =SUM(J20:J28) -> -12.642394 | K19: =SUM(K20:K28) -> 1 | L19: =SUM(L20:L28) -> -8.841801 | ... P19: =SUM(P20:P28) -> 0.12040417
A20: Prunings & damaged crops (olive stones excluded) | B20: 44 | C20: ='[1]Conversion factors selected IV '!$G$29 -> 0.50565326 | D20: =B20/C20 -> 87.01615 | E20: ='[1]Availabilities EU Austria'!$N$41/('[1]Availabilities EU Austria'!$N$40-'[1]Availabilities EU Austria'!$N$48) -> 0.032760716 | F20: ='[1]Availabilities EU Austria'!$AB41/('[1]Availabilities EU Austria'!$AB$40) -> 0.0097424065 | G20: =D20*F20 -> 0.84774671 | H20: ='[1]Availabilities EU Austria'!$Q41/('[1]Availabilities EU Austria'!$Q$40) -> 0.03010511 | I20: ='[1]Availabilities EU Austria'!$AC41/('[1]Availabilities EU Austria'!$AC$40) -> 0.010265564 | J20: =I20*D20 -> 0.89326983 | K20: =(F20+O20)/2 -> 0.0098222596 | L20: =K20*D20 -> 0.85469522 | M20: =(I20+O20)/2 -> 0.010083838 | N20: =M20*D20 -> 0.87745677 | O20: ='[1]Availabilities EU Austria'!$AD$41/'[1]Availabilities EU Austria'!$AD$40 -> 0.0099021126 | P20: =O20*D20 -> 0.86164372
A21: Lignocrops abandoned degraded | B21: 69 | C21: ='[1]Conversion factors selected IV '!$G$30 -> 0.50565326 | D21: =B21/C21 -> 136.45714 | E21: ='[1]Availabilities EU Austria'!$N$42/('[1]Availabilities EU Austria'!$N$40-'[1]Availabilities EU Austria'!$N$48) -> 0.01975637 | F21: ='[1]Availabilities EU Austria'!$AB42/('[1]Availabilities EU Austria'!$AB$40) -> 0.005035855 | G21: =D21*F21 -> 0.6871784 | H21: ='[1]Availabilities EU Austria'!$Q42/('[1]Availabilities EU Austria'!$Q$40) -> 0.021462821 | I21: ='[1]Availabilities EU Austria'!$AC42/('[1]Availabilities EU Austria'!$AC$40) -> 0.0062731056 | J21: =I21*D21 -> 0.85601008 | K21: =(F21+O21)/2 -> 0.027911309 | L21: =K21*D21 -> 3.8086975 | M21: =(I21+O21)/2 -> 0.028529934 | N21: =M21*D21 -> 3.8931133 | O21: ='[1]Availabilities EU Austria'!$AD$42/'[1]Availabilities EU Austria'!$AD$40 -> 0.050786762 | P21: =O21*D21 -> 6.9302165
A22: Lignocrops inter & cover cropping | B22: 69 | C22: ='[1]Conversion factors selected IV '!$G$31 -> 0.50565326 | D22: =B22/C22 -> 136.45714 | E22: ='[1]Availabilities EU Austria'!$N$43/('[1]Availabilities EU Austria'!$N$40-'[1]Availabilities EU Austria'!$N$48) -> 0.0089944473 | F22: ='[1]Availabilities EU Austria'!$AB43/('[1]Availabilities EU Austria'!$AB$40) -> 0.0022926647 | G22: =D22*F22 -> 0.31285048 | H22: ='[1]Availabilities EU Austria'!$Q43/('[1]Availabilities EU Austria'!$Q$40) -> 0.015079687 | I22: ='[1]Availabilities EU Austria'!$AC43/('[1]Availabilities EU Austria'!$AC$40) -> 0.0044074574 | J22: =I22*D22 -> 0.60142905 | K22: =(F22+O22)/2 -> 0.0061586477 | L22: =K22*D22 -> 0.84039148 | M22: =(I22+O22)/2 -> 0.0072160441 | N22: =M22*D22 -> 0.98468077 | O22: ='[1]Availabilities EU Austria'!$AD$43/'[1]Availabilities EU Austria'!$AD$40 -> 0.010024631 | P22: =O22*D22 -> 1.3679325
A23: Agroprocessing residues | B23: 44 | C23: ='[1]Conversion factors selected IV '!$G$32 -> 0.50565326 | D23: =B23/C23 -> 87.01615 | E23: ='[1]Availabilities EU Austria'!$N$44/('[1]Availabilities EU Austria'!$N$40-'[1]Availabilities EU Austria'!$N$48) -> 0.025238729 | F23: ='[1]Availabilities EU Austria'!$AB44/('[1]Availabilities EU Austria'!$AB$40) -> 0.045033074 | G23: =D23*F23 -> 3.9186047 | H23: ='[1]Availabilities EU Austria'!$Q44/('[1]Availabilities EU Austria'!$Q$40) -> 0.024015373 | I23: ='[1]Availabilities EU Austria'!$AC44/('[1]Availabilities EU Austria'!$AC$40) -> 0.049134117 | J23: =I23*D23 -> 4.2754617 | K23: =(F23+O23)/2 -> 0.049250794 | L23: =K23*D23 -> 4.2856145 | M23: =(I23+O23)/2 -> 0.051301316 | N23: =M23*D23 -> 4.464043 | O23: ='[1]Availabilities EU Austria'!$AD$44/'[1]Availabilities EU Austria'!$AD$40 -> 0.053468514 | P23: =O23*D23 -> 4.6526242
A24: Straw | B24: 65 | C24: ='[1]Conversion factors selected IV '!$G$33 -> 0.50565326 | D24: =B24/C24 -> 128.54659 | E24: ='[1]Availabilities EU Austria'!$N$45/('[1]Availabilities EU Austria'!$N$40-'[1]Availabilities EU Austria'!$N$48) -> 0.50476667 | F24: ='[1]Availabilities EU Austria'!$AB45/('[1]Availabilities EU Austria'!$AB$40) -> 0.12866391 | G24: =D24*F24 -> 16.539306 | H24: ='[1]Availabilities EU Austria'!$Q45/('[1]Availabilities EU Austria'!$Q$40) -> 0.50944236 | I24: ='[1]Availabilities EU Austria'!$AC45/('[1]Availabilities EU Austria'!$AC$40) -> 0.14889868 | J24: =I24*D24 -> 19.140417 | K24: =(F24+O24)/2 -> 0.13806564 | L24: =K24*D24 -> 17.747866 | M24: =(I24+O24)/2 -> 0.14818302 | N24: =M24*D24 -> 19.048421 | O24: ='[1]Availabilities EU Austria'!$AD$45/'[1]Availabilities EU Austria'!$AD$40 -> 0.14746736 | P24: =O24*D24 -> 18.956426
A25: Manure | B25: 0 | C25: ='[1]Conversion factors selected IV '!$G$34 -> 0.11659946 | D25: =B25/C25 -> 0 | E25: ='[1]Availabilities EU Austria'!$N$46/('[1]Availabilities EU Austria'!$N$40-'[1]Availabilities EU Austria'!$N$48) -> 0.37200916 | F25: ='[1]Availabilities EU Austria'!$AB46/('[1]Availabilities EU Austria'!$AB$40) -> 0.66377019 | G25: =D25*F25 -> 0 | H25: ='[1]Availabilities EU Austria'!$Q46/('[1]Availabilities EU Austria'!$Q$40) -> 0.3159246 | I25: ='[1]Availabilities EU Austria'!$AC46/('[1]Availabilities EU Austria'!$AC$40) -> 0.64636417 | J25: =I25*D25 -> 0 | K25: =(F25+O25)/2 -> 0.63783016 | L25: =K25*D25 -> 0 | M25: =(I25+O25)/2 -> 0.62912715 | N25: =M25*D25 -> 0 | O25: ='[1]Availabilities EU Austria'!$AD$46/'[1]Availabilities EU Austria'!$AD$40 -> 0.61189012 | P25: =O25*D25 -> 0
A26: Sewage sludge | B26: 0 | C26: ='[1]Conversion factors selected IV '!$G$35 -> 0.11659946 | D26: =B26/C26 -> 0 | E26: ='[1]Availabilities EU Austria'!$N$47/('[1]Availabilities EU Austria'!$N$40-'[1]Availabilities EU Austria'!$N$48) -> 0.034001984 | F26: ='[1]Availabilities EU Austria'!$AB47/('[1]Availabilities EU Austria'!$AB$40) -> 0.015167304 | G26: =D26*F26 -> 0 | H26: ='[1]Availabilities EU Austria'!$Q47/('[1]Availabilities EU Austria'!$Q$40) -> 0.024204717 | I26: ='[1]Availabilities EU Austria'!$AC47/('[1]Availabilities EU Austria'!$AC$40) -> 0.012380376 | J26: =I26*D26 -> 0 | K26: =(F26+O26)/2 -> 0.013282742 | L26: =K26*D26 -> 0 | M26: =(I26+O26)/2 -> 0.011889279 | N26: =M26*D26 -> 0 | O26: ='[1]Availabilities EU Austria'!$AD$47/'[1]Availabilities EU Austria'!$AD$40 -> 0.011398181 | P26: =O26*D26 -> 0
A27: Biowastes (post consumer woods excluded) | B27: =-(55+70)/2 -> -62.5 | C27: ='[1]Conversion factors selected IV '!$G$36 -> 0.18593291 | D27: =B27/C27 -> -336.14275 | E27: ='[1]Availabilities EU Austria'!$N$48/'[1]Availabilities EU Austria'!$N$48 -> 1 | F27: ='[1]Availabilities EU Austria'!$AB$48/'[1]Availabilities EU Austria'!$AB$40 -> 0.125884 | G27: =D27*F27 -> -42.314992 | H27: ='[1]Availabilities EU Austria'!$Q48/('[1]Availabilities EU Austria'!$Q$40) -> 0.05819089 | I27: ='[1]Availabilities EU Austria'!$AC48/('[1]Availabilities EU Austria'!$AC$40) -> 0.11905533 | J27: =I27*D27 -> -40.019584 | K27: =(F27+O27)/2 -> 0.11387803 | L27: =K27*D27 -> -38.279276 | M27: =(I27+O27)/2 -> 0.1104637 | N27: =M27*D27 -> -37.131572 | O27: ='[1]Availabilities EU Austria'!$AD$48/'[1]Availabilities EU Austria'!$AD$40 -> 0.10187207 | P27: =O27*D27 -> -34.243559
A28: Intermediate Bioenergy carrier (crude glycerine) | B28: 300 | C28: =0.6 -> 0.6 | D28: =B28/C28 -> 500 | E28: ='[1]Availabilities EU Austria'!$N$49/('[1]Availabilities EU Austria'!$N$40-'[1]Availabilities EU Austria'!$N$48) -> 0.0024719148 | F28: ='[1]Availabilities EU Austria'!$AB49/('[1]Availabilities EU Austria'!$AB$40) -> 0.0044105992 | G28: =D28*F28 -> 2.2052996 | H28: ='[1]Availabilities EU Austria'!$Q49/('[1]Availabilities EU Austria'!$Q$40) -> 0.0015744344 | I28: ='[1]Availabilities EU Austria'!$AC49/('[1]Availabilities EU Austria'!$AC$40) -> 0.0032212052 | J28: =I28*D28 -> 1.6106026 | K28: =(F28+O28)/2 -> 0.00380042 | L28: =K28*D28 -> 1.90021 | M28: =(I28+O28)/2 -> 0.003205723 | N28: =M28*D28 -> 1.6028615 | O28: ='[1]Availabilities EU Austria'!$AD$49/'[1]Availabilities EU Austria'!$AD$40 -> 0.0031902408 | P28: =O28*D28 -> 1.5951204
A29: IVC 8a | F29: =SUM(F30:F39) -> 1 | G29: =SUM(G30:G39) -> 136.38489 | H29: =SUM(H30:H39) -> 1 | I29: =SUM(I30:I39) -> 1 | J29: =SUM(J30:J39) -> 138.68457 | K29: =SUM(K30:K39) -> 1 | L29: =SUM(L30:L39) -> 139.285 | M29: =SUM(M30:M39) -> 1 | ... P29: =SUM(P30:P39) -> 142.1851
A30: Straw | B30: 65 | C30: ='[1]Conversion factors selected IV '!$G$39 -> 0.44129562 | D30: =B30/C30 -> 147.29355 | E30: ='[1]Availabilities EU Austria'!$N$51/'[1]Availabilities EU Austria'!$N$50 -> 0.5178381 | F30: ='[1]Availabilities EU Austria'!$AB51/'[1]Availabilities EU Austria'!$AB$50 -> 0.44781912 | G30: =D30*F30 -> 65.96087 | H30: ='[1]Availabilities EU Austria'!$Q$51/'[1]Availabilities EU Austria'!$Q$50 -> 0.56804069 | I30: ='[1]Availabilities EU Austria'!$AC51/'[1]Availabilities EU Austria'!$AC$50 -> 0.50267797 | J30: =I30*D30 -> 74.041224 | K30: =(F30+O30)/2 -> 0.43418777 | L30: =K30*D30 -> 63.953059 | M30: =(I30+O30)/2 -> 0.4616172 | N30: =M30*D30 -> 67.993237 | O30: ='[1]Availabilities EU Austria'!$AD$70/'[1]Availabilities EU Austria'!$AD$69 -> 0.42055642 | P30: =O30*D30 -> 61.945249
A31: Prunings & damaged crops | B31: 44 | C31: ='[1]Conversion factors selected IV '!$G$40 -> 0.44129562 | D31: =B31/C31 -> 99.706405 | E31: ='[1]Availabilities EU Austria'!$N$52/'[1]Availabilities EU Austria'!$N$50 -> 0.033609087 | F31: ='[1]Availabilities EU Austria'!$AB52/'[1]Availabilities EU Austria'!$AB$50 -> 0.033908778 | G31: =D31*F31 -> 3.3809224 | H31: ='[1]Availabilities EU Austria'!$Q$52/'[1]Availabilities EU Austria'!$Q$50 -> 0.033570732 | I31: ='[1]Availabilities EU Austria'!$AC52/'[1]Availabilities EU Austria'!$AC$50 -> 0.034659158 | J31: =I31*D31 -> 3.45574 | K31: =(F31+O31)/2 -> 0.031075451 | L31: =K31*D31 -> 3.0984215 | M31: =(I31+O31)/2 -> 0.031450641 | N31: =M31*D31 -> 3.1358304 | O31: ='[1]Availabilities EU Austria'!$AD$71/'[1]Availabilities EU Austria'!$AD$69 -> 0.028242125 | P31: =O31*D31 -> 2.8159207
A32: Sewage sludge | B32: 0 | C32: ='[1]Conversion factors selected IV '!$G$41 -> 0.30788067 | D32: =B32/C32 -> 0 | E32: ='[1]Availabilities EU Austria'!$N$53/'[1]Availabilities EU Austria'!$N$50 -> 0.034882499 | F32: ='[1]Availabilities EU Austria'!$AB53/'[1]Availabilities EU Austria'!$AB$50 -> 0.052790317 | G32: =D32*F32 -> 0 | H32: ='[1]Availabilities EU Austria'!$Q$53/'[1]Availabilities EU Austria'!$Q$50 -> 0.026988851 | I32: ='[1]Availabilities EU Austria'!$AC53/'[1]Availabilities EU Austria'!$AC$50 -> 0.041795821 | J32: =I32*D32 -> 0 | K32: =(F32+O32)/2 -> 0.042648172 | L32: =K32*D32 -> 0 | M32: =(I32+O32)/2 -> 0.037150924 | N32: =M32*D32 -> 0 | O32: ='[1]Availabilities EU Austria'!$AD$72/'[1]Availabilities EU Austria'!$AD$69 -> 0.032506027 | P32: =O32*D32 -> 0
A33: Agroprocessing residues - maize cobs | B33: 44 | C33: ='[1]Conversion factors selected IV '!$G$42 -> 0.44129562 | D33: =B33/C33 -> 99.706405 | E33: ='[1]Availabilities EU Austria'!$N$54/'[1]Availabilities EU Austria'!$N$50 -> 0.013662908 | F33: ='[1]Availabilities EU Austria'!$AB54/'[1]Availabilities EU Austria'!$AB$50 -> 0.016541687 | G33: =D33*F33 -> 1.6493122 | H33: ='[1]Availabilities EU Austria'!$Q$54/'[1]Availabilities EU Austria'!$Q$50 -> 0.014187521 | I33: ='[1]Availabilities EU Austria'!$AC54/'[1]Availabilities EU Austria'!$AC$50 -> 0.017577009 | J33: =I33*D33 -> 1.7525404 | K33: =(F33+O33)/2 -> 0.014584254 | L33: =K33*D33 -> 1.4541435 | M33: =(I33+O33)/2 -> 0.015101915 | N33: =M33*D33 -> 1.5057576 | O33: ='[1]Availabilities EU Austria'!$AD$73/'[1]Availabilities EU Austria'!$AD$69 -> 0.01262682 | P33: =O33*D33 -> 1.2589748
A34: Lignocrops abandoned degraded | B34: 69 | C34: ='[1]Conversion factors selected IV '!$G$43 -> 0.44129562 | D34: =B34/C34 -> 156.35777 | E34: ='[1]Availabilities EU Austria'!$N$55/'[1]Availabilities EU Austria'!$N$50 -> 0.020267981 | F34: ='[1]Availabilities EU Austria'!$AB55/'[1]Availabilities EU Austria'!$AB$50 -> 0.017527465 | G34: =D34*F34 -> 2.7405554 | H34: ='[1]Availabilities EU Austria'!$Q$55/'[1]Availabilities EU Austria'!$Q$50 -> 0.02393157 | I34: ='[1]Availabilities EU Austria'!$AC55/'[1]Availabilities EU Austria'!$AC$50 -> 0.021177837 | J34: =I34*D34 -> 3.3113194 | K34: =(F34+O34)/2 -> 0.081182126 | L34: =K34*D34 -> 12.693456 | M34: =(I34+O34)/2 -> 0.083007312 | N34: =M34*D34 -> 12.978838 | O34: ='[1]Availabilities EU Austria'!$AD$74/'[1]Availabilities EU Austria'!$AD$69 -> 0.14483679 | P34: =O34*D34 -> 22.646357
A35: Lignocrops inter & cover cropping | B35: 69 | C35: ='[1]Conversion factors selected IV '!$G$44 -> 0.44129562 | D35: =B35/C35 -> 156.35777 | E35: ='[1]Availabilities EU Austria'!$N$56/'[1]Availabilities EU Austria'!$N$50 -> 0.0092273673 | F35: ='[1]Availabilities EU Austria'!$AB56/'[1]Availabilities EU Austria'!$AB$50 -> 0.0079796978 | G35: =D35*F35 -> 1.2476878 | H35: ='[1]Availabilities EU Austria'!$Q$56/'[1]Availabilities EU Austria'!$Q$50 -> 0.01681422 | I35: ='[1]Availabilities EU Austria'!$AC56/'[1]Availabilities EU Austria'!$AC$50 -> 0.014879459 | J35: =I35*D35 -> 2.326519 | K35: =(F35+O35)/2 -> 0.018284276 | L35: =K35*D35 -> 2.8588886 | M35: =(I35+O35)/2 -> 0.021734156 | N35: =M35*D35 -> 3.3983042 | O35: ='[1]Availabilities EU Austria'!$AD$75/'[1]Availabilities EU Austria'!$AD$69 -> 0.028588854 | P35: =O35*D35 -> 4.4700894
A36: Primary forestry residues | B36: 69 | C36: ='[1]Conversion factors selected IV '!$G$45 -> 0.48747772 | D36: =B36/C36 -> 141.54493 | E36: ='[1]Availabilities EU Austria'!$N$57/'[1]Availabilities EU Austria'!$N$50 -> 0.14802813 | F36: ='[1]Availabilities EU Austria'!$AB57/'[1]Availabilities EU Austria'!$AB$50 -> 0.17921771 | G36: =D36*F36 -> 25.367359 | H36: ='[1]Availabilities EU Austria'!$Q$57/'[1]Availabilities EU Austria'!$Q$50 -> 0.10247464 | I36: ='[1]Availabilities EU Austria'!$AC57/'[1]Availabilities EU Austria'!$AC$50 -> 0.12695647 | J36: =I36*D36 -> 17.970045 | K36: =(F36+O36)/2 -> 0.14373173 | L36: =K36*D36 -> 20.344498 | M36: =(I36+O36)/2 -> 0.11760111 | N36: =M36*D36 -> 16.645841 | O36: ='[1]Availabilities EU Austria'!$AD$76/'[1]Availabilities EU Austria'!$AD$69 -> 0.10824575 | P36: =O36*D36 -> 15.321638
A37: Secondary forest residues | B37: 65 | C37: ='[1]Conversion factors selected IV '!$G$46 -> 0.48747772 | D37: =B37/C37 -> 133.33943 | E37: ='[1]Availabilities EU Austria'!$N$58/'[1]Availabilities EU Austria'!$N$50 -> 0.15540695 | F37: ='[1]Availabilities EU Austria'!$AB58/'[1]Availabilities EU Austria'!$AB$50 -> 0.1567927 | G37: =D37*F37 -> 20.906649 | H37: ='[1]Availabilities EU Austria'!$Q$58/'[1]Availabilities EU Austria'!$Q$50 -> 0.15073288 | I37: ='[1]Availabilities EU Austria'!$AC58/'[1]Availabilities EU Austria'!$AC$50 -> 0.15561992 | J37: =I37*D37 -> 20.750271 | K37: =(F37+O37)/2 -> 0.14772015 | L37: =K37*D37 -> 19.69692 | M37: =(I37+O37)/2 -> 0.14713376 | N37: =M37*D37 -> 19.618731 | O37: ='[1]Availabilities EU Austria'!$AD$77/'[1]Availabilities EU Austria'!$AD$69 -> 0.1386476 | P37: =O37*D37 -> 18.487191
A38: Biowastes - Post consumer wood | B38: 25 | C38: ='[1]Conversion factors selected IV '!$G$47 -> 0.41050756 | D38: =B38/C38 -> 60.900219 | E38: ='[1]Availabilities EU Austria'!$N$59/'[1]Availabilities EU Austria'!$N$50 -> 0.046552014 | F38: ='[1]Availabilities EU Austria'!$AB59/'[1]Availabilities EU Austria'!$AB$50 -> 0.05636054 | G38: =D38*F38 -> 3.4323692 | H38: ='[1]Availabilities EU Austria'!$Q$59/'[1]Availabilities EU Austria'!$Q$50 -> 0.042968416 | I38: ='[1]Availabilities EU Austria'!$AC59/'[1]Availabilities EU Austria'!$AC$50 -> 0.05323384 | J38: =I38*D38 -> 3.2419525 | K38: =(F38+O38)/2 -> 0.055191496 | L38: =K38*D38 -> 3.3611742 | M38: =(I38+O38)/2 -> 0.053628146 | N38: =M38*D38 -> 3.2659658 | O38: ='[1]Availabilities EU Austria'!$AD$78/'[1]Availabilities EU Austria'!$AD$69 -> 0.054022452 | P38: =O38*D38 -> 3.2899791
A39: Intermediate Bioenergy carrier (FPBO with lower quality) | B39: 300 | C39: ='[1]Conversion factors selected IV '!$G$48 -> 0.79651765 | D39: =B39/C39 -> 376.63949 | E39: ='[1]Availabilities EU Austria'!$N$60/'[1]Availabilities EU Austria'!$N$50 -> 0.020524961 | F39: ='[1]Availabilities EU Austria'!$AB60/'[1]Availabilities EU Austria'!$AB$50 -> 0.031061972 | G39: =D39*F39 -> 11.699165 | H39: ='[1]Availabilities EU Austria'!$Q$60/'[1]Availabilities EU Austria'!$Q$50 -> 0.020290488 | I39: ='[1]Availabilities EU Austria'!$AC60/'[1]Availabilities EU Austria'!$AC$50 -> 0.031422516 | J39: =I39*D39 -> 11.83496 | K39: =(F39+O39)/2 -> 0.031394565 | L39: =K39*D39 -> 11.824433 | M39: =(I39+O39)/2 -> 0.031574837 | N39: =M39*D39 -> 11.89233 | O39: ='[1]Availabilities EU Austria'!$AD$79/'[1]Availabilities EU Austria'!$AD$69 -> 0.031727158 | P39: =O39*D39 -> 11.9497
A40: IVC 8b | G40: =SUM(G41) -> 429.92261 | H40: =SUM(H41) -> 1 | I40: =SUM(I41) -> 1 | J40: =SUM(J41) -> 429.92261 | K40: =SUM(K41) -> 1 | L40: =SUM(L41) -> 429.92261 | M40: =SUM(M41) -> 1 | N40: =SUM(N41) -> 429.92261 | P40: 46.068597
A41: Intermediate Bioenergy carrier (biomethane) | B41: 900 | C41: ='[1]Conversion factors selected IV '!$O$49 -> 2.0934 | D41: =B41/C41 -> 429.92261 | E41: 1 | F41: 1 | G41: =D41*F41 -> 429.92261 | H41: 1 | I41: 1 | J41: =I41*D41 -> 429.92261 | K41: =(F41+O41)/2 -> 1 | L41: =K41*D41 -> 429.92261 | M41: =(I41+O41)/2 -> 1 | N41: =M41*D41 -> 429.92261 | O41: 1 | P41: 46.068597
A42: IVC 8c | G42: =SUM(G43) -> 291.86969 | H42: =SUM(H43) -> 1 | I42: =SUM(I43) -> 1 | J42: =SUM(J43) -> 291.86969 | K42: =SUM(K43) -> 1 | L42: =SUM(L43) -> 291.86969 | M42: =SUM(M43) -> 1 | N42: =SUM(N43) -> 291.86969 | P42: 96.44
A43: e-biofuel feedstocks (biogenic CO2 and hydrogen from electrolysis) | B43: =(427+795)/2 -> 611 | C43: ='[1]Conversion factors selected IV '!$O$50 -> 2.0934 | D43: =B43/C43 -> 291.86969 | E43: 1 | F43: 1 | G43: =D43*F43 -> 291.86969 | H43: 1 | I43: 1 | J43: =I43*D43 -> 291.86969 | K43: =(F43+O43)/2 -> 1 | L43: =K43*D43 -> 291.86969 | M43: =(I43+O43)/2 -> 1 | N43: =M43*D43 -> 291.86969 | O43: 1 | P43: 96.44
A44: IVC 9a | F44: =SUM(F45:F54) -> 1 | G44: =SUM(G45:G54) -> 233.90132 | H44: =SUM(H45:H54) -> 1 | I44: =SUM(I45:I54) -> 1 | J44: =SUM(J45:J54) -> 237.89337 | K44: =SUM(K45:K54) -> 1 | L44: =SUM(L45:L54) -> 238.97162 | M44: =SUM(M45:M54) -> 1 | ... P44: =SUM(P45:P54) -> 244.04192
A45: Straw | B45: 65 | C45: ='[1]Conversion factors selected IV '!$G$52 -> 0.24762705 | D45: =B45/C45 -> 262.49151 | E45: ='[1]Availabilities EU Austria'!$N$51/'[1]Availabilities EU Austria'!$N$50 -> 0.5178381 | F45: ='[1]Availabilities EU Austria'!$AB70/'[1]Availabilities EU Austria'!$AB$69 -> 0.44781912 | G45: =D45*F45 -> 117.54872 | H45: ='[1]Availabilities EU Austria'!$Q$51/'[1]Availabilities EU Austria'!$Q$50 -> 0.56804069 | I45: ='[1]Availabilities EU Austria'!$AC70/'[1]Availabilities EU Austria'!$AC$69 -> 0.50267797 | J45: =I45*D45 -> 131.9487 | K45: =(F45+O45)/2 -> 0.43418777 | L45: =K45*D45 -> 113.97061 | M45: =(I45+O45)/2 -> 0.4616172 | N45: =M45*D45 -> 121.1706 | O45: ='[1]Availabilities EU Austria'!$AD$70/'[1]Availabilities EU Austria'!$AD$69 -> 0.42055642 | P45: =O45*D45 -> 110.39249
A46: Prunings & damaged crops | B46: 44 | C46: ='[1]Conversion factors selected IV '!$G$53 -> 0.24762705 | D46: =B46/C46 -> 177.68656 | E46: ='[1]Availabilities EU Austria'!$N$52/'[1]Availabilities EU Austria'!$N$50 -> 0.033609087 | F46: ='[1]Availabilities EU Austria'!$AB71/'[1]Availabilities EU Austria'!$AB$69 -> 0.033908778 | G46: =D46*F46 -> 6.0251342 | H46: ='[1]Availabilities EU Austria'!$Q$52/'[1]Availabilities EU Austria'!$Q$50 -> 0.033570732 | I46: ='[1]Availabilities EU Austria'!$AC71/'[1]Availabilities EU Austria'!$AC$69 -> 0.034659158 | J46: =I46*D46 -> 6.1584666 | K46: =(F46+O46)/2 -> 0.031075451 | L46: =K46*D46 -> 5.5216901 | M46: =(I46+O46)/2 -> 0.031450641 | N46: =M46*D46 -> 5.5883563 | O46: ='[1]Availabilities EU Austria'!$AD$71/'[1]Availabilities EU Austria'!$AD$69 -> 0.028242125 | P46: =O46*D46 -> 5.018246
A47: Sewage sludge | B47: 0 | C47: ='[1]Conversion factors selected IV '!$G$54 -> 0.17276306 | D47: =B47/C47 -> 0 | E47: ='[1]Availabilities EU Austria'!$N$53/'[1]Availabilities EU Austria'!$N$50 -> 0.034882499 | F47: ='[1]Availabilities EU Austria'!$AB72/'[1]Availabilities EU Austria'!$AB$69 -> 0.052790317 | G47: =D47*F47 -> 0 | H47: ='[1]Availabilities EU Austria'!$Q$53/'[1]Availabilities EU Austria'!$Q$50 -> 0.026988851 | I47: ='[1]Availabilities EU Austria'!$AC72/'[1]Availabilities EU Austria'!$AC$69 -> 0.041795821 | J47: =I47*D47 -> 0 | K47: =(F47+O47)/2 -> 0.042648172 | L47: =K47*D47 -> 0 | M47: =(I47+O47)/2 -> 0.037150924 | N47: =M47*D47 -> 0 | O47: ='[1]Availabilities EU Austria'!$AD$72/'[1]Availabilities EU Austria'!$AD$69 -> 0.032506027 | P47: =O47*D47 -> 0
A48: Agroprocessing residues - maize cobs | B48: 44 | C48: ='[1]Conversion factors selected IV '!$G$55 -> 0.24762705 | D48: =B48/C48 -> 177.68656 | E48: ='[1]Availabilities EU Austria'!$N$54/'[1]Availabilities EU Austria'!$N$50 -> 0.013662908 | F48: ='[1]Availabilities EU Austria'!$AB73/'[1]Availabilities EU Austria'!$AB$69 -> 0.016541687 | G48: =D48*F48 -> 2.9392356 | H48: ='[1]Availabilities EU Austria'!$Q$54/'[1]Availabilities EU Austria'!$Q$50 -> 0.014187521 | I48: ='[1]Availabilities EU Austria'!$AC73/'[1]Availabilities EU Austria'!$AC$69 -> 0.017577009 | J48: =I48*D48 -> 3.1231983 | K48: =(F48+O48)/2 -> 0.014584254 | L48: =K48*D48 -> 2.5914259 | M48: =(I48+O48)/2 -> 0.015101915 | N48: =M48*D48 -> 2.6834073 | O48: ='[1]Availabilities EU Austria'!$AD$73/'[1]Availabilities EU Austria'!$AD$69 -> 0.01262682 | P48: =O48*D48 -> 2.2436163
